Workbook
Name _Hlk3298152: Instructions!$B$32
Name CFO: [1]Variables!$E$10
Name CFO: [1]Variables!$E$10
Name Client_Ticker: [1]Variables!$B$5
Name Client_Ticker: [1]Variables!$B$5
Name Component: 'Raw Data'!$B$31:$AY$31
Name Currency_CAD: [1]Variables!$B$3
Name Currency_CAD: [1]Variables!$B$3
Name FX_2011: [1]Variables!$H$4
Name FX_2011: [1]Variables!$H$4
Name FX_2012: [1]Variables!$H$5
Name FX_2012: [1]Variables!$H$5
Name FX_2013: [1]Variables!$H$6
Name FX_2013: [1]Variables!$H$6
Name IQ_CH: 110000
Name IQ_CQ: 5000
Name IQ_CY: 10000
Name IQ_DAILY: 500000
Name IQ_FH: 100000
Name IQ_FQ: 500
Name IQ_FY: 1000
Name IQ_LTM: 2000
Name IQ_MONTH: 15000
Name IQ_NTM: 6000
Name IQ_WEEK: 50000
Name IQ_YTD: 3000
Name Look_Up: 'Raw Data'!$B$31:$B$1048576
Name Look_Up2: 'Raw Data'!$A$31:$A$1048576
Name Peer_1_Ticker: [1]Variables!$B$7
Name Peer_1_Ticker: [1]Variables!$B$7
Name Peer_10_Ticker: [1]Variables!$B$16
Name Peer_10_Ticker: [1]Variables!$B$16
Name Peer_12_Ticker: [1]Variables!$B$18
Name Peer_12_Ticker: [1]Variables!$B$18
Name Peer_13_Ticker: [1]Variables!$B$19
Name Peer_13_Ticker: [1]Variables!$B$19
Name Peer_14_Ticker: [1]Variables!$B$20
Name Peer_14_Ticker: [1]Variables!$B$20
Name Peer_2_Ticker: [1]Variables!$B$8
Name Peer_2_Ticker: [1]Variables!$B$8
Name Peer_3_Ticker: [1]Variables!$B$9
Name Peer_3_Ticker: [1]Variables!$B$9
Name Peer_4_Ticker: [1]Variables!$B$10
Name Peer_4_Ticker: [1]Variables!$B$10
Name Peer_5_Ticker: [1]Variables!$B$11
Name Peer_5_Ticker: [1]Variables!$B$11
Name Peer_6_Ticker: [1]Variables!$B$12
Name Peer_6_Ticker: [1]Variables!$B$12
Name Peer_7_Ticker: [1]Variables!$B$13
Name Peer_7_Ticker: [1]Variables!$B$13
Name Peer_8_Ticker: [1]Variables!$B$14
Name Peer_8_Ticker: [1]Variables!$B$14
Name Peer_9_Ticker: [1]Variables!$B$15
Name Peer_9_Ticker: [1]Variables!$B$15
Name raw: '[4]Raw Data'!$A$1:$AJ$289
Name raw: '[4]Raw Data'!$A$1:$AJ$289
Name Raw_Data: '[1]Raw Data'!$1:$1048576
Name Raw_Data: '[1]Raw Data'!$1:$1048576
Name Raw_Data: 'Raw Data'!$B$31:$AY$1048576

Sheet Instructions
A1: Executive Compensation Benchmarking Methodology
A3: Effective Date | B3: 44992 | D3: Remember: | E3: • NEO order
A4: Last Revised | B4: 44992 | E4: • Currency
E5: • Incumbents serving for partial years
E6: • Date of fiscal year end
B9: Purpose
B10: Establish guidelines for executive compensation benchmarking in order to maintain consistency across client projects and teams, improve ease of training, and increase the efficiency of the benchmarking exercise
B12: Policy
B13: Roles
B14: · Record each person’s entire name and role as disclosed in the proxy
B15: o Ignore “director” roles (i.e. assume that the CEO is on the Board of directors)
B16: · Capture Executive Chairman role if it is one of the top 5 NEOs, but do not use as a comparison to any of the NEOs, unless indicated by client team
B17: o Footnote and confirm with client team
B19: Base Salary
B20: · Record the base salary in the Summary Compensation Table
B21: · If the incumbent has partial years of service, annualize the base salary
B22: · If the upcoming year’s salary is disclosed, record it in column O; it will be used in lieu of data aging
... B132: · Assume that the peer reviewer has made all of the necessary changes to the raw data sheet

Sheet Import 2023 Data
B3: x | C3: Lookup | D3: Role match | E3: Company | F3: Title | G3: Incumbent | H3: Actual TDC | I3: Target TDC
C4: tsx:hbm_2023_CEO | D4: CEO | E4: Hudbay Minerals Inc. | F4: President & CEO | G4: Peter Kukielski | H4: - | I4: 4779.9705
C5: tsx:hbm_2023_CFO | D5: CFO | E5: Hudbay Minerals Inc. | F5: CFO | G5: Eugene Lei | H5: - | I5: 1930.656
C6: tsx:hbm_2023_COO | D6: COO | E6: Hudbay Minerals Inc. | F6: COO | G6: Andre Lauzon | H6: - | I6: 2232
C7: tsx:hbm_2023_Legal | D7: Legal | E7: Hudbay Minerals Inc. | F7: SVP, Legal and Ogranizational Effectiveness | G7: Patrick Donnelly | H7: - | I7: 1582.906
C8: tsx:hbm_2023_NEO2 | D8: NEO2 | E8: Hudbay Minerals Inc. | F8: SVP, Legal and Ogranizational Effectiveness | G8: Patrick Donnelly | H8: - | I8: 1582.906
C9: tsx:hbm_2023_NEO4 | D9: Tech | E9: Hudbay Minerals Inc. | F9: SVP, Exploration & Technical Services | G9: Olivier Tavchandjilan | H9: - | I9: 1101.1
C10: tsx:hbm_2023_NEO3 | D10: NEO3 | E10: Hudbay Minerals Inc. | F10: SVP, South America and USA | G10: Javier Del Rio | H10: - | I10: 1509
C11: tsx:hbm_2023_NEO4 | D11: NEO4 | E11: Hudbay Minerals Inc. | F11: SVP, Exploration & Technical Services | G11: Olivier Tavchandjilan | H11: - | I11: 1101.1
C12: TSX:K_2023_CEO | D12: CEO | E12: Kinross Gold Corporation | F12: President and CEO | G12: J. Paul Rollinson | H12: 9041.3336 | I12: 8608.1222
C13: TSX:PAAS_2023_CEO | D13: CEO | E13: Pan American Silver Corp. | F13: President and CEO | G13: Michael Steinmann | H13: 7497.2 | I13: 7395
D14: CEO
C15: - | D15: CEO | E15: - | F15: - | G15: - | H15: - | I15: -
C16: TSX:AGI_2023_CEO | D16: CEO | E16: Alamos Gold Inc. | F16: President and CEO | G16: John McCluskey | H16: 5354.3256 | I16: 5099.3583
C17: TSX:BTO_2023_CEO | D17: CEO | E17: B2Gold Corp. | F17: Director, President and CEO | G17: Clive Johnson | H17: 5600 | I17: 7275
C18: TSX:CS_2023_CEO | D18: CEO | E18: Capstone Copper Corp. | F18: CEO and Director | G18: John MacKenzie | H18: 4059.874 | I18: 4186
C19: NYSE:HL_2023_CEO | D19: CEO | E19: Hecla Mining Company | F19: CEO | G19: Phillips S. Baker, Jr. | H19: 4635.6105 | I19: 5486.7939
C20: TSX:SSRM_2023_CEO | D20: CEO | E20: SSR Mining Inc. | F20: Executive Chairman | G20: Rod Antal | H20: 7097.5089 | I20: 7471.3908
C21: TSX:ELD_2023_CEO | D21: CEO | E21: Eldorado Gold Corporation | F21: President and CEO | G21: George Burns | H21: 4870.654 | I21: 4614.48
C22: TSX:IMG_2023_CEO | D22: CEO | E22: IAMGOLD Corporation | F22: President and CEO | G22: Renaud Adams | H22: 3647.4525 | I22: 4156.25
C23: TSX:OGC _2023_CEO | D23: CEO | E23: OceanaGold Corporation | F23: President and CEO | G23: Gerard Bond | H23: 4467.6643 | I23: 4310.2275
C24: TSX:NGD_2023_CEO | D24: CEO | E24: New Gold Inc. | F24: President and CEO | G24: Patrick Godin | H24: 3605.0004 | I24: 3325
C25: TSX:CG_2023_CEO | D25: CEO | E25: Centerra Gold Inc. | F25: President and CEO | G25: Paul Tomory | H25: 2868.8441 | I25: 3487.5
C26: TSX:ERO_2023_CEO | D26: CEO | E26: Ero Copper Corp. | F26: CEO and Director | G26: David Strang | H26: 4183.8007 | I26: 4017.2353
C27: TSX:K_2023_CFO | D27: CFO | E27: Kinross Gold Corporation | F27: EVP and CFO | G27: Andrea S. Freeborough | H27: 2504.0634 | I27: 2405.7995
... C46: TSX:CS_2023_COO | D46: COO | E46: Capstone Copper Corp. | F46: President and COO | G46: Cashel Meagher | H46: 2267.46 | I46: 2340
D47: COO
C48: - | D48: COO | E48: - | F48: - | G48: - | H48: - | I48: -
C49: TSX:SSRM_2023_COO | D49: COO | E49: SSR Mining Inc. | F49: EVP Operations and Sustainability | G49: Bill MacNevin | H49: 2223.328 | I49: 2302.6526
C50: TSX:ELD_2023_COO | D50: COO | E50: Eldorado Gold Corporation | F50: Former EVP and COO | G50: Joseph Dick | H50: 2072.381 | I50: 2005.41
C51: TSX:IMG_2023_COO | D51: COO | E51: IAMGOLD Corporation | F51: COO | G51: Bruno Lemelin | H51: 1828.591 | I51: 1820
C52: TSX:OGC _2023_COO | D52: COO | E52: OceanaGold Corporation | F52: EVP and COO, Asia-Pacific | G52: Peter Sharpe | H52: 2167.4193 | I52: 2014.7115
C53: TSX:NGD_2023_COO | D53: COO | E53: New Gold Inc. | F53: EVP and COO | G53: Yohann Bouchard | H53: 2061.8701 | I53: 2156.25
C54: TSX:CG_2023_COO | D54: COO | E54: Centerra Gold Inc. | F54: EVP and COO | G54: Paul Chawrun | H54: 1882.428 | I54: 1854
C55: TSX:ERO_2023_COO | D55: COO | E55: Ero Copper Corp. | F55: President & COO | G55: Makko DeFilippo | H55: 2133.2462 | I55: 2133.2462
C56: TSX:PAAS_2023_Legal | D56: Legal | E56: Pan American Silver Corp. | F56: General Counsel | G56: Christopher Lemon | H56: 2497.875 | I56: 2383.1
C57: TSX:LUN_2023_Legal | D57: Legal | E57: Lundin Mining Corporation | F57: General Counsel | G57: Peter Brady | H57: 1940.0917 | I57: 1851.4828
C58: TSX:AGI_2023_Legal | D58: Legal | E58: Alamos Gold Inc. | F58: SVP, General Counsel | G58: Nils F. Engelstad | H58: 1262.2693 | I58: 1216.8289
C59: TSX:BTO_2023_Legal | D59: Legal | E59: B2Gold Corp. | F59: SVP Legal and Coporate Communications | G59: Randall Chatwin | H59: 2295 | I59: 2677.583
C60: TSX:CS_2023_Legal | D60: Legal | E60: Capstone Copper Corp. | F60: SVP, Risk, ESG, General Counsel and Corporate Secretary | G60: Wendy King | H60: 1365.885 | I60: 1411.15
... C64: TSX:IMG_2023_Legal | D64: Legal | E64: IAMGOLD Corporation | F64: SVP, General Counsel and Corporate Secretary | G64: Tim Bradburn | H64: 1301.413 | I64: 1288.56
D65: Legal
C66: - | D66: Legal | E66: - | F66: - | G66: - | H66: - | I66: -
C67: TSX:NGD_2023_Legal | D67: Legal | E67: New Gold Inc. | F67: VP, General Counsel and Corporate Secretary | G67: Sean Keating | H67: 1166.226 | I67: 1111.5
C68: TSX:CG_2023_Legal | D68: Legal | E68: Centerra Gold Inc. | F68: EVP and General Counsel | G68: Yousef Rehman | H68: 1448.853 | I68: 1446.25
C69: TSX:ERO_2023_Legal | D69: Legal | E69: Ero Copper Corp. | F69: SVP, General Counsel | G69: Deepk Hundal | H69: 1649.8666 | I69: 1468.2653
C70: TSX:K_2023_NEO2 | D70: NEO2 | E70: Kinross Gold Corporation | F70: EVP and COO | G70: Claude J.S. Schimper | H70: 2606.5798 | I70: 2479.9948 | J70: (NEO4)
C71: TSX:PAAS_2023_NEO2 | D71: NEO2 | E71: Pan American Silver Corp. | F71: General Counsel | G71: Christopher Lemon | H71: 2497.875 | I71: 2383.1
C72: TSX:LUN_2023_NEO2 | D72: NEO2 | E72: Lundin Mining Corporation | F72: EVP, Josemaria Project | G72: David Dicaire | H72: 2456.0346 | I72: 2417.469
C73: TSX:AGI_2023_NEO2 | D73: NEO2 | E73: Alamos Gold Inc. | F73: SVP, General Counsel | G73: Nils F. Engelstad | H73: 1262.2693 | I73: 1216.8289
C74: TSX:BTO_2023_NEO2 | D74: NEO2 | E74: B2Gold Corp. | F74: SVP, Operations and COO | G74: William Lytle | H74: 2887.5 | I74: 2887.5
C75: TSX:CS_2023_NEO2 | D75: NEO2 | E75: Capstone Copper Corp. | F75: SVP, Risk, ESG, General Counsel and Corporate Secretary | G75: Wendy King | H75: 1365.885 | I75: 1411.15
C76: NYSE:HL_2023_NEO2 | D76: NEO2 | E76: Hecla Mining Company | F76: VP, Corporate Development and Sustainability | G76: Robert D. Brown | H76: 1314.3561 | I76: 1528.2528
C77: TSX:SSRM_2023_NEO2 | D77: NEO2 | E77: SSR Mining Inc. | F77: EVP and Chief Legal Administrative Officer | G77: Michael J. Sparks | H77: 2270.4553 | I77: 2368.4427
C78: TSX:ELD_2023_NEO2 | D78: NEO2 | E78: Eldorado Gold Corporation | F78: EVP, General Counsel and Chief Compliance Officer | G78: Frank Herbert | H78: 1560.572 | I78: 1485
C79: TSX:IMG_2023_NEO2 | D79: NEO2 | E79: IAMGOLD Corporation | F79: SVP, General Counsel and Corporate Secretary | G79: Tim Bradburn | H79: 1301.413 | I79: 1288.56
C80: TSX:OGC _2023_NEO2 | D80: NEO2 | E80: OceanaGold Corporation | F80: EVP and COO, Americas | G80: David Londono | H80: 1698.7227 | I80: 1951.5433
C81: TSX:NGD_2023_NEO2 | D81: NEO2 | E81: New Gold Inc. | F81: EVP, Strategy and Business Development | G81: Ankit Shah | H81: 1470.592 | I81: 1530
C82: TSX:CG_2023_NEO2 | D82: NEO2 | E82: Centerra Gold Inc. | F82: EVP and General Counsel | G82: Yousef Rehman | H82: 1448.853 | I82: 1446.25
... C84: TSX:K_2023_Tech | D84: Tech | E84: Kinross Gold Corporation | F84: SVP and Chief Technical Officer | G84: William D. Dunford | H84: 1425.8389 | I84: 1282.4739
C85: TSX:PAAS_2023_Tech | D85: Tech | E85: - | F85: - | G85: - | H85: - | I85: -
C86: TSX:LUN_2023_Tech | D86: Tech | E86: - | F86: - | G86: - | H86: - | I86: -
C87: TSX:AGI_2023_Tech | D87: Tech | E87: Alamos Gold Inc. | F87: SVP, Technical Services | G87: Christopher Botswick | H87: 1269.5649 | I87: 1185.213
C88: TSX:BTO_2023_Tech | D88: Tech | E88: B2Gold Corp. | F88: SVP, Exploration | G88: Victor King | H88: 2440 | I88: 2904.1369
C89: TSX:CS_2023_Tech | D89: Tech | E89: - | F89: - | G89: - | H89: - | I89: -
C90: NYSE:HL_2023_Tech | D90: Tech | E90: - | F90: - | G90: - | H90: - | I90: -
C91: TSX:SSRM_2023_Tech | D91: Tech | E91: - | F91: - | G91: - | H91: - | I91: -
C92: TSX:ELD_2023_Tech | D92: Tech | E92: - | F92: - | G92: - | H92: - | I92: -
C93: TSX:IMG_2023_Tech | D93: Tech | E93: - | F93: - | G93: - | H93: - | I93: -
C94: TSX:OGC _2023_Tech | D94: Tech | E94: - | F94: - | G94: - | H94: - | I94: -
C95: TSX:NGD_2023_Tech | D95: Tech | E95: - | F95: - | G95: - | H95: - | I95: -
C96: TSX:CG_2023_Tech | D96: Tech | E96: - | F96: - | G96: - | H96: - | I96: -
C97: TSX:ERO_2023_Tech | D97: Tech | E97: Ero Copper Corp. | F97: Chief Geological Officer | G97: Michael Richard | H97: 1951.1002 | I97: 1695.071
C98: TSX:K_2023_NEO3 | D98: NEO3 | E98: Kinross Gold Corporation | F98: SVP and Chief Technical Officer | G98: William D. Dunford | H98: 1425.8389 | I98: 1282.4739 | J98: (NEO5)
C99: TSX:PAAS_2023_NEO3 | D99: NEO3 | E99: Pan American Silver Corp. | F99: SVP, Strategic Initiatives | G99: Sean McAleer | H99: 2225.729 | I99: 2157.1575
C100: TSX:LUN_2023_NEO3 | D100: NEO3 | E100: Lundin Mining Corporation | F100: General Counsel | G100: Peter Brady | H100: 1940.0917 | I100: 1851.4828
D101: NEO3
C102: - | D102: NEO3 | E102: - | F102: - | G102: - | H102: - | I102: -
C103: TSX:BTO_2023_NEO3 | D103: NEO3 | E103: B2Gold Corp. | F103: SVP Legal and Coporate Communications | G103: Randall Chatwin | H103: 2295 | I103: 2677.583
C104: TSX:CS_2023_NEO3 | D104: NEO3 | E104: Capstone Copper Corp. | F104: SVP, Strategy & Capital Markets | G104: Jerrold Annett | H104: 1289.861 | I104: 1313.8125
C105: NYSE:HL_2023_NEO3 | D105: NEO3 | E105: Hecla Mining Company | F105: VP and General Counsel | G105: David C. Sienko | H105: 1230.6887 | I105: 1488.8336
C106: TSX:SSRM_2023_NEO3 | D106: NEO3 | E106: SSR Mining Inc. | F106: EVP Operations and Sustainability | G106: Bill MacNevin | H106: 2223.328 | I106: 2302.6526
C107: TSX:ELD_2023_NEO3 | D107: NEO3 | E107: Eldorado Gold Corporation | F107: SVP and Chief Strategy & Commercial Officer | G107: Paul Ferneyhough | H107: 1345.573 | I107: 1341.912
C108: TSX:IMG_2023_NEO3 | D108: NEO3 | E108: IAMGOLD Corporation | F108: SVP, People | G108: Dorena Quinn | H108: 1135.969 | I108: 1121.2389
D109: NEO3
C110: - | D110: NEO3 | E110: - | F110: - | G110: - | H110: - | I110: -
C111: TSX:NGD_2023_NEO3 | D111: NEO3 | E111: New Gold Inc. | F111: VP, General Counsel and Corporate Secretary | G111: Sean Keating | H111: 1166.226 | I111: 1111.5
C112: TSX:CG_2023_NEO3 | D112: NEO3 | E112: Centerra Gold Inc. | F112: EVP, Human Resources and Info Tech | G112: Claudia D'Orazio | H112: 1408.401 | I112: 1397.5
C113: TSX:ERO_2023_NEO3 | D113: NEO3 | E113: Ero Copper Corp. | F113: SVP, General Counsel | G113: Deepk Hundal | H113: 1649.8666 | I113: 1468.2653

Sheet Pension Analysis
C1: COO | D1: F38 | E1: X38 | F1: X29 | H1: Y38 | I1: Y29
C2: Legal | D2: F27 | E2: X27 | F2: X18 | H2: Y27 | I2: Y18
D3: F39 | E3: X39 | F3: X30 | H3: Y39 | I3: Y30
C4: Role | D4: Incumbent | E4: Pension | F4: Peer Median | G4: Variance to Median | H4: Other Compensation | I4: Peer Median | J4: Variance to Median
C5: CEO | D5: {=INDIRECT("'"&$C5&"'!"&D$3)} -> Peter Kukielski | E5: {=INDIRECT("'"&$C5&"'!"&E$3)} -> 122.042 | F5: {=INDIRECT("'"&$C5&"'!"&F$3)} -> 263.96897 | G5: =E5/F5-1 -> -0.53766536 | H5: {=INDIRECT("'"&$C5&"'!"&H$3)} -> 255.034 | I5: {=INDIRECT("'"&$C5&"'!"&I$3)} -> 54.95 | J5: =H5/I5-1 -> 3.6412011
C6: CFO | D6: {=INDIRECT("'"&$C6&"'!"&D$3)} -> Eugene Lei | E6: {=INDIRECT("'"&$C6&"'!"&E$3)} -> 132.222 | F6: {=INDIRECT("'"&$C6&"'!"&F$3)} -> 93.574 | G6: =E6/F6-1 -> 0.41302071 | H6: {=INDIRECT("'"&$C6&"'!"&H$3)} -> 103.501 | I6: {=INDIRECT("'"&$C6&"'!"&I$3)} -> 32.15652 | J6: =H6/I6-1 -> 2.218663
C7: COO | D7: {=INDIRECT("'"&$C7&"'!"&D$1)} -> Andre Lauzon | E7: {=INDIRECT("'"&$C7&"'!"&E$1)} -> 74.4 | F7: {=INDIRECT("'"&$C7&"'!"&F$1)} -> 114.576 | G7: =E7/F7-1 -> -0.35064935 | H7: {=INDIRECT("'"&$C7&"'!"&H$1)} -> 85.127 | I7: {=INDIRECT("'"&$C7&"'!"&I$1)} -> 39.064917 | J7: =H7/I7-1 -> 1.1791164
C8: Legal | D8: {=INDIRECT("'"&$C8&"'!"&D$2)} -> Patrick Donnelly | E8: {=INDIRECT("'"&$C8&"'!"&E$2)} -> 122.673 | F8: {=INDIRECT("'"&$C8&"'!"&F$2)} -> 86.895 | G8: =E8/F8-1 -> 0.4117383 | H8: {=INDIRECT("'"&$C8&"'!"&H$2)} -> 84.863 | I8: {=INDIRECT("'"&$C8&"'!"&I$2)} -> 54.7155 | J8: =H8/I8-1 -> 0.55098647
C9: NEO4 | D9: {=INDIRECT("'"&$C9&"'!"&D$3)} -> Patrick Donnelly | E9: {=INDIRECT("'"&$C9&"'!"&E$3)} -> 122.673 | F9: {=INDIRECT("'"&$C9&"'!"&F$3)} -> 87.84 | G9: =E9/F9-1 -> 0.39655055 | H9: {=INDIRECT("'"&$C9&"'!"&H$3)} -> 84.863 | I9: {=INDIRECT("'"&$C9&"'!"&I$3)} -> 29.806678 | J9: =H9/I9-1 -> 1.8471136
C10: NEO5 | D10: {=INDIRECT("'"&$C10&"'!"&D$3)} -> Javier Del Rio | E10: {=INDIRECT("'"&$C10&"'!"&E$3)} -> 18.435637 | F10: {=INDIRECT("'"&$C10&"'!"&F$3)} -> 85.1645 | G10: =E10/F10-1 -> -0.78352908 | H10: {=INDIRECT("'"&$C10&"'!"&H$3)} -> 101.602 | I10: {=INDIRECT("'"&$C10&"'!"&I$3)} -> 38.710768 | J10: =H10/I10-1 -> 1.6246444

Sheet Target Comp
B6: Executive | C6: Role | D6: Base Salary | E6: Target STIP (%) | F6: Target STIP ($) | G6: Target Total ($) | H6: Target LTIP (%) | I6: Target LTIP ($) | J6: Target TDC ($) | K6: 2024 Target TDC | M6: 2024 Target | N6: Increase YoY
B7: Peter Kukielski | C7: President & CEO | D7: ='Raw Data'!P32/1000 -> 1047.525 | E7: ='Raw Data'!W32 -> 1.2 | F7: =E7*D7 -> 1257.03 | G7: =SUM(F7,D7) -> 2304.555 | H7: ='Raw Data'!AI32 -> 2.65 | I7: =H7*D7 -> 2775.9413 | J7: =I7+G7 -> 5080.4963 | K7: =TEXT(M7,"$0,000")&TEXT(N7," (+0%)") -> $4,780 (+6%) | M7: 4780 | N7: =J7/M7-1 -> 0.062865324
B8: Eugene Lei | C8: CFO | D8: ='Raw Data'!P38/1000 -> 573.681 | E8: ='Raw Data'!W38 -> 0.9 | F8: =E8*D8 -> 516.3129 | G8: =SUM(F8,D8) -> 1089.9939 | H8: ='Raw Data'!AI38 -> 1.7 | I8: =H8*D8 -> 975.2577 | J8: =I8+G8 -> 2065.2516 | K8: =TEXT(M8,"$0,000")&TEXT(N8," (+0%)") -> $1,931 (+7%) | M8: 1931 | N8: =J8/M8-1 -> 0.069524392
B9: Andre Lauzon | C9: COO | D9: ='Raw Data'!P35/1000 -> 651 | E9: ='Raw Data'!W35 -> 0.9 | F9: =E9*D9 -> 585.9 | G9: =SUM(F9,D9) -> 1236.9 | H9: ='Raw Data'!AI35 -> 1.7 | I9: =H9*D9 -> 1106.7 | J9: =I9+G9 -> 2343.6 | K9: =TEXT(M9,"$0,000")&TEXT(N9," (+0%)") -> $2,232 (+5%) | M9: 2232 | N9: =J9/M9-1 -> 0.05
B10: Patrick Donnelly | C10: SVP, Legal & Organizational Effectiveness | D10: ='Raw Data'!P41/1000 -> 501.659 | E10: ='Raw Data'!W41 -> 0.75 | F10: =E10*D10 -> 376.24425 | G10: =SUM(F10,D10) -> 877.90325 | H10: ='Raw Data'!AI41 -> 1.5 | I10: =H10*D10 -> 752.4885 | J10: =I10+G10 -> 1630.3917 | K10: =TEXT(M10,"$0,000")&TEXT(N10," (+0%)") -> $1,583 (+3%) | M10: 1583 | N10: =J10/M10-1 -> 0.029937934
B11: Javier Del Rio1 | C11: SVP, US | D11: ='Raw Data'!P44/1000 -> 606.75786 | E11: ='Raw Data'!W44 -> 0.6 | F11: =E11*D11 -> 364.05472 | G11: =SUM(F11,D11) -> 970.81258 | H11: ='Raw Data'!AI44 -> 1.2 | I11: =H11*D11 -> 728.10943 | J11: =I11+G11 -> 1698.922 | K11: =TEXT(M11,"$0,000")&TEXT(N11," (+0%)") -> $1,532 (+11%) | M11: 1532 | N11: =J11/M11-1 -> 0.10895693
B12: Olivier Tavchandjian | C12: SVP, Exploration and Technical Services | D12: ='Raw Data'!P47/1000 -> 465.85 | E12: ='Raw Data'!W47 -> 0.6 | F12: =E12*D12 -> 279.51 | G12: =SUM(F12,D12) -> 745.36 | H12: ='Raw Data'!AI47 -> 1.2 | I12: =H12*D12 -> 559.02 | J12: =I12+G12 -> 1304.38 | K12: =TEXT(M12,"$0,000")&TEXT(N12," (+0%)") -> $1,101 (+18%) | M12: 1101 | N12: =J12/M12-1 -> 0.18472298
B13: Rob Carter | C13: SVP, Canada | D13: ='Raw Data'!P50/1000 -> 453.5 | E13: ='Raw Data'!W50 -> 0.6 | F13: =E13*D13 -> 272.1 | G13: =SUM(F13,D13) -> 725.6 | H13: ='Raw Data'!AI50 -> 1.2 | I13: =H13*D13 -> 544.2 | J13: =I13+G13 -> 1269.8 | K13: =TEXT(M13,"$000")&TEXT(N13," (+0%)") -> $954 (+33%) | M13: 954 | N13: =J13/M13-1 -> 0.33102725

Sheet Raw Data
C2: INPUTS
AN3: Check with client team 1) whether this benchmarking is necessary and 2) how to treat pension & other in the output tables (i.e., actual, 3-year average)
C4: Peer Ticker(s) | F4: Date | G4: 45852
C5: 1 | D5: TSX:K | F5: Currency | G5: CAD
C6: 2 | D6: TSX:LUN | F6: Client Ticker | G6: TSX:HBM
C7: 3 | D7: TSX:AGI
C8: 4 | D8: TSX:PAAS | F8: CAD/USD
C9: 5 | D9: TSX:CS | F9: 2024 | G9: =_xll.ciqfunctions.udf.CIQAVG("$CADUSD", "IQ_LASTSALEPRICE", "1/1/"&$F9, "31/12/"&$F9) -> 1.37017
C10: 6 | D10: TSX:IMG | F10: =F9-1 -> 2023 | G10: =_xll.ciqfunctions.udf.CIQAVG("$CADUSD", "IQ_LASTSALEPRICE", "1/1/"&$F10, "31/12/"&$F10) -> 1.34954
C11: 7 | D11: TSX:BTO | F11: =F10-1 -> 2022 | G11: =_xll.ciqfunctions.udf.CIQAVG("$CADUSD", "IQ_LASTSALEPRICE", "1/1/"&$F11, "31/12/"&$F11) -> 1.30175
C12: 8 | D12: NYSE:HL
C13: 9 | D13: TSX:NGD | F13: Data Aging: | G13: 0.03
C14: 10 | D14: TSX:ELD
C15: 11 | D15: TSX:SSRM
C16: 12 | D16: TSX:OGC
C17: 13 | D17: TSX:ERO
C18: 14 | D18: TSX:CG
C19: 15 | E19: =COUNTA(D5:D18) -> 14
C20: 16
C21: 17
C22: 18
C23: 19
C24: 20
C25: 21
C26: 22
C27: 23
C28: 24
O30: Base Salary | S30: STIP | Y30: Total Cash Compensation | AA30: Long-Term Incentives | AL30: Total Direct Compensation | AN30: Pension & Other | AU30: Total Compensation
A31: Look-Up2 | B31: Look-Up | C31: Ticker | D31: Company | E31: Year | F31: Incumbent Start Month | G31: End Month (Typically FYE) | H31: Months | I31: Currency of Disclosure | J31: FX Rate | K31: Role Match | L31: Position Match | M31: Position Title | N31: Incumbent | O31: Actual Paid | P31: Annualized / Converted | Q31: Latest (if disclosed) | R31: Latest (if disclosed) - Annualized / Converted | S31: Actual $ | T31: Annualized/ Converted | U31: Actual STI % | V31: 3 Year Average STIP % | W31: Target STI % | X31: Target STI $ | Y31: Actual TCC | Z31: Target TCC | AA31: RSUs | AB31: PSUs | AC31: Stock Options | AD31: DSUs | AE31: LT Cash | AF31: Total LTI $ | AG31: Total LTI % | AH31: 3 Year Average LTIP % | AI31: Target LTI % | AJ31: Target LTI $ | AK31: Total LTI (Converted) | AL31: Actual (base + actual bonus + actual LTIP) | AM31: Target (base + target bonus + Target LTIP) | AN31: Pension | AO31: DB or DC Pension? | AP31: Pension Converted | AQ31: Pension 3 Year Average | AR31: Other | AS31: Other Converted | AT31: Other 3 Year Average | AU31: Actual (Actual TDC + Pension + Other) | AV31: Target (Target TDC + Pension + Other) | AW31: Incumbent Specific Notes: | AX31: Data Recorder | AY31: Peer Reviewer
A32: =$C32&"_"&$E32&"_"&$K32 -> TSX:HBM_2024_ | B32: =$C32&"_"&$E32&"_"&$L32 -> TSX:HBM_2024_CEO | C32: =G6 -> TSX:HBM | D32: =_xll.ciqfunctions.udf.CIQ(C32,"IQ_Company_Name") -> Hudbay Minerals Inc. | E32: 2024 | F32: =E32&"-01-01" -> 2024-01-01 | G32: =E32&"-12-31" -> 2024-12-31 | H32: =_xlfn.DAYS(G32,F32)/_xlfn.DAYS(E32&"-12-31",E32&"-01-01")*12 -> 12 | I32: =$G$5 -> CAD | J32: =IF($I32="CAD",1,IF($I32="USD",VLOOKUP($E32,$F$9:$G$11,2,FALSE),"N/A")) -> 1 | L32: CEO | M32: President & CEO | N32: Peter Kukielski | O32: 1047525 | P32: =IFERROR(O32*(12/$H32)*$J32,"-") -> 1047525 | R32: =IFERROR(IF((Q32*$L32)=0,"-",(Q32*$L32)),"-") -> - | S32: 1632919 | T32: =IFERROR(S32*(12/$H32)*$J32,"-") -> 1632919 | U32: =IFERROR($T32/$P32,"-") -> 1.5588353 | V32: =IFERROR(AVERAGE(U32:U34),"N/A") -> 1.5588353 | W32: 1.2 | X32: =IFERROR(IF(ISNUMBER($W32)=TRUE, $W32*$P32,$V32*$P32),"-") -> 1257030 | Y32: =IFERROR(IF(SUM(P32,T32)=0,"-",SUM(P32,T32)),"-") -> 2680444 | Z32: =IFERROR(IF(SUM(P32,X32)=0,"-",SUM(P32,X32)),"-") -> 2304555 | AB32: 1906903 | AC32: 635634 | AD32: - | AE32: - | AF32: =IFERROR(IF(SUM(AA32:AE32)=0,IF(COUNTIF($AA32:$AE32,"=0")>0,"$0","-"),SUM(AA32:AE32)),"-") -> 2542537 | AG32: =IFERROR($AK32/$P32,"-") -> 2.427185 | AH32: =IFERROR(AVERAGE(AG32:AG34),"N/A") -> 2.427185 | AI32: 2.65 | AJ32: =IFERROR(IF(ISNUMBER($AI32)=TRUE, $AI32*$P32, $AH32*$P32), "-") -> 2775941.2 | AK32: =IFERROR($AF32*$J32,"-") -> 2542537 | AL32: =IFERROR(IF(SUM(Y32,AK32)=0,"-",SUM(Y32,AK32)),"-") -> 5222981 | AM32: =IFERROR(IF(SUM($Z32,$AJ32)=0,"-",SUM($Z32,$AJ32)),"-") -> 5080496.2 | AN32: 122042 | AO32: DC | AP32: =IFERROR(AN32*(12/$H32)*$J32,"-") -> 122042 | AQ32: =IFERROR(AVERAGE(AP32:AP34),"N/A") -> 118074.67 | AR32: 255034 | AS32: =IFERROR(AR32*(12/$H32)*$J32,"-") -> 255034 | AT32: =IFERROR(AVERAGE(AS32:AS34),"N/A") -> 245312.67 | AU32: =IFERROR(IF(SUM(AL32,AP32,AS32)=0,"-",SUM(AL32,AP32,AS32)),"-") -> 5600057 | AV32: =IFERROR(IF(SUM(AM32,AP32,AS32)=0,"-",SUM(AM32,AP32,AS32)),"-") -> 5457572.2 | AW32: - | AX32: AH
A33: =$C33&"_"&$E33&"_"&$K33 -> TSX:HBM_2023_ | B33: =$C33&"_"&$E33&"_"&$L33 -> TSX:HBM_2023_CEO | C33: =C32 -> TSX:HBM | D33: =_xll.ciqfunctions.udf.CIQ(C33,"IQ_Company_Name") -> Hudbay Minerals Inc. | E33: 2023 | F33: =E33&"-01-01" -> 2023-01-01 | G33: =E33&"-12-31" -> 2023-12-31 | H33: =_xlfn.DAYS(G33,F33)/_xlfn.DAYS(E33&"-12-31",E33&"-01-01")*12 -> 12 | I33: =I32 -> CAD | J33: =IF($I33="CAD",1,IF($I33="USD",VLOOKUP($E33,$F$9:$G$11,2,FALSE),"N/A")) -> 1 | L33: =L32 -> CEO | M33: =M32 -> President & CEO | N33: =N32 -> Peter Kukielski | P33: =IFERROR(O33*(12/$H33)*$J33,"-") -> 0 | R33: =IFERROR(IF((Q33*$L33)=0,"-",(Q33*$L33)),"-") -> - | T33: =IFERROR(S33*(12/$H33)*$J33,"-") -> 0 | U33: =IFERROR($T33/$P33,"-") -> - | X33: =IFERROR(IF(ISNUMBER($W33)=TRUE, $W33*$P33,$V33*$P33),"-") -> 0 | Y33: =IFERROR(IF(SUM(P33,T33)=0,"-",SUM(P33,T33)),"-") -> - | Z33: =IFERROR(IF(SUM(P33,X33)=0,"-",SUM(P33,X33)),"-") -> - | AD33: - | AE33: - | AF33: =IFERROR(IF(SUM(AA33:AE33)=0,IF(COUNTIF($AA33:$AE33,"=0")>0,"$0","-"),SUM(AA33:AE33)),"-") -> - | AG33: =IFERROR($AK33/$P33,"-") -> - | AJ33: =IFERROR(IF(ISNUMBER($AI33)=TRUE, $AI33*$P33, $AH33*$P33), "-") -> 0 | AK33: =IFERROR($AF33*$J33,"-") -> - | AL33: =IFERROR(IF(SUM(Y33,AK33)=0,"-",SUM(Y33,AK33)),"-") -> - | AM33: =IFERROR(IF(SUM($Z33,$AJ33)=0,"-",SUM($Z33,$AJ33)),"-") -> - | AN33: 119348 | AO33: DC | AP33: =IFERROR(AN33*(12/$H33)*$J33,"-") -> 119348 | AR33: 275237 | AS33: =IFERROR(AR33*(12/$H33)*$J33,"-") -> 275237 | AU33: =IFERROR(IF(SUM(AL33,AP33,AS33)=0,"-",SUM(AL33,AP33,AS33)),"-") -> 394585 | AV33: =IFERROR(IF(SUM(AM33,AP33,AS33)=0,"-",SUM(AM33,AP33,AS33)),"-") -> 394585 | AW33: -
A34: =$C34&"_"&$E34&"_"&$K34 -> TSX:HBM_2022_ | B34: =$C34&"_"&$E34&"_"&$L34 -> TSX:HBM_2022_CEO | C34: =C33 -> TSX:HBM | D34: =_xll.ciqfunctions.udf.CIQ(C34,"IQ_Company_Name") -> Hudbay Minerals Inc. | E34: 2022 | F34: =E34&"-01-01" -> 2022-01-01 | G34: =E34&"-12-31" -> 2022-12-31 | H34: =_xlfn.DAYS(G34,F34)/_xlfn.DAYS(E34&"-12-31",E34&"-01-01")*12 -> 12 | I34: =I33 -> CAD | J34: =IF($I34="CAD",1,IF($I34="USD",VLOOKUP($E34,$F$9:$G$11,2,FALSE),"N/A")) -> 1 | L34: =L33 -> CEO | M34: =M33 -> President & CEO | N34: =N33 -> Peter Kukielski | P34: =IFERROR(O34*(12/$H34)*$J34,"-") -> 0 | R34: =IFERROR(IF((Q34*$L34)=0,"-",(Q34*$L34)),"-") -> - | T34: =IFERROR(S34*(12/$H34)*$J34,"-") -> 0 | U34: =IFERROR($T34/$P34,"-") -> - | X34: =IFERROR(IF(ISNUMBER($W34)=TRUE, $W34*$P34,$V34*$P34),"-") -> 0 | Y34: =IFERROR(IF(SUM(P34,T34)=0,"-",SUM(P34,T34)),"-") -> - | Z34: =IFERROR(IF(SUM(P34,X34)=0,"-",SUM(P34,X34)),"-") -> - | AD34: - | AE34: - | AF34: =IFERROR(IF(SUM(AA34:AE34)=0,IF(COUNTIF($AA34:$AE34,"=0")>0,"$0","-"),SUM(AA34:AE34)),"-") -> - | AG34: =IFERROR($AK34/$P34,"-") -> - | AJ34: =IFERROR(IF(ISNUMBER($AI34)=TRUE, $AI34*$P34, $AH34*$P34), "-") -> 0 | AK34: =IFERROR($AF34*$J34,"-") -> - | AL34: =IFERROR(IF(SUM(Y34,AK34)=0,"-",SUM(Y34,AK34)),"-") -> - | AM34: =IFERROR(IF(SUM($Z34,$AJ34)=0,"-",SUM($Z34,$AJ34)),"-") -> - | AN34: 112834 | AO34: DC | AP34: =IFERROR(AN34*(12/$H34)*$J34,"-") -> 112834 | AR34: 205667 | AS34: =IFERROR(AR34*(12/$H34)*$J34,"-") -> 205667 | AU34: =IFERROR(IF(SUM(AL34,AP34,AS34)=0,"-",SUM(AL34,AP34,AS34)),"-") -> 318501 | AV34: =IFERROR(IF(SUM(AM34,AP34,AS34)=0,"-",SUM(AM34,AP34,AS34)),"-") -> 318501 | AW34: -
A35: =$C35&"_"&$E35&"_"&$K35 -> TSX:HBM_2024_COO | B35: =$C35&"_"&$E35&"_"&$L35 -> TSX:HBM_2024_NEO1 | C35: =C34 -> TSX:HBM | D35: =_xll.ciqfunctions.udf.CIQ(C35,"IQ_Company_Name") -> Hudbay Minerals Inc. | E35: =E32 -> 2024 | F35: =E35&"-01-01" -> 2024-01-01 | G35: =E35&"-12-31" -> 2024-12-31 | H35: =_xlfn.DAYS(G35,F35)/_xlfn.DAYS(E35&"-12-31",E35&"-01-01")*12 -> 12 | I35: =I34 -> CAD | J35: =IF($I35="CAD",1,IF($I35="USD",VLOOKUP($E35,$F$9:$G$11,2,FALSE),"N/A")) -> 1 | K35: COO | L35: NEO1 | M35: COO | N35: Andre Lauzon | O35: 651000 | P35: =IFERROR(O35*(12/$H35)*$J35,"-") -> 651000 | R35: =IFERROR(IF((Q35*$L35)=0,"-",(Q35*$L35)),"-") -> - | S35: 740466 | T35: =IFERROR(S35*(12/$H35)*$J35,"-") -> 740466 | U35: =IFERROR($T35/$P35,"-") -> 1.1374286 | V35: =IFERROR(AVERAGE(U35:U37),"N/A") -> 1.1374286 | W35: 0.9 | X35: =IFERROR(IF(ISNUMBER($W35)=TRUE, $W35*$P35,$V35*$P35),"-") -> 585900 | Y35: =IFERROR(IF(SUM(P35,T35)=0,"-",SUM(P35,T35)),"-") -> 1391466 | Z35: =IFERROR(IF(SUM(P35,X35)=0,"-",SUM(P35,X35)),"-") -> 1236900 | AB35: 790500 | AC35: 263500 | AD35: - | AE35: - | AF35: =IFERROR(IF(SUM(AA35:AE35)=0,IF(COUNTIF($AA35:$AE35,"=0")>0,"$0","-"),SUM(AA35:AE35)),"-") -> 1054000 | AG35: =IFERROR($AK35/$P35,"-") -> 1.6190476 | AH35: =IFERROR(AVERAGE(AG35:AG37),"N/A") -> 1.6190476 | AI35: 1.7 | AJ35: =IFERROR(IF(ISNUMBER($AI35)=TRUE, $AI35*$P35, $AH35*$P35), "-") -> 1106700 | AK35: =IFERROR($AF35*$J35,"-") -> 1054000 | AL35: =IFERROR(IF(SUM(Y35,AK35)=0,"-",SUM(Y35,AK35)),"-") -> 2445466 | AM35: =IFERROR(IF(SUM($Z35,$AJ35)=0,"-",SUM($Z35,$AJ35)),"-") -> 2343600 | AN35: 74400 | AO35: DC | AP35: =IFERROR(AN35*(12/$H35)*$J35,"-") -> 74400 | AQ35: =IFERROR(AVERAGE(AP35:AP37),"N/A") -> 67856 | AR35: 85127 | AS35: =IFERROR(AR35*(12/$H35)*$J35,"-") -> 85127 | AT35: =IFERROR(AVERAGE(AS35:AS37),"N/A") -> 196002.67 | AU35: =IFERROR(IF(SUM(AL35,AP35,AS35)=0,"-",SUM(AL35,AP35,AS35)),"-") -> 2604993 | AV35: =IFERROR(IF(SUM(AM35,AP35,AS35)=0,"-",SUM(AM35,AP35,AS35)),"-") -> 2503127 | AW35: - | AX35: AH
A36: =$C36&"_"&$E36&"_"&$K36 -> TSX:HBM_2023_COO | B36: =$C36&"_"&$E36&"_"&$L36 -> TSX:HBM_2023_NEO1 | C36: =C35 -> TSX:HBM | D36: =_xll.ciqfunctions.udf.CIQ(C36,"IQ_Company_Name") -> Hudbay Minerals Inc. | E36: =E33 -> 2023 | F36: =E36&"-01-01" -> 2023-01-01 | G36: =E36&"-12-31" -> 2023-12-31 | H36: =_xlfn.DAYS(G36,F36)/_xlfn.DAYS(E36&"-12-31",E36&"-01-01")*12 -> 12 | I36: =I35 -> CAD | J36: =IF($I36="CAD",1,IF($I36="USD",VLOOKUP($E36,$F$9:$G$11,2,FALSE),"N/A")) -> 1 | K36: COO | L36: =L35 -> NEO1 | M36: =M35 -> COO | N36: =N35 -> Andre Lauzon | P36: =IFERROR(O36*(12/$H36)*$J36,"-") -> 0 | R36: =IFERROR(IF((Q36*$L36)=0,"-",(Q36*$L36)),"-") -> - | T36: =IFERROR(S36*(12/$H36)*$J36,"-") -> 0 | U36: =IFERROR($T36/$P36,"-") -> - | X36: =IFERROR(IF(ISNUMBER($W36)=TRUE, $W36*$P36,$V36*$P36),"-") -> 0 | Y36: =IFERROR(IF(SUM(P36,T36)=0,"-",SUM(P36,T36)),"-") -> - | Z36: =IFERROR(IF(SUM(P36,X36)=0,"-",SUM(P36,X36)),"-") -> - | AD36: - | AE36: - | AF36: =IFERROR(IF(SUM(AA36:AE36)=0,IF(COUNTIF($AA36:$AE36,"=0")>0,"$0","-"),SUM(AA36:AE36)),"-") -> - | AG36: =IFERROR($AK36/$P36,"-") -> - | AJ36: =IFERROR(IF(ISNUMBER($AI36)=TRUE, $AI36*$P36, $AH36*$P36), "-") -> 0 | AK36: =IFERROR($AF36*$J36,"-") -> - | AL36: =IFERROR(IF(SUM(Y36,AK36)=0,"-",SUM(Y36,AK36)),"-") -> - | AM36: =IFERROR(IF(SUM($Z36,$AJ36)=0,"-",SUM($Z36,$AJ36)),"-") -> - | AN36: 66768 | AO36: DC | AP36: =IFERROR(AN36*(12/$H36)*$J36,"-") -> 66768 | AR36: 179092 | AS36: =IFERROR(AR36*(12/$H36)*$J36,"-") -> 179092 | AU36: =IFERROR(IF(SUM(AL36,AP36,AS36)=0,"-",SUM(AL36,AP36,AS36)),"-") -> 245860 | AV36: =IFERROR(IF(SUM(AM36,AP36,AS36)=0,"-",SUM(AM36,AP36,AS36)),"-") -> 245860 | AW36: -
A37: =$C37&"_"&$E37&"_"&$K37 -> TSX:HBM_2022_COO | B37: =$C37&"_"&$E37&"_"&$L37 -> TSX:HBM_2022_NEO1 | C37: =C36 -> TSX:HBM | D37: =_xll.ciqfunctions.udf.CIQ(C37,"IQ_Company_Name") -> Hudbay Minerals Inc. | E37: =E34 -> 2022 | F37: =E37&"-01-01" -> 2022-01-01 | G37: =E37&"-12-31" -> 2022-12-31 | H37: =_xlfn.DAYS(G37,F37)/_xlfn.DAYS(E37&"-12-31",E37&"-01-01")*12 -> 12 | I37: =I36 -> CAD | J37: =IF($I37="CAD",1,IF($I37="USD",VLOOKUP($E37,$F$9:$G$11,2,FALSE),"N/A")) -> 1 | K37: COO | L37: =L36 -> NEO1 | M37: =M36 -> COO | N37: =N36 -> Andre Lauzon | P37: =IFERROR(O37*(12/$H37)*$J37,"-") -> 0 | R37: =IFERROR(IF((Q37*$L37)=0,"-",(Q37*$L37)),"-") -> - | T37: =IFERROR(S37*(12/$H37)*$J37,"-") -> 0 | U37: =IFERROR($T37/$P37,"-") -> - | X37: =IFERROR(IF(ISNUMBER($W37)=TRUE, $W37*$P37,$V37*$P37),"-") -> 0 | Y37: =IFERROR(IF(SUM(P37,T37)=0,"-",SUM(P37,T37)),"-") -> - | Z37: =IFERROR(IF(SUM(P37,X37)=0,"-",SUM(P37,X37)),"-") -> - | AD37: - | AE37: - | AF37: =IFERROR(IF(SUM(AA37:AE37)=0,IF(COUNTIF($AA37:$AE37,"=0")>0,"$0","-"),SUM(AA37:AE37)),"-") -> - | AG37: =IFERROR($AK37/$P37,"-") -> - | AJ37: =IFERROR(IF(ISNUMBER($AI37)=TRUE, $AI37*$P37, $AH37*$P37), "-") -> 0 | AK37: =IFERROR($AF37*$J37,"-") -> - | AL37: =IFERROR(IF(SUM(Y37,AK37)=0,"-",SUM(Y37,AK37)),"-") -> - | AM37: =IFERROR(IF(SUM($Z37,$AJ37)=0,"-",SUM($Z37,$AJ37)),"-") -> - | AN37: 62400 | AO37: DC | AP37: =IFERROR(AN37*(12/$H37)*$J37,"-") -> 62400 | AR37: 323789 | AS37: =IFERROR(AR37*(12/$H37)*$J37,"-") -> 323789 | AU37: =IFERROR(IF(SUM(AL37,AP37,AS37)=0,"-",SUM(AL37,AP37,AS37)),"-") -> 386189 | AV37: =IFERROR(IF(SUM(AM37,AP37,AS37)=0,"-",SUM(AM37,AP37,AS37)),"-") -> 386189 | AW37: -
A38: =$C38&"_"&$E38&"_"&$K38 -> TSX:HBM_2024_ | B38: =$C38&"_"&$E38&"_"&$L38 -> TSX:HBM_2024_CFO | C38: =C37 -> TSX:HBM | D38: =_xll.ciqfunctions.udf.CIQ(C38,"IQ_Company_Name") -> Hudbay Minerals Inc. | E38: =E35 -> 2024 | F38: =E38&"-01-01" -> 2024-01-01 | G38: =E38&"-12-31" -> 2024-12-31 | H38: =_xlfn.DAYS(G38,F38)/_xlfn.DAYS(E38&"-12-31",E38&"-01-01")*12 -> 12 | I38: =I37 -> CAD | J38: =IF($I38="CAD",1,IF($I38="USD",VLOOKUP($E38,$F$9:$G$11,2,FALSE),"N/A")) -> 1 | L38: CFO | M38: CFO | N38: Eugene Lei | O38: 573681 | P38: =IFERROR(O38*(12/$H38)*$J38,"-") -> 573681 | R38: =IFERROR(IF((Q38*$L38)=0,"-",(Q38*$L38)),"-") -> - | S38: 658795 | T38: =IFERROR(S38*(12/$H38)*$J38,"-") -> 658795 | U38: =IFERROR($T38/$P38,"-") -> 1.1483647 | V38: =IFERROR(AVERAGE(U38:U40),"N/A") -> 1.1483647 | W38: 0.9 | X38: =IFERROR(IF(ISNUMBER($W38)=TRUE, $W38*$P38,$V38*$P38),"-") -> 516312.9 | Y38: =IFERROR(IF(SUM(P38,T38)=0,"-",SUM(P38,T38)),"-") -> 1232476 | Z38: =IFERROR(IF(SUM(P38,X38)=0,"-",SUM(P38,X38)),"-") -> 1089993.9 | AB38: 661939 | AC38: 220646 | AD38: - | AE38: - | AF38: =IFERROR(IF(SUM(AA38:AE38)=0,IF(COUNTIF($AA38:$AE38,"=0")>0,"$0","-"),SUM(AA38:AE38)),"-") -> 882585 | AG38: =IFERROR($AK38/$P38,"-") -> 1.5384595 | AH38: =IFERROR(AVERAGE(AG38:AG40),"N/A") -> 1.5384595 | AI38: 1.7 | AJ38: =IFERROR(IF(ISNUMBER($AI38)=TRUE, $AI38*$P38, $AH38*$P38), "-") -> 975257.7 | AK38: =IFERROR($AF38*$J38,"-") -> 882585 | AL38: =IFERROR(IF(SUM(Y38,AK38)=0,"-",SUM(Y38,AK38)),"-") -> 2115061 | AM38: =IFERROR(IF(SUM($Z38,$AJ38)=0,"-",SUM($Z38,$AJ38)),"-") -> 2065251.6 | AN38: 132222 | AO38: DB & DC | AP38: =IFERROR(AN38*(12/$H38)*$J38,"-") -> 132222 | AQ38: =IFERROR(AVERAGE(AP38:AP40),"N/A") -> 157909.67 | AR38: 103501 | AS38: =IFERROR(AR38*(12/$H38)*$J38,"-") -> 103501 | AT38: =IFERROR(AVERAGE(AS38:AS40),"N/A") -> 119085.67 | AU38: =IFERROR(IF(SUM(AL38,AP38,AS38)=0,"-",SUM(AL38,AP38,AS38)),"-") -> 2350784 | AV38: =IFERROR(IF(SUM(AM38,AP38,AS38)=0,"-",SUM(AM38,AP38,AS38)),"-") -> 2300974.6 | AW38: - | AX38: AH
A39: =$C39&"_"&$E39&"_"&$K39 -> TSX:HBM_2023_ | B39: =$C39&"_"&$E39&"_"&$L39 -> TSX:HBM_2023_CFO | C39: =C38 -> TSX:HBM | D39: =_xll.ciqfunctions.udf.CIQ(C39,"IQ_Company_Name") -> Hudbay Minerals Inc. | E39: =E36 -> 2023 | F39: =E39&"-01-01" -> 2023-01-01 | G39: =E39&"-12-31" -> 2023-12-31 | H39: =_xlfn.DAYS(G39,F39)/_xlfn.DAYS(E39&"-12-31",E39&"-01-01")*12 -> 12 | I39: =I38 -> CAD | J39: =IF($I39="CAD",1,IF($I39="USD",VLOOKUP($E39,$F$9:$G$11,2,FALSE),"N/A")) -> 1 | L39: =L38 -> CFO | M39: =M38 -> CFO | N39: =N38 -> Eugene Lei | P39: =IFERROR(O39*(12/$H39)*$J39,"-") -> 0 | R39: =IFERROR(IF((Q39*$L39)=0,"-",(Q39*$L39)),"-") -> - | T39: =IFERROR(S39*(12/$H39)*$J39,"-") -> 0 | U39: =IFERROR($T39/$P39,"-") -> - | X39: =IFERROR(IF(ISNUMBER($W39)=TRUE, $W39*$P39,$V39*$P39),"-") -> 0 | Y39: =IFERROR(IF(SUM(P39,T39)=0,"-",SUM(P39,T39)),"-") -> - | Z39: =IFERROR(IF(SUM(P39,X39)=0,"-",SUM(P39,X39)),"-") -> - | AD39: - | AE39: - | AF39: =IFERROR(IF(SUM(AA39:AE39)=0,IF(COUNTIF($AA39:$AE39,"=0")>0,"$0","-"),SUM(AA39:AE39)),"-") -> - | AG39: =IFERROR($AK39/$P39,"-") -> - | AJ39: =IFERROR(IF(ISNUMBER($AI39)=TRUE, $AI39*$P39, $AH39*$P39), "-") -> 0 | AK39: =IFERROR($AF39*$J39,"-") -> - | AL39: =IFERROR(IF(SUM(Y39,AK39)=0,"-",SUM(Y39,AK39)),"-") -> - | AM39: =IFERROR(IF(SUM($Z39,$AJ39)=0,"-",SUM($Z39,$AJ39)),"-") -> - | AN39: 108961 | AO39: DB & DC | AP39: =IFERROR(AN39*(12/$H39)*$J39,"-") -> 108961 | AR39: 141406 | AS39: =IFERROR(AR39*(12/$H39)*$J39,"-") -> 141406 | AU39: =IFERROR(IF(SUM(AL39,AP39,AS39)=0,"-",SUM(AL39,AP39,AS39)),"-") -> 250367 | AV39: =IFERROR(IF(SUM(AM39,AP39,AS39)=0,"-",SUM(AM39,AP39,AS39)),"-") -> 250367 | AW39: -
A40: =$C40&"_"&$E40&"_"&$K40 -> TSX:HBM_2022_ | B40: =$C40&"_"&$E40&"_"&$L40 -> TSX:HBM_2022_CFO | C40: =C39 -> TSX:HBM | D40: =_xll.ciqfunctions.udf.CIQ(C40,"IQ_Company_Name") -> Hudbay Minerals Inc. | E40: =E37 -> 2022 | F40: =E40&"-01-01" -> 2022-01-01 | G40: =E40&"-12-31" -> 2022-12-31 | H40: =_xlfn.DAYS(G40,F40)/_xlfn.DAYS(E40&"-12-31",E40&"-01-01")*12 -> 12 | I40: =I39 -> CAD | J40: =IF($I40="CAD",1,IF($I40="USD",VLOOKUP($E40,$F$9:$G$11,2,FALSE),"N/A")) -> 1 | L40: =L39 -> CFO | M40: =M39 -> CFO | N40: =N39 -> Eugene Lei | P40: =IFERROR(O40*(12/$H40)*$J40,"-") -> 0 | R40: =IFERROR(IF((Q40*$L40)=0,"-",(Q40*$L40)),"-") -> - | T40: =IFERROR(S40*(12/$H40)*$J40,"-") -> 0 | U40: =IFERROR($T40/$P40,"-") -> - | X40: =IFERROR(IF(ISNUMBER($W40)=TRUE, $W40*$P40,$V40*$P40),"-") -> 0 | Y40: =IFERROR(IF(SUM(P40,T40)=0,"-",SUM(P40,T40)),"-") -> - | Z40: =IFERROR(IF(SUM(P40,X40)=0,"-",SUM(P40,X40)),"-") -> - | AD40: - | AE40: - | AF40: =IFERROR(IF(SUM(AA40:AE40)=0,IF(COUNTIF($AA40:$AE40,"=0")>0,"$0","-"),SUM(AA40:AE40)),"-") -> - | AG40: =IFERROR($AK40/$P40,"-") -> - | AJ40: =IFERROR(IF(ISNUMBER($AI40)=TRUE, $AI40*$P40, $AH40*$P40), "-") -> 0 | AK40: =IFERROR($AF40*$J40,"-") -> - | AL40: =IFERROR(IF(SUM(Y40,AK40)=0,"-",SUM(Y40,AK40)),"-") -> - | AM40: =IFERROR(IF(SUM($Z40,$AJ40)=0,"-",SUM($Z40,$AJ40)),"-") -> - | AN40: 232546 | AO40: DB & DC | AP40: =IFERROR(AN40*(12/$H40)*$J40,"-") -> 232546 | AR40: 112350 | AS40: =IFERROR(AR40*(12/$H40)*$J40,"-") -> 112350 | AU40: =IFERROR(IF(SUM(AL40,AP40,AS40)=0,"-",SUM(AL40,AP40,AS40)),"-") -> 344896 | AV40: =IFERROR(IF(SUM(AM40,AP40,AS40)=0,"-",SUM(AM40,AP40,AS40)),"-") -> 344896 | AW40: -
A41: =$C41&"_"&$E41&"_"&$K41 -> TSX:HBM_2024_Legal | B41: =$C41&"_"&$E41&"_"&$L41 -> TSX:HBM_2024_NEO2 | C41: =C40 -> TSX:HBM | D41: =_xll.ciqfunctions.udf.CIQ(C41,"IQ_Company_Name") -> Hudbay Minerals Inc. | E41: =E38 -> 2024 | F41: =E41&"-01-01" -> 2024-01-01 | G41: =E41&"-12-31" -> 2024-12-31 | H41: =_xlfn.DAYS(G41,F41)/_xlfn.DAYS(E41&"-12-31",E41&"-01-01")*12 -> 12 | I41: =I40 -> CAD | J41: =IF($I41="CAD",1,IF($I41="USD",VLOOKUP($E41,$F$9:$G$11,2,FALSE),"N/A")) -> 1 | K41: Legal | L41: NEO2 | M41: SVP, Legal and Organizational Effectiveness | N41: Patrick Donnelly | O41: 501659 | P41: =IFERROR(O41*(12/$H41)*$J41,"-") -> 501659 | R41: =IFERROR(IF((Q41*$L41)=0,"-",(Q41*$L41)),"-") -> - | S41: 479256 | T41: =IFERROR(S41*(12/$H41)*$J41,"-") -> 479256 | U41: =IFERROR($T41/$P41,"-") -> 0.95534217 | V41: =IFERROR(AVERAGE(U41:U43),"N/A") -> 0.95534217 | W41: 0.75 | X41: =IFERROR(IF(ISNUMBER($W41)=TRUE, $W41*$P41,$V41*$P41),"-") -> 376244.25 | Y41: =IFERROR(IF(SUM(P41,T41)=0,"-",SUM(P41,T41)),"-") -> 980915 | Z41: =IFERROR(IF(SUM(P41,X41)=0,"-",SUM(P41,X41)),"-") -> 877903.25 | AB41: 547929 | AC41: 182643 | AD41: - | AE41: - | AF41: =IFERROR(IF(SUM(AA41:AE41)=0,IF(COUNTIF($AA41:$AE41,"=0")>0,"$0","-"),SUM(AA41:AE41)),"-") -> 730572 | AG41: =IFERROR($AK41/$P41,"-") -> 1.456312 | AH41: =IFERROR(AVERAGE(AG41:AG43),"N/A") -> 1.456312 | AI41: 1.5 | AJ41: =IFERROR(IF(ISNUMBER($AI41)=TRUE, $AI41*$P41, $AH41*$P41), "-") -> 752488.5 | AK41: =IFERROR($AF41*$J41,"-") -> 730572 | AL41: =IFERROR(IF(SUM(Y41,AK41)=0,"-",SUM(Y41,AK41)),"-") -> 1711487 | AM41: =IFERROR(IF(SUM($Z41,$AJ41)=0,"-",SUM($Z41,$AJ41)),"-") -> 1630391.8 | AN41: 122673 | AO41: DB | AP41: =IFERROR(AN41*(12/$H41)*$J41,"-") -> 122673 | AQ41: =IFERROR(AVERAGE(AP41:AP43),"N/A") -> 97104 | AR41: 84863 | AS41: =IFERROR(AR41*(12/$H41)*$J41,"-") -> 84863 | AT41: =IFERROR(AVERAGE(AS41:AS43),"N/A") -> 89528.333 | AU41: =IFERROR(IF(SUM(AL41,AP41,AS41)=0,"-",SUM(AL41,AP41,AS41)),"-") -> 1919023 | AV41: =IFERROR(IF(SUM(AM41,AP41,AS41)=0,"-",SUM(AM41,AP41,AS41)),"-") -> 1837927.8 | AW41: - | AX41: AH
A42: =$C42&"_"&$E42&"_"&$K42 -> TSX:HBM_2023_Legal | B42: =$C42&"_"&$E42&"_"&$L42 -> TSX:HBM_2023_NEO2 | C42: =C41 -> TSX:HBM | D42: =_xll.ciqfunctions.udf.CIQ(C42,"IQ_Company_Name") -> Hudbay Minerals Inc. | E42: =E39 -> 2023 | F42: =E42&"-01-01" -> 2023-01-01 | G42: =E42&"-12-31" -> 2023-12-31 | H42: =_xlfn.DAYS(G42,F42)/_xlfn.DAYS(E42&"-12-31",E42&"-01-01")*12 -> 12 | I42: =I41 -> CAD | J42: =IF($I42="CAD",1,IF($I42="USD",VLOOKUP($E42,$F$9:$G$11,2,FALSE),"N/A")) -> 1 | K42: Legal | L42: =L41 -> NEO2 | M42: =M41 -> SVP, Legal and Organizational Effectiveness | N42: =N41 -> Patrick Donnelly | P42: =IFERROR(O42*(12/$H42)*$J42,"-") -> 0 | R42: =IFERROR(IF((Q42*$L42)=0,"-",(Q42*$L42)),"-") -> - | T42: =IFERROR(S42*(12/$H42)*$J42,"-") -> 0 | U42: =IFERROR($T42/$P42,"-") -> - | X42: =IFERROR(IF(ISNUMBER($W42)=TRUE, $W42*$P42,$V42*$P42),"-") -> 0 | Y42: =IFERROR(IF(SUM(P42,T42)=0,"-",SUM(P42,T42)),"-") -> - | Z42: =IFERROR(IF(SUM(P42,X42)=0,"-",SUM(P42,X42)),"-") -> - | AD42: - | AE42: - | AF42: =IFERROR(IF(SUM(AA42:AE42)=0,IF(COUNTIF($AA42:$AE42,"=0")>0,"$0","-"),SUM(AA42:AE42)),"-") -> - | AG42: =IFERROR($AK42/$P42,"-") -> - | AJ42: =IFERROR(IF(ISNUMBER($AI42)=TRUE, $AI42*$P42, $AH42*$P42), "-") -> 0 | AK42: =IFERROR($AF42*$J42,"-") -> - | AL42: =IFERROR(IF(SUM(Y42,AK42)=0,"-",SUM(Y42,AK42)),"-") -> - | AM42: =IFERROR(IF(SUM($Z42,$AJ42)=0,"-",SUM($Z42,$AJ42)),"-") -> - | AN42: 54180 | AO42: DB | AP42: =IFERROR(AN42*(12/$H42)*$J42,"-") -> 54180 | AR42: 104737 | AS42: =IFERROR(AR42*(12/$H42)*$J42,"-") -> 104737 | AU42: =IFERROR(IF(SUM(AL42,AP42,AS42)=0,"-",SUM(AL42,AP42,AS42)),"-") -> 158917 | AV42: =IFERROR(IF(SUM(AM42,AP42,AS42)=0,"-",SUM(AM42,AP42,AS42)),"-") -> 158917 | AW42: -
A43: =$C43&"_"&$E43&"_"&$K43 -> TSX:HBM_2022_Legal | B43: =$C43&"_"&$E43&"_"&$L43 -> TSX:HBM_2022_NEO2 | C43: =C42 -> TSX:HBM | D43: =_xll.ciqfunctions.udf.CIQ(C43,"IQ_Company_Name") -> Hudbay Minerals Inc. | E43: =E40 -> 2022 | F43: =E43&"-01-01" -> 2022-01-01 | G43: =E43&"-12-31" -> 2022-12-31 | H43: =_xlfn.DAYS(G43,F43)/_xlfn.DAYS(E43&"-12-31",E43&"-01-01")*12 -> 12 | I43: =I42 -> CAD | J43: =IF($I43="CAD",1,IF($I43="USD",VLOOKUP($E43,$F$9:$G$11,2,FALSE),"N/A")) -> 1 | K43: Legal | L43: =L42 -> NEO2 | M43: =M42 -> SVP, Legal and Organizational Effectiveness | N43: =N42 -> Patrick Donnelly | P43: =IFERROR(O43*(12/$H43)*$J43,"-") -> 0 | R43: =IFERROR(IF((Q43*$L43)=0,"-",(Q43*$L43)),"-") -> - | T43: =IFERROR(S43*(12/$H43)*$J43,"-") -> 0 | U43: =IFERROR($T43/$P43,"-") -> - | X43: =IFERROR(IF(ISNUMBER($W43)=TRUE, $W43*$P43,$V43*$P43),"-") -> 0 | Y43: =IFERROR(IF(SUM(P43,T43)=0,"-",SUM(P43,T43)),"-") -> - | Z43: =IFERROR(IF(SUM(P43,X43)=0,"-",SUM(P43,X43)),"-") -> - | AD43: - | AE43: - | AF43: =IFERROR(IF(SUM(AA43:AE43)=0,IF(COUNTIF($AA43:$AE43,"=0")>0,"$0","-"),SUM(AA43:AE43)),"-") -> - | AG43: =IFERROR($AK43/$P43,"-") -> - | AJ43: =IFERROR(IF(ISNUMBER($AI43)=TRUE, $AI43*$P43, $AH43*$P43), "-") -> 0 | AK43: =IFERROR($AF43*$J43,"-") -> - | AL43: =IFERROR(IF(SUM(Y43,AK43)=0,"-",SUM(Y43,AK43)),"-") -> - | AM43: =IFERROR(IF(SUM($Z43,$AJ43)=0,"-",SUM($Z43,$AJ43)),"-") -> - | AN43: 114459 | AO43: DB | AP43: =IFERROR(AN43*(12/$H43)*$J43,"-") -> 114459 | AR43: 78985 | AS43: =IFERROR(AR43*(12/$H43)*$J43,"-") -> 78985 | AU43: =IFERROR(IF(SUM(AL43,AP43,AS43)=0,"-",SUM(AL43,AP43,AS43)),"-") -> 193444 | AV43: =IFERROR(IF(SUM(AM43,AP43,AS43)=0,"-",SUM(AM43,AP43,AS43)),"-") -> 193444 | AW43: -
A44: =$C44&"_"&$E44&"_"&$K44 -> TSX:HBM_2024_Region2 | B44: =$C44&"_"&$E44&"_"&$L44 -> TSX:HBM_2024_NEO3 | C44: =C40 -> TSX:HBM | D44: =_xll.ciqfunctions.udf.CIQ(C44,"IQ_Company_Name") -> Hudbay Minerals Inc. | E44: =E38 -> 2024 | F44: =E44&"-01-01" -> 2024-01-01 | G44: =E44&"-12-31" -> 2024-12-31 | H44: =_xlfn.DAYS(G44,F44)/_xlfn.DAYS(E44&"-12-31",E44&"-01-01")*12 -> 12 | I44: USD | J44: =IF($I44="CAD",1,IF($I44="USD",VLOOKUP($E44,$F$9:$G$11,2,FALSE),"N/A")) -> 1.37017 | K44: Region2 | L44: NEO3 | M44: SVP, US Business Unit | N44: Javier Del Rio | O44: 442834 | P44: =IFERROR(O44*(12/$H44)*$J44,"-") -> 606757.86 | R44: =IFERROR(IF((Q44*$L44)=0,"-",(Q44*$L44)),"-") -> - | S44: 445010 | T44: =IFERROR(S44*(12/$H44)*$J44,"-") -> 609739.35 | U44: =IFERROR($T44/$P44,"-") -> 1.0049138 | V44: =IFERROR(AVERAGE(U44:U46),"N/A") -> 1.0049138 | W44: 0.6 | X44: =IFERROR(IF(ISNUMBER($W44)=TRUE, $W44*$P44,$V44*$P44),"-") -> 364054.72 | Y44: =IFERROR(IF(SUM(P44,T44)=0,"-",SUM(P44,T44)),"-") -> 1216497.2 | Z44: =IFERROR(IF(SUM(P44,X44)=0,"-",SUM(P44,X44)),"-") -> 970812.58 | AB44: 479373 | AC44: 159791 | AD44: - | AE44: - | AF44: =IFERROR(IF(SUM(AA44:AE44)=0,IF(COUNTIF($AA44:$AE44,"=0")>0,"$0","-"),SUM(AA44:AE44)),"-") -> 639164 | AG44: =IFERROR($AK44/$P44,"-") -> 1.443349 | AH44: =IFERROR(AVERAGE(AG44:AG46),"N/A") -> 1.443349 | AI44: 1.2 | AJ44: =IFERROR(IF(ISNUMBER($AI44)=TRUE, $AI44*$P44, $AH44*$P44), "-") -> 728109.43 | AK44: =IFERROR($AF44*$J44,"-") -> 875763.34 | AL44: =IFERROR(IF(SUM(Y44,AK44)=0,"-",SUM(Y44,AK44)),"-") -> 2092260.6 | AM44: =IFERROR(IF(SUM($Z44,$AJ44)=0,"-",SUM($Z44,$AJ44)),"-") -> 1698922 | AN44: 13455 | AO44: DB | AP44: =IFERROR(AN44*(12/$H44)*$J44,"-") -> 18435.637 | AQ44: =IFERROR(AVERAGE(AP44:AP46),"N/A") -> 17902.109 | AR44: =(523315-421713) -> 101602 | AS44: =AR44 -> 101602 | AT44: =IFERROR(AVERAGE(AS44:AS46),"N/A") -> 122729 | AU44: =IFERROR(IF(SUM(AL44,AP44,AS44)=0,"-",SUM(AL44,AP44,AS44)),"-") -> 2212298.2 | AV44: =IFERROR(IF(SUM(AM44,AP44,AS44)=0,"-",SUM(AM44,AP44,AS44)),"-") -> 1818959.7 | AW44: Other compensation includes tax top-ups for duplicate tax levied on income in US and Peru (-421713) | AX44: AH
A45: =$C45&"_"&$E45&"_"&$K45 -> TSX:HBM_2023_Region2 | B45: =$C45&"_"&$E45&"_"&$L45 -> TSX:HBM_2023_NEO3 | C45: =C44 -> TSX:HBM | D45: =_xll.ciqfunctions.udf.CIQ(C45,"IQ_Company_Name") -> Hudbay Minerals Inc. | E45: =E39 -> 2023 | F45: =E45&"-01-01" -> 2023-01-01 | G45: =E45&"-12-31" -> 2023-12-31 | H45: =_xlfn.DAYS(G45,F45)/_xlfn.DAYS(E45&"-12-31",E45&"-01-01")*12 -> 12 | I45: USD | J45: =IF($I45="CAD",1,IF($I45="USD",VLOOKUP($E45,$F$9:$G$11,2,FALSE),"N/A")) -> 1.34954 | K45: Region2 | L45: =L44 -> NEO3 | M45: =M44 -> SVP, US Business Unit | N45: =N44 -> Javier Del Rio | P45: =IFERROR(O45*(12/$H45)*$J45,"-") -> 0 | R45: =IFERROR(IF((Q45*$L45)=0,"-",(Q45*$L45)),"-") -> - | T45: =IFERROR(S45*(12/$H45)*$J45,"-") -> 0 | U45: =IFERROR($T45/$P45,"-") -> - | X45: =IFERROR(IF(ISNUMBER($W45)=TRUE, $W45*$P45,$V45*$P45),"-") -> 0 | Y45: =IFERROR(IF(SUM(P45,T45)=0,"-",SUM(P45,T45)),"-") -> - | Z45: =IFERROR(IF(SUM(P45,X45)=0,"-",SUM(P45,X45)),"-") -> - | AD45: - | AE45: - | AF45: =IFERROR(IF(SUM(AA45:AE45)=0,IF(COUNTIF($AA45:$AE45,"=0")>0,"$0","-"),SUM(AA45:AE45)),"-") -> - | AG45: =IFERROR($AK45/$P45,"-") -> - | AJ45: =IFERROR(IF(ISNUMBER($AI45)=TRUE, $AI45*$P45, $AH45*$P45), "-") -> 0 | AK45: =IFERROR($AF45*$J45,"-") -> - | AL45: =IFERROR(IF(SUM(Y45,AK45)=0,"-",SUM(Y45,AK45)),"-") -> - | AM45: =IFERROR(IF(SUM($Z45,$AJ45)=0,"-",SUM($Z45,$AJ45)),"-") -> - | AN45: 12870 | AO45: DB | AP45: =IFERROR(AN45*(12/$H45)*$J45,"-") -> 17368.58 | AR45: 144308 | AS45: =AR45 -> 144308 | AU45: =IFERROR(IF(SUM(AL45,AP45,AS45)=0,"-",SUM(AL45,AP45,AS45)),"-") -> 161676.58 | AV45: =IFERROR(IF(SUM(AM45,AP45,AS45)=0,"-",SUM(AM45,AP45,AS45)),"-") -> 161676.58 | AW45: -
A46: =$C46&"_"&$E46&"_"&$K46 -> TSX:HBM_2022_Region2 | B46: =$C46&"_"&$E46&"_"&$L46 -> TSX:HBM_2022_NEO3 | C46: =C45 -> TSX:HBM | D46: =_xll.ciqfunctions.udf.CIQ(C46,"IQ_Company_Name") -> Hudbay Minerals Inc. | E46: =E40 -> 2022 | F46: =E46&"-01-01" -> 2022-01-01 | G46: =E46&"-12-31" -> 2022-12-31 | H46: =_xlfn.DAYS(G46,F46)/_xlfn.DAYS(E46&"-12-31",E46&"-01-01")*12 -> 12 | I46: USD | J46: =IF($I46="CAD",1,IF($I46="USD",VLOOKUP($E46,$F$9:$G$11,2,FALSE),"N/A")) -> 1.30175 | K46: Region2 | L46: =L45 -> NEO3 | M46: =M45 -> SVP, US Business Unit | N46: =N45 -> Javier Del Rio | P46: =IFERROR(O46*(12/$H46)*$J46,"-") -> 0 | R46: =IFERROR(IF((Q46*$L46)=0,"-",(Q46*$L46)),"-") -> - | T46: =IFERROR(S46*(12/$H46)*$J46,"-") -> 0 | X46: =IFERROR(IF(ISNUMBER($W46)=TRUE, $W46*$P46,$V46*$P46),"-") -> 0 | Y46: =IFERROR(IF(SUM(P46,T46)=0,"-",SUM(P46,T46)),"-") -> - | Z46: =IFERROR(IF(SUM(P46,X46)=0,"-",SUM(P46,X46)),"-") -> - | AD46: - | AE46: - | AF46: =IFERROR(IF(SUM(AA46:AE46)=0,IF(COUNTIF($AA46:$AE46,"=0")>0,"$0","-"),SUM(AA46:AE46)),"-") -> - | AG46: =IFERROR($AK46/$P46,"-") -> - | AL46: =IFERROR(IF(SUM(Y46,AK46)=0,"-",SUM(Y46,AK46)),"-") -> - | AM46: =IFERROR(IF(SUM($Z46,$AJ46)=0,"-",SUM($Z46,$AJ46)),"-") -> - | AN46: - | AO46: - | AP46: =IFERROR(AN46*(12/$H46)*$J46,"-") -> - | AR46: =(579031-456754) -> 122277 | AS46: =AR46 -> 122277 | AU46: =IFERROR(IF(SUM(AL46,AP46,AS46)=0,"-",SUM(AL46,AP46,AS46)),"-") -> 122277 | AV46: =IFERROR(IF(SUM(AM46,AP46,AS46)=0,"-",SUM(AM46,AP46,AS46)),"-") -> 122277 | AW46: Other compensation includes relocation/travel allowances (-456754)
A47: =$C47&"_"&$E47&"_"&$K47 -> TSX:HBM_2024_Tech | B47: =$C47&"_"&$E47&"_"&$L47 -> TSX:HBM_2024_NEO4 | C47: =C40 -> TSX:HBM | D47: =_xll.ciqfunctions.udf.CIQ(C47,"IQ_Company_Name") -> Hudbay Minerals Inc. | E47: =E38 -> 2024 | F47: =E47&"-01-01" -> 2024-01-01 | G47: =E47&"-12-31" -> 2024-12-31 | H47: =_xlfn.DAYS(G47,F47)/_xlfn.DAYS(E47&"-12-31",E47&"-01-01")*12 -> 12 | I47: =I40 -> CAD | J47: =IF($I47="CAD",1,IF($I47="USD",VLOOKUP($E47,$F$9:$G$11,2,FALSE),"N/A")) -> 1 | K47: Tech | L47: NEO4 | M47: SVP, Exploration and Technical Services | N47: Olivier Tavchandjian | O47: 465850 | P47: =IFERROR(O47*(12/$H47)*$J47,"-") -> 465850 | R47: =IFERROR(IF((Q47*$L47)=0,"-",(Q47*$L47)),"-") -> - | T47: =IFERROR(S47*(12/$H47)*$J47,"-") -> 0 | U47: =IFERROR($T47/$P47,"-") -> 0 | V47: =IFERROR(AVERAGE(U47:U49),"N/A") -> 0 | W47: 0.6 | X47: =IFERROR(IF(ISNUMBER($W47)=TRUE, $W47*$P47,$V47*$P47),"-") -> 279510 | Y47: =IFERROR(IF(SUM(P47,T47)=0,"-",SUM(P47,T47)),"-") -> 465850 | Z47: =IFERROR(IF(SUM(P47,X47)=0,"-",SUM(P47,X47)),"-") -> 745360 | AD47: - | AE47: - | AF47: =IFERROR(IF(SUM(AA47:AE47)=0,IF(COUNTIF($AA47:$AE47,"=0")>0,"$0","-"),SUM(AA47:AE47)),"-") -> - | AG47: =IFERROR($AK47/$P47,"-") -> - | AH47: =IFERROR(AVERAGE(AG47:AG49),"N/A") -> N/A | AI47: 1.2 | AJ47: =IFERROR(IF(ISNUMBER($AI47)=TRUE, $AI47*$P47, $AH47*$P47), "-") -> 559020 | AK47: =IFERROR($AF47*$J47,"-") -> - | AL47: =IFERROR(IF(SUM(Y47,AK47)=0,"-",SUM(Y47,AK47)),"-") -> 465850 | AM47: =IFERROR(IF(SUM($Z47,$AJ47)=0,"-",SUM($Z47,$AJ47)),"-") -> 1304380 | AP47: =IFERROR(AN47*(12/$H47)*$J47,"-") -> 0 | AQ47: =IFERROR(AVERAGE(AP47:AP49),"N/A") -> 0 | AS47: =IFERROR(AR47*(12/$H47)*$J47,"-") -> 0 | AT47: =IFERROR(AVERAGE(AS47:AS49),"N/A") -> 0 | AU47: =IFERROR(IF(SUM(AL47,AP47,AS47)=0,"-",SUM(AL47,AP47,AS47)),"-") -> 465850 | AV47: =IFERROR(IF(SUM(AM47,AP47,AS47)=0,"-",SUM(AM47,AP47,AS47)),"-") -> 1304380 | AX47: AH
A48: =$C48&"_"&$E48&"_"&$K48 -> TSX:HBM_2023_Tech | B48: =$C48&"_"&$E48&"_"&$L48 -> TSX:HBM_2023_NEO4 | C48: =C47 -> TSX:HBM | D48: =_xll.ciqfunctions.udf.CIQ(C48,"IQ_Company_Name") -> Hudbay Minerals Inc. | E48: =E39 -> 2023 | F48: =E48&"-01-01" -> 2023-01-01 | G48: =E48&"-12-31" -> 2023-12-31 | H48: =_xlfn.DAYS(G48,F48)/_xlfn.DAYS(E48&"-12-31",E48&"-01-01")*12 -> 12 | I48: =I47 -> CAD | J48: =IF($I48="CAD",1,IF($I48="USD",VLOOKUP($E48,$F$9:$G$11,2,FALSE),"N/A")) -> 1 | K48: Tech | L48: =L47 -> NEO4 | M48: =M47 -> SVP, Exploration and Technical Services | N48: =N47 -> Olivier Tavchandjian | P48: =IFERROR(O48*(12/$H48)*$J48,"-") -> 0 | R48: =IFERROR(IF((Q48*$L48)=0,"-",(Q48*$L48)),"-") -> - | T48: =IFERROR(S48*(12/$H48)*$J48,"-") -> 0 | U48: =IFERROR($T48/$P48,"-") -> - | X48: =IFERROR(IF(ISNUMBER($W48)=TRUE, $W48*$P48,$V48*$P48),"-") -> 0 | Y48: =IFERROR(IF(SUM(P48,T48)=0,"-",SUM(P48,T48)),"-") -> - | Z48: =IFERROR(IF(SUM(P48,X48)=0,"-",SUM(P48,X48)),"-") -> - | AD48: - | AE48: - | AF48: =IFERROR(IF(SUM(AA48:AE48)=0,IF(COUNTIF($AA48:$AE48,"=0")>0,"$0","-"),SUM(AA48:AE48)),"-") -> - | AG48: =IFERROR($AK48/$P48,"-") -> - | AI48: - | AJ48: =IFERROR(IF(ISNUMBER($AI48)=TRUE, $AI48*$P48, $AH48*$P48), "-") -> 0 | AK48: =IFERROR($AF48*$J48,"-") -> - | AL48: =IFERROR(IF(SUM(Y48,AK48)=0,"-",SUM(Y48,AK48)),"-") -> - | AM48: =IFERROR(IF(SUM($Z48,$AJ48)=0,"-",SUM($Z48,$AJ48)),"-") -> - | AP48: =IFERROR(AN48*(12/$H48)*$J48,"-") -> 0 | AS48: =IFERROR(AR48*(12/$H48)*$J48,"-") -> 0 | AU48: =IFERROR(IF(SUM(AL48,AP48,AS48)=0,"-",SUM(AL48,AP48,AS48)),"-") -> - | AV48: =IFERROR(IF(SUM(AM48,AP48,AS48)=0,"-",SUM(AM48,AP48,AS48)),"-") -> -
A49: =$C49&"_"&$E49&"_"&$K49 -> TSX:HBM_2022_Tech | B49: =$C49&"_"&$E49&"_"&$L49 -> TSX:HBM_2022_NEO4 | C49: =C48 -> TSX:HBM | D49: =_xll.ciqfunctions.udf.CIQ(C49,"IQ_Company_Name") -> Hudbay Minerals Inc. | E49: =E40 -> 2022 | F49: =E49&"-01-01" -> 2022-01-01 | G49: =E49&"-12-31" -> 2022-12-31 | H49: =_xlfn.DAYS(G49,F49)/_xlfn.DAYS(E49&"-12-31",E49&"-01-01")*12 -> 12 | I49: =I48 -> CAD | J49: =IF($I49="CAD",1,IF($I49="USD",VLOOKUP($E49,$F$9:$G$11,2,FALSE),"N/A")) -> 1 | K49: Tech | L49: =L48 -> NEO4 | M49: =M48 -> SVP, Exploration and Technical Services | N49: =N48 -> Olivier Tavchandjian | P49: =IFERROR(O49*(12/$H49)*$J49,"-") -> 0 | R49: =IFERROR(IF((Q49*$L49)=0,"-",(Q49*$L49)),"-") -> - | T49: =IFERROR(S49*(12/$H49)*$J49,"-") -> 0 | U49: =IFERROR($T49/$P49,"-") -> - | X49: =IFERROR(IF(ISNUMBER($W49)=TRUE, $W49*$P49,$V49*$P49),"-") -> 0 | Y49: =IFERROR(IF(SUM(P49,T49)=0,"-",SUM(P49,T49)),"-") -> - | Z49: =IFERROR(IF(SUM(P49,X49)=0,"-",SUM(P49,X49)),"-") -> - | AD49: - | AE49: - | AF49: =IFERROR(IF(SUM(AA49:AE49)=0,IF(COUNTIF($AA49:$AE49,"=0")>0,"$0","-"),SUM(AA49:AE49)),"-") -> - | AG49: =IFERROR($AK49/$P49,"-") -> - | AI49: - | AJ49: =IFERROR(IF(ISNUMBER($AI49)=TRUE, $AI49*$P49, $AH49*$P49), "-") -> 0 | AK49: =IFERROR($AF49*$J49,"-") -> - | AL49: =IFERROR(IF(SUM(Y49,AK49)=0,"-",SUM(Y49,AK49)),"-") -> - | AM49: =IFERROR(IF(SUM($Z49,$AJ49)=0,"-",SUM($Z49,$AJ49)),"-") -> - | AP49: =IFERROR(AN49*(12/$H49)*$J49,"-") -> 0 | AS49: =IFERROR(AR49*(12/$H49)*$J49,"-") -> 0 | AU49: =IFERROR(IF(SUM(AL49,AP49,AS49)=0,"-",SUM(AL49,AP49,AS49)),"-") -> - | AV49: =IFERROR(IF(SUM(AM49,AP49,AS49)=0,"-",SUM(AM49,AP49,AS49)),"-") -> -
A50: =$C50&"_"&$E50&"_"&$K50 -> TSX:HBM_2024_Region | B50: =$C50&"_"&$E50&"_"&$L50 -> TSX:HBM_2024_NEO5 | C50: =C43 -> TSX:HBM | D50: =_xll.ciqfunctions.udf.CIQ(C50,"IQ_Company_Name") -> Hudbay Minerals Inc. | E50: =E41 -> 2024 | F50: =E50&"-01-01" -> 2024-01-01 | G50: =E50&"-12-31" -> 2024-12-31 | H50: =_xlfn.DAYS(G50,F50)/_xlfn.DAYS(E50&"-12-31",E50&"-01-01")*12 -> 12 | I50: =I43 -> CAD | J50: =IF($I50="CAD",1,IF($I50="USD",VLOOKUP($E50,$F$9:$G$11,2,FALSE),"N/A")) -> 1 | K50: Region | L50: NEO5 | M50: SVP, Canada | N50: Rob Carter | O50: 453500 | P50: =IFERROR(O50*(12/$H50)*$J50,"-") -> 453500 | R50: =IFERROR(IF((Q50*$L50)=0,"-",(Q50*$L50)),"-") -> - | T50: =IFERROR(S50*(12/$H50)*$J50,"-") -> 0 | U50: =IFERROR($T50/$P50,"-") -> 0 | V50: =IFERROR(AVERAGE(U50:U52),"N/A") -> 0 | W50: 0.6 | X50: =IFERROR(IF(ISNUMBER($W50)=TRUE, $W50*$P50,$V50*$P50),"-") -> 272100 | Y50: =IFERROR(IF(SUM(P50,T50)=0,"-",SUM(P50,T50)),"-") -> 453500 | Z50: =IFERROR(IF(SUM(P50,X50)=0,"-",SUM(P50,X50)),"-") -> 725600 | AD50: - | AE50: - | AF50: =IFERROR(IF(SUM(AA50:AE50)=0,IF(COUNTIF($AA50:$AE50,"=0")>0,"$0","-"),SUM(AA50:AE50)),"-") -> - | AG50: =IFERROR($AK50/$P50,"-") -> - | AH50: =IFERROR(AVERAGE(AG50:AG52),"N/A") -> N/A | AI50: 1.2 | AJ50: =IFERROR(IF(ISNUMBER($AI50)=TRUE, $AI50*$P50, $AH50*$P50), "-") -> 544200 | AK50: =IFERROR($AF50*$J50,"-") -> - | AL50: =IFERROR(IF(SUM(Y50,AK50)=0,"-",SUM(Y50,AK50)),"-") -> 453500 | AM50: =IFERROR(IF(SUM($Z50,$AJ50)=0,"-",SUM($Z50,$AJ50)),"-") -> 1269800 | AP50: =IFERROR(AN50*(12/$H50)*$J50,"-") -> 0 | AQ50: =IFERROR(AVERAGE(AP50:AP52),"N/A") -> 0 | AS50: =IFERROR(AR50*(12/$H50)*$J50,"-") -> 0 | AT50: =IFERROR(AVERAGE(AS50:AS52),"N/A") -> 0 | AU50: =IFERROR(IF(SUM(AL50,AP50,AS50)=0,"-",SUM(AL50,AP50,AS50)),"-") -> 453500 | AV50: =IFERROR(IF(SUM(AM50,AP50,AS50)=0,"-",SUM(AM50,AP50,AS50)),"-") -> 1269800 | AX50: AH
A51: =$C51&"_"&$E51&"_"&$K51 -> TSX:HBM_2023_Region | B51: =$C51&"_"&$E51&"_"&$L51 -> TSX:HBM_2023_NEO5 | C51: =C50 -> TSX:HBM | D51: =_xll.ciqfunctions.udf.CIQ(C51,"IQ_Company_Name") -> Hudbay Minerals Inc. | E51: =E42 -> 2023 | F51: =E51&"-01-01" -> 2023-01-01 | G51: =E51&"-12-31" -> 2023-12-31 | H51: =_xlfn.DAYS(G51,F51)/_xlfn.DAYS(E51&"-12-31",E51&"-01-01")*12 -> 12 | I51: =I50 -> CAD | J51: =IF($I51="CAD",1,IF($I51="USD",VLOOKUP($E51,$F$9:$G$11,2,FALSE),"N/A")) -> 1 | K51: Region | L51: =L50 -> NEO5 | M51: =M50 -> SVP, Canada | N51: =N50 -> Rob Carter | P51: =IFERROR(O51*(12/$H51)*$J51,"-") -> 0 | R51: =IFERROR(IF((Q51*$L51)=0,"-",(Q51*$L51)),"-") -> - | T51: =IFERROR(S51*(12/$H51)*$J51,"-") -> 0 | U51: =IFERROR($T51/$P51,"-") -> - | X51: =IFERROR(IF(ISNUMBER($W51)=TRUE, $W51*$P51,$V51*$P51),"-") -> 0 | Y51: =IFERROR(IF(SUM(P51,T51)=0,"-",SUM(P51,T51)),"-") -> - | Z51: =IFERROR(IF(SUM(P51,X51)=0,"-",SUM(P51,X51)),"-") -> - | AD51: - | AE51: - | AF51: =IFERROR(IF(SUM(AA51:AE51)=0,IF(COUNTIF($AA51:$AE51,"=0")>0,"$0","-"),SUM(AA51:AE51)),"-") -> - | AG51: =IFERROR($AK51/$P51,"-") -> - | AI51: - | AJ51: =IFERROR(IF(ISNUMBER($AI51)=TRUE, $AI51*$P51, $AH51*$P51), "-") -> 0 | AK51: =IFERROR($AF51*$J51,"-") -> - | AL51: =IFERROR(IF(SUM(Y51,AK51)=0,"-",SUM(Y51,AK51)),"-") -> - | AM51: =IFERROR(IF(SUM($Z51,$AJ51)=0,"-",SUM($Z51,$AJ51)),"-") -> - | AP51: =IFERROR(AN51*(12/$H51)*$J51,"-") -> 0 | AS51: =IFERROR(AR51*(12/$H51)*$J51,"-") -> 0 | AU51: =IFERROR(IF(SUM(AL51,AP51,AS51)=0,"-",SUM(AL51,AP51,AS51)),"-") -> - | AV51: =IFERROR(IF(SUM(AM51,AP51,AS51)=0,"-",SUM(AM51,AP51,AS51)),"-") -> -
A52: =$C52&"_"&$E52&"_"&$K52 -> TSX:HBM_2022_Region | B52: =$C52&"_"&$E52&"_"&$L52 -> TSX:HBM_2022_NEO5 | C52: =C51 -> TSX:HBM | D52: =_xll.ciqfunctions.udf.CIQ(C52,"IQ_Company_Name") -> Hudbay Minerals Inc. | E52: =E43 -> 2022 | F52: =E52&"-01-01" -> 2022-01-01 | G52: =E52&"-12-31" -> 2022-12-31 | H52: =_xlfn.DAYS(G52,F52)/_xlfn.DAYS(E52&"-12-31",E52&"-01-01")*12 -> 12 | I52: =I51 -> CAD | J52: =IF($I52="CAD",1,IF($I52="USD",VLOOKUP($E52,$F$9:$G$11,2,FALSE),"N/A")) -> 1 | K52: Region | L52: =L51 -> NEO5 | M52: =M51 -> SVP, Canada | N52: =N51 -> Rob Carter | P52: =IFERROR(O52*(12/$H52)*$J52,"-") -> 0 | R52: =IFERROR(IF((Q52*$L52)=0,"-",(Q52*$L52)),"-") -> - | T52: =IFERROR(S52*(12/$H52)*$J52,"-") -> 0 | U52: =IFERROR($T52/$P52,"-") -> - | X52: =IFERROR(IF(ISNUMBER($W52)=TRUE, $W52*$P52,$V52*$P52),"-") -> 0 | Y52: =IFERROR(IF(SUM(P52,T52)=0,"-",SUM(P52,T52)),"-") -> - | Z52: =IFERROR(IF(SUM(P52,X52)=0,"-",SUM(P52,X52)),"-") -> - | AD52: - | AE52: - | AF52: =IFERROR(IF(SUM(AA52:AE52)=0,IF(COUNTIF($AA52:$AE52,"=0")>0,"$0","-"),SUM(AA52:AE52)),"-") -> - | AG52: =IFERROR($AK52/$P52,"-") -> - | AI52: - | AL52: =IFERROR(IF(SUM(Y52,AK52)=0,"-",SUM(Y52,AK52)),"-") -> - | AM52: =IFERROR(IF(SUM($Z52,$AJ52)=0,"-",SUM($Z52,$AJ52)),"-") -> - | AP52: =IFERROR(AN52*(12/$H52)*$J52,"-") -> 0 | AS52: =IFERROR(AR52*(12/$H52)*$J52,"-") -> 0 | AU52: =IFERROR(IF(SUM(AL52,AP52,AS52)=0,"-",SUM(AL52,AP52,AS52)),"-") -> - | AV52: =IFERROR(IF(SUM(AM52,AP52,AS52)=0,"-",SUM(AM52,AP52,AS52)),"-") -> -
A53: =$C53&"_"&$E53&"_"&$K53 -> TSX:K_2024_ | B53: =$C53&"_"&$E53&"_"&$L53 -> TSX:K_2024_CEO | C53: =D5 -> TSX:K | D53: =_xll.ciqfunctions.udf.CIQ(C53,"IQ_Company_Name") -> Kinross Gold Corporation | E53: =$F$9 -> 2024 | F53: =E53&"-01-01" -> 2024-01-01 | G53: =E53&"-12-31" -> 2024-12-31 | H53: =_xlfn.DAYS(G53,F53)/_xlfn.DAYS(E53&"-12-31",E53&"-01-01")*12 -> 12 | I53: USD | J53: =IF($I53="CAD",1,IF($I53="USD",VLOOKUP($E53,$F$9:$G$11,2,FALSE),"N/A")) -> 1.37017 | L53: CEO | M53: CEO | N53: J. Paul Rollinson | O53: 1181500 | P53: =IFERROR(O53*(12/$H53)*$J53,"-") -> 1618855.9 | Q53: - | R53: 1700000 | S53: 2259619 | T53: =IFERROR(S53*(12/$H53)*$J53,"-") -> 3096062.2 | U53: =IFERROR($T53/$P53,"-") -> 1.9125002 | V53: =IFERROR(AVERAGE(U53:U55),"N/A") -> 1.5787501 | W53: 1.5 | X53: =IFERROR(IF(ISNUMBER($W53)=TRUE, $W53*$P53,$V53*$P53),"-") -> 2428283.8 | Y53: =IFERROR(IF(SUM(P53,T53)=0,"-",SUM(P53,T53)),"-") -> 4714918 | Z53: =IFERROR(IF(SUM(P53,X53)=0,"-",SUM(P53,X53)),"-") -> 4047139.6 | AA53: 1520590.5 | AB53: 1858499.5 | AC53: - | AD53: - | AE53: - | AF53: =IFERROR(IF(SUM(AA53:AE53)=0,IF(COUNTIF($AA53:$AE53,"=0")>0,"$0","-"),SUM(AA53:AE53)),"-") -> 3379090 | AG53: =IFERROR($AK53/$P53,"-") -> 2.86 | AH53: =IFERROR(AVERAGE(AG53:AG55),"N/A") -> 2.8733336 | AI53: - | AJ53: =IFERROR(IF(ISNUMBER($AI53)=TRUE, $AI53*$P53, $AH53*$P53), "-") -> 4651513 | AK53: =IFERROR($AF53*$J53,"-") -> 4629927.7 | AL53: =IFERROR(IF(SUM(Y53,AK53)=0,"-",SUM(Y53,AK53)),"-") -> 9344845.8 | AM53: =IFERROR(IF(SUM($Z53,$AJ53)=0,"-",SUM($Z53,$AJ53)),"-") -> 8698652.6 | AN53: 531675 | AO53: DC | AP53: =IFERROR(AN53*(12/$H53)*$J53,"-") -> 728485.13 | AQ53: =IFERROR(AVERAGE(AP53:AP55),"N/A") -> 709464.56 | AR53: 300233 | AS53: =IFERROR(AR53*(12/$H53)*$J53,"-") -> 411370.25 | AT53: =IFERROR(AVERAGE(AS53:AS55),"N/A") -> 406331.51 | AU53: =IFERROR(IF(SUM(AL53,AP53,AS53)=0,"-",SUM(AL53,AP53,AS53)),"-") -> 10484701 | AV53: =IFERROR(IF(SUM(AM53,AP53,AS53)=0,"-",SUM(AM53,AP53,AS53)),"-") -> 9838508 | AW53: - | AX53: AH | AY53: sc
A54: =$C54&"_"&$E54&"_"&$K54 -> TSX:K_2023_ | B54: =$C54&"_"&$E54&"_"&$L54 -> TSX:K_2023_CEO | C54: =C53 -> TSX:K | D54: =_xll.ciqfunctions.udf.CIQ(C54,"IQ_Company_Name") -> Kinross Gold Corporation | E54: =$F$10 -> 2023 | F54: =E54&"-01-01" -> 2023-01-01 | G54: =E54&"-12-31" -> 2023-12-31 | H54: =_xlfn.DAYS(G54,F54)/_xlfn.DAYS(E54&"-12-31",E54&"-01-01")*12 -> 12 | I54: =I53 -> USD | J54: =IF($I54="CAD",1,IF($I54="USD",VLOOKUP($E54,$F$9:$G$11,2,FALSE),"N/A")) -> 1.34954 | L54: =L53 -> CEO | M54: =M53 -> CEO | N54: =N53 -> J. Paul Rollinson | O54: 1187077 | P54: =IFERROR(O54*(12/$H54)*$J54,"-") -> 1602007.9 | Q54: - | R54: =IFERROR(IF((Q54*$J54)=0,"-",(Q54*$J54)),"-") -> - | S54: 2069966 | T54: =IFERROR(S54*(12/$H54)*$J54,"-") -> 2793501.9 | U54: =IFERROR($T54/$P54,"-") -> 1.7437504 | W54: - | X54: =IFERROR(IF(ISNUMBER($W54)=TRUE, $W54*$P54,$V54*$P54),"-") -> 0 | Y54: =IFERROR(IF(SUM(P54,T54)=0,"-",SUM(P54,T54)),"-") -> 4395509.8 | Z54: =IFERROR(IF(SUM(P54,X54)=0,"-",SUM(P54,X54)),"-") -> 1602007.9 | AA54: 1549135.8 | AB54: 1893388.2 | AC54: - | AD54: - | AE54: - | AF54: =IFERROR(IF(SUM(AA54:AE54)=0,IF(COUNTIF($AA54:$AE54,"=0")>0,"$0","-"),SUM(AA54:AE54)),"-") -> 3442524 | AG54: =IFERROR($AK54/$P54,"-") -> 2.9000006 | AI54: - | AJ54: =IFERROR(IF(ISNUMBER($AI54)=TRUE, $AI54*$P54, $AH54*$P54), "-") -> 0 | AK54: =IFERROR($AF54*$J54,"-") -> 4645823.8 | AL54: =IFERROR(IF(SUM(Y54,AK54)=0,"-",SUM(Y54,AK54)),"-") -> 9041333.6 | AM54: =IFERROR(IF(SUM($Z54,$AJ54)=0,"-",SUM($Z54,$AJ54)),"-") -> 1602007.9 | AN54: 534185 | AO54: DC | AP54: =IFERROR(AN54*(12/$H54)*$J54,"-") -> 720904.02 | AR54: 312030 | AS54: =IFERROR(AR54*(12/$H54)*$J54,"-") -> 421096.97 | AU54: =IFERROR(IF(SUM(AL54,AP54,AS54)=0,"-",SUM(AL54,AP54,AS54)),"-") -> 10183335 | AV54: =IFERROR(IF(SUM(AM54,AP54,AS54)=0,"-",SUM(AM54,AP54,AS54)),"-") -> 2744008.9 | AW54: - | AX54: AH | AY54: sc
A55: =$C55&"_"&$E55&"_"&$K55 -> TSX:K_2022_ | B55: =$C55&"_"&$E55&"_"&$L55 -> TSX:K_2022_CEO | C55: =C54 -> TSX:K | D55: =_xll.ciqfunctions.udf.CIQ(C55,"IQ_Company_Name") -> Kinross Gold Corporation | E55: =$F$11 -> 2022 | F55: =E55&"-01-01" -> 2022-01-01 | G55: =E55&"-12-31" -> 2022-12-31 | H55: =_xlfn.DAYS(G55,F55)/_xlfn.DAYS(E55&"-12-31",E55&"-01-01")*12 -> 12 | I55: =I54 -> USD | J55: =IF($I55="CAD",1,IF($I55="USD",VLOOKUP($E55,$F$9:$G$11,2,FALSE),"N/A")) -> 1.30175 | L55: =L54 -> CEO | M55: =M54 -> CEO | N55: =N54 -> J. Paul Rollinson | O55: 1159131 | P55: =IFERROR(O55*(12/$H55)*$J55,"-") -> 1508898.8 | Q55: - | R55: =IFERROR(IF((Q55*$J55)=0,"-",(Q55*$J55)),"-") -> - | S55: 1251861 | T55: =IFERROR(S55*(12/$H55)*$J55,"-") -> 1629610.1 | U55: =IFERROR($T55/$P55,"-") -> 1.0799996 | W55: - | X55: =IFERROR(IF(ISNUMBER($W55)=TRUE, $W55*$P55,$V55*$P55),"-") -> 0 | Y55: =IFERROR(IF(SUM(P55,T55)=0,"-",SUM(P55,T55)),"-") -> 3138508.8 | Z55: =IFERROR(IF(SUM(P55,X55)=0,"-",SUM(P55,X55)),"-") -> 1508898.8 | AA55: 1491801.8 | AB55: 1823313.3 | AC55: - | AD55: - | AE55: - | AF55: =IFERROR(IF(SUM(AA55:AE55)=0,IF(COUNTIF($AA55:$AE55,"=0")>0,"$0","-"),SUM(AA55:AE55)),"-") -> 3315115 | AG55: =IFERROR($AK55/$P55,"-") -> 2.8600003 | AI55: - | AJ55: =IFERROR(IF(ISNUMBER($AI55)=TRUE, $AI55*$P55, $AH55*$P55), "-") -> 0 | AK55: =IFERROR($AF55*$J55,"-") -> 4315451 | AL55: =IFERROR(IF(SUM(Y55,AK55)=0,"-",SUM(Y55,AK55)),"-") -> 7453959.8 | AM55: =IFERROR(IF(SUM($Z55,$AJ55)=0,"-",SUM($Z55,$AJ55)),"-") -> 1508898.8 | AN55: 521609 | AO55: DC | AP55: =IFERROR(AN55*(12/$H55)*$J55,"-") -> 679004.52 | AR55: 296929 | AS55: =IFERROR(AR55*(12/$H55)*$J55,"-") -> 386527.33 | AU55: =IFERROR(IF(SUM(AL55,AP55,AS55)=0,"-",SUM(AL55,AP55,AS55)),"-") -> 8519491.6 | AV55: =IFERROR(IF(SUM(AM55,AP55,AS55)=0,"-",SUM(AM55,AP55,AS55)),"-") -> 2574430.6 | AW55: - | AX55: AH | AY55: sc
A56: =$C56&"_"&$E56&"_"&$K56 -> TSX:K_2024_ | B56: =$C56&"_"&$E56&"_"&$L56 -> TSX:K_2024_CFO | C56: =C55 -> TSX:K | D56: =_xll.ciqfunctions.udf.CIQ(C56,"IQ_Company_Name") -> Kinross Gold Corporation | E56: =E53 -> 2024 | F56: =E56&"-01-01" -> 2024-01-01 | G56: =E56&"-12-31" -> 2024-12-31 | H56: =_xlfn.DAYS(G56,F56)/_xlfn.DAYS(E56&"-12-31",E56&"-01-01")*12 -> 12 | I56: =I55 -> USD | J56: =IF($I56="CAD",1,IF($I56="USD",VLOOKUP($E56,$F$9:$G$11,2,FALSE),"N/A")) -> 1.37017 | L56: CFO | M56: EVP & CFO | N56: Andrea S. Freeborough | O56: 451750 | P56: =IFERROR(O56*(12/$H56)*$J56,"-") -> 618974.3 | Q56: - | R56: 670000 | S56: 489888 | T56: =IFERROR(S56*(12/$H56)*$J56,"-") -> 671229.84 | U56: =IFERROR($T56/$P56,"-") -> 1.0844228 | V56: =IFERROR(AVERAGE(U56:U58),"N/A") -> 0.96822428 | W56: 0.9 | X56: =IFERROR(IF(ISNUMBER($W56)=TRUE, $W56*$P56,$V56*$P56),"-") -> 557076.87 | Y56: =IFERROR(IF(SUM(P56,T56)=0,"-",SUM(P56,T56)),"-") -> 1290204.1 | Z56: =IFERROR(IF(SUM(P56,X56)=0,"-",SUM(P56,X56)),"-") -> 1176051.2 | AA56: 423463.5 | AB56: 517566.5 | AC56: - | AD56: - | AE56: - | AF56: =IFERROR(IF(SUM(AA56:AE56)=0,IF(COUNTIF($AA56:$AE56,"=0")>0,"$0","-"),SUM(AA56:AE56)),"-") -> 941030 | AG56: =IFERROR($AK56/$P56,"-") -> 2.0830769 | AH56: =IFERROR(AVERAGE(AG56:AG58),"N/A") -> 2.0110263 | AI56: - | AJ56: =IFERROR(IF(ISNUMBER($AI56)=TRUE, $AI56*$P56, $AH56*$P56), "-") -> 1244773.6 | AK56: =IFERROR($AF56*$J56,"-") -> 1289371.1 | AL56: =IFERROR(IF(SUM(Y56,AK56)=0,"-",SUM(Y56,AK56)),"-") -> 2579575.2 | AM56: =IFERROR(IF(SUM($Z56,$AJ56)=0,"-",SUM($Z56,$AJ56)),"-") -> 2420824.7 | AN56: 145916 | AO56: DC | AP56: =IFERROR(AN56*(12/$H56)*$J56,"-") -> 199929.73 | AQ56: =IFERROR(AVERAGE(AP56:AP58),"N/A") -> 180527.78 | AR56: 79205 | AS56: =IFERROR(AR56*(12/$H56)*$J56,"-") -> 108524.31 | AT56: =IFERROR(AVERAGE(AS56:AS58),"N/A") -> 91589.25 | AU56: =IFERROR(IF(SUM(AL56,AP56,AS56)=0,"-",SUM(AL56,AP56,AS56)),"-") -> 2888029.3 | AV56: =IFERROR(IF(SUM(AM56,AP56,AS56)=0,"-",SUM(AM56,AP56,AS56)),"-") -> 2729278.8 | AW56: Ms. Freeborough’s 2024 STI calculated on formula would have been US$518,383. However, the human resources and compensation committee decided to reduce her STI payment by C$41,000 and increase her long-term incentive by the same amount to better align to the company’s target pay mix. | AX56: AH | AY56: sc
A57: =$C57&"_"&$E57&"_"&$K57 -> TSX:K_2023_ | B57: =$C57&"_"&$E57&"_"&$L57 -> TSX:K_2023_CFO | C57: =C56 -> TSX:K | D57: =_xll.ciqfunctions.udf.CIQ(C57,"IQ_Company_Name") -> Kinross Gold Corporation | E57: =E54 -> 2023 | F57: =E57&"-01-01" -> 2023-01-01 | G57: =E57&"-12-31" -> 2023-12-31 | H57: =_xlfn.DAYS(G57,F57)/_xlfn.DAYS(E57&"-12-31",E57&"-01-01")*12 -> 12 | I57: =I56 -> USD | J57: =IF($I57="CAD",1,IF($I57="USD",VLOOKUP($E57,$F$9:$G$11,2,FALSE),"N/A")) -> 1.34954 | L57: =L56 -> CFO | M57: =M56 -> EVP & CFO | N57: =N56 -> Andrea S. Freeborough | O57: 457441 | P57: =IFERROR(O57*(12/$H57)*$J57,"-") -> 617334.93 | Q57: - | R57: =IFERROR(IF((Q57*$J57)=0,"-",(Q57*$J57)),"-") -> - | S57: 478597 | T57: =IFERROR(S57*(12/$H57)*$J57,"-") -> 645885.8 | U57: =IFERROR($T57/$P57,"-") -> 1.0462486 | W57: - | X57: =IFERROR(IF(ISNUMBER($W57)=TRUE, $W57*$P57,$V57*$P57),"-") -> 0 | Y57: =IFERROR(IF(SUM(P57,T57)=0,"-",SUM(P57,T57)),"-") -> 1263220.7 | Z57: =IFERROR(IF(SUM(P57,X57)=0,"-",SUM(P57,X57)),"-") -> 617334.93 | AA57: 413755.2 | AB57: 505700.8 | AC57: - | AD57: - | AE57: - | AF57: =IFERROR(IF(SUM(AA57:AE57)=0,IF(COUNTIF($AA57:$AE57,"=0")>0,"$0","-"),SUM(AA57:AE57)),"-") -> 919456 | AG57: =IFERROR($AK57/$P57,"-") -> 2.0099991 | AI57: - | AJ57: =IFERROR(IF(ISNUMBER($AI57)=TRUE, $AI57*$P57, $AH57*$P57), "-") -> 0 | AK57: =IFERROR($AF57*$J57,"-") -> 1240842.7 | AL57: =IFERROR(IF(SUM(Y57,AK57)=0,"-",SUM(Y57,AK57)),"-") -> 2504063.4 | AM57: =IFERROR(IF(SUM($Z57,$AJ57)=0,"-",SUM($Z57,$AJ57)),"-") -> 617334.93 | AN57: 130370 | AO57: DC | AP57: =IFERROR(AN57*(12/$H57)*$J57,"-") -> 175939.53 | AR57: 63539 | AS57: =IFERROR(AR57*(12/$H57)*$J57,"-") -> 85748.422 | AU57: =IFERROR(IF(SUM(AL57,AP57,AS57)=0,"-",SUM(AL57,AP57,AS57)),"-") -> 2765751.3 | AV57: =IFERROR(IF(SUM(AM57,AP57,AS57)=0,"-",SUM(AM57,AP57,AS57)),"-") -> 879022.88 | AW57: - | AX57: AH | AY57: sc
A58: =$C58&"_"&$E58&"_"&$K58 -> TSX:K_2022_ | B58: =$C58&"_"&$E58&"_"&$L58 -> TSX:K_2022_CFO | C58: =C57 -> TSX:K | D58: =_xll.ciqfunctions.udf.CIQ(C58,"IQ_Company_Name") -> Kinross Gold Corporation | E58: =E55 -> 2022 | F58: =E58&"-01-01" -> 2022-01-01 | G58: =E58&"-12-31" -> 2022-12-31 | H58: =_xlfn.DAYS(G58,F58)/_xlfn.DAYS(E58&"-12-31",E58&"-01-01")*12 -> 12 | I58: =I57 -> USD | J58: =IF($I58="CAD",1,IF($I58="USD",VLOOKUP($E58,$F$9:$G$11,2,FALSE),"N/A")) -> 1.30175 | L58: =L57 -> CFO | M58: =M57 -> EVP & CFO | N58: =N57 -> Andrea S. Freeborough | O58: 446671 | P58: =IFERROR(O58*(12/$H58)*$J58,"-") -> 581453.97 | Q58: - | R58: =IFERROR(IF((Q58*$J58)=0,"-",(Q58*$J58)),"-") -> - | S58: 345724 | T58: =IFERROR(S58*(12/$H58)*$J58,"-") -> 450046.22 | U58: =IFERROR($T58/$P58,"-") -> 0.77400145 | W58: - | X58: =IFERROR(IF(ISNUMBER($W58)=TRUE, $W58*$P58,$V58*$P58),"-") -> 0 | Y58: =IFERROR(IF(SUM(P58,T58)=0,"-",SUM(P58,T58)),"-") -> 1031500.2 | Z58: =IFERROR(IF(SUM(P58,X58)=0,"-",SUM(P58,X58)),"-") -> 581453.97 | AA58: 389944.35 | AB58: 476598.65 | AC58: - | AD58: - | AE58: - | AF58: =IFERROR(IF(SUM(AA58:AE58)=0,IF(COUNTIF($AA58:$AE58,"=0")>0,"$0","-"),SUM(AA58:AE58)),"-") -> 866543 | AG58: =IFERROR($AK58/$P58,"-") -> 1.9400028 | AI58: - | AJ58: =IFERROR(IF(ISNUMBER($AI58)=TRUE, $AI58*$P58, $AH58*$P58), "-") -> 0 | AK58: =IFERROR($AF58*$J58,"-") -> 1128022.4 | AL58: =IFERROR(IF(SUM(Y58,AK58)=0,"-",SUM(Y58,AK58)),"-") -> 2159522.5 | AM58: =IFERROR(IF(SUM($Z58,$AJ58)=0,"-",SUM($Z58,$AJ58)),"-") -> 581453.97 | AN58: 127301 | AO58: DC | AP58: =IFERROR(AN58*(12/$H58)*$J58,"-") -> 165714.08 | AR58: 61836 | AS58: =IFERROR(AR58*(12/$H58)*$J58,"-") -> 80495.013 | AU58: =IFERROR(IF(SUM(AL58,AP58,AS58)=0,"-",SUM(AL58,AP58,AS58)),"-") -> 2405731.6 | AV58: =IFERROR(IF(SUM(AM58,AP58,AS58)=0,"-",SUM(AM58,AP58,AS58)),"-") -> 827663.06 | AW58: - | AX58: AH | AY58: sc
A59: =$C59&"_"&$E59&"_"&$K59 -> TSX:K_2024_ | B59: =$C59&"_"&$E59&"_"&$L59 -> TSX:K_2024_NEO1 | C59: =C58 -> TSX:K | D59: =_xll.ciqfunctions.udf.CIQ(C59,"IQ_Company_Name") -> Kinross Gold Corporation | E59: =E56 -> 2024 | F59: =E59&"-01-01" -> 2024-01-01 | G59: =E59&"-12-31" -> 2024-12-31 | H59: =_xlfn.DAYS(G59,F59)/_xlfn.DAYS(E59&"-12-31",E59&"-01-01")*12 -> 12 | I59: =I58 -> USD | J59: =IF($I59="CAD",1,IF($I59="USD",VLOOKUP($E59,$F$9:$G$11,2,FALSE),"N/A")) -> 1.37017 | L59: NEO1 | M59: President | N59: Geoffrey P. Gold | O59: 625500 | P59: =IFERROR(O59*(12/$H59)*$J59,"-") -> 857041.34 | Q59: - | R59: 900000 | S59: 977517 | T59: =IFERROR(S59*(12/$H59)*$J59,"-") -> 1339364.5 | U59: =IFERROR($T59/$P59,"-") -> 1.562777 | V59: =IFERROR(AVERAGE(U59:U61),"N/A") -> 1.4304419 | W59: 1.4 | X59: =IFERROR(IF(ISNUMBER($W59)=TRUE, $W59*$P59,$V59*$P59),"-") -> 1199857.9 | Y59: =IFERROR(IF(SUM(P59,T59)=0,"-",SUM(P59,T59)),"-") -> 2196405.8 | Z59: =IFERROR(IF(SUM(P59,X59)=0,"-",SUM(P59,X59)),"-") -> 2056899.2 | AA59: 721201.5 | AB59: 881468.5 | AC59: - | AD59: - | AE59: - | AF59: =IFERROR(IF(SUM(AA59:AE59)=0,IF(COUNTIF($AA59:$AE59,"=0")>0,"$0","-"),SUM(AA59:AE59)),"-") -> 1602670 | AG59: =IFERROR($AK59/$P59,"-") -> 2.5622222 | AH59: =IFERROR(AVERAGE(AG59:AG61),"N/A") -> 2.4377253 | AI59: - | AJ59: =IFERROR(IF(ISNUMBER($AI59)=TRUE, $AI59*$P59, $AH59*$P59), "-") -> 2089231.3 | AK59: =IFERROR($AF59*$J59,"-") -> 2195930.4 | AL59: =IFERROR(IF(SUM(Y59,AK59)=0,"-",SUM(Y59,AK59)),"-") -> 4392336.2 | AM59: =IFERROR(IF(SUM($Z59,$AJ59)=0,"-",SUM($Z59,$AJ59)),"-") -> 4146130.5 | AN59: 281475 | AO59: DC | AP59: =IFERROR(AN59*(12/$H59)*$J59,"-") -> 385668.6 | AQ59: =IFERROR(AVERAGE(AP59:AP61),"N/A") -> 378221.24 | AR59: 105108 | AS59: =IFERROR(AR59*(12/$H59)*$J59,"-") -> 144015.83 | AT59: =IFERROR(AVERAGE(AS59:AS61),"N/A") -> 163070.3 | AU59: =IFERROR(IF(SUM(AL59,AP59,AS59)=0,"-",SUM(AL59,AP59,AS59)),"-") -> 4922020.6 | AV59: =IFERROR(IF(SUM(AM59,AP59,AS59)=0,"-",SUM(AM59,AP59,AS59)),"-") -> 4675814.9 | AW59: Mr. Gold’s 2024 STI calculated on formula would have been US$1,116,517. However, the human resources and compensation committee decided to reduce his STI payment by C$200,000 and increase his long-term incentive by the same amount to better align to the company’s target pay mix. | AX59: AH | AY59: sc
A60: =$C60&"_"&$E60&"_"&$K60 -> TSX:K_2023_ | B60: =$C60&"_"&$E60&"_"&$L60 -> TSX:K_2023_NEO1 | C60: =C59 -> TSX:K | D60: =_xll.ciqfunctions.udf.CIQ(C60,"IQ_Company_Name") -> Kinross Gold Corporation | E60: =E57 -> 2023 | F60: =E60&"-01-01" -> 2023-01-01 | G60: =E60&"-12-31" -> 2023-12-31 | H60: =_xlfn.DAYS(G60,F60)/_xlfn.DAYS(E60&"-12-31",E60&"-01-01")*12 -> 12 | I60: =I59 -> USD | J60: =IF($I60="CAD",1,IF($I60="USD",VLOOKUP($E60,$F$9:$G$11,2,FALSE),"N/A")) -> 1.34954 | L60: =L59 -> NEO1 | M60: =M59 -> President | N60: =N59 -> Geoffrey P. Gold | O60: 635124 | P60: =IFERROR(O60*(12/$H60)*$J60,"-") -> 857125.24 | Q60: - | R60: =IFERROR(IF((Q60*$J60)=0,"-",(Q60*$J60)),"-") -> - | S60: 950494 | T60: =IFERROR(S60*(12/$H60)*$J60,"-") -> 1282729.7 | U60: =IFERROR($T60/$P60,"-") -> 1.4965487 | W60: - | X60: =IFERROR(IF(ISNUMBER($W60)=TRUE, $W60*$P60,$V60*$P60),"-") -> 0 | Y60: =IFERROR(IF(SUM(P60,T60)=0,"-",SUM(P60,T60)),"-") -> 2139854.9 | Z60: =IFERROR(IF(SUM(P60,X60)=0,"-",SUM(P60,X60)),"-") -> 857125.24 | AA60: 700496.55 | AB60: 856162.45 | AC60: - | AD60: - | AE60: - | AF60: =IFERROR(IF(SUM(AA60:AE60)=0,IF(COUNTIF($AA60:$AE60,"=0")>0,"$0","-"),SUM(AA60:AE60)),"-") -> 1556659 | AG60: =IFERROR($AK60/$P60,"-") -> 2.4509529 | AI60: - | AJ60: =IFERROR(IF(ISNUMBER($AI60)=TRUE, $AI60*$P60, $AH60*$P60), "-") -> 0 | AK60: =IFERROR($AF60*$J60,"-") -> 2100773.6 | AL60: =IFERROR(IF(SUM(Y60,AK60)=0,"-",SUM(Y60,AK60)),"-") -> 4240628.5 | AM60: =IFERROR(IF(SUM($Z60,$AJ60)=0,"-",SUM($Z60,$AJ60)),"-") -> 857125.24 | AN60: 285806 | AO60: DC | AP60: =IFERROR(AN60*(12/$H60)*$J60,"-") -> 385706.63 | AR60: 128015 | AS60: =IFERROR(AR60*(12/$H60)*$J60,"-") -> 172761.36 | AU60: =IFERROR(IF(SUM(AL60,AP60,AS60)=0,"-",SUM(AL60,AP60,AS60)),"-") -> 4799096.5 | AV60: =IFERROR(IF(SUM(AM60,AP60,AS60)=0,"-",SUM(AM60,AP60,AS60)),"-") -> 1415593.2 | AW60: - | AX60: AH | AY60: sc
A61: =$C61&"_"&$E61&"_"&$K61 -> TSX:K_2022_ | B61: =$C61&"_"&$E61&"_"&$L61 -> TSX:K_2022_NEO1 | C61: =C60 -> TSX:K | D61: =_xll.ciqfunctions.udf.CIQ(C61,"IQ_Company_Name") -> Kinross Gold Corporation | E61: =E58 -> 2022 | F61: =E61&"-01-01" -> 2022-01-01 | G61: =E61&"-12-31" -> 2022-12-31 | H61: =_xlfn.DAYS(G61,F61)/_xlfn.DAYS(E61&"-12-31",E61&"-01-01")*12 -> 12 | I61: =I60 -> USD | J61: =IF($I61="CAD",1,IF($I61="USD",VLOOKUP($E61,$F$9:$G$11,2,FALSE),"N/A")) -> 1.30175 | L61: =L60 -> NEO1 | M61: =M60 -> President | N61: =N60 -> Geoffrey P. Gold | O61: 620172 | P61: =IFERROR(O61*(12/$H61)*$J61,"-") -> 807308.9 | Q61: - | R61: =IFERROR(IF((Q61*$J61)=0,"-",(Q61*$J61)),"-") -> - | S61: 764052 | T61: =IFERROR(S61*(12/$H61)*$J61,"-") -> 994604.69 | U61: =IFERROR($T61/$P61,"-") -> 1.2320002 | W61: - | X61: =IFERROR(IF(ISNUMBER($W61)=TRUE, $W61*$P61,$V61*$P61),"-") -> 0 | Y61: =IFERROR(IF(SUM(P61,T61)=0,"-",SUM(P61,T61)),"-") -> 1801913.6 | Z61: =IFERROR(IF(SUM(P61,X61)=0,"-",SUM(P61,X61)),"-") -> 807308.9 | AA61: 641878.2 | AB61: 784517.8 | AC61: - | AD61: - | AE61: - | AF61: =IFERROR(IF(SUM(AA61:AE61)=0,IF(COUNTIF($AA61:$AE61,"=0")>0,"$0","-"),SUM(AA61:AE61)),"-") -> 1426396 | AG61: =IFERROR($AK61/$P61,"-") -> 2.3000006 | AI61: - | AJ61: =IFERROR(IF(ISNUMBER($AI61)=TRUE, $AI61*$P61, $AH61*$P61), "-") -> 0 | AK61: =IFERROR($AF61*$J61,"-") -> 1856811 | AL61: =IFERROR(IF(SUM(Y61,AK61)=0,"-",SUM(Y61,AK61)),"-") -> 3658724.6 | AM61: =IFERROR(IF(SUM($Z61,$AJ61)=0,"-",SUM($Z61,$AJ61)),"-") -> 807308.9 | AN61: 279077 | AO61: DC | AP61: =IFERROR(AN61*(12/$H61)*$J61,"-") -> 363288.48 | AR61: 132463 | AS61: =IFERROR(AR61*(12/$H61)*$J61,"-") -> 172433.71 | AU61: =IFERROR(IF(SUM(AL61,AP61,AS61)=0,"-",SUM(AL61,AP61,AS61)),"-") -> 4194446.8 | AV61: =IFERROR(IF(SUM(AM61,AP61,AS61)=0,"-",SUM(AM61,AP61,AS61)),"-") -> 1343031.1 | AW61: - | AX61: AH | AY61: sc
A62: =$C62&"_"&$E62&"_"&$K62 -> TSX:K_2024_COO | B62: =$C62&"_"&$E62&"_"&$L62 -> TSX:K_2024_NEO2 | C62: =C61 -> TSX:K | D62: =_xll.ciqfunctions.udf.CIQ(C62,"IQ_Company_Name") -> Kinross Gold Corporation | E62: =E59 -> 2024 | F62: =E62&"-01-01" -> 2024-01-01 | G62: =E62&"-12-31" -> 2024-12-31 | H62: =_xlfn.DAYS(G62,F62)/_xlfn.DAYS(E62&"-12-31",E62&"-01-01")*12 -> 12 | I62: =I61 -> USD | J62: =IF($I62="CAD",1,IF($I62="USD",VLOOKUP($E62,$F$9:$G$11,2,FALSE),"N/A")) -> 1.37017 | K62: COO | L62: NEO2 | M62: EVP & COO | N62: Claude J.S. Schimper | O62: 451750 | P62: =IFERROR(O62*(12/$H62)*$J62,"-") -> 618974.3 | Q62: - | R62: 670000 | S62: 523465 | T62: =IFERROR(S62*(12/$H62)*$J62,"-") -> 717236.04 | U62: =IFERROR($T62/$P62,"-") -> 1.1587493 | V62: =IFERROR(AVERAGE(U62:U64),"N/A") -> 1.0098415 | W62: 0.9 | X62: =IFERROR(IF(ISNUMBER($W62)=TRUE, $W62*$P62,$V62*$P62),"-") -> 557076.87 | Y62: =IFERROR(IF(SUM(P62,T62)=0,"-",SUM(P62,T62)),"-") -> 1336210.3 | Z62: =IFERROR(IF(SUM(P62,X62)=0,"-",SUM(P62,X62)),"-") -> 1176051.2 | AA62: 439101 | AB62: 536679 | AC62: - | AD62: - | AE62: - | AF62: =IFERROR(IF(SUM(AA62:AE62)=0,IF(COUNTIF($AA62:$AE62,"=0")>0,"$0","-"),SUM(AA62:AE62)),"-") -> 975780 | AG62: =IFERROR($AK62/$P62,"-") -> 2.16 | AH62: =IFERROR(AVERAGE(AG62:AG64),"N/A") -> 2.1538277 | AI62: - | AJ62: =IFERROR(IF(ISNUMBER($AI62)=TRUE, $AI62*$P62, $AH62*$P62), "-") -> 1333164 | AK62: =IFERROR($AF62*$J62,"-") -> 1336984.5 | AL62: =IFERROR(IF(SUM(Y62,AK62)=0,"-",SUM(Y62,AK62)),"-") -> 2673194.8 | AM62: =IFERROR(IF(SUM($Z62,$AJ62)=0,"-",SUM($Z62,$AJ62)),"-") -> 2509215.1 | AN62: 128750 | AO62: DC | AP62: =IFERROR(AN62*(12/$H62)*$J62,"-") -> 176409.39 | AQ62: =IFERROR(AVERAGE(AP62:AP64),"N/A") -> 169084.19 | AR62: 97423 | AS62: =IFERROR(AR62*(12/$H62)*$J62,"-") -> 133486.07 | AT62: =IFERROR(AVERAGE(AS62:AS64),"N/A") -> 487819.12 | AU62: =IFERROR(IF(SUM(AL62,AP62,AS62)=0,"-",SUM(AL62,AP62,AS62)),"-") -> 2983090.3 | AV62: =IFERROR(IF(SUM(AM62,AP62,AS62)=0,"-",SUM(AM62,AP62,AS62)),"-") -> 2819110.6 | AW62: - | AX62: AH | AY62: sc
A63: =$C63&"_"&$E63&"_"&$K63 -> TSX:K_2023_COO | B63: =$C63&"_"&$E63&"_"&$L63 -> TSX:K_2023_NEO2 | C63: =C62 -> TSX:K | D63: =_xll.ciqfunctions.udf.CIQ(C63,"IQ_Company_Name") -> Kinross Gold Corporation | E63: =E60 -> 2023 | F63: =E63&"-01-01" -> 2023-01-01 | G63: =E63&"-12-31" -> 2023-12-31 | H63: =_xlfn.DAYS(G63,F63)/_xlfn.DAYS(E63&"-12-31",E63&"-01-01")*12 -> 12 | I63: =I62 -> USD | J63: =IF($I63="CAD",1,IF($I63="USD",VLOOKUP($E63,$F$9:$G$11,2,FALSE),"N/A")) -> 1.34954 | K63: COO | L63: =L62 -> NEO2 | M63: =M62 -> EVP & COO | N63: =N62 -> Claude J.S. Schimper | O63: 453660 | P63: =IFERROR(O63*(12/$H63)*$J63,"-") -> 612232.32 | Q63: - | R63: =IFERROR(IF((Q63*$J63)=0,"-",(Q63*$J63)),"-") -> - | S63: 479746 | T63: =IFERROR(S63*(12/$H63)*$J63,"-") -> 647436.42 | U63: =IFERROR($T63/$P63,"-") -> 1.0575012 | W63: - | X63: =IFERROR(IF(ISNUMBER($W63)=TRUE, $W63*$P63,$V63*$P63),"-") -> 0 | Y63: =IFERROR(IF(SUM(P63,T63)=0,"-",SUM(P63,T63)),"-") -> 1259668.7 | Z63: =IFERROR(IF(SUM(P63,X63)=0,"-",SUM(P63,X63)),"-") -> 612232.32 | AA63: 449123.4 | AB63: 548928.6 | AC63: - | AD63: - | AE63: - | AF63: =IFERROR(IF(SUM(AA63:AE63)=0,IF(COUNTIF($AA63:$AE63,"=0")>0,"$0","-"),SUM(AA63:AE63)),"-") -> 998052 | AG63: =IFERROR($AK63/$P63,"-") -> 2.2 | AI63: - | AJ63: =IFERROR(IF(ISNUMBER($AI63)=TRUE, $AI63*$P63, $AH63*$P63), "-") -> 0 | AK63: =IFERROR($AF63*$J63,"-") -> 1346911.1 | AL63: =IFERROR(IF(SUM(Y63,AK63)=0,"-",SUM(Y63,AK63)),"-") -> 2606579.8 | AM63: =IFERROR(IF(SUM($Z63,$AJ63)=0,"-",SUM($Z63,$AJ63)),"-") -> 612232.32 | AN63: 129293 | AO63: DC | AP63: =IFERROR(AN63*(12/$H63)*$J63,"-") -> 174486.08 | AR63: 156583 | AS63: =IFERROR(AR63*(12/$H63)*$J63,"-") -> 211315.02 | AU63: =IFERROR(IF(SUM(AL63,AP63,AS63)=0,"-",SUM(AL63,AP63,AS63)),"-") -> 2992380.9 | AV63: =IFERROR(IF(SUM(AM63,AP63,AS63)=0,"-",SUM(AM63,AP63,AS63)),"-") -> 998033.41 | AW63: Mr. Schimper's other compensation includes administrative costs relative to his long-term savings plan, hence relatively high amount in 2022 (prior to which represented amounts of >$1M). | AX63: AH | AY63: sc
A64: =$C64&"_"&$E64&"_"&$K64 -> TSX:K_2022_COO | B64: =$C64&"_"&$E64&"_"&$L64 -> TSX:K_2022_NEO2 | C64: =C63 -> TSX:K | D64: =_xll.ciqfunctions.udf.CIQ(C64,"IQ_Company_Name") -> Kinross Gold Corporation | E64: =E61 -> 2022 | F64: =E64&"-01-01" -> 2022-01-01 | G64: =E64&"-12-31" -> 2022-12-31 | H64: =_xlfn.DAYS(G64,F64)/_xlfn.DAYS(E64&"-12-31",E64&"-01-01")*12 -> 12 | I64: =I63 -> USD | J64: =IF($I64="CAD",1,IF($I64="USD",VLOOKUP($E64,$F$9:$G$11,2,FALSE),"N/A")) -> 1.30175 | K64: COO | L64: =L63 -> NEO2 | M64: =M63 -> EVP & COO | N64: =N63 -> Claude J.S. Schimper | O64: 421588 | P64: =IFERROR(O64*(12/$H64)*$J64,"-") -> 548802.18 | Q64: - | R64: =IFERROR(IF((Q64*$J64)=0,"-",(Q64*$J64)),"-") -> - | S64: =398239-75000*0.7383 -> 342866.5 | T64: =IFERROR(S64*(12/$H64)*$J64,"-") -> 446326.47 | U64: =IFERROR($T64/$P64,"-") -> 0.81327386 | W64: - | X64: =IFERROR(IF(ISNUMBER($W64)=TRUE, $W64*$P64,$V64*$P64),"-") -> 0 | Y64: =IFERROR(IF(SUM(P64,T64)=0,"-",SUM(P64,T64)),"-") -> 995128.65 | Z64: =IFERROR(IF(SUM(P64,X64)=0,"-",SUM(P64,X64)),"-") -> 548802.18 | AA64: 398682 | AB64: 487278 | AC64: - | AD64: - | AE64: - | AF64: =IFERROR(IF(SUM(AA64:AE64)=0,IF(COUNTIF($AA64:$AE64,"=0")>0,"$0","-"),SUM(AA64:AE64)),"-") -> 885960 | AG64: =IFERROR($AK64/$P64,"-") -> 2.101483 | AI64: - | AJ64: =IFERROR(IF(ISNUMBER($AI64)=TRUE, $AI64*$P64, $AH64*$P64), "-") -> 0 | AK64: =IFERROR($AF64*$J64,"-") -> 1153298.4 | AL64: =IFERROR(IF(SUM(Y64,AK64)=0,"-",SUM(Y64,AK64)),"-") -> 2148427.1 | AM64: =IFERROR(IF(SUM($Z64,$AJ64)=0,"-",SUM($Z64,$AJ64)),"-") -> 548802.18 | AN64: 120113 | AO64: DC | AP64: =IFERROR(AN64*(12/$H64)*$J64,"-") -> 156357.1 | AR64: 859348 | AS64: =IFERROR(AR64*(12/$H64)*$J64,"-") -> 1118656.3 | AU64: =IFERROR(IF(SUM(AL64,AP64,AS64)=0,"-",SUM(AL64,AP64,AS64)),"-") -> 3423440.4 | AV64: =IFERROR(IF(SUM(AM64,AP64,AS64)=0,"-",SUM(AM64,AP64,AS64)),"-") -> 1823815.5 | AW64: Mr. Schimper received a one-time performance-based cash award in the amount of C$75,000, awarded in 2021 and paid in 2022, upon achievement of specific safety and operational objectives at Tasiast.This has been excluded from the benchmarking. | AX64: AH | AY64: sc
A65: =$C65&"_"&$E65&"_"&$K65 -> TSX:K_2024_Tech | B65: =$C65&"_"&$E65&"_"&$L65 -> TSX:K_2024_NEO3 | C65: =C64 -> TSX:K | D65: =_xll.ciqfunctions.udf.CIQ(C65,"IQ_Company_Name") -> Kinross Gold Corporation | E65: =E62 -> 2024 | F65: =E65&"-01-01" -> 2024-01-01 | G65: =E65&"-12-31" -> 2024-12-31 | H65: =_xlfn.DAYS(G65,F65)/_xlfn.DAYS(E65&"-12-31",E65&"-01-01")*12 -> 12 | I65: =I64 -> USD | J65: =IF($I65="CAD",1,IF($I65="USD",VLOOKUP($E65,$F$9:$G$11,2,FALSE),"N/A")) -> 1.37017 | K65: Tech | L65: NEO3 | M65: SVP, Technical Services | N65: William D. Dunford | O65: 354450 | P65: =IFERROR(O65*(12/$H65)*$J65,"-") -> 485656.76 | Q65: - | R65: 535000 | S65: 338943 | T65: =IFERROR(S65*(12/$H65)*$J65,"-") -> 464409.53 | U65: =IFERROR($T65/$P65,"-") -> 0.95625053 | V65: =IFERROR(AVERAGE(U65:U67),"N/A") -> 0.95625053 | W65: 0.75 | X65: =IFERROR(IF(ISNUMBER($W65)=TRUE, $W65*$P65,$V65*$P65),"-") -> 364242.57 | Y65: =IFERROR(IF(SUM(P65,T65)=0,"-",SUM(P65,T65)),"-") -> 950066.29 | Z65: =IFERROR(IF(SUM(P65,X65)=0,"-",SUM(P65,X65)),"-") -> 849899.32 | AA65: 338145.3 | AB65: 413288.7 | AC65: - | AD65: - | AE65: - | AF65: =IFERROR(IF(SUM(AA65:AE65)=0,IF(COUNTIF($AA65:$AE65,"=0")>0,"$0","-"),SUM(AA65:AE65)),"-") -> 751434 | AG65: =IFERROR($AK65/$P65,"-") -> 2.12 | AH65: =IFERROR(AVERAGE(AG65:AG67),"N/A") -> 2.12 | AI65: - | AJ65: =IFERROR(IF(ISNUMBER($AI65)=TRUE, $AI65*$P65, $AH65*$P65), "-") -> 1029592.3 | AK65: =IFERROR($AF65*$J65,"-") -> 1029592.3 | AL65: =IFERROR(IF(SUM(Y65,AK65)=0,"-",SUM(Y65,AK65)),"-") -> 1979658.6 | AM65: =IFERROR(IF(SUM($Z65,$AJ65)=0,"-",SUM($Z65,$AJ65)),"-") -> 1879491.6 | AN65: 93044 | AO65: DC | AP65: =IFERROR(AN65*(12/$H65)*$J65,"-") -> 127486.1 | AQ65: =IFERROR(AVERAGE(AP65:AP67),"N/A") -> 127486.1 | AR65: 89138 | AS65: =IFERROR(AR65*(12/$H65)*$J65,"-") -> 122134.21 | AT65: =IFERROR(AVERAGE(AS65:AS67),"N/A") -> 122134.21 | AU65: =IFERROR(IF(SUM(AL65,AP65,AS65)=0,"-",SUM(AL65,AP65,AS65)),"-") -> 2229278.9 | AV65: =IFERROR(IF(SUM(AM65,AP65,AS65)=0,"-",SUM(AM65,AP65,AS65)),"-") -> 2129112 | AW65: - | AX65: AH | AY65: sc
A66: =$C66&"_"&$E66&"_"&$K66 -> TSX:K_2023_Tech | B66: =$C66&"_"&$E66&"_"&$L66 -> TSX:K_2023_NEO3 | C66: =C65 -> TSX:K | D66: =_xll.ciqfunctions.udf.CIQ(C66,"IQ_Company_Name") -> Kinross Gold Corporation | E66: =E63 -> 2023 | F66: =E66&"-01-01" -> 2023-01-01 | G66: =E66&"-12-31" -> 2023-12-31 | H66: =_xlfn.DAYS(G66,F66)/_xlfn.DAYS(E66&"-12-31",E66&"-01-01")*12 -> 12 | I66: =I65 -> USD | J66: =IF($I66="CAD",1,IF($I66="USD",VLOOKUP($E66,$F$9:$G$11,2,FALSE),"N/A")) -> 1.34954 | K66: Tech | L66: =L65 -> NEO3 | M66: =M65 -> SVP, Technical Services | N66: =N65 -> William D. Dunford | O66: - | P66: =IFERROR(O66*(12/$H66)*$J66,"-") -> - | Q66: - | R66: =IFERROR(IF((Q66*$J66)=0,"-",(Q66*$J66)),"-") -> - | U66: =IFERROR($T66/$P66,"-") -> - | W66: - | X66: =IFERROR(IF(ISNUMBER($W66)=TRUE, $W66*$P66,$V66*$P66),"-") -> - | Y66: =IFERROR(IF(SUM(P66,T66)=0,"-",SUM(P66,T66)),"-") -> - | Z66: =IFERROR(IF(SUM(P66,X66)=0,"-",SUM(P66,X66)),"-") -> - | AA66: - | AB66: - | AC66: - | AD66: - | AE66: - | AF66: =IFERROR(IF(SUM(AA66:AE66)=0,IF(COUNTIF($AA66:$AE66,"=0")>0,"$0","-"),SUM(AA66:AE66)),"-") -> - | AG66: =IFERROR($AK66/$P66,"-") -> - | AI66: - | AJ66: =IFERROR(IF(ISNUMBER($AI66)=TRUE, $AI66*$P66, $AH66*$P66), "-") -> - | AK66: =IFERROR($AF66*$J66,"-") -> - | AL66: =IFERROR(IF(SUM(Y66,AK66)=0,"-",SUM(Y66,AK66)),"-") -> - | AM66: =IFERROR(IF(SUM($Z66,$AJ66)=0,"-",SUM($Z66,$AJ66)),"-") -> - | AN66: - | AP66: =IFERROR(AN66*(12/$H66)*$J66,"-") -> - | AR66: - | AS66: =IFERROR(AR66*(12/$H66)*$J66,"-") -> - | AW66: Appointed Sept 1, 2023 ; was VP Mining Operations until Aug 31, 2023 | AX66: AH | AY66: sc
A67: =$C67&"_"&$E67&"_"&$K67 -> TSX:K_2022_Tech | B67: =$C67&"_"&$E67&"_"&$L67 -> TSX:K_2022_NEO3 | C67: =C66 -> TSX:K | D67: =_xll.ciqfunctions.udf.CIQ(C67,"IQ_Company_Name") -> Kinross Gold Corporation | E67: =E64 -> 2022 | F67: =E67&"-01-01" -> 2022-01-01 | G67: =E67&"-12-31" -> 2022-12-31 | H67: =_xlfn.DAYS(G67,F67)/_xlfn.DAYS(E67&"-12-31",E67&"-01-01")*12 -> 12 | I67: =I66 -> USD | J67: =IF($I67="CAD",1,IF($I67="USD",VLOOKUP($E67,$F$9:$G$11,2,FALSE),"N/A")) -> 1.30175 | K67: Tech | L67: =L66 -> NEO3 | M67: =M66 -> SVP, Technical Services | N67: =N66 -> William D. Dunford | AN67: - | AP67: =IFERROR(AN67*(12/$H67)*$J67,"-") -> - | AR67: - | AS67: =IFERROR(AR67*(12/$H67)*$J67,"-") -> - | AX67: AH | AY67: sc
A68: =$C68&"_"&$E68&"_"&$K68 -> TSX:LUN_2024_ | B68: =$C68&"_"&$E68&"_"&$L68 -> TSX:LUN_2024_CEO | C68: =D6 -> TSX:LUN | D68: =_xll.ciqfunctions.udf.CIQ(C68,"IQ_Company_Name") -> Lundin Mining Corporation | E68: =$F$9 -> 2024 | F68: =E68&"-01-01" -> 2024-01-01 | G68: =E68&"-12-31" -> 2024-12-31 | H68: =_xlfn.DAYS(G68,F68)/_xlfn.DAYS(E68&"-12-31",E68&"-01-01")*12 -> 12 | I68: USD | J68: =IF($I68="CAD",1,IF($I68="USD",VLOOKUP($E68,$F$9:$G$11,2,FALSE),"N/A")) -> 1.37017 | L68: CEO | M68: President & CEO | N68: Jack Lundin | O68: 620620 | P68: 850000 | Q68: - | R68: 850000 | S68: 1463932 | T68: =IFERROR(S68*(12/$H68)*$J68,"-") -> 2005835.7 | U68: =IFERROR($T68/$P68,"-") -> 2.3598067 | V68: =IFERROR(AVERAGE(U68:U70),"N/A") -> 1.6330075 | W68: 1.2 | X68: =IFERROR(IF(ISNUMBER($W68)=TRUE, $W68*$P68,$V68*$P68),"-") -> 1020000 | Y68: =IFERROR(IF(SUM(P68,T68)=0,"-",SUM(P68,T68)),"-") -> 2855835.7 | Z68: =IFERROR(IF(SUM(P68,X68)=0,"-",SUM(P68,X68)),"-") -> 1870000 | AA68: - | AB68: =915876 -> 915876 | AC68: 916534 | AD68: - | AE68: - | AF68: =IFERROR(IF(SUM(AA68:AE68)=0,IF(COUNTIF($AA68:$AE68,"=0")>0,"$0","-"),SUM(AA68:AE68)),"-") -> 1832410 | AG68: =IFERROR($AK68/$P68,"-") -> 2.9537802 | AH68: =IFERROR(AVERAGE(AG68:AG70),"N/A") -> 3.5038333 | AI68: 3 | AJ68: =IFERROR(IF(ISNUMBER($AI68)=TRUE, $AI68*$P68, $AH68*$P68), "-") -> 2550000 | AK68: =IFERROR($AF68*$J68,"-") -> 2510713.2 | AL68: =IFERROR(IF(SUM(Y68,AK68)=0,"-",SUM(Y68,AK68)),"-") -> 5366548.9 | AM68: =IFERROR(IF(SUM($Z68,$AJ68)=0,"-",SUM($Z68,$AJ68)),"-") -> 4420000 | AN68: N/A | AO68: N/A | AP68: =IFERROR(AN68*(12/$H68)*$J68,"-") -> - | AQ68: =IFERROR(AVERAGE(AP68:AP70),"N/A") -> N/A | AR68: 33403 | AS68: =IFERROR(AR68*(12/$H68)*$J68,"-") -> 45767.789 | AT68: =IFERROR(AVERAGE(AS68:AS70),"N/A") -> 44137.125 | AU68: =IFERROR(IF(SUM(AL68,AP68,AS68)=0,"-",SUM(AL68,AP68,AS68)),"-") -> 5412316.7 | AV68: =IFERROR(IF(SUM(AM68,AP68,AS68)=0,"-",SUM(AM68,AP68,AS68)),"-") -> 4465767.8 | AW68: A portion of the STIP amounts awarded to Messrs. Lundin, Poulsen, Morel, and Brady is contingent upon the successful closing of the transaction involving the sale of the Neves Corvo and Zinkgruvan operations which is anticipated to close in mid-2025. The amounts payable on closing are C$425,000 for Jack Lundin, C$362,500 for Teitur Paulsen, CLP132,597,850 for Juan Andres Morel and C$307,500 for Peter Brady. | AX68: AH | AY68: sc
A69: =$C69&"_"&$E69&"_"&$K69 -> TSX:LUN_2023_ | B69: =$C69&"_"&$E69&"_"&$L69 -> TSX:LUN_2023_CEO | C69: =C68 -> TSX:LUN | D69: =_xll.ciqfunctions.udf.CIQ(C69,"IQ_Company_Name") -> Lundin Mining Corporation | E69: =$F$10 -> 2023 | F69: =E69&"-01-01" -> 2023-01-01 | G69: =E69&"-12-31" -> 2023-12-31 | H69: =_xlfn.DAYS(G69,F69)/_xlfn.DAYS(E69&"-12-31",E69&"-01-01")*12 -> 12 | I69: =I68 -> USD | J69: =IF($I69="CAD",1,IF($I69="USD",VLOOKUP($E69,$F$9:$G$11,2,FALSE),"N/A")) -> 1.34954 | L69: =L68 -> CEO | M69: =M68 -> President & CEO | N69: =N68 -> Jack Lundin | O69: 358198 | P69: =IFERROR(O69*(12/$H69)*$J69,"-") -> 483402.53 | Q69: - | R69: =IFERROR(IF((Q69*$J69)=0,"-",(Q69*$J69)),"-") -> - | S69: 324602 | T69: =IFERROR(S69*(12/$H69)*$J69,"-") -> 438063.38 | U69: =IFERROR($T69/$P69,"-") -> 0.9062083 | W69: - | X69: =IFERROR(IF(ISNUMBER($W69)=TRUE, $W69*$P69,$V69*$P69),"-") -> 0 | Y69: =IFERROR(IF(SUM(P69,T69)=0,"-",SUM(P69,T69)),"-") -> 921465.91 | Z69: =IFERROR(IF(SUM(P69,X69)=0,"-",SUM(P69,X69)),"-") -> 483402.53 | AA69: =1092544*0.33 -> 360539.52 | AB69: =1092544*0.67 -> 732004.48 | AC69: 359550 | AD69: - | AE69: - | AF69: =IFERROR(IF(SUM(AA69:AE69)=0,IF(COUNTIF($AA69:$AE69,"=0")>0,"$0","-"),SUM(AA69:AE69)),"-") -> 1452094 | AG69: =IFERROR($AK69/$P69,"-") -> 4.0538864 | AI69: - | AJ69: =IFERROR(IF(ISNUMBER($AI69)=TRUE, $AI69*$P69, $AH69*$P69), "-") -> 0 | AK69: =IFERROR($AF69*$J69,"-") -> 1959658.9 | AL69: =IFERROR(IF(SUM(Y69,AK69)=0,"-",SUM(Y69,AK69)),"-") -> 2881124.8 | AM69: =IFERROR(IF(SUM($Z69,$AJ69)=0,"-",SUM($Z69,$AJ69)),"-") -> 483402.53 | AN69: N/A | AO69: N/A | AP69: =IFERROR(AN69*(12/$H69)*$J69,"-") -> - | AR69: 31497 | AS69: =IFERROR(AR69*(12/$H69)*$J69,"-") -> 42506.461 | AU69: =IFERROR(IF(SUM(AL69,AP69,AS69)=0,"-",SUM(AL69,AP69,AS69)),"-") -> 2923631.3 | AV69: =IFERROR(IF(SUM(AM69,AP69,AS69)=0,"-",SUM(AM69,AP69,AS69)),"-") -> 525908.99 | AW69: Jack Lundin was promoted from President to Chief Executive Officer in December 2023 | AX69: AH | AY69: sc
A70: =$C70&"_"&$E70&"_"&$K70 -> TSX:LUN_2022_ | B70: =$C70&"_"&$E70&"_"&$L70 -> TSX:LUN_2022_CEO | C70: =C69 -> TSX:LUN | D70: =_xll.ciqfunctions.udf.CIQ(C70,"IQ_Company_Name") -> Lundin Mining Corporation | E70: =$F$11 -> 2022 | F70: =E70&"-01-01" -> 2022-01-01 | G70: =E70&"-12-31" -> 2022-12-31 | H70: =_xlfn.DAYS(G70,F70)/_xlfn.DAYS(E70&"-12-31",E70&"-01-01")*12 -> 12 | I70: =I69 -> USD | J70: =IF($I70="CAD",1,IF($I70="USD",VLOOKUP($E70,$F$9:$G$11,2,FALSE),"N/A")) -> 1.30175 | L70: =L69 -> CEO | M70: =M69 -> President & CEO | N70: =N69 -> Jack Lundin | O70: - | P70: =IFERROR(O70*(12/$H70)*$J70,"-") -> - | Q70: - | R70: =IFERROR(IF((Q70*$J70)=0,"-",(Q70*$J70)),"-") -> - | S70: - | T70: =IFERROR(S70*(12/$H70)*$J70,"-") -> - | U70: =IFERROR($T70/$P70,"-") -> - | W70: - | X70: =IFERROR(IF(ISNUMBER($W70)=TRUE, $W70*$P70,$V70*$P70),"-") -> - | Y70: =IFERROR(IF(SUM(P70,T70)=0,"-",SUM(P70,T70)),"-") -> - | Z70: =IFERROR(IF(SUM(P70,X70)=0,"-",SUM(P70,X70)),"-") -> - | AA70: - | AB70: - | AC70: - | AD70: - | AE70: - | AF70: =IFERROR(IF(SUM(AA70:AE70)=0,IF(COUNTIF($AA70:$AE70,"=0")>0,"$0","-"),SUM(AA70:AE70)),"-") -> - | AG70: =IFERROR($AK70/$P70,"-") -> - | AI70: - | AJ70: =IFERROR(IF(ISNUMBER($AI70)=TRUE, $AI70*$P70, $AH70*$P70), "-") -> - | AK70: =IFERROR($AF70*$J70,"-") -> - | AL70: =IFERROR(IF(SUM(Y70,AK70)=0,"-",SUM(Y70,AK70)),"-") -> - | AM70: =IFERROR(IF(SUM($Z70,$AJ70)=0,"-",SUM($Z70,$AJ70)),"-") -> - | AN70: - | AO70: - | AP70: =IFERROR(AN70*(12/$H70)*$J70,"-") -> - | AR70: - | AS70: =IFERROR(AR70*(12/$H70)*$J70,"-") -> - | AU70: =IFERROR(IF(SUM(AL70,AP70,AS70)=0,"-",SUM(AL70,AP70,AS70)),"-") -> - | AV70: =IFERROR(IF(SUM(AM70,AP70,AS70)=0,"-",SUM(AM70,AP70,AS70)),"-") -> - | AW70: His performance equity grants for 2022 include an initial on hire grant of 108,500 SUs and 106,400 Options on March 9, 2023, using the fair value of C$7.99 and Black Scholes value of C$2.57 as at March 9, 2023 | AX70: AH | AY70: sc
A71: =$C71&"_"&$E71&"_"&$K71 -> TSX:LUN_2024_ | B71: =$C71&"_"&$E71&"_"&$L71 -> TSX:LUN_2024_CFO | C71: =C70 -> TSX:LUN | D71: =_xll.ciqfunctions.udf.CIQ(C71,"IQ_Company_Name") -> Lundin Mining Corporation | E71: =E68 -> 2024 | F71: =E71&"-01-01" -> 2024-01-01 | G71: =E71&"-12-31" -> 2024-12-31 | H71: =_xlfn.DAYS(G71,F71)/_xlfn.DAYS(E71&"-12-31",E71&"-01-01")*12 -> 12 | I71: =I70 -> USD | J71: =IF($I71="CAD",1,IF($I71="USD",VLOOKUP($E71,$F$9:$G$11,2,FALSE),"N/A")) -> 1.37017 | L71: CFO | M71: CFO | N71: Teitur Poulsen | O71: 529352 | P71: 725000 | Q71: - | R71: 758000 | S71: 1009055 | T71: =IFERROR(S71*(12/$H71)*$J71,"-") -> 1382576.9 | U71: =IFERROR($T71/$P71,"-") -> 1.9070026 | V71: =IFERROR(AVERAGE(U71:U73),"N/A") -> 1.0852875 | W71: 0.8 | X71: =IFERROR(IF(ISNUMBER($W71)=TRUE, $W71*$P71,$V71*$P71),"-") -> 580000 | Y71: =IFERROR(IF(SUM(P71,T71)=0,"-",SUM(P71,T71)),"-") -> 2107576.9 | Z71: =IFERROR(IF(SUM(P71,X71)=0,"-",SUM(P71,X71)),"-") -> 1305000 | AA71: - | AB71: =435613 -> 435613 | AC71: 435910 | AD71: - | AE71: - | AF71: =IFERROR(IF(SUM(AA71:AE71)=0,IF(COUNTIF($AA71:$AE71,"=0")>0,"$0","-"),SUM(AA71:AE71)),"-") -> 871523 | AG71: =IFERROR($AK71/$P71,"-") -> 1.6470823 | AH71: =IFERROR(AVERAGE(AG71:AG73),"N/A") -> 1.5817899 | AI71: - | AJ71: =IFERROR(IF(ISNUMBER($AI71)=TRUE, $AI71*$P71, $AH71*$P71), "-") -> 1146797.7 | AK71: =IFERROR($AF71*$J71,"-") -> 1194134.7 | AL71: =IFERROR(IF(SUM(Y71,AK71)=0,"-",SUM(Y71,AK71)),"-") -> 3301711.6 | AM71: =IFERROR(IF(SUM($Z71,$AJ71)=0,"-",SUM($Z71,$AJ71)),"-") -> 2451797.7 | AN71: N/A | AO71: N/A | AP71: =IFERROR(AN71*(12/$H71)*$J71,"-") -> - | AQ71: =IFERROR(AVERAGE(AP71:AP73),"N/A") -> N/A | AR71: 102270 | AS71: =IFERROR(AR71*(12/$H71)*$J71,"-") -> 140127.29 | AT71: =IFERROR(AVERAGE(AS71:AS73),"N/A") -> 103202.94 | AU71: =IFERROR(IF(SUM(AL71,AP71,AS71)=0,"-",SUM(AL71,AP71,AS71)),"-") -> 3441838.8 | AV71: =IFERROR(IF(SUM(AM71,AP71,AS71)=0,"-",SUM(AM71,AP71,AS71)),"-") -> 2591924.9 | AW71: - | AX71: AH | AY71: sc
A72: =$C72&"_"&$E72&"_"&$K72 -> TSX:LUN_2023_ | B72: =$C72&"_"&$E72&"_"&$L72 -> TSX:LUN_2023_CFO | C72: =C71 -> TSX:LUN | D72: =_xll.ciqfunctions.udf.CIQ(C72,"IQ_Company_Name") -> Lundin Mining Corporation | E72: =E69 -> 2023 | F72: =E72&"-01-01" -> 2023-01-01 | G72: =E72&"-12-31" -> 2023-12-31 | H72: =_xlfn.DAYS(G72,F72)/_xlfn.DAYS(E72&"-12-31",E72&"-01-01")*12 -> 12 | I72: =I71 -> USD | J72: =IF($I72="CAD",1,IF($I72="USD",VLOOKUP($E72,$F$9:$G$11,2,FALSE),"N/A")) -> 1.34954 | L72: =L71 -> CFO | M72: =M71 -> CFO | N72: =N71 -> Teitur Poulsen | O72: 518770 | P72: =IFERROR(O72*(12/$H72)*$J72,"-") -> 700100.87 | Q72: - | R72: =IFERROR(IF((Q72*$J72)=0,"-",(Q72*$J72)),"-") -> - | S72: 463188 | T72: =IFERROR(S72*(12/$H72)*$J72,"-") -> 625090.73 | U72: =IFERROR($T72/$P72,"-") -> 0.89285811 | W72: - | X72: =IFERROR(IF(ISNUMBER($W72)=TRUE, $W72*$P72,$V72*$P72),"-") -> 0 | Y72: =IFERROR(IF(SUM(P72,T72)=0,"-",SUM(P72,T72)),"-") -> 1325191.6 | Z72: =IFERROR(IF(SUM(P72,X72)=0,"-",SUM(P72,X72)),"-") -> 700100.87 | AA72: =0.33*621702 -> 205161.66 | AB72: =0.67*621702 -> 416540.34 | AC72: 204450 | AD72: - | AE72: - | AF72: =IFERROR(IF(SUM(AA72:AE72)=0,IF(COUNTIF($AA72:$AE72,"=0")>0,"$0","-"),SUM(AA72:AE72)),"-") -> 826152 | AG72: =IFERROR($AK72/$P72,"-") -> 1.5925208 | AI72: - | AJ72: =IFERROR(IF(ISNUMBER($AI72)=TRUE, $AI72*$P72, $AH72*$P72), "-") -> 0 | AK72: =IFERROR($AF72*$J72,"-") -> 1114925.2 | AL72: =IFERROR(IF(SUM(Y72,AK72)=0,"-",SUM(Y72,AK72)),"-") -> 2440116.8 | AM72: =IFERROR(IF(SUM($Z72,$AJ72)=0,"-",SUM($Z72,$AJ72)),"-") -> 700100.87 | AN72: N/A | AO72: N/A | AP72: =IFERROR(AN72*(12/$H72)*$J72,"-") -> - | AR72: 81339 | AS72: =IFERROR(AR72*(12/$H72)*$J72,"-") -> 109770.23 | AU72: =IFERROR(IF(SUM(AL72,AP72,AS72)=0,"-",SUM(AL72,AP72,AS72)),"-") -> 2549887 | AV72: =IFERROR(IF(SUM(AM72,AP72,AS72)=0,"-",SUM(AM72,AP72,AS72)),"-") -> 809871.1 | AW72: - | AX72: AH | AY72: sc
A73: =$C73&"_"&$E73&"_"&$K73 -> TSX:LUN_2022_ | B73: =$C73&"_"&$E73&"_"&$L73 -> TSX:LUN_2022_CFO | C73: =C72 -> TSX:LUN | D73: =_xll.ciqfunctions.udf.CIQ(C73,"IQ_Company_Name") -> Lundin Mining Corporation | E73: =E70 -> 2022 | F73: 2022-09-01 | G73: =E73&"-12-31" -> 2022-12-31 | H73: =_xlfn.DAYS(G73,F73)/_xlfn.DAYS(E73&"-12-31",E73&"-01-01")*12 -> 3.989011 | I73: =I72 -> USD | J73: =IF($I73="CAD",1,IF($I73="USD",VLOOKUP($E73,$F$9:$G$11,2,FALSE),"N/A")) -> 1.30175 | L73: =L72 -> CFO | M73: =M72 -> CFO | N73: =N72 -> Teitur Poulsen | O73: 192190 | P73: =IFERROR(O73*(12/$H73)*$J73,"-") -> 752617.63 | Q73: - | R73: =IFERROR(IF((Q73*$J73)=0,"-",(Q73*$J73)),"-") -> - | S73: 87639 | T73: =IFERROR(S73*(12/$H73)*$J73,"-") -> 343195.05 | U73: =IFERROR($T73/$P73,"-") -> 0.45600187 | W73: - | X73: =IFERROR(IF(ISNUMBER($W73)=TRUE, $W73*$P73,$V73*$P73),"-") -> 0 | Y73: =IFERROR(IF(SUM(P73,T73)=0,"-",SUM(P73,T73)),"-") -> 1095812.7 | Z73: =IFERROR(IF(SUM(P73,X73)=0,"-",SUM(P73,X73)),"-") -> 752617.63 | AA73: 663079.5 | AB73: - | AC73: 207492 | AD73: - | AE73: - | AF73: =IFERROR(IF(SUM(AA73:AE73)=0,IF(COUNTIF($AA73:$AE73,"=0")>0,"$0","-"),SUM(AA73:AE73)),"-") -> 870571.5 | AG73: =IFERROR($AK73/$P73,"-") -> 1.5057666 | AI73: - | AJ73: =IFERROR(IF(ISNUMBER($AI73)=TRUE, $AI73*$P73, $AH73*$P73), "-") -> 0 | AK73: =IFERROR($AF73*$J73,"-") -> 1133266.5 | AL73: =IFERROR(IF(SUM(Y73,AK73)=0,"-",SUM(Y73,AK73)),"-") -> 2229079.1 | AM73: =IFERROR(IF(SUM($Z73,$AJ73)=0,"-",SUM($Z73,$AJ73)),"-") -> 752617.63 | AN73: N/A | AO73: N/A | AP73: =IFERROR(AN73*(12/$H73)*$J73,"-") -> - | AR73: 15248 | AS73: =IFERROR(AR73*(12/$H73)*$J73,"-") -> 59711.294 | AU73: =IFERROR(IF(SUM(AL73,AP73,AS73)=0,"-",SUM(AL73,AP73,AS73)),"-") -> 2288790.4 | AV73: =IFERROR(IF(SUM(AM73,AP73,AS73)=0,"-",SUM(AM73,AP73,AS73)),"-") -> 812328.92 | AW73: Mr. Poulsen joined the company on September 1, 2022 | AX73: AH | AY73: sc
A74: =$C74&"_"&$E74&"_"&$K74 -> TSX:LUN_2024_COO | B74: =$C74&"_"&$E74&"_"&$L74 -> TSX:LUN_2024_NEO1 | C74: =C73 -> TSX:LUN | D74: =_xll.ciqfunctions.udf.CIQ(C74,"IQ_Company_Name") -> Lundin Mining Corporation | E74: =E71 -> 2024 | F74: =E74&"-01-01" -> 2024-01-01 | G74: =E74&"-12-31" -> 2024-12-31 | H74: =_xlfn.DAYS(G74,F74)/_xlfn.DAYS(E74&"-12-31",E74&"-01-01")*12 -> 12 | I74: =I73 -> USD | J74: =IF($I74="CAD",1,IF($I74="USD",VLOOKUP($E74,$F$9:$G$11,2,FALSE),"N/A")) -> 1.37017 | K74: COO | L74: NEO1 | M74: COO | N74: Juan Andres Morel | O74: 562287 | P74: =IFERROR(562287*(12/$H74)*$J74,"-") -> 770428.78 | Q74: - | R74: =IFERROR(IF((595462*$J74)=0,"-",(595462*$J74)),"-") -> 815884.17 | S74: 790576 | T74: =IFERROR(S74*(12/$H74)*$J74,"-") -> 1083223.5 | U74: =IFERROR($T74/$P74,"-") -> 1.4060009 | V74: =IFERROR(AVERAGE(U74:U76),"N/A") -> 0.95688569 | W74: 0.8 | X74: =IFERROR(IF(ISNUMBER($W74)=TRUE, $W74*$P74,$V74*$P74),"-") -> 616343.02 | Y74: =IFERROR(IF(SUM(P74,T74)=0,"-",SUM(P74,T74)),"-") -> 1853652.3 | Z74: =IFERROR(IF(SUM(P74,X74)=0,"-",SUM(P74,X74)),"-") -> 1386771.8 | AA74: - | AB74: =468351 -> 468351 | AC74: 468695 | AD74: - | AE74: - | AF74: =IFERROR(IF(SUM(AA74:AE74)=0,IF(COUNTIF($AA74:$AE74,"=0")>0,"$0","-"),SUM(AA74:AE74)),"-") -> 937046 | AG74: =IFERROR($AK74/$P74,"-") -> 1.6664906 | AH74: =IFERROR(AVERAGE(AG74:AG76),"N/A") -> 1.510687 | AI74: - | AJ74: =IFERROR(IF(ISNUMBER($AI74)=TRUE, $AI74*$P74, $AH74*$P74), "-") -> 1163876.8 | AK74: =IFERROR($AF74*$J74,"-") -> 1283912.3 | AL74: =IFERROR(IF(SUM(Y74,AK74)=0,"-",SUM(Y74,AK74)),"-") -> 3137564.6 | AM74: =IFERROR(IF(SUM($Z74,$AJ74)=0,"-",SUM($Z74,$AJ74)),"-") -> 2550648.6 | AN74: N/A | AO74: N/A | AP74: =IFERROR(AN74*(12/$H74)*$J74,"-") -> - | AQ74: =IFERROR(AVERAGE(AP74:AP76),"N/A") -> N/A | AR74: 1466 | AS74: =IFERROR(AR74*(12/$H74)*$J74,"-") -> 2008.6692 | AT74: =IFERROR(AVERAGE(AS74:AS76),"N/A") -> 2822.5968 | AU74: =IFERROR(IF(SUM(AL74,AP74,AS74)=0,"-",SUM(AL74,AP74,AS74)),"-") -> 3139573.3 | AV74: =IFERROR(IF(SUM(AM74,AP74,AS74)=0,"-",SUM(AM74,AP74,AS74)),"-") -> 2552657.2 | AW74: - | AX74: AH | AY74: sc
A75: =$C75&"_"&$E75&"_"&$K75 -> TSX:LUN_2023_COO | B75: =$C75&"_"&$E75&"_"&$L75 -> TSX:LUN_2023_NEO1 | C75: =C74 -> TSX:LUN | D75: =_xll.ciqfunctions.udf.CIQ(C75,"IQ_Company_Name") -> Lundin Mining Corporation | E75: =E72 -> 2023 | F75: =E75&"-01-01" -> 2023-01-01 | G75: =E75&"-12-31" -> 2023-12-31 | H75: =_xlfn.DAYS(G75,F75)/_xlfn.DAYS(E75&"-12-31",E75&"-01-01")*12 -> 12 | I75: =I74 -> USD | J75: =IF($I75="CAD",1,IF($I75="USD",VLOOKUP($E75,$F$9:$G$11,2,FALSE),"N/A")) -> 1.34954 | K75: COO | L75: =L74 -> NEO1 | M75: =M74 -> COO | N75: =N74 -> Juan Andres Morel | O75: 609060 | P75: =IFERROR(O75*(12/$H75)*$J75,"-") -> 821950.83 | Q75: - | R75: =IFERROR(IF((Q75*$J75)=0,"-",(Q75*$J75)),"-") -> - | S75: 566426 | T75: =IFERROR(S75*(12/$H75)*$J75,"-") -> 764414.54 | U75: =IFERROR($T75/$P75,"-") -> 0.93000033 | W75: - | X75: =IFERROR(IF(ISNUMBER($W75)=TRUE, $W75*$P75,$V75*$P75),"-") -> 0 | Y75: =IFERROR(IF(SUM(P75,T75)=0,"-",SUM(P75,T75)),"-") -> 1586365.4 | Z75: =IFERROR(IF(SUM(P75,X75)=0,"-",SUM(P75,X75)),"-") -> 821950.83 | AA75: =0.33*730480 -> 241058.4 | AB75: =0.67*730480 -> 489421.6 | AC75: 240264 | AD75: - | AE75: - | AF75: =IFERROR(IF(SUM(AA75:AE75)=0,IF(COUNTIF($AA75:$AE75,"=0")>0,"$0","-"),SUM(AA75:AE75)),"-") -> 970744 | AG75: =IFERROR($AK75/$P75,"-") -> 1.5938397 | AI75: - | AJ75: =IFERROR(IF(ISNUMBER($AI75)=TRUE, $AI75*$P75, $AH75*$P75), "-") -> 0 | AK75: =IFERROR($AF75*$J75,"-") -> 1310057.9 | AL75: =IFERROR(IF(SUM(Y75,AK75)=0,"-",SUM(Y75,AK75)),"-") -> 2896423.2 | AM75: =IFERROR(IF(SUM($Z75,$AJ75)=0,"-",SUM($Z75,$AJ75)),"-") -> 821950.83 | AN75: N/A | AO75: N/A | AP75: =IFERROR(AN75*(12/$H75)*$J75,"-") -> - | AR75: 1446 | AS75: =IFERROR(AR75*(12/$H75)*$J75,"-") -> 1951.4348 | AU75: =IFERROR(IF(SUM(AL75,AP75,AS75)=0,"-",SUM(AL75,AP75,AS75)),"-") -> 2898374.7 | AV75: =IFERROR(IF(SUM(AM75,AP75,AS75)=0,"-",SUM(AM75,AP75,AS75)),"-") -> 823902.27 | AW75: - | AX75: AH | AY75: sc
A76: =$C76&"_"&$E76&"_"&$K76 -> TSX:LUN_2022_COO | B76: =$C76&"_"&$E76&"_"&$L76 -> TSX:LUN_2022_NEO1 | C76: =C75 -> TSX:LUN | D76: =_xll.ciqfunctions.udf.CIQ(C76,"IQ_Company_Name") -> Lundin Mining Corporation | E76: =E73 -> 2022 | F76: 2022-08-01 | G76: =E76&"-12-31" -> 2022-12-31 | H76: =_xlfn.DAYS(G76,F76)/_xlfn.DAYS(E76&"-12-31",E76&"-01-01")*12 -> 5.010989 | I76: =I75 -> USD | J76: =IF($I76="CAD",1,IF($I76="USD",VLOOKUP($E76,$F$9:$G$11,2,FALSE),"N/A")) -> 1.30175 | K76: COO | L76: =L75 -> NEO1 | M76: =M75 -> COO | N76: =N75 -> Juan Andres Morel | O76: 231519 | P76: =IFERROR(O76*(12/$H76)*$J76,"-") -> 721725.45 | Q76: - | R76: =IFERROR(IF((Q76*$J76)=0,"-",(Q76*$J76)),"-") -> - | S76: 123783 | T76: =IFERROR(S76*(12/$H76)*$J76,"-") -> 385874.77 | U76: =IFERROR($T76/$P76,"-") -> 0.5346559 | W76: - | X76: =IFERROR(IF(ISNUMBER($W76)=TRUE, $W76*$P76,$V76*$P76),"-") -> 0 | Y76: =IFERROR(IF(SUM(P76,T76)=0,"-",SUM(P76,T76)),"-") -> 1107600.2 | Z76: =IFERROR(IF(SUM(P76,X76)=0,"-",SUM(P76,X76)),"-") -> 721725.45 | AA76: 500410 | AB76: - | AC76: 204672 | AD76: - | AE76: - | AF76: =IFERROR(IF(SUM(AA76:AE76)=0,IF(COUNTIF($AA76:$AE76,"=0")>0,"$0","-"),SUM(AA76:AE76)),"-") -> 705082 | AG76: =IFERROR($AK76/$P76,"-") -> 1.2717308 | AI76: - | AJ76: =IFERROR(IF(ISNUMBER($AI76)=TRUE, $AI76*$P76, $AH76*$P76), "-") -> 0 | AK76: =IFERROR($AF76*$J76,"-") -> 917840.49 | AL76: =IFERROR(IF(SUM(Y76,AK76)=0,"-",SUM(Y76,AK76)),"-") -> 2025440.7 | AM76: =IFERROR(IF(SUM($Z76,$AJ76)=0,"-",SUM($Z76,$AJ76)),"-") -> 721725.45 | AN76: N/A | AO76: N/A | AP76: =IFERROR(AN76*(12/$H76)*$J76,"-") -> - | AR76: 1446 | AS76: =IFERROR(AR76*(12/$H76)*$J76,"-") -> 4507.6862 | AU76: =IFERROR(IF(SUM(AL76,AP76,AS76)=0,"-",SUM(AL76,AP76,AS76)),"-") -> 2029948.4 | AV76: =IFERROR(IF(SUM(AM76,AP76,AS76)=0,"-",SUM(AM76,AP76,AS76)),"-") -> 726233.14 | AW76: Juan Andres Morel joined the Company on August 1, 2022. We have excluded from his performance equity grants for 2022 an initial on hire grant of 18,000 SUs and 50,000 options granted on August 15, 2022, using the fair value of C$11.54 and Black Scholes value of C$4.15 as at February 23, 2022. | AX76: AH | AY76: sc
A77: =$C77&"_"&$E77&"_"&$K77 -> TSX:LUN_2024_Region | B77: =$C77&"_"&$E77&"_"&$L77 -> TSX:LUN_2024_NEO2 | C77: =C76 -> TSX:LUN | D77: =_xll.ciqfunctions.udf.CIQ(C77,"IQ_Company_Name") -> Lundin Mining Corporation | E77: =E74 -> 2024 | F77: =E77&"-01-01" -> 2024-01-01 | G77: =E77&"-12-31" -> 2024-12-31 | H77: =_xlfn.DAYS(G77,F77)/_xlfn.DAYS(E77&"-12-31",E77&"-01-01")*12 -> 12 | I77: =I76 -> USD | J77: =IF($I77="CAD",1,IF($I77="USD",VLOOKUP($E77,$F$9:$G$11,2,FALSE),"N/A")) -> 1.37017 | K77: Region | L77: NEO2 | M77: EVP, Josemaría Project | N77: David Dicaire | O77: 547606 | P77: 750000 | Q77: - | R77: =IFERROR(IF((Q77*$J77)=0,"-",(Q77*$J77)),"-") -> - | S77: 809726 | T77: =IFERROR(S77*(12/$H77)*$J77,"-") -> 1109462.3 | U77: =IFERROR($T77/$P77,"-") -> 1.479283 | V77: =IFERROR(AVERAGE(U77:U79),"N/A") -> 0.92553849 | W77: 0.75 | X77: =IFERROR(IF(ISNUMBER($W77)=TRUE, $W77*$P77,$V77*$P77),"-") -> 562500 | Y77: =IFERROR(IF(SUM(P77,T77)=0,"-",SUM(P77,T77)),"-") -> 1859462.3 | Z77: =IFERROR(IF(SUM(P77,X77)=0,"-",SUM(P77,X77)),"-") -> 1312500 | AA77: - | AB77: - | AC77: - | AD77: - | AE77: - | AF77: =IFERROR(IF(SUM(AA77:AE77)=0,IF(COUNTIF($AA77:$AE77,"=0")>0,"$0","-"),SUM(AA77:AE77)),"-") -> - | AG77: =IFERROR($AK77/$P77,"-") -> - | AH77: =IFERROR(AVERAGE(AG77:AG79),"N/A") -> 1.4728276 | AI77: - | AJ77: =IFERROR(IF(ISNUMBER($AI77)=TRUE, $AI77*$P77, $AH77*$P77), "-") -> 1104620.7 | AK77: =IFERROR($AF77*$J77,"-") -> - | AL77: =IFERROR(IF(SUM(Y77,AK77)=0,"-",SUM(Y77,AK77)),"-") -> 1859462.3 | AM77: =IFERROR(IF(SUM($Z77,$AJ77)=0,"-",SUM($Z77,$AJ77)),"-") -> 2417120.7 | AN77: N/A | AO77: N/A | AP77: =IFERROR(AN77*(12/$H77)*$J77,"-") -> - | AQ77: =IFERROR(AVERAGE(AP77:AP79),"N/A") -> N/A | AR77: 102092 | AS77: =IFERROR(AR77*(12/$H77)*$J77,"-") -> 139883.4 | AT77: =IFERROR(AVERAGE(AS77:AS79),"N/A") -> 85796.017 | AU77: =IFERROR(IF(SUM(AL77,AP77,AS77)=0,"-",SUM(AL77,AP77,AS77)),"-") -> 1999345.7 | AV77: =IFERROR(IF(SUM(AM77,AP77,AS77)=0,"-",SUM(AM77,AP77,AS77)),"-") -> 2557004.1 | AW77: David Dicaire transitioned from his employment with Lundin Mining Corporation to Vicuña Corp., the newly formed joint venture with BHP, effective January 15, 2025. | AX77: AH | AY77: sc
A78: =$C78&"_"&$E78&"_"&$K78 -> TSX:LUN_2023_Region | B78: =$C78&"_"&$E78&"_"&$L78 -> TSX:LUN_2023_NEO2 | C78: =C77 -> TSX:LUN | D78: =_xll.ciqfunctions.udf.CIQ(C78,"IQ_Company_Name") -> Lundin Mining Corporation | E78: =E75 -> 2023 | F78: =E78&"-01-01" -> 2023-01-01 | G78: =E78&"-12-31" -> 2023-12-31 | H78: =_xlfn.DAYS(G78,F78)/_xlfn.DAYS(E78&"-12-31",E78&"-01-01")*12 -> 12 | I78: =I77 -> USD | J78: =IF($I78="CAD",1,IF($I78="USD",VLOOKUP($E78,$F$9:$G$11,2,FALSE),"N/A")) -> 1.34954 | K78: Region | L78: =L77 -> NEO2 | M78: =M77 -> EVP, Josemaría Project | N78: =N77 -> David Dicaire | O78: 555825 | P78: =IFERROR(O78*(12/$H78)*$J78,"-") -> 750108.07 | Q78: - | R78: =IFERROR(IF((Q78*$J78)=0,"-",(Q78*$J78)),"-") -> - | S78: 463188 | T78: =IFERROR(S78*(12/$H78)*$J78,"-") -> 625090.73 | U78: =IFERROR($T78/$P78,"-") -> 0.83333423 | W78: - | X78: =IFERROR(IF(ISNUMBER($W78)=TRUE, $W78*$P78,$V78*$P78),"-") -> 0 | Y78: =IFERROR(IF(SUM(P78,T78)=0,"-",SUM(P78,T78)),"-") -> 1375198.8 | Z78: =IFERROR(IF(SUM(P78,X78)=0,"-",SUM(P78,X78)),"-") -> 750108.07 | AA78: =0.33*602646 -> 198873.18 | AB78: =0.67*602646 -> 403772.82 | AC78: 198246 | AD78: - | AE78: - | AF78: =IFERROR(IF(SUM(AA78:AE78)=0,IF(COUNTIF($AA78:$AE78,"=0")>0,"$0","-"),SUM(AA78:AE78)),"-") -> 800892 | AG78: =IFERROR($AK78/$P78,"-") -> 1.4409068 | AI78: - | AJ78: =IFERROR(IF(ISNUMBER($AI78)=TRUE, $AI78*$P78, $AH78*$P78), "-") -> 0 | AK78: =IFERROR($AF78*$J78,"-") -> 1080835.8 | AL78: =IFERROR(IF(SUM(Y78,AK78)=0,"-",SUM(Y78,AK78)),"-") -> 2456034.6 | AM78: =IFERROR(IF(SUM($Z78,$AJ78)=0,"-",SUM($Z78,$AJ78)),"-") -> 750108.07 | AN78: N/A | AO78: N/A | AP78: =IFERROR(AN78*(12/$H78)*$J78,"-") -> - | AR78: 78036 | AS78: =IFERROR(AR78*(12/$H78)*$J78,"-") -> 105312.7 | AU78: =IFERROR(IF(SUM(AL78,AP78,AS78)=0,"-",SUM(AL78,AP78,AS78)),"-") -> 2561347.3 | AV78: =IFERROR(IF(SUM(AM78,AP78,AS78)=0,"-",SUM(AM78,AP78,AS78)),"-") -> 855420.77 | AW78: - | AX78: AH | AY78: sc
A79: =$C79&"_"&$E79&"_"&$K79 -> TSX:LUN_2022_Region | B79: =$C79&"_"&$E79&"_"&$L79 -> TSX:LUN_2022_NEO2 | C79: =C78 -> TSX:LUN | D79: =_xll.ciqfunctions.udf.CIQ(C79,"IQ_Company_Name") -> Lundin Mining Corporation | E79: =E76 -> 2022 | F79: 2022-08-01 | G79: =E79&"-12-31" -> 2022-12-31 | H79: =_xlfn.DAYS(G79,F79)/_xlfn.DAYS(E79&"-12-31",E79&"-01-01")*12 -> 5.010989 | I79: =I78 -> USD | J79: =IF($I79="CAD",1,IF($I79="USD",VLOOKUP($E79,$F$9:$G$11,2,FALSE),"N/A")) -> 1.30175 | K79: Region | L79: =L78 -> NEO2 | M79: =M78 -> EVP, Josemaría Project | N79: =N78 -> David Dicaire | O79: 240238 | P79: =IFERROR(O79*(12/$H79)*$J79,"-") -> 748905.61 | Q79: - | R79: =IFERROR(IF((Q79*$J79)=0,"-",(Q79*$J79)),"-") -> - | S79: 111470 | T79: =IFERROR(S79*(12/$H79)*$J79,"-") -> 347490.86 | U79: =IFERROR($T79/$P79,"-") -> 0.4639982 | W79: - | X79: =IFERROR(IF(ISNUMBER($W79)=TRUE, $W79*$P79,$V79*$P79),"-") -> 0 | Y79: =IFERROR(IF(SUM(P79,T79)=0,"-",SUM(P79,T79)),"-") -> 1096396.5 | Z79: =IFERROR(IF(SUM(P79,X79)=0,"-",SUM(P79,X79)),"-") -> 748905.61 | AA79: 657594 | AB79: - | AC79: 208098 | AD79: - | AE79: - | AF79: =IFERROR(IF(SUM(AA79:AE79)=0,IF(COUNTIF($AA79:$AE79,"=0")>0,"$0","-"),SUM(AA79:AE79)),"-") -> 865692 | AG79: =IFERROR($AK79/$P79,"-") -> 1.5047485 | AI79: - | AJ79: =IFERROR(IF(ISNUMBER($AI79)=TRUE, $AI79*$P79, $AH79*$P79), "-") -> 0 | AK79: =IFERROR($AF79*$J79,"-") -> 1126914.6 | AL79: =IFERROR(IF(SUM(Y79,AK79)=0,"-",SUM(Y79,AK79)),"-") -> 2223311 | AM79: =IFERROR(IF(SUM($Z79,$AJ79)=0,"-",SUM($Z79,$AJ79)),"-") -> 748905.61 | AN79: N/A | AO79: N/A | AP79: =IFERROR(AN79*(12/$H79)*$J79,"-") -> - | AR79: 3911 | AS79: =IFERROR(AR79*(12/$H79)*$J79,"-") -> 12191.951 | AU79: =IFERROR(IF(SUM(AL79,AP79,AS79)=0,"-",SUM(AL79,AP79,AS79)),"-") -> 2235503 | AV79: =IFERROR(IF(SUM(AM79,AP79,AS79)=0,"-",SUM(AM79,AP79,AS79)),"-") -> 761097.56 | AW79: David Dicaire joined the company on August 1, 2024 | AX79: AH | AY79: sc
A80: =$C80&"_"&$E80&"_"&$K80 -> TSX:LUN_2024_Legal | B80: =$C80&"_"&$E80&"_"&$L80 -> TSX:LUN_2024_NEO3 | C80: =C79 -> TSX:LUN | D80: =_xll.ciqfunctions.udf.CIQ(C80,"IQ_Company_Name") -> Lundin Mining Corporation | E80: =E77 -> 2024 | F80: =E80&"-01-01" -> 2024-01-01 | G80: =E80&"-12-31" -> 2024-12-31 | H80: =_xlfn.DAYS(G80,F80)/_xlfn.DAYS(E80&"-12-31",E80&"-01-01")*12 -> 12 | I80: =I79 -> USD | J80: =IF($I80="CAD",1,IF($I80="USD",VLOOKUP($E80,$F$9:$G$11,2,FALSE),"N/A")) -> 1.37017 | K80: Legal | L80: NEO3 | M80: General Counsel | N80: Peter Brady | O80: 449037 | P80: 615000 | Q80: - | R80: 630000 | S80: 813377 | T80: =IFERROR(S80*(12/$H80)*$J80,"-") -> 1114464.8 | U80: =IFERROR($T80/$P80,"-") -> 1.8121378 | V80: =IFERROR(AVERAGE(U80:U82),"N/A") -> 1.3288333 | W80: 0.75 | X80: =IFERROR(IF(ISNUMBER($W80)=TRUE, $W80*$P80,$V80*$P80),"-") -> 461250 | Y80: =IFERROR(IF(SUM(P80,T80)=0,"-",SUM(P80,T80)),"-") -> 1729464.8 | Z80: =IFERROR(IF(SUM(P80,X80)=0,"-",SUM(P80,X80)),"-") -> 1076250 | AA80: - | AB80: =339458 -> 339458 | AC80: 339661 | AD80: - | AE80: - | AF80: =IFERROR(IF(SUM(AA80:AE80)=0,IF(COUNTIF($AA80:$AE80,"=0")>0,"$0","-"),SUM(AA80:AE80)),"-") -> 679119 | AG80: =IFERROR($AK80/$P80,"-") -> 1.5130219 | AH80: =IFERROR(AVERAGE(AG80:AG82),"N/A") -> 1.4269231 | AI80: - | AJ80: =IFERROR(IF(ISNUMBER($AI80)=TRUE, $AI80*$P80, $AH80*$P80), "-") -> 877557.69 | AK80: =IFERROR($AF80*$J80,"-") -> 930508.48 | AL80: =IFERROR(IF(SUM(Y80,AK80)=0,"-",SUM(Y80,AK80)),"-") -> 2659973.2 | AM80: =IFERROR(IF(SUM($Z80,$AJ80)=0,"-",SUM($Z80,$AJ80)),"-") -> 1953807.7 | AN80: N/A | AO80: N/A | AP80: =IFERROR(AN80*(12/$H80)*$J80,"-") -> - | AQ80: =IFERROR(AVERAGE(AP80:AP82),"N/A") -> N/A | AR80: 205055 | AS80: =IFERROR(AR80*(12/$H80)*$J80,"-") -> 280960.21 | AT80: =IFERROR(AVERAGE(AS80:AS82),"N/A") -> 347606.58 | AU80: =IFERROR(IF(SUM(AL80,AP80,AS80)=0,"-",SUM(AL80,AP80,AS80)),"-") -> 2940933.5 | AV80: =IFERROR(IF(SUM(AM80,AP80,AS80)=0,"-",SUM(AM80,AP80,AS80)),"-") -> 2234767.9 | AW80: - | AX80: AH | AY80: sc
A81: =$C81&"_"&$E81&"_"&$K81 -> TSX:LUN_2023_Legal | B81: =$C81&"_"&$E81&"_"&$L81 -> TSX:LUN_2023_NEO3 | C81: =C80 -> TSX:LUN | D81: =_xll.ciqfunctions.udf.CIQ(C81,"IQ_Company_Name") -> Lundin Mining Corporation | E81: =E78 -> 2023 | F81: 2023-09-23 | G81: =E81&"-12-31" -> 2023-12-31 | H81: =_xlfn.DAYS(G81,F81)/_xlfn.DAYS(E81&"-12-31",E81&"-01-01")*12 -> 3.2637363 | I81: =I80 -> USD | J81: =IF($I81="CAD",1,IF($I81="USD",VLOOKUP($E81,$F$9:$G$11,2,FALSE),"N/A")) -> 1.34954 | K81: Legal | L81: =L80 -> NEO3 | M81: =M80 -> General Counsel | N81: =N80 -> Peter Brady | O81: 122709 | P81: =IFERROR(O81*(12/$H81)*$J81,"-") -> 608875.32 | Q81: - | R81: =IFERROR(IF((Q81*$J81)=0,"-",(Q81*$J81)),"-") -> - | S81: 103754 | T81: =IFERROR(S81*(12/$H81)*$J81,"-") -> 514821.65 | U81: =IFERROR($T81/$P81,"-") -> 0.84552885 | W81: - | X81: =IFERROR(IF(ISNUMBER($W81)=TRUE, $W81*$P81,$V81*$P81),"-") -> 0 | Y81: =IFERROR(IF(SUM(P81,T81)=0,"-",SUM(P81,T81)),"-") -> 1123697 | Z81: =IFERROR(IF(SUM(P81,X81)=0,"-",SUM(P81,X81)),"-") -> 608875.32 | AA81: =0.33*987814-37000*6.71 -> 77708.62 | AB81: =0.67*987814-37000*6.71 -> 413565.38 | AC81: 113669 | AD81: - | AE81: - | AF81: =IFERROR(IF(SUM(AA81:AE81)=0,IF(COUNTIF($AA81:$AE81,"=0")>0,"$0","-"),SUM(AA81:AE81)),"-") -> 604943 | AG81: =IFERROR($AK81/$P81,"-") -> 1.3408242 | AI81: - | AJ81: =IFERROR(IF(ISNUMBER($AI81)=TRUE, $AI81*$P81, $AH81*$P81), "-") -> 0 | AK81: =IFERROR($AF81*$J81,"-") -> 816394.78 | AL81: =IFERROR(IF(SUM(Y81,AK81)=0,"-",SUM(Y81,AK81)),"-") -> 1940091.7 | AM81: =IFERROR(IF(SUM($Z81,$AJ81)=0,"-",SUM($Z81,$AJ81)),"-") -> 608875.32 | AN81: N/A | AO81: N/A | AP81: =IFERROR(AN81*(12/$H81)*$J81,"-") -> - | AR81: 83486 | AS81: =IFERROR(AR81*(12/$H81)*$J81,"-") -> 414252.94 | AU81: =IFERROR(IF(SUM(AL81,AP81,AS81)=0,"-",SUM(AL81,AP81,AS81)),"-") -> 2354344.7 | AV81: =IFERROR(IF(SUM(AM81,AP81,AS81)=0,"-",SUM(AM81,AP81,AS81)),"-") -> 1023128.3 | AW81: LTIP excludes on-hire grant of 37,000 SU and 37,000 PSU valued at 6.71 USD each | AX81: AH | AY81: sc
A82: =$C82&"_"&$E82&"_"&$K82 -> TSX:LUN_2022_Legal | B82: =$C82&"_"&$E82&"_"&$L82 -> TSX:LUN_2022_NEO3 | C82: =C81 -> TSX:LUN | D82: =_xll.ciqfunctions.udf.CIQ(C82,"IQ_Company_Name") -> Lundin Mining Corporation | E82: =E79 -> 2022 | F82: =E82&"-01-01" -> 2022-01-01 | G82: =E82&"-12-31" -> 2022-12-31 | H82: =_xlfn.DAYS(G82,F82)/_xlfn.DAYS(E82&"-12-31",E82&"-01-01")*12 -> 12 | I82: =I81 -> USD | J82: =IF($I82="CAD",1,IF($I82="USD",VLOOKUP($E82,$F$9:$G$11,2,FALSE),"N/A")) -> 1.30175 | K82: Legal | L82: =L81 -> NEO3 | M82: =M81 -> General Counsel | N82: =N81 -> Peter Brady | O82: - | P82: =IFERROR(O82*(12/$H82)*$J82,"-") -> - | Q82: - | R82: =IFERROR(IF((Q82*$J82)=0,"-",(Q82*$J82)),"-") -> - | S82: - | T82: =IFERROR(S82*(12/$H82)*$J82,"-") -> - | U82: =IFERROR($T82/$P82,"-") -> - | W82: - | X82: =IFERROR(IF(ISNUMBER($W82)=TRUE, $W82*$P82,$V82*$P82),"-") -> - | Y82: =IFERROR(IF(SUM(P82,T82)=0,"-",SUM(P82,T82)),"-") -> - | Z82: =IFERROR(IF(SUM(P82,X82)=0,"-",SUM(P82,X82)),"-") -> - | AA82: - | AB82: - | AC82: - | AD82: - | AE82: - | AF82: =IFERROR(IF(SUM(AA82:AE82)=0,IF(COUNTIF($AA82:$AE82,"=0")>0,"$0","-"),SUM(AA82:AE82)),"-") -> - | AG82: =IFERROR($AK82/$P82,"-") -> - | AI82: - | AJ82: =IFERROR(IF(ISNUMBER($AI82)=TRUE, $AI82*$P82, $AH82*$P82), "-") -> - | AK82: =IFERROR($AF82*$J82,"-") -> - | AL82: =IFERROR(IF(SUM(Y82,AK82)=0,"-",SUM(Y82,AK82)),"-") -> - | AM82: =IFERROR(IF(SUM($Z82,$AJ82)=0,"-",SUM($Z82,$AJ82)),"-") -> - | AN82: - | AO82: - | AP82: =IFERROR(AN82*(12/$H82)*$J82,"-") -> - | AR82: - | AS82: =IFERROR(AR82*(12/$H82)*$J82,"-") -> - | AU82: =IFERROR(IF(SUM(AL82,AP82,AS82)=0,"-",SUM(AL82,AP82,AS82)),"-") -> - | AV82: =IFERROR(IF(SUM(AM82,AP82,AS82)=0,"-",SUM(AM82,AP82,AS82)),"-") -> - | AW82: - | AX82: AH | AY82: sc
A83: =$C83&"_"&$E83&"_"&$K83 -> TSX:AGI_2024_ | B83: =$C83&"_"&$E83&"_"&$L83 -> TSX:AGI_2024_CEO | C83: =D7 -> TSX:AGI | D83: =_xll.ciqfunctions.udf.CIQ(C83,"IQ_Company_Name") -> Alamos Gold Inc. | E83: =$F$9 -> 2024 | F83: =E83&"-01-01" -> 2024-01-01 | G83: =E83&"-12-31" -> 2024-12-31 | H83: =_xlfn.DAYS(G83,F83)/_xlfn.DAYS(E83&"-12-31",E83&"-01-01")*12 -> 12 | I83: USD | J83: =IF($I83="CAD",1,IF($I83="USD",VLOOKUP($E83,$F$9:$G$11,2,FALSE),"N/A")) -> 1.37017 | L83: CEO | M83: CEO | N83: John A. McCluskey | O83: 784965 | P83: 1075000 | Q83: - | R83: =IFERROR(IF((Q83*$J83)=0,"-",(Q83*$J83)),"-") -> - | S83: 1249076 | T83: =IFERROR(S83*(12/$H83)*$J83,"-") -> 1711446.5 | U83: =IFERROR($T83/$P83,"-") -> 1.5920432 | V83: =IFERROR(AVERAGE(U83:U85),"N/A") -> 1.4890139 | W83: 1.25 | X83: =IFERROR(IF(ISNUMBER($W83)=TRUE, $W83*$P83,$V83*$P83),"-") -> 1343750 | Y83: =IFERROR(IF(SUM(P83,T83)=0,"-",SUM(P83,T83)),"-") -> 2786446.5 | Z83: =IFERROR(IF(SUM(P83,X83)=0,"-",SUM(P83,X83)),"-") -> 2418750 | AA83: =1766171*1/3 -> 588723.67 | AB83: =1766171*2/3 -> 1177447.3 | AC83: 588724 | AD83: - | AE83: - | AF83: =IFERROR(IF(SUM(AA83:AE83)=0,IF(COUNTIF($AA83:$AE83,"=0")>0,"$0","-"),SUM(AA83:AE83)),"-") -> 2354895 | AG83: =IFERROR($AK83/$P83,"-") -> 3.0014944 | AH83: =IFERROR(AVERAGE(AG83:AG85),"N/A") -> 2.7171645 | AI83: 2.75 | AJ83: =IFERROR(IF(ISNUMBER($AI83)=TRUE, $AI83*$P83, $AH83*$P83), "-") -> 2956250 | AK83: =IFERROR($AF83*$J83,"-") -> 3226606.5 | AL83: =IFERROR(IF(SUM(Y83,AK83)=0,"-",SUM(Y83,AK83)),"-") -> 6013052.9 | AM83: =IFERROR(IF(SUM($Z83,$AJ83)=0,"-",SUM($Z83,$AJ83)),"-") -> 5375000 | AN83: 244085 | AO83: DC | AP83: =IFERROR(AN83*(12/$H83)*$J83,"-") -> 334437.94 | AQ83: =IFERROR(AVERAGE(AP83:AP85),"N/A") -> 301399.08 | AR83: 69230 | AS83: =IFERROR(AR83*(12/$H83)*$J83,"-") -> 94856.869 | AT83: =IFERROR(AVERAGE(AS83:AS85),"N/A") -> 89626.554 | AU83: =IFERROR(IF(SUM(AL83,AP83,AS83)=0,"-",SUM(AL83,AP83,AS83)),"-") -> 6442347.8 | AV83: =IFERROR(IF(SUM(AM83,AP83,AS83)=0,"-",SUM(AM83,AP83,AS83)),"-") -> 5804294.8 | AW83: - | AX83: AH | AY83: sc
A84: =$C84&"_"&$E84&"_"&$K84 -> TSX:AGI_2023_ | B84: =$C84&"_"&$E84&"_"&$L84 -> TSX:AGI_2023_CEO | C84: =C83 -> TSX:AGI | D84: =_xll.ciqfunctions.udf.CIQ(C84,"IQ_Company_Name") -> Alamos Gold Inc. | E84: =$F$10 -> 2023 | F84: =E84&"-01-01" -> 2023-01-01 | G84: =E84&"-12-31" -> 2023-12-31 | H84: =_xlfn.DAYS(G84,F84)/_xlfn.DAYS(E84&"-12-31",E84&"-01-01")*12 -> 12 | I84: =I83 -> USD | J84: =IF($I84="CAD",1,IF($I84="USD",VLOOKUP($E84,$F$9:$G$11,2,FALSE),"N/A")) -> 1.34954 | L84: =L83 -> CEO | M84: =M83 -> CEO | N84: =N83 -> John A. McCluskey | O84: 755718 | P84: =IFERROR(O84*(12/$H84)*$J84,"-") -> 1019871.7 | Q84: - | R84: =IFERROR(IF((Q84*$J84)=0,"-",(Q84*$J84)),"-") -> - | S84: 1133577 | T84: =IFERROR(S84*(12/$H84)*$J84,"-") -> 1529807.5 | U84: =IFERROR($T84/$P84,"-") -> 1.5 | W84: - | X84: =IFERROR(IF(ISNUMBER($W84)=TRUE, $W84*$P84,$V84*$P84),"-") -> 0 | Y84: =IFERROR(IF(SUM(P84,T84)=0,"-",SUM(P84,T84)),"-") -> 2549679.2 | Z84: =IFERROR(IF(SUM(P84,X84)=0,"-",SUM(P84,X84)),"-") -> 1019871.7 | AA84: 519556 | AB84: 1039112 | AC84: 519556 | AD84: - | AE84: - | AF84: =IFERROR(IF(SUM(AA84:AE84)=0,IF(COUNTIF($AA84:$AE84,"=0")>0,"$0","-"),SUM(AA84:AE84)),"-") -> 2078224 | AG84: =IFERROR($AK84/$P84,"-") -> 2.7499993 | AI84: - | AJ84: =IFERROR(IF(ISNUMBER($AI84)=TRUE, $AI84*$P84, $AH84*$P84), "-") -> 0 | AK84: =IFERROR($AF84*$J84,"-") -> 2804646.4 | AL84: =IFERROR(IF(SUM(Y84,AK84)=0,"-",SUM(Y84,AK84)),"-") -> 5354325.6 | AM84: =IFERROR(IF(SUM($Z84,$AJ84)=0,"-",SUM($Z84,$AJ84)),"-") -> 1019871.7 | AN84: 226715 | AO84: DC | AP84: =IFERROR(AN84*(12/$H84)*$J84,"-") -> 305960.96 | AR84: 66265 | AS84: =IFERROR(AR84*(12/$H84)*$J84,"-") -> 89427.268 | AU84: =IFERROR(IF(SUM(AL84,AP84,AS84)=0,"-",SUM(AL84,AP84,AS84)),"-") -> 5749713.8 | AV84: =IFERROR(IF(SUM(AM84,AP84,AS84)=0,"-",SUM(AM84,AP84,AS84)),"-") -> 1415259.9 | AW84: - | AX84: AH | AY84: sc
A85: =$C85&"_"&$E85&"_"&$K85 -> TSX:AGI_2022_ | B85: =$C85&"_"&$E85&"_"&$L85 -> TSX:AGI_2022_CEO | C85: =C84 -> TSX:AGI | D85: =_xll.ciqfunctions.udf.CIQ(C85,"IQ_Company_Name") -> Alamos Gold Inc. | E85: =$F$11 -> 2022 | F85: =E85&"-01-01" -> 2022-01-01 | G85: =E85&"-12-31" -> 2022-12-31 | H85: =_xlfn.DAYS(G85,F85)/_xlfn.DAYS(E85&"-12-31",E85&"-01-01")*12 -> 12 | I85: =I84 -> USD | J85: =IF($I85="CAD",1,IF($I85="USD",VLOOKUP($E85,$F$9:$G$11,2,FALSE),"N/A")) -> 1.30175 | L85: =L84 -> CEO | M85: =M84 -> CEO | N85: =N84 -> John A. McCluskey | O85: 711048 | P85: =IFERROR(O85*(12/$H85)*$J85,"-") -> 925606.73 | Q85: - | R85: =IFERROR(IF((Q85*$J85)=0,"-",(Q85*$J85)),"-") -> - | S85: 977690 | T85: =IFERROR(S85*(12/$H85)*$J85,"-") -> 1272708 | U85: =IFERROR($T85/$P85,"-") -> 1.3749986 | W85: - | X85: =IFERROR(IF(ISNUMBER($W85)=TRUE, $W85*$P85,$V85*$P85),"-") -> 0 | Y85: =IFERROR(IF(SUM(P85,T85)=0,"-",SUM(P85,T85)),"-") -> 2198314.7 | Z85: =IFERROR(IF(SUM(P85,X85)=0,"-",SUM(P85,X85)),"-") -> 925606.73 | AA85: 426629 | AB85: 853257 | AC85: 426629 | AD85: - | AE85: - | AF85: =IFERROR(IF(SUM(AA85:AE85)=0,IF(COUNTIF($AA85:$AE85,"=0")>0,"$0","-"),SUM(AA85:AE85)),"-") -> 1706515 | AG85: =IFERROR($AK85/$P85,"-") -> 2.3999997 | AI85: - | AJ85: =IFERROR(IF(ISNUMBER($AI85)=TRUE, $AI85*$P85, $AH85*$P85), "-") -> 0 | AK85: =IFERROR($AF85*$J85,"-") -> 2221455.9 | AL85: =IFERROR(IF(SUM(Y85,AK85)=0,"-",SUM(Y85,AK85)),"-") -> 4419770.6 | AM85: =IFERROR(IF(SUM($Z85,$AJ85)=0,"-",SUM($Z85,$AJ85)),"-") -> 925606.73 | AN85: 202649 | AO85: DC | AP85: =IFERROR(AN85*(12/$H85)*$J85,"-") -> 263798.34 | AR85: 64986 | AS85: =IFERROR(AR85*(12/$H85)*$J85,"-") -> 84595.526 | AU85: =IFERROR(IF(SUM(AL85,AP85,AS85)=0,"-",SUM(AL85,AP85,AS85)),"-") -> 4768164.5 | AV85: =IFERROR(IF(SUM(AM85,AP85,AS85)=0,"-",SUM(AM85,AP85,AS85)),"-") -> 1274000.6 | AW85: - | AX85: AH | AY85: sc
A86: =$C86&"_"&$E86&"_"&$K86 -> TSX:AGI_2024_ | B86: =$C86&"_"&$E86&"_"&$L86 -> TSX:AGI_2024_CFO | C86: =C85 -> TSX:AGI | D86: =_xll.ciqfunctions.udf.CIQ(C86,"IQ_Company_Name") -> Alamos Gold Inc. | E86: =E83 -> 2024 | F86: =E86&"-01-01" -> 2024-01-01 | G86: =E86&"-12-31" -> 2024-12-31 | H86: =_xlfn.DAYS(G86,F86)/_xlfn.DAYS(E86&"-12-31",E86&"-01-01")*12 -> 12 | I86: =I85 -> USD | J86: =IF($I86="CAD",1,IF($I86="USD",VLOOKUP($E86,$F$9:$G$11,2,FALSE),"N/A")) -> 1.37017 | L86: CFO | M86: CFO | N86: Gregory Fisher | O86: 379704 | P86: 520000 | Q86: - | R86: =IFERROR(IF((Q86*$J86)=0,"-",(Q86*$J86)),"-") -> - | S86: 390371 | T86: =IFERROR(S86*(12/$H86)*$J86,"-") -> 534874.63 | U86: =IFERROR($T86/$P86,"-") -> 1.0286051 | V86: =IFERROR(AVERAGE(U86:U88),"N/A") -> 0.85468595 | W86: 0.85 | X86: =IFERROR(IF(ISNUMBER($W86)=TRUE, $W86*$P86,$V86*$P86),"-") -> 442000 | Y86: =IFERROR(IF(SUM(P86,T86)=0,"-",SUM(P86,T86)),"-") -> 1054874.6 | Z86: =IFERROR(IF(SUM(P86,X86)=0,"-",SUM(P86,X86)),"-") -> 962000 | AA86: =421143*1/3 -> 140381 | AB86: =421143*2/3 -> 280762 | AC86: 140381 | AD86: - | AE86: - | AF86: =IFERROR(IF(SUM(AA86:AE86)=0,IF(COUNTIF($AA86:$AE86,"=0")>0,"$0","-"),SUM(AA86:AE86)),"-") -> 561524 | AG86: =IFERROR($AK86/$P86,"-") -> 1.4795833 | AH86: =IFERROR(AVERAGE(AG86:AG88),"N/A") -> 1.3284208 | AI86: 1.55 | AJ86: =IFERROR(IF(ISNUMBER($AI86)=TRUE, $AI86*$P86, $AH86*$P86), "-") -> 806000 | AK86: =IFERROR($AF86*$J86,"-") -> 769383.34 | AL86: =IFERROR(IF(SUM(Y86,AK86)=0,"-",SUM(Y86,AK86)),"-") -> 1824258 | AM86: =IFERROR(IF(SUM($Z86,$AJ86)=0,"-",SUM($Z86,$AJ86)),"-") -> 1768000 | AN86: 92409 | AO86: DC | AP86: =IFERROR(AN86*(12/$H86)*$J86,"-") -> 126616.04 | AQ86: =IFERROR(AVERAGE(AP86:AP88),"N/A") -> 100373.28 | AR86: 23626 | AS86: =IFERROR(AR86*(12/$H86)*$J86,"-") -> 32371.636 | AT86: =IFERROR(AVERAGE(AS86:AS88),"N/A") -> 28275.662 | AU86: =IFERROR(IF(SUM(AL86,AP86,AS86)=0,"-",SUM(AL86,AP86,AS86)),"-") -> 1983245.6 | AV86: =IFERROR(IF(SUM(AM86,AP86,AS86)=0,"-",SUM(AM86,AP86,AS86)),"-") -> 1926987.7 | AW86: - | AX86: AH | AY86: sc
A87: =$C87&"_"&$E87&"_"&$K87 -> TSX:AGI_2023_ | B87: =$C87&"_"&$E87&"_"&$L87 -> TSX:AGI_2023_CFO | C87: =C86 -> TSX:AGI | D87: =_xll.ciqfunctions.udf.CIQ(C87,"IQ_Company_Name") -> Alamos Gold Inc. | E87: =E84 -> 2023 | F87: =E87&"-01-01" -> 2023-01-01 | G87: =E87&"-12-31" -> 2023-12-31 | H87: =_xlfn.DAYS(G87,F87)/_xlfn.DAYS(E87&"-12-31",E87&"-01-01")*12 -> 12 | I87: =I86 -> USD | J87: =IF($I87="CAD",1,IF($I87="USD",VLOOKUP($E87,$F$9:$G$11,2,FALSE),"N/A")) -> 1.34954 | L87: =L86 -> CFO | M87: =M86 -> CFO | N87: =N86 -> Gregory Fisher | O87: 339579 | P87: =IFERROR(O87*(12/$H87)*$J87,"-") -> 458275.44 | Q87: - | R87: =IFERROR(IF((Q87*$J87)=0,"-",(Q87*$J87)),"-") -> - | S87: 301955 | T87: =IFERROR(S87*(12/$H87)*$J87,"-") -> 407500.35 | U87: =IFERROR($T87/$P87,"-") -> 0.88920398 | W87: - | X87: =IFERROR(IF(ISNUMBER($W87)=TRUE, $W87*$P87,$V87*$P87),"-") -> 0 | Y87: =IFERROR(IF(SUM(P87,T87)=0,"-",SUM(P87,T87)),"-") -> 865775.79 | Z87: =IFERROR(IF(SUM(P87,X87)=0,"-",SUM(P87,X87)),"-") -> 458275.44 | AA87: 100540 | AB87: 201080 | AC87: 100540 | AD87: - | AE87: - | AF87: =IFERROR(IF(SUM(AA87:AE87)=0,IF(COUNTIF($AA87:$AE87,"=0")>0,"$0","-"),SUM(AA87:AE87)),"-") -> 402160 | AG87: =IFERROR($AK87/$P87,"-") -> 1.18429 | AI87: - | AJ87: =IFERROR(IF(ISNUMBER($AI87)=TRUE, $AI87*$P87, $AH87*$P87), "-") -> 0 | AK87: =IFERROR($AF87*$J87,"-") -> 542731.01 | AL87: =IFERROR(IF(SUM(Y87,AK87)=0,"-",SUM(Y87,AK87)),"-") -> 1408506.8 | AM87: =IFERROR(IF(SUM($Z87,$AJ87)=0,"-",SUM($Z87,$AJ87)),"-") -> 458275.44 | AN87: 76984 | AO87: DC | AP87: =IFERROR(AN87*(12/$H87)*$J87,"-") -> 103892.99 | AR87: 22037 | AS87: =IFERROR(AR87*(12/$H87)*$J87,"-") -> 29739.813 | AU87: =IFERROR(IF(SUM(AL87,AP87,AS87)=0,"-",SUM(AL87,AP87,AS87)),"-") -> 1542139.6 | AV87: =IFERROR(IF(SUM(AM87,AP87,AS87)=0,"-",SUM(AM87,AP87,AS87)),"-") -> 591908.24 | AW87: Gregory Fisher was promoted to CFO on May 1, 2023; prior role was SVP Finance. Actual compensation reflects both roles | AX87: AH | AY87: sc
A88: =$C88&"_"&$E88&"_"&$K88 -> TSX:AGI_2022_ | B88: =$C88&"_"&$E88&"_"&$L88 -> TSX:AGI_2022_CFO | C88: =C87 -> TSX:AGI | D88: =_xll.ciqfunctions.udf.CIQ(C88,"IQ_Company_Name") -> Alamos Gold Inc. | E88: =E85 -> 2022 | F88: =E88&"-01-01" -> 2022-01-01 | G88: =E88&"-12-31" -> 2022-12-31 | H88: =_xlfn.DAYS(G88,F88)/_xlfn.DAYS(E88&"-12-31",E88&"-01-01")*12 -> 12 | I88: =I87 -> USD | J88: =IF($I88="CAD",1,IF($I88="USD",VLOOKUP($E88,$F$9:$G$11,2,FALSE),"N/A")) -> 1.30175 | L88: =L87 -> CFO | M88: =M87 -> CFO | N88: =N87 -> Gregory Fisher | O88: 274580 | P88: =IFERROR(O88*(12/$H88)*$J88,"-") -> 357434.52 | Q88: - | R88: =IFERROR(IF((Q88*$J88)=0,"-",(Q88*$J88)),"-") -> - | S88: 177447 | T88: =IFERROR(S88*(12/$H88)*$J88,"-") -> 230991.63 | U88: =IFERROR($T88/$P88,"-") -> 0.64624882 | W88: - | X88: =IFERROR(IF(ISNUMBER($W88)=TRUE, $W88*$P88,$V88*$P88),"-") -> 0 | Y88: =IFERROR(IF(SUM(P88,T88)=0,"-",SUM(P88,T88)),"-") -> 588426.15 | Z88: =IFERROR(IF(SUM(P88,X88)=0,"-",SUM(P88,X88)),"-") -> 357434.52 | AA88: 90707 | AB88: 181413 | AC88: 90707 | AD88: - | AE88: - | AF88: =IFERROR(IF(SUM(AA88:AE88)=0,IF(COUNTIF($AA88:$AE88,"=0")>0,"$0","-"),SUM(AA88:AE88)),"-") -> 362827 | AG88: =IFERROR($AK88/$P88,"-") -> 1.321389 | AI88: - | AJ88: =IFERROR(IF(ISNUMBER($AI88)=TRUE, $AI88*$P88, $AH88*$P88), "-") -> 0 | AK88: =IFERROR($AF88*$J88,"-") -> 472310.05 | AL88: =IFERROR(IF(SUM(Y88,AK88)=0,"-",SUM(Y88,AK88)),"-") -> 1060736.2 | AM88: =IFERROR(IF(SUM($Z88,$AJ88)=0,"-",SUM($Z88,$AJ88)),"-") -> 357434.52 | AN88: 54243 | AO88: DC | AP88: =IFERROR(AN88*(12/$H88)*$J88,"-") -> 70610.825 | AR88: 17450 | AS88: =IFERROR(AR88*(12/$H88)*$J88,"-") -> 22715.537 | AU88: =IFERROR(IF(SUM(AL88,AP88,AS88)=0,"-",SUM(AL88,AP88,AS88)),"-") -> 1154062.6 | AV88: =IFERROR(IF(SUM(AM88,AP88,AS88)=0,"-",SUM(AM88,AP88,AS88)),"-") -> 450760.88 | AW88: - | AX88: AH | AY88: sc
A89: =$C89&"_"&$E89&"_"&$K89 -> TSX:AGI_2024_COO | B89: =$C89&"_"&$E89&"_"&$L89 -> TSX:AGI_2024_NEO1 | C89: =C88 -> TSX:AGI | D89: =_xll.ciqfunctions.udf.CIQ(C89,"IQ_Company_Name") -> Alamos Gold Inc. | E89: =E86 -> 2024 | F89: =E89&"-01-01" -> 2024-01-01 | G89: =E89&"-12-31" -> 2024-12-31 | H89: =_xlfn.DAYS(G89,F89)/_xlfn.DAYS(E89&"-12-31",E89&"-01-01")*12 -> 12 | I89: =I88 -> USD | J89: =IF($I89="CAD",1,IF($I89="USD",VLOOKUP($E89,$F$9:$G$11,2,FALSE),"N/A")) -> 1.37017 | K89: COO | L89: NEO1 | M89: COO | N89: Luc Guimond | O89: 474630 | P89: 650000 | Q89: - | R89: =IFERROR(IF((Q89*$J89)=0,"-",(Q89*$J89)),"-") -> - | S89: 481146 | T89: =IFERROR(S89*(12/$H89)*$J89,"-") -> 659251.81 | U89: =IFERROR($T89/$P89,"-") -> 1.0142336 | V89: =IFERROR(AVERAGE(U89:U91),"N/A") -> 0.92825291 | W89: 0.85 | X89: =IFERROR(IF(ISNUMBER($W89)=TRUE, $W89*$P89,$V89*$P89),"-") -> 552500 | Y89: =IFERROR(IF(SUM(P89,T89)=0,"-",SUM(P89,T89)),"-") -> 1309251.8 | Z89: =IFERROR(IF(SUM(P89,X89)=0,"-",SUM(P89,X89)),"-") -> 1202500 | AA89: =587355*1/3 -> 195785 | AB89: =587355*2/3 -> 391570 | AC89: 195785 | AD89: - | AE89: - | AF89: =IFERROR(IF(SUM(AA89:AE89)=0,IF(COUNTIF($AA89:$AE89,"=0")>0,"$0","-"),SUM(AA89:AE89)),"-") -> 783140 | AG89: =IFERROR($AK89/$P89,"-") -> 1.650823 | AH89: =IFERROR(AVERAGE(AG89:AG91),"N/A") -> 1.6363901 | AI89: 1.7 | AJ89: =IFERROR(IF(ISNUMBER($AI89)=TRUE, $AI89*$P89, $AH89*$P89), "-") -> 1105000 | AK89: =IFERROR($AF89*$J89,"-") -> 1073034.9 | AL89: =IFERROR(IF(SUM(Y89,AK89)=0,"-",SUM(Y89,AK89)),"-") -> 2382286.7 | AM89: =IFERROR(IF(SUM($Z89,$AJ89)=0,"-",SUM($Z89,$AJ89)),"-") -> 2307500 | AN89: 114693 | AO89: DC | AP89: =IFERROR(AN89*(12/$H89)*$J89,"-") -> 157148.91 | AQ89: =IFERROR(AVERAGE(AP89:AP91),"N/A") -> 120254.42 | AR89: 28511 | AS89: =IFERROR(AR89*(12/$H89)*$J89,"-") -> 39064.917 | AT89: =IFERROR(AVERAGE(AS89:AS91),"N/A") -> 32173.696 | AU89: =IFERROR(IF(SUM(AL89,AP89,AS89)=0,"-",SUM(AL89,AP89,AS89)),"-") -> 2578500.6 | AV89: =IFERROR(IF(SUM(AM89,AP89,AS89)=0,"-",SUM(AM89,AP89,AS89)),"-") -> 2503713.8 | AW89: - | AX89: AH | AY89: sc
A90: =$C90&"_"&$E90&"_"&$K90 -> TSX:AGI_2023_COO | B90: =$C90&"_"&$E90&"_"&$L90 -> TSX:AGI_2023_NEO1 | C90: =C89 -> TSX:AGI | D90: =_xll.ciqfunctions.udf.CIQ(C90,"IQ_Company_Name") -> Alamos Gold Inc. | E90: =E87 -> 2023 | F90: =E90&"-01-01" -> 2023-01-01 | G90: =E90&"-12-31" -> 2023-12-31 | H90: =_xlfn.DAYS(G90,F90)/_xlfn.DAYS(E90&"-12-31",E90&"-01-01")*12 -> 12 | I90: =I89 -> USD | J90: =IF($I90="CAD",1,IF($I90="USD",VLOOKUP($E90,$F$9:$G$11,2,FALSE),"N/A")) -> 1.34954 | K90: COO | L90: =L89 -> NEO1 | M90: =M89 -> COO | N90: =N89 -> Luc Guimond | O90: 379711 | P90: =IFERROR(O90*(12/$H90)*$J90,"-") -> 512435.18 | Q90: - | R90: =IFERROR(IF((Q90*$J90)=0,"-",(Q90*$J90)),"-") -> - | S90: 375914 | T90: =IFERROR(S90*(12/$H90)*$J90,"-") -> 507310.98 | U90: =IFERROR($T90/$P90,"-") -> 0.99000029 | W90: - | X90: =IFERROR(IF(ISNUMBER($W90)=TRUE, $W90*$P90,$V90*$P90),"-") -> 0 | Y90: =IFERROR(IF(SUM(P90,T90)=0,"-",SUM(P90,T90)),"-") -> 1019746.2 | Z90: =IFERROR(IF(SUM(P90,X90)=0,"-",SUM(P90,X90)),"-") -> 512435.18 | AA90: 153969 | AB90: 307937 | AC90: 153969 | AD90: - | AE90: - | AF90: =IFERROR(IF(SUM(AA90:AE90)=0,IF(COUNTIF($AA90:$AE90,"=0")>0,"$0","-"),SUM(AA90:AE90)),"-") -> 615875 | AG90: =IFERROR($AK90/$P90,"-") -> 1.6219572 | AI90: - | AJ90: =IFERROR(IF(ISNUMBER($AI90)=TRUE, $AI90*$P90, $AH90*$P90), "-") -> 0 | AK90: =IFERROR($AF90*$J90,"-") -> 831147.95 | AL90: =IFERROR(IF(SUM(Y90,AK90)=0,"-",SUM(Y90,AK90)),"-") -> 1850894.1 | AM90: =IFERROR(IF(SUM($Z90,$AJ90)=0,"-",SUM($Z90,$AJ90)),"-") -> 512435.18 | AN90: 90675 | AO90: DC | AP90: =IFERROR(AN90*(12/$H90)*$J90,"-") -> 122369.54 | AR90: 23797 | AS90: =IFERROR(AR90*(12/$H90)*$J90,"-") -> 32115.003 | AU90: =IFERROR(IF(SUM(AL90,AP90,AS90)=0,"-",SUM(AL90,AP90,AS90)),"-") -> 2005378.7 | AV90: =IFERROR(IF(SUM(AM90,AP90,AS90)=0,"-",SUM(AM90,AP90,AS90)),"-") -> 666919.73 | AW90: - | AX90: AH | AY90: sc
A91: =$C91&"_"&$E91&"_"&$K91 -> TSX:AGI_2022_COO | B91: =$C91&"_"&$E91&"_"&$L91 -> TSX:AGI_2022_NEO1 | C91: =C90 -> TSX:AGI | D91: =_xll.ciqfunctions.udf.CIQ(C91,"IQ_Company_Name") -> Alamos Gold Inc. | E91: =E88 -> 2022 | F91: =E91&"-01-01" -> 2022-01-01 | G91: =E91&"-12-31" -> 2022-12-31 | H91: =_xlfn.DAYS(G91,F91)/_xlfn.DAYS(E91&"-12-31",E91&"-01-01")*12 -> 12 | I91: =I90 -> USD | J91: =IF($I91="CAD",1,IF($I91="USD",VLOOKUP($E91,$F$9:$G$11,2,FALSE),"N/A")) -> 1.30175 | K91: COO | L91: =L90 -> NEO1 | M91: =M90 -> COO | N91: =N90 -> Luc Guimond | O91: 292106 | P91: =IFERROR(O91*(12/$H91)*$J91,"-") -> 380248.99 | Q91: - | R91: =IFERROR(IF((Q91*$J91)=0,"-",(Q91*$J91)),"-") -> - | S91: 227996 | T91: =IFERROR(S91*(12/$H91)*$J91,"-") -> 296793.79 | U91: =IFERROR($T91/$P91,"-") -> 0.78052488 | W91: - | X91: =IFERROR(IF(ISNUMBER($W91)=TRUE, $W91*$P91,$V91*$P91),"-") -> 0 | Y91: =IFERROR(IF(SUM(P91,T91)=0,"-",SUM(P91,T91)),"-") -> 677042.78 | Z91: =IFERROR(IF(SUM(P91,X91)=0,"-",SUM(P91,X91)),"-") -> 380248.99 | AA91: - | AB91: - | AC91: - | AD91: - | AE91: - | AF91: =IFERROR(IF(SUM(AA91:AE91)=0,IF(COUNTIF($AA91:$AE91,"=0")>0,"$0","-"),SUM(AA91:AE91)),"-") -> - | AG91: =IFERROR($AK91/$P91,"-") -> - | AI91: - | AJ91: =IFERROR(IF(ISNUMBER($AI91)=TRUE, $AI91*$P91, $AH91*$P91), "-") -> 0 | AK91: =IFERROR($AF91*$J91,"-") -> - | AL91: =IFERROR(IF(SUM(Y91,AK91)=0,"-",SUM(Y91,AK91)),"-") -> 677042.78 | AM91: =IFERROR(IF(SUM($Z91,$AJ91)=0,"-",SUM($Z91,$AJ91)),"-") -> 380248.99 | AN91: 62412 | AO91: DC | AP91: =IFERROR(AN91*(12/$H91)*$J91,"-") -> 81244.821 | AR91: 19467 | AS91: =IFERROR(AR91*(12/$H91)*$J91,"-") -> 25341.167 | AU91: =IFERROR(IF(SUM(AL91,AP91,AS91)=0,"-",SUM(AL91,AP91,AS91)),"-") -> 783628.77 | AV91: =IFERROR(IF(SUM(AM91,AP91,AS91)=0,"-",SUM(AM91,AP91,AS91)),"-") -> 486834.97 | AW91: Mr. Guimond was promoted to COO on September 1 2022. | AX91: AH | AY91: sc
A92: =$C92&"_"&$E92&"_"&$K92 -> TSX:AGI_2024_Region | B92: =$C92&"_"&$E92&"_"&$L92 -> TSX:AGI_2024_NEO3 | C92: =C91 -> TSX:AGI | D92: =_xll.ciqfunctions.udf.CIQ(C92,"IQ_Company_Name") -> Alamos Gold Inc. | E92: =E89 -> 2024 | F92: =E92&"-01-01" -> 2024-01-01 | G92: =E92&"-12-31" -> 2024-12-31 | H92: =_xlfn.DAYS(G92,F92)/_xlfn.DAYS(E92&"-12-31",E92&"-01-01")*12 -> 12 | I92: =I91 -> USD | J92: =IF($I92="CAD",1,IF($I92="USD",VLOOKUP($E92,$F$9:$G$11,2,FALSE),"N/A")) -> 1.37017 | K92: Region | L92: NEO3 | M92: SVP, Mexico | N92: Luis Chavez | O92: 343026 | P92: =IFERROR(343026*(12/$H92)*$J92,"-") -> 470003.93 | Q92: - | R92: =IFERROR(IF((Q92*$J92)=0,"-",(Q92*$J92)),"-") -> - | S92: 236322 | T92: =IFERROR(S92*(12/$H92)*$J92,"-") -> 323801.31 | U92: =IFERROR($T92/$P92,"-") -> 0.6889332 | V92: =IFERROR(AVERAGE(U92:U94),"N/A") -> 0.6794541 | W92: 0.6 | X92: =IFERROR(IF(ISNUMBER($W92)=TRUE, $W92*$P92,$V92*$P92),"-") -> 282002.36 | Y92: =IFERROR(IF(SUM(P92,T92)=0,"-",SUM(P92,T92)),"-") -> 793805.25 | Z92: =IFERROR(IF(SUM(P92,X92)=0,"-",SUM(P92,X92)),"-") -> 752006.3 | AA92: =279302*1/3 -> 93100.667 | AB92: =279302*2/3 -> 186201.33 | AC92: 93101 | AD92: - | AE92: - | AF92: =IFERROR(IF(SUM(AA92:AE92)=0,IF(COUNTIF($AA92:$AE92,"=0")>0,"$0","-"),SUM(AA92:AE92)),"-") -> 372403 | AG92: =IFERROR($AK92/$P92,"-") -> 1.0856407 | AH92: =IFERROR(AVERAGE(AG92:AG94),"N/A") -> 1.0908179 | AI92: - | AJ92: =IFERROR(IF(ISNUMBER($AI92)=TRUE, $AI92*$P92, $AH92*$P92), "-") -> 512688.71 | AK92: =IFERROR($AF92*$J92,"-") -> 510255.42 | AL92: =IFERROR(IF(SUM(Y92,AK92)=0,"-",SUM(Y92,AK92)),"-") -> 1304060.7 | AM92: =IFERROR(IF(SUM($Z92,$AJ92)=0,"-",SUM($Z92,$AJ92)),"-") -> 1264695 | AN92: - | AO92: - | AP92: =IFERROR(AN92*(12/$H92)*$J92,"-") -> - | AQ92: =IFERROR(AVERAGE(AP92:AP94),"N/A") -> N/A | AR92: 27451 | AS92: =IFERROR(AR92*(12/$H92)*$J92,"-") -> 37612.537 | AT92: =IFERROR(AVERAGE(AS92:AS94),"N/A") -> 41425.751 | AU92: =IFERROR(IF(SUM(AL92,AP92,AS92)=0,"-",SUM(AL92,AP92,AS92)),"-") -> 1341673.2 | AV92: =IFERROR(IF(SUM(AM92,AP92,AS92)=0,"-",SUM(AM92,AP92,AS92)),"-") -> 1302307.5 | AW92: - | AX92: AH | AY92: sc
A93: =$C93&"_"&$E93&"_"&$K93 -> TSX:AGI_2023_Region | B93: =$C93&"_"&$E93&"_"&$L93 -> TSX:AGI_2023_NEO3 | C93: =C92 -> TSX:AGI | D93: =_xll.ciqfunctions.udf.CIQ(C93,"IQ_Company_Name") -> Alamos Gold Inc. | E93: =E90 -> 2023 | F93: =E93&"-01-01" -> 2023-01-01 | G93: =E93&"-12-31" -> 2023-12-31 | H93: =_xlfn.DAYS(G93,F93)/_xlfn.DAYS(E93&"-12-31",E93&"-01-01")*12 -> 12 | I93: =I92 -> USD | J93: =IF($I93="CAD",1,IF($I93="USD",VLOOKUP($E93,$F$9:$G$11,2,FALSE),"N/A")) -> 1.34954 | K93: Region | L93: =L92 -> NEO3 | M93: =M92 -> SVP, Mexico | N93: =N92 -> Luis Chavez | O93: 336300 | P93: =IFERROR(O93*(12/$H93)*$J93,"-") -> 453850.3 | Q93: - | R93: =IFERROR(IF((Q93*$J93)=0,"-",(Q93*$J93)),"-") -> - | S93: 232047 | T93: =IFERROR(S93*(12/$H93)*$J93,"-") -> 313156.71 | U93: =IFERROR($T93/$P93,"-") -> 0.69 | W93: - | X93: =IFERROR(IF(ISNUMBER($W93)=TRUE, $W93*$P93,$V93*$P93),"-") -> 0 | Y93: =IFERROR(IF(SUM(P93,T93)=0,"-",SUM(P93,T93)),"-") -> 767007.01 | Z93: =IFERROR(IF(SUM(P93,X93)=0,"-",SUM(P93,X93)),"-") -> 453850.3 | AA93: =273059*1/3 -> 91019.667 | AB93: =273059*2/3 -> 182039.33 | AC93: 91020 | AD93: - | AE93: - | AF93: =IFERROR(IF(SUM(AA93:AE93)=0,IF(COUNTIF($AA93:$AE93,"=0")>0,"$0","-"),SUM(AA93:AE93)),"-") -> 364079 | AG93: =IFERROR($AK93/$P93,"-") -> 1.0826018 | AI93: - | AJ93: =IFERROR(IF(ISNUMBER($AI93)=TRUE, $AI93*$P93, $AH93*$P93), "-") -> 0 | AK93: =IFERROR($AF93*$J93,"-") -> 491339.17 | AL93: =IFERROR(IF(SUM(Y93,AK93)=0,"-",SUM(Y93,AK93)),"-") -> 1258346.2 | AM93: =IFERROR(IF(SUM($Z93,$AJ93)=0,"-",SUM($Z93,$AJ93)),"-") -> 453850.3 | AN93: - | AO93: - | AP93: =IFERROR(AN93*(12/$H93)*$J93,"-") -> - | AR93: 23740 | AS93: =IFERROR(AR93*(12/$H93)*$J93,"-") -> 32038.08 | AU93: =IFERROR(IF(SUM(AL93,AP93,AS93)=0,"-",SUM(AL93,AP93,AS93)),"-") -> 1290384.3 | AV93: =IFERROR(IF(SUM(AM93,AP93,AS93)=0,"-",SUM(AM93,AP93,AS93)),"-") -> 485888.38 | AW93: - | AX93: AH | AY93: sc
A94: =$C94&"_"&$E94&"_"&$K94 -> TSX:AGI_2022_Region | B94: =$C94&"_"&$E94&"_"&$L94 -> TSX:AGI_2022_NEO3 | C94: =C93 -> TSX:AGI | D94: =_xll.ciqfunctions.udf.CIQ(C94,"IQ_Company_Name") -> Alamos Gold Inc. | E94: =E91 -> 2022 | F94: =E94&"-01-01" -> 2022-01-01 | G94: =E94&"-12-31" -> 2022-12-31 | H94: =_xlfn.DAYS(G94,F94)/_xlfn.DAYS(E94&"-12-31",E94&"-01-01")*12 -> 12 | I94: =I93 -> USD | J94: =IF($I94="CAD",1,IF($I94="USD",VLOOKUP($E94,$F$9:$G$11,2,FALSE),"N/A")) -> 1.30175 | K94: Region | L94: =L93 -> NEO3 | M94: =M93 -> SVP, Mexico | N94: =N93 -> Luis Chavez | O94: 325800 | P94: =IFERROR(O94*(12/$H94)*$J94,"-") -> 424110.15 | Q94: - | R94: =IFERROR(IF((Q94*$J94)=0,"-",(Q94*$J94)),"-") -> - | S94: 214842 | T94: =IFERROR(S94*(12/$H94)*$J94,"-") -> 279670.57 | U94: =IFERROR($T94/$P94,"-") -> 0.6594291 | W94: - | X94: =IFERROR(IF(ISNUMBER($W94)=TRUE, $W94*$P94,$V94*$P94),"-") -> 0 | Y94: =IFERROR(IF(SUM(P94,T94)=0,"-",SUM(P94,T94)),"-") -> 703780.72 | Z94: =IFERROR(IF(SUM(P94,X94)=0,"-",SUM(P94,X94)),"-") -> 424110.15 | AA94: =269814*1/3 -> 89938 | AB94: =269814*2/3 -> 179876 | AC94: 89938 | AD94: - | AE94: - | AF94: =IFERROR(IF(SUM(AA94:AE94)=0,IF(COUNTIF($AA94:$AE94,"=0")>0,"$0","-"),SUM(AA94:AE94)),"-") -> 359752 | AG94: =IFERROR($AK94/$P94,"-") -> 1.1042112 | AI94: - | AJ94: =IFERROR(IF(ISNUMBER($AI94)=TRUE, $AI94*$P94, $AH94*$P94), "-") -> 0 | AK94: =IFERROR($AF94*$J94,"-") -> 468307.17 | AL94: =IFERROR(IF(SUM(Y94,AK94)=0,"-",SUM(Y94,AK94)),"-") -> 1172087.9 | AM94: =IFERROR(IF(SUM($Z94,$AJ94)=0,"-",SUM($Z94,$AJ94)),"-") -> 424110.15 | AN94: - | AO94: - | AP94: =IFERROR(AN94*(12/$H94)*$J94,"-") -> - | AR94: 41964 | AS94: =IFERROR(AR94*(12/$H94)*$J94,"-") -> 54626.637 | AU94: =IFERROR(IF(SUM(AL94,AP94,AS94)=0,"-",SUM(AL94,AP94,AS94)),"-") -> 1226714.5 | AV94: =IFERROR(IF(SUM(AM94,AP94,AS94)=0,"-",SUM(AM94,AP94,AS94)),"-") -> 478736.79 | AW94: - | AX94: AH | AY94: sc
A95: =$C95&"_"&$E95&"_"&$K95 -> TSX:AGI_2024_Tech | B95: =$C95&"_"&$E95&"_"&$L95 -> TSX:AGI_2024_NEO2 | C95: =C94 -> TSX:AGI | D95: =_xll.ciqfunctions.udf.CIQ(C95,"IQ_Company_Name") -> Alamos Gold Inc. | E95: =E92 -> 2024 | F95: =E95&"-01-01" -> 2024-01-01 | G95: =E95&"-12-31" -> 2024-12-31 | H95: =_xlfn.DAYS(G95,F95)/_xlfn.DAYS(E95&"-12-31",E95&"-01-01")*12 -> 12 | I95: =I94 -> USD | J95: =IF($I95="CAD",1,IF($I95="USD",VLOOKUP($E95,$F$9:$G$11,2,FALSE),"N/A")) -> 1.37017 | K95: Tech | L95: NEO2 | M95: SVP, Technical Services | N95: Christopher Bostwick | O95: 324939 | P95: 445000 | Q95: - | R95: =IFERROR(IF((Q95*$J95)=0,"-",(Q95*$J95)),"-") -> - | S95: 274655 | T95: =IFERROR(S95*(12/$H95)*$J95,"-") -> 376324.04 | U95: =IFERROR($T95/$P95,"-") -> 0.845672 | V95: =IFERROR(AVERAGE(U95:U97),"N/A") -> 0.73189048 | W95: 0.7 | X95: =IFERROR(IF(ISNUMBER($W95)=TRUE, $W95*$P95,$V95*$P95),"-") -> 311500 | Y95: =IFERROR(IF(SUM(P95,T95)=0,"-",SUM(P95,T95)),"-") -> 821324.04 | Z95: =IFERROR(IF(SUM(P95,X95)=0,"-",SUM(P95,X95)),"-") -> 756500 | AA95: =352960*1/3 -> 117653.33 | AB95: =352960*2/3 -> 235306.67 | AC95: 117653 | AD95: - | AE95: - | AF95: =IFERROR(IF(SUM(AA95:AE95)=0,IF(COUNTIF($AA95:$AE95,"=0")>0,"$0","-"),SUM(AA95:AE95)),"-") -> 470613 | AG95: =IFERROR($AK95/$P95,"-") -> 1.4490333 | AH95: =IFERROR(AVERAGE(AG95:AG97),"N/A") -> 1.2992227 | AI95: 1.55 | AJ95: =IFERROR(IF(ISNUMBER($AI95)=TRUE, $AI95*$P95, $AH95*$P95), "-") -> 689750 | AK95: =IFERROR($AF95*$J95,"-") -> 644819.81 | AL95: =IFERROR(IF(SUM(Y95,AK95)=0,"-",SUM(Y95,AK95)),"-") -> 1466143.9 | AM95: =IFERROR(IF(SUM($Z95,$AJ95)=0,"-",SUM($Z95,$AJ95)),"-") -> 1446250 | AN95: 71951 | AO95: DC | AP95: =IFERROR(AN95*(12/$H95)*$J95,"-") -> 98585.102 | AQ95: =IFERROR(AVERAGE(AP95:AP97),"N/A") -> 88608.354 | AR95: 21023 | AS95: =IFERROR(AR95*(12/$H95)*$J95,"-") -> 28805.084 | AT95: =IFERROR(AVERAGE(AS95:AS97),"N/A") -> 27737.96 | AU95: =IFERROR(IF(SUM(AL95,AP95,AS95)=0,"-",SUM(AL95,AP95,AS95)),"-") -> 1593534 | AV95: =IFERROR(IF(SUM(AM95,AP95,AS95)=0,"-",SUM(AM95,AP95,AS95)),"-") -> 1573640.2 | AW95: - | AX95: AH | AY95: sc
A96: =$C96&"_"&$E96&"_"&$K96 -> TSX:AGI_2023_Tech | B96: =$C96&"_"&$E96&"_"&$L96 -> TSX:AGI_2023_NEO2 | C96: =C95 -> TSX:AGI | D96: =_xll.ciqfunctions.udf.CIQ(C96,"IQ_Company_Name") -> Alamos Gold Inc. | E96: =E93 -> 2023 | F96: =E96&"-01-01" -> 2023-01-01 | G96: =E96&"-12-31" -> 2023-12-31 | H96: =_xlfn.DAYS(G96,F96)/_xlfn.DAYS(E96&"-12-31",E96&"-01-01")*12 -> 12 | I96: =I95 -> USD | J96: =IF($I96="CAD",1,IF($I96="USD",VLOOKUP($E96,$F$9:$G$11,2,FALSE),"N/A")) -> 1.34954 | K96: Tech | L96: =L95 -> NEO2 | M96: =M95 -> SVP, Technical Services | N96: =N95 -> Christopher Bostwick | O96: 314883 | P96: =IFERROR(O96*(12/$H96)*$J96,"-") -> 424947.2 | Q96: - | R96: =IFERROR(IF((Q96*$J96)=0,"-",(Q96*$J96)),"-") -> - | S96: 221992 | T96: =IFERROR(S96*(12/$H96)*$J96,"-") -> 299587.08 | U96: =IFERROR($T96/$P96,"-") -> 0.70499836 | W96: - | X96: =IFERROR(IF(ISNUMBER($W96)=TRUE, $W96*$P96,$V96*$P96),"-") -> 0 | Y96: =IFERROR(IF(SUM(P96,T96)=0,"-",SUM(P96,T96)),"-") -> 724534.29 | Z96: =IFERROR(IF(SUM(P96,X96)=0,"-",SUM(P96,X96)),"-") -> 424947.2 | AA96: 100966 | AB96: 201932 | AC96: 100966 | AD96: - | AE96: - | AF96: =IFERROR(IF(SUM(AA96:AE96)=0,IF(COUNTIF($AA96:$AE96,"=0")>0,"$0","-"),SUM(AA96:AE96)),"-") -> 403864 | AG96: =IFERROR($AK96/$P96,"-") -> 1.2825843 | AI96: - | AJ96: =IFERROR(IF(ISNUMBER($AI96)=TRUE, $AI96*$P96, $AH96*$P96), "-") -> 0 | AK96: =IFERROR($AF96*$J96,"-") -> 545030.62 | AL96: =IFERROR(IF(SUM(Y96,AK96)=0,"-",SUM(Y96,AK96)),"-") -> 1269564.9 | AM96: =IFERROR(IF(SUM($Z96,$AJ96)=0,"-",SUM($Z96,$AJ96)),"-") -> 424947.2 | AN96: 64425 | AO96: DC | AP96: =IFERROR(AN96*(12/$H96)*$J96,"-") -> 86944.114 | AR96: 20556 | AS96: =IFERROR(AR96*(12/$H96)*$J96,"-") -> 27741.144 | AU96: =IFERROR(IF(SUM(AL96,AP96,AS96)=0,"-",SUM(AL96,AP96,AS96)),"-") -> 1384250.2 | AV96: =IFERROR(IF(SUM(AM96,AP96,AS96)=0,"-",SUM(AM96,AP96,AS96)),"-") -> 539632.46 | AW96: - | AX96: AH | AY96: sc
A97: =$C97&"_"&$E97&"_"&$K97 -> TSX:AGI_2022_Tech | B97: =$C97&"_"&$E97&"_"&$L97 -> TSX:AGI_2022_NEO2 | C97: =C96 -> TSX:AGI | D97: =_xll.ciqfunctions.udf.CIQ(C97,"IQ_Company_Name") -> Alamos Gold Inc. | E97: =E94 -> 2022 | F97: =E97&"-01-01" -> 2022-01-01 | G97: =E97&"-12-31" -> 2022-12-31 | H97: =_xlfn.DAYS(G97,F97)/_xlfn.DAYS(E97&"-12-31",E97&"-01-01")*12 -> 12 | I97: =I96 -> USD | J97: =IF($I97="CAD",1,IF($I97="USD",VLOOKUP($E97,$F$9:$G$11,2,FALSE),"N/A")) -> 1.30175 | K97: Tech | L97: =L96 -> NEO2 | M97: =M96 -> SVP, Technical Services | N97: =N96 -> Christopher Bostwick | O97: 312477 | P97: =IFERROR(O97*(12/$H97)*$J97,"-") -> 406766.93 | Q97: - | R97: =IFERROR(IF((Q97*$J97)=0,"-",(Q97*$J97)),"-") -> - | S97: 201548 | T97: =IFERROR(S97*(12/$H97)*$J97,"-") -> 262365.11 | U97: =IFERROR($T97/$P97,"-") -> 0.64500107 | W97: - | X97: =IFERROR(IF(ISNUMBER($W97)=TRUE, $W97*$P97,$V97*$P97),"-") -> 0 | Y97: =IFERROR(IF(SUM(P97,T97)=0,"-",SUM(P97,T97)),"-") -> 669132.04 | Z97: =IFERROR(IF(SUM(P97,X97)=0,"-",SUM(P97,X97)),"-") -> 406766.93 | AA97: 91091 | AB97: 182182 | AC97: 91091 | AD97: - | AE97: - | AF97: =IFERROR(IF(SUM(AA97:AE97)=0,IF(COUNTIF($AA97:$AE97,"=0")>0,"$0","-"),SUM(AA97:AE97)),"-") -> 364364 | AG97: =IFERROR($AK97/$P97,"-") -> 1.1660506 | AI97: - | AJ97: =IFERROR(IF(ISNUMBER($AI97)=TRUE, $AI97*$P97, $AH97*$P97), "-") -> 0 | AK97: =IFERROR($AF97*$J97,"-") -> 474310.84 | AL97: =IFERROR(IF(SUM(Y97,AK97)=0,"-",SUM(Y97,AK97)),"-") -> 1143442.9 | AM97: =IFERROR(IF(SUM($Z97,$AJ97)=0,"-",SUM($Z97,$AJ97)),"-") -> 406766.93 | AN97: 61683 | AO97: DC | AP97: =IFERROR(AN97*(12/$H97)*$J97,"-") -> 80295.845 | AR97: 20486 | AS97: =IFERROR(AR97*(12/$H97)*$J97,"-") -> 26667.65 | AU97: =IFERROR(IF(SUM(AL97,AP97,AS97)=0,"-",SUM(AL97,AP97,AS97)),"-") -> 1250406.4 | AV97: =IFERROR(IF(SUM(AM97,AP97,AS97)=0,"-",SUM(AM97,AP97,AS97)),"-") -> 513730.43 | AW97: - | AX97: AH | AY97: sc
A98: =$C98&"_"&$E98&"_"&$K98 -> TSX:PAAS_2024_ | B98: =$C98&"_"&$E98&"_"&$L98 -> TSX:PAAS_2024_CEO | C98: =D8 -> TSX:PAAS | D98: =_xll.ciqfunctions.udf.CIQ(C98,"IQ_Company_Name") -> Pan American Silver Corp. | E98: =$F$9 -> 2024 | F98: =E98&"-01-01" -> 2024-01-01 | G98: =E98&"-12-31" -> 2024-12-31 | H98: =_xlfn.DAYS(G98,F98)/_xlfn.DAYS(E98&"-12-31",E98&"-01-01")*12 -> 12 | I98: CAD | J98: =IF($I98="CAD",1,IF($I98="USD",VLOOKUP($E98,$F$9:$G$11,2,FALSE),"N/A")) -> 1 | L98: CEO | M98: CEO | N98: Michael Steinmann | O98: 1508000 | P98: =IFERROR(O98*(12/$H98)*$J98,"-") -> 1508000 | Q98: - | R98: =IFERROR(IF((Q98*$J98)=0,"-",(Q98*$J98)),"-") -> - | S98: 1932130 | T98: =IFERROR(S98*(12/$H98)*$J98,"-") -> 1932130 | U98: =IFERROR($T98/$P98,"-") -> 1.2812533 | V98: =IFERROR(AVERAGE(U98:U100),"N/A") -> 1.1351649 | W98: 1.25 | X98: =IFERROR(IF(ISNUMBER($W98)=TRUE, $W98*$P98,$V98*$P98),"-") -> 1885000 | Y98: =IFERROR(IF(SUM(P98,T98)=0,"-",SUM(P98,T98)),"-") -> 3440130 | Z98: =IFERROR(IF(SUM(P98,X98)=0,"-",SUM(P98,X98)),"-") -> 3393000 | AA98: 1885000 | AB98: 2412800 | AC98: - | AD98: - | AE98: - | AF98: =IFERROR(IF(SUM(AA98:AE98)=0,IF(COUNTIF($AA98:$AE98,"=0")>0,"$0","-"),SUM(AA98:AE98)),"-") -> 4297800 | AG98: =IFERROR($AK98/$P98,"-") -> 2.85 | AH98: =IFERROR(AVERAGE(AG98:AG100),"N/A") -> 2.5833784 | AI98: 2.85 | AJ98: =IFERROR(IF(ISNUMBER($AI98)=TRUE, $AI98*$P98, $AH98*$P98), "-") -> 4297800 | AK98: =IFERROR($AF98*$J98,"-") -> 4297800 | AL98: =IFERROR(IF(SUM(Y98,AK98)=0,"-",SUM(Y98,AK98)),"-") -> 7737930 | AM98: =IFERROR(IF(SUM($Z98,$AJ98)=0,"-",SUM($Z98,$AJ98)),"-") -> 7690800 | AN98: 678600 | AO98: DC | AP98: =IFERROR(AN98*(12/$H98)*$J98,"-") -> 678600 | AQ98: =IFERROR(AVERAGE(AP98:AP100),"N/A") -> 621750 | AR98: - | AS98: =IFERROR(AR98*(12/$H98)*$J98,"-") -> - | AT98: =IFERROR(AVERAGE(AS98:AS100),"N/A") -> N/A | AU98: =IFERROR(IF(SUM(AL98,AP98,AS98)=0,"-",SUM(AL98,AP98,AS98)),"-") -> 8416530 | AV98: =IFERROR(IF(SUM(AM98,AP98,AS98)=0,"-",SUM(AM98,AP98,AS98)),"-") -> 8369400 | AW98: Restricted Shares as a component of compensation were removed from the LTIP guidelines in November 2024 and will not be issued for future LTIP awards. | AX98: AH | AY98: sc
A99: =$C99&"_"&$E99&"_"&$K99 -> TSX:PAAS_2023_ | B99: =$C99&"_"&$E99&"_"&$L99 -> TSX:PAAS_2023_CEO | C99: =C98 -> TSX:PAAS | D99: =_xll.ciqfunctions.udf.CIQ(C99,"IQ_Company_Name") -> Pan American Silver Corp. | E99: =$F$10 -> 2023 | F99: =E99&"-01-01" -> 2023-01-01 | G99: =E99&"-12-31" -> 2023-12-31 | H99: =_xlfn.DAYS(G99,F99)/_xlfn.DAYS(E99&"-12-31",E99&"-01-01")*12 -> 12 | I99: =I98 -> CAD | J99: =IF($I99="CAD",1,IF($I99="USD",VLOOKUP($E99,$F$9:$G$11,2,FALSE),"N/A")) -> 1 | L99: =L98 -> CEO | M99: =M98 -> CEO | N99: =N98 -> Michael Steinmann | O99: 1425175 | P99: =IFERROR(O99*(12/$H99)*$J99,"-") -> 1425175 | Q99: - | R99: =IFERROR(IF((Q99*$J99)=0,"-",(Q99*$J99)),"-") -> - | S99: 1914000 | T99: =IFERROR(S99*(12/$H99)*$J99,"-") -> 1914000 | U99: =IFERROR($T99/$P99,"-") -> 1.342993 | W99: - | X99: =IFERROR(IF(ISNUMBER($W99)=TRUE, $W99*$P99,$V99*$P99),"-") -> 0 | Y99: =IFERROR(IF(SUM(P99,T99)=0,"-",SUM(P99,T99)),"-") -> 3339175 | Z99: =IFERROR(IF(SUM(P99,X99)=0,"-",SUM(P99,X99)),"-") -> 1425175 | AA99: =(5483200-1350000)*0.11 -> 454652 | AB99: =(5483200-1350000)*0.56 -> 2314592 | AC99: - | AD99: =(5483200-1350000)*0.33 -> 1363956 | AE99: - | AF99: =IFERROR(IF(SUM(AA99:AE99)=0,IF(COUNTIF($AA99:$AE99,"=0")>0,"$0","-"),SUM(AA99:AE99)),"-") -> 4133200 | AG99: =IFERROR($AK99/$P99,"-") -> 2.9001351 | AI99: - | AJ99: =IFERROR(IF(ISNUMBER($AI99)=TRUE, $AI99*$P99, $AH99*$P99), "-") -> 0 | AK99: =IFERROR($AF99*$J99,"-") -> 4133200 | AL99: =IFERROR(IF(SUM(Y99,AK99)=0,"-",SUM(Y99,AK99)),"-") -> 7472375 | AM99: =IFERROR(IF(SUM($Z99,$AJ99)=0,"-",SUM($Z99,$AJ99)),"-") -> 1425175 | AN99: 607815 | AO99: DC | AP99: =IFERROR(AN99*(12/$H99)*$J99,"-") -> 607815 | AR99: - | AS99: =IFERROR(AR99*(12/$H99)*$J99,"-") -> - | AU99: =IFERROR(IF(SUM(AL99,AP99,AS99)=0,"-",SUM(AL99,AP99,AS99)),"-") -> 8080190 | AV99: =IFERROR(IF(SUM(AM99,AP99,AS99)=0,"-",SUM(AM99,AP99,AS99)),"-") -> 2032990 | AW99: - | AX99: AH | AY99: sc
A100: =$C100&"_"&$E100&"_"&$K100 -> TSX:PAAS_2022_ | B100: =$C100&"_"&$E100&"_"&$L100 -> TSX:PAAS_2022_CEO | C100: =C99 -> TSX:PAAS | D100: =_xll.ciqfunctions.udf.CIQ(C100,"IQ_Company_Name") -> Pan American Silver Corp. | E100: =$F$11 -> 2022 | F100: =E100&"-01-01" -> 2022-01-01 | G100: =E100&"-12-31" -> 2022-12-31 | H100: =_xlfn.DAYS(G100,F100)/_xlfn.DAYS(E100&"-12-31",E100&"-01-01")*12 -> 12 | I100: =I99 -> CAD | J100: =IF($I100="CAD",1,IF($I100="USD",VLOOKUP($E100,$F$9:$G$11,2,FALSE),"N/A")) -> 1 | L100: =L99 -> CEO | M100: =M99 -> CEO | N100: =N99 -> Michael Steinmann | O100: 1286300 | P100: =IFERROR(O100*(12/$H100)*$J100,"-") -> 1286300 | Q100: - | R100: =IFERROR(IF((Q100*$J100)=0,"-",(Q100*$J100)),"-") -> - | S100: 1004920 | T100: =IFERROR(S100*(12/$H100)*$J100,"-") -> 1004920 | U100: =IFERROR($T100/$P100,"-") -> 0.78124854 | W100: - | X100: =IFERROR(IF(ISNUMBER($W100)=TRUE, $W100*$P100,$V100*$P100),"-") -> 0 | Y100: =IFERROR(IF(SUM(P100,T100)=0,"-",SUM(P100,T100)),"-") -> 2291220 | Z100: =IFERROR(IF(SUM(P100,X100)=0,"-",SUM(P100,X100)),"-") -> 1286300 | AA100: 964725 | AB100: 1286300 | AC100: - | AD100: 321575 | AE100: - | AF100: =IFERROR(IF(SUM(AA100:AE100)=0,IF(COUNTIF($AA100:$AE100,"=0")>0,"$0","-"),SUM(AA100:AE100)),"-") -> 2572600 | AG100: =IFERROR($AK100/$P100,"-") -> 2 | AI100: - | AJ100: =IFERROR(IF(ISNUMBER($AI100)=TRUE, $AI100*$P100, $AH100*$P100), "-") -> 0 | AK100: =IFERROR($AF100*$J100,"-") -> 2572600 | AL100: =IFERROR(IF(SUM(Y100,AK100)=0,"-",SUM(Y100,AK100)),"-") -> 4863820 | AM100: =IFERROR(IF(SUM($Z100,$AJ100)=0,"-",SUM($Z100,$AJ100)),"-") -> 1286300 | AN100: 578835 | AO100: DC | AP100: =IFERROR(AN100*(12/$H100)*$J100,"-") -> 578835 | AR100: - | AS100: =IFERROR(AR100*(12/$H100)*$J100,"-") -> - | AU100: =IFERROR(IF(SUM(AL100,AP100,AS100)=0,"-",SUM(AL100,AP100,AS100)),"-") -> 5442655 | AV100: =IFERROR(IF(SUM(AM100,AP100,AS100)=0,"-",SUM(AM100,AP100,AS100)),"-") -> 1865135 | AW100: - | AX100: AH | AY100: sc
A101: =$C101&"_"&$E101&"_"&$K101 -> TSX:PAAS_2024_COO | B101: =$C101&"_"&$E101&"_"&$L101 -> TSX:PAAS_2024_NEO1 | C101: =C100 -> TSX:PAAS | D101: =_xll.ciqfunctions.udf.CIQ(C101,"IQ_Company_Name") -> Pan American Silver Corp. | E101: =E98 -> 2024 | F101: =E101&"-01-01" -> 2024-01-01 | G101: =E101&"-12-31" -> 2024-12-31 | H101: =_xlfn.DAYS(G101,F101)/_xlfn.DAYS(E101&"-12-31",E101&"-01-01")*12 -> 12 | I101: =I100 -> CAD | J101: =IF($I101="CAD",1,IF($I101="USD",VLOOKUP($E101,$F$9:$G$11,2,FALSE),"N/A")) -> 1 | K101: COO | L101: NEO1 | M101: COO | N101: Steven Busby | O101: 780000 | P101: =IFERROR(O101*(12/$H101)*$J101,"-") -> 780000 | Q101: - | R101: =IFERROR(IF((Q101*$J101)=0,"-",(Q101*$J101)),"-") -> - | S101: 639000 | T101: =IFERROR(S101*(12/$H101)*$J101,"-") -> 639000 | U101: =IFERROR($T101/$P101,"-") -> 0.81923077 | V101: =IFERROR(AVERAGE(U101:U103),"N/A") -> 0.72375771 | W101: 0.8 | X101: =IFERROR(IF(ISNUMBER($W101)=TRUE, $W101*$P101,$V101*$P101),"-") -> 624000 | Y101: =IFERROR(IF(SUM(P101,T101)=0,"-",SUM(P101,T101)),"-") -> 1419000 | Z101: =IFERROR(IF(SUM(P101,X101)=0,"-",SUM(P101,X101)),"-") -> 1404000 | AA101: 936000 | AB101: 780000 | AC101: - | AD101: - | AE101: - | AF101: =IFERROR(IF(SUM(AA101:AE101)=0,IF(COUNTIF($AA101:$AE101,"=0")>0,"$0","-"),SUM(AA101:AE101)),"-") -> 1716000 | AG101: =IFERROR($AK101/$P101,"-") -> 2.2 | AH101: =IFERROR(AVERAGE(AG101:AG103),"N/A") -> 1.9396201 | AI101: 2.2 | AJ101: =IFERROR(IF(ISNUMBER($AI101)=TRUE, $AI101*$P101, $AH101*$P101), "-") -> 1716000 | AK101: =IFERROR($AF101*$J101,"-") -> 1716000 | AL101: =IFERROR(IF(SUM(Y101,AK101)=0,"-",SUM(Y101,AK101)),"-") -> 3135000 | AM101: =IFERROR(IF(SUM($Z101,$AJ101)=0,"-",SUM($Z101,$AJ101)),"-") -> 3120000 | AN101: 351000 | AO101: DC | AP101: =IFERROR(AN101*(12/$H101)*$J101,"-") -> 351000 | AQ101: =IFERROR(AVERAGE(AP101:AP103),"N/A") -> 329175 | AR101: - | AS101: =IFERROR(AR101*(12/$H101)*$J101,"-") -> - | AT101: =IFERROR(AVERAGE(AS101:AS103),"N/A") -> N/A | AU101: =IFERROR(IF(SUM(AL101,AP101,AS101)=0,"-",SUM(AL101,AP101,AS101)),"-") -> 3486000 | AV101: =IFERROR(IF(SUM(AM101,AP101,AS101)=0,"-",SUM(AM101,AP101,AS101)),"-") -> 3471000 | AW101: - | AX101: AH | AY101: sc
A102: =$C102&"_"&$E102&"_"&$K102 -> TSX:PAAS_2023_COO | B102: =$C102&"_"&$E102&"_"&$L102 -> TSX:PAAS_2023_NEO1 | C102: =C101 -> TSX:PAAS | D102: =_xll.ciqfunctions.udf.CIQ(C102,"IQ_Company_Name") -> Pan American Silver Corp. | E102: =E99 -> 2023 | F102: =E102&"-01-01" -> 2023-01-01 | G102: =E102&"-12-31" -> 2023-12-31 | H102: =_xlfn.DAYS(G102,F102)/_xlfn.DAYS(E102&"-12-31",E102&"-01-01")*12 -> 12 | I102: =I101 -> CAD | J102: =IF($I102="CAD",1,IF($I102="USD",VLOOKUP($E102,$F$9:$G$11,2,FALSE),"N/A")) -> 1 | K102: COO | L102: =L101 -> NEO1 | M102: =M101 -> COO | N102: =N101 -> Steven Busby | O102: 743625 | P102: =IFERROR(O102*(12/$H102)*$J102,"-") -> 743625 | Q102: - | R102: =IFERROR(IF((Q102*$J102)=0,"-",(Q102*$J102)),"-") -> - | S102: 633600 | T102: =IFERROR(S102*(12/$H102)*$J102,"-") -> 633600 | U102: =IFERROR($T102/$P102,"-") -> 0.85204236 | W102: - | X102: =IFERROR(IF(ISNUMBER($W102)=TRUE, $W102*$P102,$V102*$P102),"-") -> 0 | Y102: =IFERROR(IF(SUM(P102,T102)=0,"-",SUM(P102,T102)),"-") -> 1377225 | Z102: =IFERROR(IF(SUM(P102,X102)=0,"-",SUM(P102,X102)),"-") -> 743625 | AA102: =(2374500-724500)*0.14 -> 231000 | AB102: =(2374500-724500)*0.45 -> 742500 | AC102: - | AD102: =(2374500-724500)*0.41 -> 676500 | AE102: - | AF102: =IFERROR(IF(SUM(AA102:AE102)=0,IF(COUNTIF($AA102:$AE102,"=0")>0,"$0","-"),SUM(AA102:AE102)),"-") -> 1650000 | AG102: =IFERROR($AK102/$P102,"-") -> 2.2188603 | AI102: - | AJ102: =IFERROR(IF(ISNUMBER($AI102)=TRUE, $AI102*$P102, $AH102*$P102), "-") -> 0 | AK102: =IFERROR($AF102*$J102,"-") -> 1650000 | AL102: =IFERROR(IF(SUM(Y102,AK102)=0,"-",SUM(Y102,AK102)),"-") -> 3027225 | AM102: =IFERROR(IF(SUM($Z102,$AJ102)=0,"-",SUM($Z102,$AJ102)),"-") -> 743625 | AN102: 326025 | AO102: DC | AP102: =IFERROR(AN102*(12/$H102)*$J102,"-") -> 326025 | AR102: - | AS102: =IFERROR(AR102*(12/$H102)*$J102,"-") -> - | AU102: =IFERROR(IF(SUM(AL102,AP102,AS102)=0,"-",SUM(AL102,AP102,AS102)),"-") -> 3353250 | AV102: =IFERROR(IF(SUM(AM102,AP102,AS102)=0,"-",SUM(AM102,AP102,AS102)),"-") -> 1069650 | AW102: - | AX102: AH | AY102: sc
...

Sheet Master - Summary
A1: =TODAY() -> 45975
A2: CAD | B2: Position
B3: Year | C3: 2018
C4: Company | D4: Market Cap | E4: TEV | F4: Incumbent | G4: Position Title | H4: Annualized / Converted | I4: Annualized/ Converted | J4: Actual STI % | K4: 3 Year Average STIP % | L4: Target STI $ | M4: Target STI % | N4: Actual TCC | O4: Target TCC | P4: Total LTI (Converted) | Q4: Total LTI % | R4: 3 Year Average LTIP % | S4: Target LTI $ | T4: Target LTI % | U4: Actual (base + actual bonus + actual LTIP) | V4: Target (base + target bonus + Target LTIP) | X4: Cash | Y4: Equity
C5: =+C2& " Benchmarking - "&'Raw Data'!G5&" $000s" -> Benchmarking - CAD $000s
C6: Company | D6: Market Cap | E6: TEV | F6: Incumbent | G6: Title | H6: Base Salary | I6: STIP | L6: STIP | N6: Total Cash Compensation | P6: LTIP | S6: LTIP | U6: Total Direct Compensation | X6: Pay Mix
A7: Look-up | B7: Ticker | D7: Market Cap | E7: TEV | F7: Incumbent | G7: Title | H7: Base Salary | I7: Actual $ | J7: Actual % | K7: 3 Year Average STIP % | L7: Target $ | M7: Target % | N7: Actual $ | O7: Target $ | P7: Actual $ | Q7: Actual% | R7: 3 Year Average LTIP % | S7: Target $ | T7: Target % | U7: Actual $ | V7: Target $ | X7: Cash | Y7: Equity
A8: =$B8&"_"&$C$3&"_"&$C$2 -> TSX:T_2018_ | B8: TSX:T | C8: =IFERROR(INDEX(Raw_Data,MATCH($A8,Look_Up,0),MATCH(C$4,Component,0)),"-") -> - | D8: =_xll.ciqfunctions.udf.CIQ(B8, "IQ_MARKETCAP", $A$1,$A$2) -> 31919.76 | E8: =_xll.ciqfunctions.udf.CIQ($B8, "IQ_TEV", $A$1,$A$2) -> 61771.76 | F8: =IFERROR(INDEX(Raw_Data,MATCH($A8,Look_Up,0),MATCH(F$4,Component,0)),"-") -> - | G8: =IFERROR(INDEX(Raw_Data,MATCH($A8,Look_Up,0),MATCH(G$4,Component,0)),"-") -> - | H8: =IFERROR(INDEX(Raw_Data,MATCH($A8,Look_Up,0),MATCH(H$4,Component,0))/1000,"-") -> - | I8: =IFERROR(INDEX(Raw_Data,MATCH($A8,Look_Up,0),MATCH(I$4,Component,0))/1000,"-") -> - | J8: =IFERROR(INDEX(Raw_Data,MATCH($A8,Look_Up,0),MATCH(J$4,Component,0)),"-") -> - | K8: =IFERROR(INDEX(Raw_Data,MATCH($A8,Look_Up,0),MATCH(K$4,Component,0)),"-") -> - | L8: =IFERROR(INDEX(Raw_Data,MATCH($A8,Look_Up,0),MATCH(L$4,Component,0))/1000,"-") -> - | M8: =IFERROR(INDEX(Raw_Data,MATCH($A8,Look_Up,0),MATCH(M$4,Component,0)),"-") -> - | N8: =IFERROR(INDEX(Raw_Data,MATCH($A8,Look_Up,0),MATCH(N$4,Component,0))/1000,"-") -> - | O8: =IFERROR(INDEX(Raw_Data,MATCH($A8,Look_Up,0),MATCH(O$4,Component,0))/1000,"-") -> - | P8: =IFERROR(INDEX(Raw_Data,MATCH($A8,Look_Up,0),MATCH(P$4,Component,0))/1000,"-") -> - | Q8: =IFERROR(INDEX(Raw_Data,MATCH($A8,Look_Up,0),MATCH(Q$4,Component,0)),"-") -> - | R8: =IFERROR(INDEX(Raw_Data,MATCH($A8,Look_Up,0),MATCH(R$4,Component,0)),"-") -> - | S8: =IFERROR(INDEX(Raw_Data,MATCH($A8,Look_Up,0),MATCH(S$4,Component,0))/1000,"-") -> - | T8: =IFERROR(INDEX(Raw_Data,MATCH($A8,Look_Up,0),MATCH(T$4,Component,0)),"-") -> - | U8: =IFERROR(INDEX(Raw_Data,MATCH($A8,Look_Up,0),MATCH(U$4,Component,0))/1000,"-") -> - | V8: =IFERROR(INDEX(Raw_Data,MATCH($A8,Look_Up,0),MATCH(V$4,Component,0))/1000,"-") -> - | X8: =IFERROR(N8/U8,"-") -> - | Y8: =IFERROR(P8/U8,"-") -> -
A9: =$B9&"_"&$C$3&"_"&$C$2 -> TSX:S_2018_ | B9: TSX:S | C9: =IFERROR(INDEX(Raw_Data,MATCH($A9,Look_Up,0),MATCH(C$4,Component,0)),"-") -> - | D9: =_xll.ciqfunctions.udf.CIQ(B9, "IQ_MARKETCAP", $A$1,$A$2) -> 62.03609 | E9: =_xll.ciqfunctions.udf.CIQ($B9, "IQ_TEV", $A$1,$A$2) -> 267.43609 | F9: =IFERROR(INDEX(Raw_Data,MATCH($A9,Look_Up,0),MATCH(F$4,Component,0)),"-") -> - | G9: =IFERROR(INDEX(Raw_Data,MATCH($A9,Look_Up,0),MATCH(G$4,Component,0)),"-") -> - | H9: =IFERROR(INDEX(Raw_Data,MATCH($A9,Look_Up,0),MATCH(H$4,Component,0))/1000,"-") -> - | I9: =IFERROR(INDEX(Raw_Data,MATCH($A9,Look_Up,0),MATCH(I$4,Component,0))/1000,"-") -> - | J9: =IFERROR(INDEX(Raw_Data,MATCH($A9,Look_Up,0),MATCH(J$4,Component,0)),"-") -> - | K9: =IFERROR(INDEX(Raw_Data,MATCH($A9,Look_Up,0),MATCH(K$4,Component,0)),"-") -> - | L9: =IFERROR(INDEX(Raw_Data,MATCH($A9,Look_Up,0),MATCH(L$4,Component,0))/1000,"-") -> - | M9: =IFERROR(INDEX(Raw_Data,MATCH($A9,Look_Up,0),MATCH(M$4,Component,0)),"-") -> - | N9: =IFERROR(INDEX(Raw_Data,MATCH($A9,Look_Up,0),MATCH(N$4,Component,0))/1000,"-") -> - | O9: =IFERROR(INDEX(Raw_Data,MATCH($A9,Look_Up,0),MATCH(O$4,Component,0))/1000,"-") -> - | P9: =IFERROR(INDEX(Raw_Data,MATCH($A9,Look_Up,0),MATCH(P$4,Component,0))/1000,"-") -> - | Q9: =IFERROR(INDEX(Raw_Data,MATCH($A9,Look_Up,0),MATCH(Q$4,Component,0)),"-") -> - | R9: =IFERROR(INDEX(Raw_Data,MATCH($A9,Look_Up,0),MATCH(R$4,Component,0)),"-") -> - | S9: =IFERROR(INDEX(Raw_Data,MATCH($A9,Look_Up,0),MATCH(S$4,Component,0))/1000,"-") -> - | T9: =IFERROR(INDEX(Raw_Data,MATCH($A9,Look_Up,0),MATCH(T$4,Component,0)),"-") -> - | U9: =IFERROR(INDEX(Raw_Data,MATCH($A9,Look_Up,0),MATCH(U$4,Component,0))/1000,"-") -> - | V9: =IFERROR(INDEX(Raw_Data,MATCH($A9,Look_Up,0),MATCH(V$4,Component,0))/1000,"-") -> - | X9: =IFERROR(N9/U9,"-") -> - | Y9: =IFERROR(P9/U9,"-") -> -
A10: =$B10&"_"&$C$3&"_"&$C$2 -> TSX:R_2018_ | B10: TSX:R | C10: =IFERROR(INDEX(Raw_Data,MATCH($A10,Look_Up,0),MATCH(C$4,Component,0)),"-") -> - | D10: =_xll.ciqfunctions.udf.CIQ(B10, "IQ_MARKETCAP", $A$1,$A$2) -> (Invalid Identifier) | E10: =_xll.ciqfunctions.udf.CIQ($B10, "IQ_TEV", $A$1,$A$2) -> (Invalid Identifier) | F10: =IFERROR(INDEX(Raw_Data,MATCH($A10,Look_Up,0),MATCH(F$4,Component,0)),"-") -> - | G10: =IFERROR(INDEX(Raw_Data,MATCH($A10,Look_Up,0),MATCH(G$4,Component,0)),"-") -> - | H10: =IFERROR(INDEX(Raw_Data,MATCH($A10,Look_Up,0),MATCH(H$4,Component,0))/1000,"-") -> - | I10: =IFERROR(INDEX(Raw_Data,MATCH($A10,Look_Up,0),MATCH(I$4,Component,0))/1000,"-") -> - | J10: =IFERROR(INDEX(Raw_Data,MATCH($A10,Look_Up,0),MATCH(J$4,Component,0)),"-") -> - | K10: =IFERROR(INDEX(Raw_Data,MATCH($A10,Look_Up,0),MATCH(K$4,Component,0)),"-") -> - | L10: =IFERROR(INDEX(Raw_Data,MATCH($A10,Look_Up,0),MATCH(L$4,Component,0))/1000,"-") -> - | M10: =IFERROR(INDEX(Raw_Data,MATCH($A10,Look_Up,0),MATCH(M$4,Component,0)),"-") -> - | N10: =IFERROR(INDEX(Raw_Data,MATCH($A10,Look_Up,0),MATCH(N$4,Component,0))/1000,"-") -> - | O10: =IFERROR(INDEX(Raw_Data,MATCH($A10,Look_Up,0),MATCH(O$4,Component,0))/1000,"-") -> - | P10: =IFERROR(INDEX(Raw_Data,MATCH($A10,Look_Up,0),MATCH(P$4,Component,0))/1000,"-") -> - | Q10: =IFERROR(INDEX(Raw_Data,MATCH($A10,Look_Up,0),MATCH(Q$4,Component,0)),"-") -> - | R10: =IFERROR(INDEX(Raw_Data,MATCH($A10,Look_Up,0),MATCH(R$4,Component,0)),"-") -> - | S10: =IFERROR(INDEX(Raw_Data,MATCH($A10,Look_Up,0),MATCH(S$4,Component,0))/1000,"-") -> - | T10: =IFERROR(INDEX(Raw_Data,MATCH($A10,Look_Up,0),MATCH(T$4,Component,0)),"-") -> - | U10: =IFERROR(INDEX(Raw_Data,MATCH($A10,Look_Up,0),MATCH(U$4,Component,0))/1000,"-") -> - | V10: =IFERROR(INDEX(Raw_Data,MATCH($A10,Look_Up,0),MATCH(V$4,Component,0))/1000,"-") -> - | X10: =IFERROR(N10/U10,"-") -> - | Y10: =IFERROR(P10/U10,"-") -> -
A11: =$B11&"_"&$C$3&"_"&$C$2 -> TSX:Q_2018_ | B11: TSX:Q | C11: =IFERROR(INDEX(Raw_Data,MATCH($A11,Look_Up,0),MATCH(C$4,Component,0)),"-") -> - | D11: =_xll.ciqfunctions.udf.CIQ(B11, "IQ_MARKETCAP", $A$1,$A$2) -> (Invalid Identifier) | E11: =_xll.ciqfunctions.udf.CIQ($B11, "IQ_TEV", $A$1,$A$2) -> (Invalid Identifier) | F11: =IFERROR(INDEX(Raw_Data,MATCH($A11,Look_Up,0),MATCH(F$4,Component,0)),"-") -> - | G11: =IFERROR(INDEX(Raw_Data,MATCH($A11,Look_Up,0),MATCH(G$4,Component,0)),"-") -> - | H11: =IFERROR(INDEX(Raw_Data,MATCH($A11,Look_Up,0),MATCH(H$4,Component,0))/1000,"-") -> - | I11: =IFERROR(INDEX(Raw_Data,MATCH($A11,Look_Up,0),MATCH(I$4,Component,0))/1000,"-") -> - | J11: =IFERROR(INDEX(Raw_Data,MATCH($A11,Look_Up,0),MATCH(J$4,Component,0)),"-") -> - | K11: =IFERROR(INDEX(Raw_Data,MATCH($A11,Look_Up,0),MATCH(K$4,Component,0)),"-") -> - | L11: =IFERROR(INDEX(Raw_Data,MATCH($A11,Look_Up,0),MATCH(L$4,Component,0))/1000,"-") -> - | M11: =IFERROR(INDEX(Raw_Data,MATCH($A11,Look_Up,0),MATCH(M$4,Component,0)),"-") -> - | N11: =IFERROR(INDEX(Raw_Data,MATCH($A11,Look_Up,0),MATCH(N$4,Component,0))/1000,"-") -> - | O11: =IFERROR(INDEX(Raw_Data,MATCH($A11,Look_Up,0),MATCH(O$4,Component,0))/1000,"-") -> - | P11: =IFERROR(INDEX(Raw_Data,MATCH($A11,Look_Up,0),MATCH(P$4,Component,0))/1000,"-") -> - | Q11: =IFERROR(INDEX(Raw_Data,MATCH($A11,Look_Up,0),MATCH(Q$4,Component,0)),"-") -> - | R11: =IFERROR(INDEX(Raw_Data,MATCH($A11,Look_Up,0),MATCH(R$4,Component,0)),"-") -> - | S11: =IFERROR(INDEX(Raw_Data,MATCH($A11,Look_Up,0),MATCH(S$4,Component,0))/1000,"-") -> - | T11: =IFERROR(INDEX(Raw_Data,MATCH($A11,Look_Up,0),MATCH(T$4,Component,0)),"-") -> - | U11: =IFERROR(INDEX(Raw_Data,MATCH($A11,Look_Up,0),MATCH(U$4,Component,0))/1000,"-") -> - | V11: =IFERROR(INDEX(Raw_Data,MATCH($A11,Look_Up,0),MATCH(V$4,Component,0))/1000,"-") -> - | X11: =IFERROR(N11/U11,"-") -> - | Y11: =IFERROR(P11/U11,"-") -> -
A12: =$B12&"_"&$C$3&"_"&$C$2 -> TSX:P_2018_ | B12: TSX:P | C12: =IFERROR(INDEX(Raw_Data,MATCH($A12,Look_Up,0),MATCH(C$4,Component,0)),"-") -> - | D12: =_xll.ciqfunctions.udf.CIQ(B12, "IQ_MARKETCAP", $A$1,$A$2) -> (Invalid Identifier) | E12: =_xll.ciqfunctions.udf.CIQ($B12, "IQ_TEV", $A$1,$A$2) -> (Invalid Identifier) | F12: =IFERROR(INDEX(Raw_Data,MATCH($A12,Look_Up,0),MATCH(F$4,Component,0)),"-") -> - | G12: =IFERROR(INDEX(Raw_Data,MATCH($A12,Look_Up,0),MATCH(G$4,Component,0)),"-") -> - | H12: =IFERROR(INDEX(Raw_Data,MATCH($A12,Look_Up,0),MATCH(H$4,Component,0))/1000,"-") -> - | I12: =IFERROR(INDEX(Raw_Data,MATCH($A12,Look_Up,0),MATCH(I$4,Component,0))/1000,"-") -> - | J12: =IFERROR(INDEX(Raw_Data,MATCH($A12,Look_Up,0),MATCH(J$4,Component,0)),"-") -> - | K12: =IFERROR(INDEX(Raw_Data,MATCH($A12,Look_Up,0),MATCH(K$4,Component,0)),"-") -> - | L12: =IFERROR(INDEX(Raw_Data,MATCH($A12,Look_Up,0),MATCH(L$4,Component,0))/1000,"-") -> - | M12: =IFERROR(INDEX(Raw_Data,MATCH($A12,Look_Up,0),MATCH(M$4,Component,0)),"-") -> - | N12: =IFERROR(INDEX(Raw_Data,MATCH($A12,Look_Up,0),MATCH(N$4,Component,0))/1000,"-") -> - | O12: =IFERROR(INDEX(Raw_Data,MATCH($A12,Look_Up,0),MATCH(O$4,Component,0))/1000,"-") -> - | P12: =IFERROR(INDEX(Raw_Data,MATCH($A12,Look_Up,0),MATCH(P$4,Component,0))/1000,"-") -> - | Q12: =IFERROR(INDEX(Raw_Data,MATCH($A12,Look_Up,0),MATCH(Q$4,Component,0)),"-") -> - | R12: =IFERROR(INDEX(Raw_Data,MATCH($A12,Look_Up,0),MATCH(R$4,Component,0)),"-") -> - | S12: =IFERROR(INDEX(Raw_Data,MATCH($A12,Look_Up,0),MATCH(S$4,Component,0))/1000,"-") -> - | T12: =IFERROR(INDEX(Raw_Data,MATCH($A12,Look_Up,0),MATCH(T$4,Component,0)),"-") -> - | U12: =IFERROR(INDEX(Raw_Data,MATCH($A12,Look_Up,0),MATCH(U$4,Component,0))/1000,"-") -> - | V12: =IFERROR(INDEX(Raw_Data,MATCH($A12,Look_Up,0),MATCH(V$4,Component,0))/1000,"-") -> - | X12: =IFERROR(N12/U12,"-") -> - | Y12: =IFERROR(P12/U12,"-") -> -
A13: =$B13&"_"&$C$3&"_"&$C$2 -> TSX:O_2018_ | B13: TSX:O | C13: =IFERROR(INDEX(Raw_Data,MATCH($A13,Look_Up,0),MATCH(C$4,Component,0)),"-") -> - | D13: =_xll.ciqfunctions.udf.CIQ(B13, "IQ_MARKETCAP", $A$1,$A$2) -> (Invalid Identifier) | E13: =_xll.ciqfunctions.udf.CIQ($B13, "IQ_TEV", $A$1,$A$2) -> (Invalid Identifier) | F13: =IFERROR(INDEX(Raw_Data,MATCH($A13,Look_Up,0),MATCH(F$4,Component,0)),"-") -> - | G13: =IFERROR(INDEX(Raw_Data,MATCH($A13,Look_Up,0),MATCH(G$4,Component,0)),"-") -> - | H13: =IFERROR(INDEX(Raw_Data,MATCH($A13,Look_Up,0),MATCH(H$4,Component,0))/1000,"-") -> - | I13: =IFERROR(INDEX(Raw_Data,MATCH($A13,Look_Up,0),MATCH(I$4,Component,0))/1000,"-") -> - | J13: =IFERROR(INDEX(Raw_Data,MATCH($A13,Look_Up,0),MATCH(J$4,Component,0)),"-") -> - | K13: =IFERROR(INDEX(Raw_Data,MATCH($A13,Look_Up,0),MATCH(K$4,Component,0)),"-") -> - | L13: =IFERROR(INDEX(Raw_Data,MATCH($A13,Look_Up,0),MATCH(L$4,Component,0))/1000,"-") -> - | M13: =IFERROR(INDEX(Raw_Data,MATCH($A13,Look_Up,0),MATCH(M$4,Component,0)),"-") -> - | N13: =IFERROR(INDEX(Raw_Data,MATCH($A13,Look_Up,0),MATCH(N$4,Component,0))/1000,"-") -> - | O13: =IFERROR(INDEX(Raw_Data,MATCH($A13,Look_Up,0),MATCH(O$4,Component,0))/1000,"-") -> - | P13: =IFERROR(INDEX(Raw_Data,MATCH($A13,Look_Up,0),MATCH(P$4,Component,0))/1000,"-") -> - | Q13: =IFERROR(INDEX(Raw_Data,MATCH($A13,Look_Up,0),MATCH(Q$4,Component,0)),"-") -> - | R13: =IFERROR(INDEX(Raw_Data,MATCH($A13,Look_Up,0),MATCH(R$4,Component,0)),"-") -> - | S13: =IFERROR(INDEX(Raw_Data,MATCH($A13,Look_Up,0),MATCH(S$4,Component,0))/1000,"-") -> - | T13: =IFERROR(INDEX(Raw_Data,MATCH($A13,Look_Up,0),MATCH(T$4,Component,0)),"-") -> - | U13: =IFERROR(INDEX(Raw_Data,MATCH($A13,Look_Up,0),MATCH(U$4,Component,0))/1000,"-") -> - | V13: =IFERROR(INDEX(Raw_Data,MATCH($A13,Look_Up,0),MATCH(V$4,Component,0))/1000,"-") -> - | X13: =IFERROR(N13/U13,"-") -> - | Y13: =IFERROR(P13/U13,"-") -> -
A14: =$B14&"_"&$C$3&"_"&$C$2 -> TSX:N_2018_ | B14: TSX:N | C14: =IFERROR(INDEX(Raw_Data,MATCH($A14,Look_Up,0),MATCH(C$4,Component,0)),"-") -> - | D14: =_xll.ciqfunctions.udf.CIQ(B14, "IQ_MARKETCAP", $A$1,$A$2) -> (Invalid Identifier) | E14: =_xll.ciqfunctions.udf.CIQ($B14, "IQ_TEV", $A$1,$A$2) -> (Invalid Identifier) | F14: =IFERROR(INDEX(Raw_Data,MATCH($A14,Look_Up,0),MATCH(F$4,Component,0)),"-") -> - | G14: =IFERROR(INDEX(Raw_Data,MATCH($A14,Look_Up,0),MATCH(G$4,Component,0)),"-") -> - | H14: =IFERROR(INDEX(Raw_Data,MATCH($A14,Look_Up,0),MATCH(H$4,Component,0))/1000,"-") -> - | I14: =IFERROR(INDEX(Raw_Data,MATCH($A14,Look_Up,0),MATCH(I$4,Component,0))/1000,"-") -> - | J14: =IFERROR(INDEX(Raw_Data,MATCH($A14,Look_Up,0),MATCH(J$4,Component,0)),"-") -> - | K14: =IFERROR(INDEX(Raw_Data,MATCH($A14,Look_Up,0),MATCH(K$4,Component,0)),"-") -> - | L14: =IFERROR(INDEX(Raw_Data,MATCH($A14,Look_Up,0),MATCH(L$4,Component,0))/1000,"-") -> - | M14: =IFERROR(INDEX(Raw_Data,MATCH($A14,Look_Up,0),MATCH(M$4,Component,0)),"-") -> - | N14: =IFERROR(INDEX(Raw_Data,MATCH($A14,Look_Up,0),MATCH(N$4,Component,0))/1000,"-") -> - | O14: =IFERROR(INDEX(Raw_Data,MATCH($A14,Look_Up,0),MATCH(O$4,Component,0))/1000,"-") -> - | P14: =IFERROR(INDEX(Raw_Data,MATCH($A14,Look_Up,0),MATCH(P$4,Component,0))/1000,"-") -> - | Q14: =IFERROR(INDEX(Raw_Data,MATCH($A14,Look_Up,0),MATCH(Q$4,Component,0)),"-") -> - | R14: =IFERROR(INDEX(Raw_Data,MATCH($A14,Look_Up,0),MATCH(R$4,Component,0)),"-") -> - | S14: =IFERROR(INDEX(Raw_Data,MATCH($A14,Look_Up,0),MATCH(S$4,Component,0))/1000,"-") -> - | T14: =IFERROR(INDEX(Raw_Data,MATCH($A14,Look_Up,0),MATCH(T$4,Component,0)),"-") -> - | U14: =IFERROR(INDEX(Raw_Data,MATCH($A14,Look_Up,0),MATCH(U$4,Component,0))/1000,"-") -> - | V14: =IFERROR(INDEX(Raw_Data,MATCH($A14,Look_Up,0),MATCH(V$4,Component,0))/1000,"-") -> - | X14: =IFERROR(N14/U14,"-") -> - | Y14: =IFERROR(P14/U14,"-") -> -
A15: =$B15&"_"&$C$3&"_"&$C$2 -> TSX:M_2018_ | B15: TSX:M | C15: =IFERROR(INDEX(Raw_Data,MATCH($A15,Look_Up,0),MATCH(C$4,Component,0)),"-") -> - | D15: =_xll.ciqfunctions.udf.CIQ(B15, "IQ_MARKETCAP", $A$1,$A$2) -> (Invalid Identifier) | E15: =_xll.ciqfunctions.udf.CIQ($B15, "IQ_TEV", $A$1,$A$2) -> (Invalid Identifier) | F15: =IFERROR(INDEX(Raw_Data,MATCH($A15,Look_Up,0),MATCH(F$4,Component,0)),"-") -> - | G15: =IFERROR(INDEX(Raw_Data,MATCH($A15,Look_Up,0),MATCH(G$4,Component,0)),"-") -> - | H15: =IFERROR(INDEX(Raw_Data,MATCH($A15,Look_Up,0),MATCH(H$4,Component,0))/1000,"-") -> - | I15: =IFERROR(INDEX(Raw_Data,MATCH($A15,Look_Up,0),MATCH(I$4,Component,0))/1000,"-") -> - | J15: =IFERROR(INDEX(Raw_Data,MATCH($A15,Look_Up,0),MATCH(J$4,Component,0)),"-") -> - | K15: =IFERROR(INDEX(Raw_Data,MATCH($A15,Look_Up,0),MATCH(K$4,Component,0)),"-") -> - | L15: =IFERROR(INDEX(Raw_Data,MATCH($A15,Look_Up,0),MATCH(L$4,Component,0))/1000,"-") -> - | M15: =IFERROR(INDEX(Raw_Data,MATCH($A15,Look_Up,0),MATCH(M$4,Component,0)),"-") -> - | N15: =IFERROR(INDEX(Raw_Data,MATCH($A15,Look_Up,0),MATCH(N$4,Component,0))/1000,"-") -> - | O15: =IFERROR(INDEX(Raw_Data,MATCH($A15,Look_Up,0),MATCH(O$4,Component,0))/1000,"-") -> - | P15: =IFERROR(INDEX(Raw_Data,MATCH($A15,Look_Up,0),MATCH(P$4,Component,0))/1000,"-") -> - | Q15: =IFERROR(INDEX(Raw_Data,MATCH($A15,Look_Up,0),MATCH(Q$4,Component,0)),"-") -> - | R15: =IFERROR(INDEX(Raw_Data,MATCH($A15,Look_Up,0),MATCH(R$4,Component,0)),"-") -> - | S15: =IFERROR(INDEX(Raw_Data,MATCH($A15,Look_Up,0),MATCH(S$4,Component,0))/1000,"-") -> - | T15: =IFERROR(INDEX(Raw_Data,MATCH($A15,Look_Up,0),MATCH(T$4,Component,0)),"-") -> - | U15: =IFERROR(INDEX(Raw_Data,MATCH($A15,Look_Up,0),MATCH(U$4,Component,0))/1000,"-") -> - | V15: =IFERROR(INDEX(Raw_Data,MATCH($A15,Look_Up,0),MATCH(V$4,Component,0))/1000,"-") -> - | X15: =IFERROR(N15/U15,"-") -> - | Y15: =IFERROR(P15/U15,"-") -> -
A16: =$B16&"_"&$C$3&"_"&$C$2 -> TSX:L_2018_ | B16: TSX:L | C16: =IFERROR(INDEX(Raw_Data,MATCH($A16,Look_Up,0),MATCH(C$4,Component,0)),"-") -> - | D16: =_xll.ciqfunctions.udf.CIQ(B16, "IQ_MARKETCAP", $A$1,$A$2) -> 69884.25 | E16: =_xll.ciqfunctions.udf.CIQ($B16, "IQ_TEV", $A$1,$A$2) -> 87934.25 | F16: =IFERROR(INDEX(Raw_Data,MATCH($A16,Look_Up,0),MATCH(F$4,Component,0)),"-") -> - | G16: =IFERROR(INDEX(Raw_Data,MATCH($A16,Look_Up,0),MATCH(G$4,Component,0)),"-") -> - | H16: =IFERROR(INDEX(Raw_Data,MATCH($A16,Look_Up,0),MATCH(H$4,Component,0))/1000,"-") -> - | I16: =IFERROR(INDEX(Raw_Data,MATCH($A16,Look_Up,0),MATCH(I$4,Component,0))/1000,"-") -> - | J16: =IFERROR(INDEX(Raw_Data,MATCH($A16,Look_Up,0),MATCH(J$4,Component,0)),"-") -> - | K16: =IFERROR(INDEX(Raw_Data,MATCH($A16,Look_Up,0),MATCH(K$4,Component,0)),"-") -> - | L16: =IFERROR(INDEX(Raw_Data,MATCH($A16,Look_Up,0),MATCH(L$4,Component,0))/1000,"-") -> - | M16: =IFERROR(INDEX(Raw_Data,MATCH($A16,Look_Up,0),MATCH(M$4,Component,0)),"-") -> - | N16: =IFERROR(INDEX(Raw_Data,MATCH($A16,Look_Up,0),MATCH(N$4,Component,0))/1000,"-") -> - | O16: =IFERROR(INDEX(Raw_Data,MATCH($A16,Look_Up,0),MATCH(O$4,Component,0))/1000,"-") -> - | P16: =IFERROR(INDEX(Raw_Data,MATCH($A16,Look_Up,0),MATCH(P$4,Component,0))/1000,"-") -> - | Q16: =IFERROR(INDEX(Raw_Data,MATCH($A16,Look_Up,0),MATCH(Q$4,Component,0)),"-") -> - | R16: =IFERROR(INDEX(Raw_Data,MATCH($A16,Look_Up,0),MATCH(R$4,Component,0)),"-") -> - | S16: =IFERROR(INDEX(Raw_Data,MATCH($A16,Look_Up,0),MATCH(S$4,Component,0))/1000,"-") -> - | T16: =IFERROR(INDEX(Raw_Data,MATCH($A16,Look_Up,0),MATCH(T$4,Component,0)),"-") -> - | U16: =IFERROR(INDEX(Raw_Data,MATCH($A16,Look_Up,0),MATCH(U$4,Component,0))/1000,"-") -> - | V16: =IFERROR(INDEX(Raw_Data,MATCH($A16,Look_Up,0),MATCH(V$4,Component,0))/1000,"-") -> - | X16: =IFERROR(N16/U16,"-") -> - | Y16: =IFERROR(P16/U16,"-") -> -
A17: =$B17&"_"&$C$3&"_"&$C$2 -> TSX:K_2018_ | B17: TSX:K | C17: =IFERROR(INDEX(Raw_Data,MATCH($A17,Look_Up,0),MATCH(C$4,Component,0)),"-") -> - | D17: =_xll.ciqfunctions.udf.CIQ(B17, "IQ_MARKETCAP", $A$1,$A$2) -> 43214.18 | E17: =_xll.ciqfunctions.udf.CIQ($B17, "IQ_TEV", $A$1,$A$2) -> 42579.719 | F17: =IFERROR(INDEX(Raw_Data,MATCH($A17,Look_Up,0),MATCH(F$4,Component,0)),"-") -> - | G17: =IFERROR(INDEX(Raw_Data,MATCH($A17,Look_Up,0),MATCH(G$4,Component,0)),"-") -> - | H17: =IFERROR(INDEX(Raw_Data,MATCH($A17,Look_Up,0),MATCH(H$4,Component,0))/1000,"-") -> - | I17: =IFERROR(INDEX(Raw_Data,MATCH($A17,Look_Up,0),MATCH(I$4,Component,0))/1000,"-") -> - | J17: =IFERROR(INDEX(Raw_Data,MATCH($A17,Look_Up,0),MATCH(J$4,Component,0)),"-") -> - | K17: =IFERROR(INDEX(Raw_Data,MATCH($A17,Look_Up,0),MATCH(K$4,Component,0)),"-") -> - | L17: =IFERROR(INDEX(Raw_Data,MATCH($A17,Look_Up,0),MATCH(L$4,Component,0))/1000,"-") -> - | M17: =IFERROR(INDEX(Raw_Data,MATCH($A17,Look_Up,0),MATCH(M$4,Component,0)),"-") -> - | N17: =IFERROR(INDEX(Raw_Data,MATCH($A17,Look_Up,0),MATCH(N$4,Component,0))/1000,"-") -> - | O17: =IFERROR(INDEX(Raw_Data,MATCH($A17,Look_Up,0),MATCH(O$4,Component,0))/1000,"-") -> - | P17: =IFERROR(INDEX(Raw_Data,MATCH($A17,Look_Up,0),MATCH(P$4,Component,0))/1000,"-") -> - | Q17: =IFERROR(INDEX(Raw_Data,MATCH($A17,Look_Up,0),MATCH(Q$4,Component,0)),"-") -> - | R17: =IFERROR(INDEX(Raw_Data,MATCH($A17,Look_Up,0),MATCH(R$4,Component,0)),"-") -> - | S17: =IFERROR(INDEX(Raw_Data,MATCH($A17,Look_Up,0),MATCH(S$4,Component,0))/1000,"-") -> - | T17: =IFERROR(INDEX(Raw_Data,MATCH($A17,Look_Up,0),MATCH(T$4,Component,0)),"-") -> - | U17: =IFERROR(INDEX(Raw_Data,MATCH($A17,Look_Up,0),MATCH(U$4,Component,0))/1000,"-") -> - | V17: =IFERROR(INDEX(Raw_Data,MATCH($A17,Look_Up,0),MATCH(V$4,Component,0))/1000,"-") -> - | X17: =IFERROR(N17/U17,"-") -> - | Y17: =IFERROR(P17/U17,"-") -> -
A18: =$B18&"_"&$C$3&"_"&$C$2 -> TSX:J_2018_ | B18: TSX:J | C18: =IFERROR(INDEX(Raw_Data,MATCH($A18,Look_Up,0),MATCH(C$4,Component,0)),"-") -> - | D18: =_xll.ciqfunctions.udf.CIQ(B18, "IQ_MARKETCAP", $A$1,$A$2) -> 0 | E18: =_xll.ciqfunctions.udf.CIQ($B18, "IQ_TEV", $A$1,$A$2) -> 0 | F18: =IFERROR(INDEX(Raw_Data,MATCH($A18,Look_Up,0),MATCH(F$4,Component,0)),"-") -> - | G18: =IFERROR(INDEX(Raw_Data,MATCH($A18,Look_Up,0),MATCH(G$4,Component,0)),"-") -> - | H18: =IFERROR(INDEX(Raw_Data,MATCH($A18,Look_Up,0),MATCH(H$4,Component,0))/1000,"-") -> - | I18: =IFERROR(INDEX(Raw_Data,MATCH($A18,Look_Up,0),MATCH(I$4,Component,0))/1000,"-") -> - | J18: =IFERROR(INDEX(Raw_Data,MATCH($A18,Look_Up,0),MATCH(J$4,Component,0)),"-") -> - | K18: =IFERROR(INDEX(Raw_Data,MATCH($A18,Look_Up,0),MATCH(K$4,Component,0)),"-") -> - | L18: =IFERROR(INDEX(Raw_Data,MATCH($A18,Look_Up,0),MATCH(L$4,Component,0))/1000,"-") -> - | M18: =IFERROR(INDEX(Raw_Data,MATCH($A18,Look_Up,0),MATCH(M$4,Component,0)),"-") -> - | N18: =IFERROR(INDEX(Raw_Data,MATCH($A18,Look_Up,0),MATCH(N$4,Component,0))/1000,"-") -> - | O18: =IFERROR(INDEX(Raw_Data,MATCH($A18,Look_Up,0),MATCH(O$4,Component,0))/1000,"-") -> - | P18: =IFERROR(INDEX(Raw_Data,MATCH($A18,Look_Up,0),MATCH(P$4,Component,0))/1000,"-") -> - | Q18: =IFERROR(INDEX(Raw_Data,MATCH($A18,Look_Up,0),MATCH(Q$4,Component,0)),"-") -> - | R18: =IFERROR(INDEX(Raw_Data,MATCH($A18,Look_Up,0),MATCH(R$4,Component,0)),"-") -> - | S18: =IFERROR(INDEX(Raw_Data,MATCH($A18,Look_Up,0),MATCH(S$4,Component,0))/1000,"-") -> - | T18: =IFERROR(INDEX(Raw_Data,MATCH($A18,Look_Up,0),MATCH(T$4,Component,0)),"-") -> - | U18: =IFERROR(INDEX(Raw_Data,MATCH($A18,Look_Up,0),MATCH(U$4,Component,0))/1000,"-") -> - | V18: =IFERROR(INDEX(Raw_Data,MATCH($A18,Look_Up,0),MATCH(V$4,Component,0))/1000,"-") -> - | X18: =IFERROR(N18/U18,"-") -> - | Y18: =IFERROR(P18/U18,"-") -> -
A19: =$B19&"_"&$C$3&"_"&$C$2 -> TSX:I_2018_ | B19: TSX:I | C19: =IFERROR(INDEX(Raw_Data,MATCH($A19,Look_Up,0),MATCH(C$4,Component,0)),"-") -> - | D19: =_xll.ciqfunctions.udf.CIQ(B19, "IQ_MARKETCAP", $A$1,$A$2) -> (Invalid Identifier) | E19: =_xll.ciqfunctions.udf.CIQ($B19, "IQ_TEV", $A$1,$A$2) -> (Invalid Identifier) | F19: =IFERROR(INDEX(Raw_Data,MATCH($A19,Look_Up,0),MATCH(F$4,Component,0)),"-") -> - | G19: =IFERROR(INDEX(Raw_Data,MATCH($A19,Look_Up,0),MATCH(G$4,Component,0)),"-") -> - | H19: =IFERROR(INDEX(Raw_Data,MATCH($A19,Look_Up,0),MATCH(H$4,Component,0))/1000,"-") -> - | I19: =IFERROR(INDEX(Raw_Data,MATCH($A19,Look_Up,0),MATCH(I$4,Component,0))/1000,"-") -> - | J19: =IFERROR(INDEX(Raw_Data,MATCH($A19,Look_Up,0),MATCH(J$4,Component,0)),"-") -> - | K19: =IFERROR(INDEX(Raw_Data,MATCH($A19,Look_Up,0),MATCH(K$4,Component,0)),"-") -> - | L19: =IFERROR(INDEX(Raw_Data,MATCH($A19,Look_Up,0),MATCH(L$4,Component,0))/1000,"-") -> - | M19: =IFERROR(INDEX(Raw_Data,MATCH($A19,Look_Up,0),MATCH(M$4,Component,0)),"-") -> - | N19: =IFERROR(INDEX(Raw_Data,MATCH($A19,Look_Up,0),MATCH(N$4,Component,0))/1000,"-") -> - | O19: =IFERROR(INDEX(Raw_Data,MATCH($A19,Look_Up,0),MATCH(O$4,Component,0))/1000,"-") -> - | P19: =IFERROR(INDEX(Raw_Data,MATCH($A19,Look_Up,0),MATCH(P$4,Component,0))/1000,"-") -> - | Q19: =IFERROR(INDEX(Raw_Data,MATCH($A19,Look_Up,0),MATCH(Q$4,Component,0)),"-") -> - | R19: =IFERROR(INDEX(Raw_Data,MATCH($A19,Look_Up,0),MATCH(R$4,Component,0)),"-") -> - | S19: =IFERROR(INDEX(Raw_Data,MATCH($A19,Look_Up,0),MATCH(S$4,Component,0))/1000,"-") -> - | T19: =IFERROR(INDEX(Raw_Data,MATCH($A19,Look_Up,0),MATCH(T$4,Component,0)),"-") -> - | U19: =IFERROR(INDEX(Raw_Data,MATCH($A19,Look_Up,0),MATCH(U$4,Component,0))/1000,"-") -> - | V19: =IFERROR(INDEX(Raw_Data,MATCH($A19,Look_Up,0),MATCH(V$4,Component,0))/1000,"-") -> - | X19: =IFERROR(N19/U19,"-") -> - | Y19: =IFERROR(P19/U19,"-") -> -
... A27: =$B27&"_"&$C$3&"_"&$C$2 -> TSX:A_2018_ | B27: TSX:A | C27: =IFERROR(INDEX(Raw_Data,MATCH($A27,Look_Up,0),MATCH(C$4,Component,0)),"-") -> - | D27: =_xll.ciqfunctions.udf.CIQ(B27, "IQ_MARKETCAP", $A$1,$A$2) -> (Invalid Identifier) | E27: =_xll.ciqfunctions.udf.CIQ($B27, "IQ_TEV", $A$1,$A$2) -> (Invalid Identifier) | F27: =IFERROR(INDEX(Raw_Data,MATCH($A27,Look_Up,0),MATCH(F$4,Component,0)),"-") -> - | G27: =IFERROR(INDEX(Raw_Data,MATCH($A27,Look_Up,0),MATCH(G$4,Component,0)),"-") -> - | H27: =IFERROR(INDEX(Raw_Data,MATCH($A27,Look_Up,0),MATCH(H$4,Component,0))/1000,"-") -> - | I27: =IFERROR(INDEX(Raw_Data,MATCH($A27,Look_Up,0),MATCH(I$4,Component,0))/1000,"-") -> - | J27: =IFERROR(INDEX(Raw_Data,MATCH($A27,Look_Up,0),MATCH(J$4,Component,0)),"-") -> - | K27: =IFERROR(INDEX(Raw_Data,MATCH($A27,Look_Up,0),MATCH(K$4,Component,0)),"-") -> - | L27: =IFERROR(INDEX(Raw_Data,MATCH($A27,Look_Up,0),MATCH(L$4,Component,0))/1000,"-") -> - | M27: =IFERROR(INDEX(Raw_Data,MATCH($A27,Look_Up,0),MATCH(M$4,Component,0)),"-") -> - | N27: =IFERROR(INDEX(Raw_Data,MATCH($A27,Look_Up,0),MATCH(N$4,Component,0))/1000,"-") -> - | O27: =IFERROR(INDEX(Raw_Data,MATCH($A27,Look_Up,0),MATCH(O$4,Component,0))/1000,"-") -> - | P27: =IFERROR(INDEX(Raw_Data,MATCH($A27,Look_Up,0),MATCH(P$4,Component,0))/1000,"-") -> - | Q27: =IFERROR(INDEX(Raw_Data,MATCH($A27,Look_Up,0),MATCH(Q$4,Component,0)),"-") -> - | R27: =IFERROR(INDEX(Raw_Data,MATCH($A27,Look_Up,0),MATCH(R$4,Component,0)),"-") -> - | S27: =IFERROR(INDEX(Raw_Data,MATCH($A27,Look_Up,0),MATCH(S$4,Component,0))/1000,"-") -> - | T27: =IFERROR(INDEX(Raw_Data,MATCH($A27,Look_Up,0),MATCH(T$4,Component,0)),"-") -> - | U27: =IFERROR(INDEX(Raw_Data,MATCH($A27,Look_Up,0),MATCH(U$4,Component,0))/1000,"-") -> - | V27: =IFERROR(INDEX(Raw_Data,MATCH($A27,Look_Up,0),MATCH(V$4,Component,0))/1000,"-") -> - | X27: =IFERROR(N27/U27,"-") -> - | Y27: =IFERROR(P27/U27,"-") -> -
C28: Summary Statistics
B29: 0.75 | C29: 75th Percentile | D29: =PERCENTILE(D$8:D$27,$B29) -> 34811.311 | E29: =PERCENTILE(E$8:E$27,$B29) -> 53321.206 | H29: =PERCENTILE(H$8:H$27,$B29) -> #NUM! | I29: =PERCENTILE(I$8:I$27,$B29) -> #NUM! | J29: =PERCENTILE(J$8:J$27,$B29) -> #NUM! | K29: =PERCENTILE(K$8:K$27,$B29) -> #NUM! | L29: =PERCENTILE(L$8:L$27,$B29) -> #NUM! | M29: =PERCENTILE(M$8:M$27,$B29) -> #NUM! | N29: =PERCENTILE(N$8:N$27,$B29) -> #NUM! | O29: =PERCENTILE(O$8:O$27,$B29) -> #NUM! | ... V29: =PERCENTILE(V$8:V$27,$B29) -> #NUM! | X29: =PERCENTILE(X$8:X$27,$B29) -> #NUM! | Y29: =PERCENTILE(Y$8:Y$27,$B29) -> #NUM!
B30: 0.5 | C30: Median | D30: =PERCENTILE(D$8:D$27,$B30) -> 16010.962 | E30: =PERCENTILE(E$8:E$27,$B30) -> 21423.577 | H30: =PERCENTILE(H$8:H$27,$B30) -> #NUM! | I30: =PERCENTILE(I$8:I$27,$B30) -> #NUM! | J30: =PERCENTILE(J$8:J$27,$B30) -> #NUM! | K30: =PERCENTILE(K$8:K$27,$B30) -> #NUM! | L30: =PERCENTILE(L$8:L$27,$B30) -> #NUM! | M30: =PERCENTILE(M$8:M$27,$B30) -> #NUM! | N30: =PERCENTILE(N$8:N$27,$B30) -> #NUM! | O30: =PERCENTILE(O$8:O$27,$B30) -> #NUM! | ... V30: =PERCENTILE(V$8:V$27,$B30) -> #NUM! | X30: =PERCENTILE(X$8:X$27,$B30) -> #NUM! | Y30: =PERCENTILE(Y$8:Y$27,$B30) -> #NUM!
B31: 0.25 | C31: 25th Percentile | D31: =PERCENTILE(D$8:D$27,$B31) -> 46.527068 | E31: =PERCENTILE(E$8:E$27,$B31) -> 89.424292 | H31: =PERCENTILE(H$8:H$27,$B31) -> #NUM! | I31: =PERCENTILE(I$8:I$27,$B31) -> #NUM! | J31: =PERCENTILE(J$8:J$27,$B31) -> #NUM! | K31: =PERCENTILE(K$8:K$27,$B31) -> #NUM! | L31: =PERCENTILE(L$8:L$27,$B31) -> #NUM! | M31: =PERCENTILE(M$8:M$27,$B31) -> #NUM! | N31: =PERCENTILE(N$8:N$27,$B31) -> #NUM! | O31: =PERCENTILE(O$8:O$27,$B31) -> #NUM! | ... V31: =PERCENTILE(V$8:V$27,$B31) -> #NUM! | X31: =PERCENTILE(X$8:X$27,$B31) -> #NUM! | Y31: =PERCENTILE(Y$8:Y$27,$B31) -> #NUM!
C32: Average | D32: =AVERAGE(D8:D27) -> 22149.093 | E32: =AVERAGE(E8:E27) -> 30397.094 | H32: =AVERAGE(H8:H27) -> #DIV/0! | I32: =AVERAGE(I8:I27) -> #DIV/0! | J32: =AVERAGE(J8:J27) -> #DIV/0! | K32: =AVERAGE(K8:K27) -> #DIV/0! | L32: =AVERAGE(L8:L27) -> #DIV/0! | M32: =AVERAGE(M8:M27) -> #DIV/0! | N32: =AVERAGE(N8:N27) -> #DIV/0! | O32: =AVERAGE(O8:O27) -> #DIV/0! | ... V32: =AVERAGE(V8:V27) -> #DIV/0! | X32: =AVERAGE(X8:X27) -> #DIV/0! | Y32: =AVERAGE(Y8:Y27) -> #DIV/0!
A34: =$B34&"_"&$C$3&"_"&$C$2 -> TSX:RY_2018_ | B34: TSX:RY | C34: =IFERROR(INDEX(Raw_Data,MATCH($A34,Look_Up,0),MATCH(C$4,Component,0)),"-") -> - | D34: =_xll.ciqfunctions.udf.CIQ(B34, "IQ_MARKETCAP", $A$1,$A$2) -> 289217.22 | E34: =_xll.ciqfunctions.udf.CIQ($B34, "IQ_TEV", $A$1,$A$2) -> 0 | F34: =IFERROR(INDEX(Raw_Data,MATCH($A34,Look_Up,0),MATCH(F$4,Component,0)),"-") -> - | G34: =IFERROR(INDEX(Raw_Data,MATCH($A34,Look_Up,0),MATCH(G$4,Component,0)),"-") -> - | H34: =IFERROR(INDEX(Raw_Data,MATCH($A34,Look_Up,0),MATCH(H$4,Component,0))/1000,"-") -> - | I34: =IFERROR(INDEX(Raw_Data,MATCH($A34,Look_Up,0),MATCH(I$4,Component,0))/1000,"-") -> - | J34: =IFERROR(INDEX(Raw_Data,MATCH($A34,Look_Up,0),MATCH(J$4,Component,0)),"-") -> - | K34: =IFERROR(INDEX(Raw_Data,MATCH($A34,Look_Up,0),MATCH(K$4,Component,0)),"-") -> - | L34: =IFERROR(INDEX(Raw_Data,MATCH($A34,Look_Up,0),MATCH(L$4,Component,0))/1000,"-") -> - | M34: =IFERROR(INDEX(Raw_Data,MATCH($A34,Look_Up,0),MATCH(M$4,Component,0)),"-") -> - | N34: =IFERROR(INDEX(Raw_Data,MATCH($A34,Look_Up,0),MATCH(N$4,Component,0))/1000,"-") -> - | O34: =IFERROR(INDEX(Raw_Data,MATCH($A34,Look_Up,0),MATCH(O$4,Component,0))/1000,"-") -> - | P34: =IFERROR(INDEX(Raw_Data,MATCH($A34,Look_Up,0),MATCH(P$4,Component,0))/1000,"-") -> - | Q34: =IFERROR(INDEX(Raw_Data,MATCH($A34,Look_Up,0),MATCH(Q$4,Component,0)),"-") -> - | R34: =IFERROR(INDEX(Raw_Data,MATCH($A34,Look_Up,0),MATCH(R$4,Component,0)),"-") -> - | S34: =IFERROR(INDEX(Raw_Data,MATCH($A34,Look_Up,0),MATCH(S$4,Component,0))/1000,"-") -> - | T34: =IFERROR(INDEX(Raw_Data,MATCH($A34,Look_Up,0),MATCH(T$4,Component,0)),"-") -> - | U34: =IFERROR(INDEX(Raw_Data,MATCH($A34,Look_Up,0),MATCH(U$4,Component,0))/1000,"-") -> - | V34: =IFERROR(INDEX(Raw_Data,MATCH($A34,Look_Up,0),MATCH(V$4,Component,0))/1000,"-") -> - | X34: =IFERROR(N34/U34,"-") -> - | Y34: =IFERROR(P34/U34,"-") -> -
C35: Percent Rank | D35: =IF(D$34>=MAX(D$8:D$27),"max",IF(D$34<=MIN(D$8:D$27),"min",PERCENTRANK(D$8:D$27,D$34))) -> max | E35: =IF(E$34>=MAX(E$8:E$27),"max",IF(E$34<=MIN(E$8:E$27),"min",PERCENTRANK(E$8:E$27,E$34))) -> min | H35: =IF(H$34>=MAX(H$8:H$27),"max",IF(H$34<=MIN(H$8:H$27),"min",PERCENTRANK(H$8:H$27,H$34))) -> max | I35: =IF(I$34>=MAX(I$8:I$27),"max",IF(I$34<=MIN(I$8:I$27),"min",PERCENTRANK(I$8:I$27,I$34))) -> max | J35: =IF(J$34>=MAX(J$8:J$27),"max",IF(J$34<=MIN(J$8:J$27),"min",PERCENTRANK(J$8:J$27,J$34))) -> max | K35: =IF(K$34>=MAX(K$8:K$27),"max",IF(K$34<=MIN(K$8:K$27),"min",PERCENTRANK(K$8:K$27,K$34))) -> max | L35: =IF(L$34>=MAX(L$8:L$27),"max",IF(L$34<=MIN(L$8:L$27),"min",PERCENTRANK(L$8:L$27,L$34))) -> max | M35: =IF(M$34>=MAX(M$8:M$27),"max",IF(M$34<=MIN(M$8:M$27),"min",PERCENTRANK(M$8:M$27,M$34))) -> max | N35: =IF(N$34>=MAX(N$8:N$27),"max",IF(N$34<=MIN(N$8:N$27),"min",PERCENTRANK(N$8:N$27,N$34))) -> max | O35: =IF(O$34>=MAX(O$8:O$27),"max",IF(O$34<=MIN(O$8:O$27),"min",PERCENTRANK(O$8:O$27,O$34))) -> max | ... V35: =IF(V$34>=MAX(V$8:V$27),"max",IF(V$34<=MIN(V$8:V$27),"min",PERCENTRANK(V$8:V$27,V$34))) -> max | X35: =IF(X$34>=MAX(X$8:X27),"max",IF(X$34<=MIN(X$8:X27),"min",PERCENTRANK(X$8:X27,X$34))) -> max | Y35: =IF(Y$34>=MAX(Y$8:Y27),"max",IF(Y$34<=MIN(Y$8:Y27),"min",PERCENTRANK(Y$8:Y27,Y$34))) -> max
C37: =+"Sources: "&C3&" proxy data" -> Sources: 2018 proxy data
C38: Incumbent Specific Notes:
C39: =IFERROR(INDEX(Raw_Data,MATCH(#REF!,Look_Up,0),MATCH(C$38,Component,0)),"N/A") -> N/A

Sheet Master - Charts
C3: Master - Summary | D3: Master - Summary | E3: Master - Summary
C4: Base Salary | D4: Target TCC | E4: Target TDC
B5: LINK DATA HERE
B6: 75th Percentile | C6: ='Master - Summary'!H29 -> #NUM! | D6: ='Master - Summary'!O29 -> #NUM! | E6: ='Master - Summary'!V29 -> #NUM!
B7: Median | C7: ='Master - Summary'!H30 -> #NUM! | D7: ='Master - Summary'!O30 -> #NUM! | E7: ='Master - Summary'!V30 -> #NUM!
B8: 25th Percentile | C8: ='Master - Summary'!H31 -> #NUM! | D8: ='Master - Summary'!O31 -> #NUM! | E8: ='Master - Summary'!V31 -> #NUM!
B9: Average | C9: ='Master - Summary'!H32 -> #DIV/0! | D9: ='Master - Summary'!O32 -> #DIV/0! | E9: ='Master - Summary'!V32 -> #DIV/0!
B10: ='Master - Summary'!C34 -> - | C10: ='Master - Summary'!H34 -> - | D10: ='Master - Summary'!O34 -> - | E10: ='Master - Summary'!V34 -> -
B12: LINK TO CHARTS
B13: 25th | C13: =C8 -> #NUM! | D13: =D8 -> #NUM! | E13: =E8 -> #NUM!
B14: 50th | C14: =(C7-C8) -> #NUM! | D14: =(D7-D8) -> #NUM! | E14: =(E7-E8) -> #NUM!
B15: 75th | C15: =(C6-C7) -> #NUM! | D15: =(D6-D7) -> #NUM! | E15: =(E6-E7) -> #NUM!
B16: Average | C16: =C9 -> #DIV/0! | D16: =D9 -> #DIV/0! | E16: =E9 -> #DIV/0!
B17: ='Master - Summary'!C34 -> - | C17: =C10 -> - | D17: =D10 -> - | E17: =E10 -> -
B19: Distance From Median | C19: =C10-C7 -> #VALUE! | D19: =D10-D7 -> #VALUE! | E19: =E10-E7 -> #VALUE!

Sheet TC Chart
B2: Row | C2: =C24 -> CEO | D2: =D24 -> CEO | E2: =E24 -> CFO | F2: =F24 -> CFO | G2: =G24 -> COO | H2: =H24 -> COO | I2: =I24 -> Legal | J2: =J24 -> Legal | ... N2: =N24 -> NEO5
B3: 75th Percentile | C3: 34 | D3: 34 | E3: 34 | F3: 34 | G3: 33 | H3: 33 | I3: 22 | J3: 22 | K3: 34 | L3: 34 | M3: 34 | N3: 34
B4: Median | C4: =C3+1 -> 35 | D4: =D3+1 -> 35 | E4: =E3+1 -> 35 | F4: =F3+1 -> 35 | G4: =G3+1 -> 34 | H4: =H3+1 -> 34 | I4: =I3+1 -> 23 | J4: =J3+1 -> 23 | ... N4: =N3+1 -> 35
B5: 25th Percentile | C5: =C4+1 -> 36 | D5: =D4+1 -> 36 | E5: =E4+1 -> 36 | F5: =F4+1 -> 36 | G5: =G4+1 -> 35 | H5: =H4+1 -> 35 | I5: =I4+1 -> 24 | J5: =J4+1 -> 24 | ... N5: =N4+1 -> 36
B6: Average | C6: =C5+1 -> 37 | D6: =D5+1 -> 37 | E6: =E5+1 -> 37 | F6: =F5+1 -> 37 | G6: =G5+1 -> 36 | H6: =H5+1 -> 36 | I6: =I5+1 -> 25 | J6: =J5+1 -> 25 | ... N6: =N5+1 -> 37
B7: Hudbay Minerals Inc. | C7: 39 | D7: 39 | E7: 39 | F7: 39 | G7: 38 | H7: 38 | I7: 27 | J7: 27 | K7: 39 | L7: 39 | M7: 39 | N7: 39
B8: Hudbay2 | M8: =M7+2 -> 41 | N8: =N7+2 -> 41
B9: Hudbay3 | M9: =M8+2 -> 43 | N9: =N8+2 -> 43
B10: Percentiles | C10: =C7+1 -> 40 | D10: =D7+1 -> 40 | E10: =E7+1 -> 40 | F10: =F7+1 -> 40 | G10: =G7+1 -> 39 | H10: =H7+1 -> 39 | I10: =I7+1 -> 28 | J10: =J7+1 -> 28 | ... N10: =N7+1 -> 40
B12: Address | C12: W | D12: AA | E12: =C12 -> W | F12: =D12 -> AA | G12: =E12 -> W | H12: =F12 -> AA | I12: =G12 -> W | J12: =H12 -> AA | K12: =I12 -> W | L12: =J12 -> AA | ... N12: =L12 -> AA
B13: =B28 -> 75th Percentile | C13: =C$12&C3 -> W34 | D13: =D$12&D3 -> AA34 | E13: =E$12&E3 -> W34 | F13: =F$12&F3 -> AA34 | G13: =G$12&G3 -> W33 | H13: =H$12&H3 -> AA33 | I13: =I$12&I3 -> W22 | J13: =J$12&J3 -> AA22 | ... N13: =N$12&N3 -> AA34
B14: =B29 -> Median | C14: =C$12&C4 -> W35 | D14: =D$12&D4 -> AA35 | E14: =E$12&E4 -> W35 | F14: =F$12&F4 -> AA35 | G14: =G$12&G4 -> W34 | H14: =H$12&H4 -> AA34 | I14: =I$12&I4 -> W23 | J14: =J$12&J4 -> AA23 | ... N14: =N$12&N4 -> AA35
B15: =B30 -> 25th Percentile | C15: =C$12&C5 -> W36 | D15: =D$12&D5 -> AA36 | E15: =E$12&E5 -> W36 | F15: =F$12&F5 -> AA36 | G15: =G$12&G5 -> W35 | H15: =H$12&H5 -> AA35 | I15: =I$12&I5 -> W24 | J15: =J$12&J5 -> AA24 | ... N15: =N$12&N5 -> AA36
B16: =B31 -> Average | C16: =C$12&C6 -> W37 | D16: =D$12&D6 -> AA37 | E16: =E$12&E6 -> W37 | F16: =F$12&F6 -> AA37 | G16: =G$12&G6 -> W36 | H16: =H$12&H6 -> AA36 | I16: =I$12&I6 -> W25 | J16: =J$12&J6 -> AA25 | ... N16: =N$12&N6 -> AA37
B17: =B32 -> Hudbay Minerals Inc. | C17: =C$12&C7 -> W39 | D17: =D$12&D7 -> AA39 | E17: =E$12&E7 -> W39 | F17: =F$12&F7 -> AA39 | G17: =G$12&G7 -> W38 | H17: =H$12&H7 -> AA38 | I17: =I$12&I7 -> W27 | J17: =J$12&J7 -> AA27 | ... N17: =N$12&N7 -> AA39
B18: =B8 -> Hudbay2 | M18: =M$12&M8 -> W41 | N18: =N$12&N8 -> AA41
B19: =B9 -> Hudbay3 | M19: =M$12&M9 -> W43 | N19: =N$12&N9 -> AA43
B20: =B10 -> Percentiles | C20: =C$12&C10 -> W40 | D20: =D$12&D10 -> AA40 | E20: =E$12&E10 -> W40 | F20: =F$12&F10 -> AA40 | G20: =G$12&G10 -> W39 | H20: =H$12&H10 -> AA39 | I20: =I$12&I10 -> W28 | J20: =J$12&J10 -> AA28 | ... N20: =N$12&N10 -> AA40
M21: =M$12&M$10+2 -> W42 | N21: =N$12&N$10+2 -> AA42
M22: =M$12&M$10+4 -> W44 | N22: =N$12&N$10+4 -> AA44
C24: CEO | D24: =C24 -> CEO | E24: CFO | F24: =E24 -> CFO | G24: COO | H24: =G24 -> COO | I24: Legal | J24: =I24 -> Legal | K24: NEO4 | L24: =K24 -> NEO4 | M24: NEO5 | N24: =M24 -> NEO5
C25: CEO (Kukielski) | E25: CFO (Lei) | G25: COO (Lauzon) | I25: Legal (Donnelly) | K25: NEO4 (Donnelly) | M25: NEO5 (Del Rio)
C26: TDC | D26: TC | E26: =C26 -> TDC | F26: =D26 -> TC | G26: =E26 -> TDC | H26: =F26 -> TC | I26: =G26 -> TDC | J26: =H26 -> TC | K26: =I26 -> TDC | L26: =J26 -> TC | ... N26: =L26 -> TC
B27: LINK DATA HERE
B28: 75th Percentile | C28: {=INDIRECT("'"&C$24&"'!"&C13)} -> 7308.3083 | D28: {=INDIRECT("'"&D$24&"'!"&D13)} -> 7314.592 | E28: {=INDIRECT("'"&E$24&"'!"&E13)} -> 2606.1399 | F28: {=INDIRECT("'"&F$24&"'!"&F13)} -> 2687.8052 | G28: {=INDIRECT("'"&G$24&"'!"&G13)} -> 2780.696 | H28: {=INDIRECT("'"&H$24&"'!"&H13)} -> 2981.7174 | I28: {=INDIRECT("'"&I$24&"'!"&I13)} -> 2154.5282 | J28: {=INDIRECT("'"&J$24&"'!"&J13)} -> 2432.1551 | ... N28: {=INDIRECT("'"&N$24&"'!"&N13)} -> 2284.5597
B29: Median | C29: {=INDIRECT("'"&C$24&"'!"&C14)} -> 5171.8978 | D29: {=INDIRECT("'"&D$24&"'!"&D14)} -> 5486.9213 | E29: {=INDIRECT("'"&E$24&"'!"&E14)} -> 2005.6181 | F29: {=INDIRECT("'"&F$24&"'!"&F14)} -> 2116.8867 | G29: {=INDIRECT("'"&G$24&"'!"&G14)} -> 2603.8726 | H29: {=INDIRECT("'"&H$24&"'!"&H14)} -> 2646.9629 | I29: {=INDIRECT("'"&I$24&"'!"&I14)} -> 1724.5542 | J29: {=INDIRECT("'"&J$24&"'!"&J14)} -> 1876.939 | ... N29: {=INDIRECT("'"&N$24&"'!"&N14)} -> 1639.1808
B30: 25th Percentile | C30: {=INDIRECT("'"&C$24&"'!"&C15)} -> 4412.0242 | D30: {=INDIRECT("'"&D$24&"'!"&D15)} -> 4495.807 | E30: {=INDIRECT("'"&E$24&"'!"&E15)} -> 1835.1017 | F30: {=INDIRECT("'"&F$24&"'!"&F15)} -> 1908.7374 | G30: {=INDIRECT("'"&G$24&"'!"&G15)} -> 2191.2833 | H30: {=INDIRECT("'"&H$24&"'!"&H15)} -> 2231.5866 | I30: {=INDIRECT("'"&I$24&"'!"&I15)} -> 1506.1273 | J30: {=INDIRECT("'"&J$24&"'!"&J15)} -> 1633.0278 | ... N30: {=INDIRECT("'"&N$24&"'!"&N15)} -> 1557.1223
B31: Average | C31: {=INDIRECT("'"&C$24&"'!"&C16)} -> 5748.5395 | D31: {=INDIRECT("'"&D$24&"'!"&D16)} -> 5997.4397 | E31: {=INDIRECT("'"&E$24&"'!"&E16)} -> 2155.0188 | F31: {=INDIRECT("'"&F$24&"'!"&F16)} -> 2247.7605 | G31: {=INDIRECT("'"&G$24&"'!"&G16)} -> 2516.0841 | H31: {=INDIRECT("'"&H$24&"'!"&H16)} -> 2629.0558 | I31: {=INDIRECT("'"&I$24&"'!"&I16)} -> 1913.3745 | J31: {=INDIRECT("'"&J$24&"'!"&J16)} -> 2059.221 | ... N31: {=INDIRECT("'"&N$24&"'!"&N16)} -> 1856.3996
B32: =CEO!C39 -> Hudbay Minerals Inc. | C32: {=INDIRECT("'"&C$24&"'!"&C17)} -> 5080.4963 | D32: {=INDIRECT("'"&D$24&"'!"&D17)} -> 5457.5723 | E32: {=INDIRECT("'"&E$24&"'!"&E17)} -> 2065.2516 | F32: {=INDIRECT("'"&F$24&"'!"&F17)} -> 2300.9746 | G32: {=INDIRECT("'"&G$24&"'!"&G17)} -> 2343.6 | H32: {=INDIRECT("'"&H$24&"'!"&H17)} -> 2503.127 | I32: {=INDIRECT("'"&I$24&"'!"&I17)} -> 1630.3918 | J32: {=INDIRECT("'"&J$24&"'!"&J17)} -> 1837.9278 | ... N32: {=INDIRECT("'"&N$24&"'!"&N17)} -> 1818.9597
B33: ='NEO5'!G43 -> SVP, Canada | M33: {=INDIRECT("'"&M$24&"'!"&M18)} -> 1304.38
B34: ='NEO5'!G41 -> SVP, Exploration and Technical Services | M34: {=INDIRECT("'"&M$24&"'!"&M19)} -> 1269.8
B36: LINK TO CHARTS
B37: 25th | C37: =C30 -> 4412.0242 | D37: =D30 -> 4495.807 | E37: =E30 -> 1835.1017 | F37: =F30 -> 1908.7374 | G37: =G30 -> 2191.2833 | H37: =H30 -> 2231.5866 | I37: =I30 -> 1506.1273 | J37: =J30 -> 1633.0278 | ... N37: =N30 -> 1557.1223
B38: 50th | C38: =(C29-C30) -> 759.87358 | D38: =(D29-D30) -> 991.11426 | E38: =(E29-E30) -> 170.51646 | F38: =(F29-F30) -> 208.14928 | G38: =(G29-G30) -> 412.58928 | H38: =(H29-H30) -> 415.37628 | I38: =(I29-I30) -> 218.4269 | J38: =(J29-J30) -> 243.91119 | ... N38: =(N29-N30) -> 82.058525
B39: 75th | C39: =(C28-C29) -> 2136.4105 | D39: =(D28-D29) -> 1827.6708 | E39: =(E28-E29) -> 600.52175 | F39: =(F28-F29) -> 570.91852 | G39: =(G28-G29) -> 176.82345 | H39: =(H28-H29) -> 334.75445 | I39: =(I28-I29) -> 429.97397 | J39: =(J28-J29) -> 555.21606 | ... N39: =(N28-N29) -> 645.37886
B40: Average | C40: =C31 -> 5748.5395 | D40: =D31 -> 5997.4397 | E40: =E31 -> 2155.0188 | F40: =F31 -> 2247.7605 | G40: =G31 -> 2516.0841 | H40: =H31 -> 2629.0558 | I40: =I31 -> 1913.3745 | J40: =J31 -> 2059.221 | ... N40: =N31 -> 1856.3996
B41: =B32 -> Hudbay Minerals Inc. | C41: =C32 -> 5080.4963 | D41: =D32 -> 5457.5723 | E41: =E32 -> 2065.2516 | F41: =F32 -> 2300.9746 | G41: =G32 -> 2343.6 | H41: =H32 -> 2503.127 | I41: =I32 -> 1630.3918 | ... N41: =N32 -> 1818.9597
B42: Percentile | C42: {=INDIRECT("'"&C$24&"'!"&C20)*100} -> 49 | D42: {=INDIRECT("'"&D$24&"'!"&D20)*100} -> 49.6 | E42: {=INDIRECT("'"&E$24&"'!"&E20)*100} -> 52.2 | F42: {=INDIRECT("'"&F$24&"'!"&F20)*100} -> 62 | G42: {=INDIRECT("'"&G$24&"'!"&G20)*100} -> 34.4 | H42: {=INDIRECT("'"&H$24&"'!"&H20)*100} -> 34.4 | I42: {=INDIRECT("'"&I$24&"'!"&I20)*100} -> 44.1 | J42: {=INDIRECT("'"&J$24&"'!"&J20)*100} -> 48.4 | ... N42: {=INDIRECT("'"&N$24&"'!"&N20)*100} -> 62
M43: {=IFERROR(INDIRECT("'"&M$24&"'!"&M21)*100,"P00")} -> 1.1 | N43: {=IFERROR(INDIRECT("'"&N$24&"'!"&N21)*100,"P00")} -> P00
M44: {=IFERROR(INDIRECT("'"&M$24&"'!"&M22)*100,"P00")} -> P00 | N44: {=IFERROR(INDIRECT("'"&N$24&"'!"&N22)*100,"P00")} -> P00
N45: ='NEO5'!AB40*100 -> 16.6
B46: Distance From Median | C46: =C32-C29 -> -91.40155 | D46: =D32-D29 -> -29.349006 | E46: =E32-E29 -> 59.633463 | F46: =F32-F29 -> 184.08789 | G46: =G32-G29 -> -260.27257 | H46: =H32-H29 -> -143.8359 | I46: =I32-I29 -> -94.162431 | J46: =J32-J29 -> -39.011283 | ... N46: =N32-N29 -> 179.77886
B48: Specific Reference Peers
B49: =B33 -> SVP, Canada | M49: 10.8 | N49: =M49+1 -> 11.8
B50: =B34 -> SVP, Exploration and Technical Services | M50: 11.2 | N50: =M50+1 -> 12.2
B51: Javier, Excl. tax top-ups | N51: ='NEO5'!AB39 -> 1397.2467
B52: Company 4
B54: Change in Summary Statistics | O54: Avg
B55: =B28 -> 75th Percentile | D55: =D28/C28-1 -> 0.00085980008 | F55: =F28/E28-1 -> 0.031335748 | H55: =H28/G28-1 -> 0.072291734 | J55: =J28/I28-1 -> 0.12885742 | L55: =L28/K28-1 -> 0.091257515 | N55: =N28/M28-1 -> 0.11268091 | O55: =AVERAGE(C55:N55) -> 0.072880521
B56: =B29 -> Median | D56: =D29/C29-1 -> 0.060910611 | F56: =F29/E29-1 -> 0.055478442 | H56: =H29/G29-1 -> 0.016548557 | J56: =J29/I29-1 -> 0.088361881 | L56: =L29/K29-1 -> 0.057134445 | N56: =N29/M29-1 -> 0.029884848 | O56: =AVERAGE(C56:N56) -> 0.051386464
