Workbook
Name _Hlk3298152: Instructions!$B$32
Name CFO: #REF!
Name CFO: #REF!
Name Client_Ticker: #REF!
Name Client_Ticker: #REF!
Name Component: 'Raw Data'!$B$31:$BA$31
Name Currency_CAD: #REF!
Name Currency_CAD: #REF!
Name FX_2011: #REF!
Name FX_2011: #REF!
Name FX_2012: #REF!
Name FX_2012: #REF!
Name FX_2013: #REF!
Name FX_2013: #REF!
Name IQ_CH: 110000
Name IQ_CQ: 5000
Name IQ_CY: 10000
Name IQ_DAILY: 500000
Name IQ_FH: 100000
Name IQ_FQ: 500
Name IQ_FY: 1000
Name IQ_LTM: 2000
Name IQ_MONTH: 15000
Name IQ_NTM: 6000
Name IQ_WEEK: 50000
Name IQ_YTD: 3000
Name Look_Up: 'Raw Data'!$B$31:$B$1048576
Name Look_Up2: 'Raw Data'!$A$31:$A$1048576
Name Look_Up3: 'Raw Data'!$C$31:$C$1048576
Name Peer_1_Ticker: #REF!
Name Peer_1_Ticker: #REF!
Name Peer_10_Ticker: #REF!
Name Peer_10_Ticker: #REF!
Name Peer_12_Ticker: #REF!
Name Peer_12_Ticker: #REF!
Name Peer_13_Ticker: #REF!
Name Peer_13_Ticker: #REF!
Name Peer_14_Ticker: #REF!
Name Peer_14_Ticker: #REF!
Name Peer_2_Ticker: #REF!
Name Peer_2_Ticker: #REF!
Name Peer_3_Ticker: #REF!
Name Peer_3_Ticker: #REF!
Name Peer_4_Ticker: #REF!
Name Peer_4_Ticker: #REF!
Name Peer_5_Ticker: #REF!
Name Peer_5_Ticker: #REF!
Name Peer_6_Ticker: #REF!
Name Peer_6_Ticker: #REF!
Name Peer_7_Ticker: #REF!
Name Peer_7_Ticker: #REF!
Name Peer_8_Ticker: #REF!
Name Peer_8_Ticker: #REF!
Name Peer_9_Ticker: #REF!
Name Peer_9_Ticker: #REF!
Name raw: #REF!
Name raw: #REF!
Name Raw_Data: #REF!
Name Raw_Data: #REF!
Name Raw_Data: 'Raw Data'!$B$31:$BA$1048576

Sheet __snloffice
A1: 允䅁䍁䅯䅁䵁䅁䅁䅖呂䙁䅧杏䉂䅁䅁䅁䅁䵁䉙䅁㡁䙁䅁兙祂䝁䅅兢杁䝁䅫䅚㥁䍁䅉兎楁䑁䄴免㡁䍁䄸䅕桂䡁䅉兙瑂䑁䄴䅐兂䝁䅅杣桂䝁䄰䅉灂䝁䅑児楁䑁䅅杉⭁䍁䄰免㑁䑁䅫免穁䑁䅫李㑁䑁䅕䅎㡁䍁䄸䅕桂䡁䅉兙瑂䑁䄴䅐兂䝁䅅杣桂䝁䄰䅉灂䝁䅑児楁䑁䅍杉⭁䑁䅉睎㡁䍁䄸䅕桂䡁䅉兙瑂䑁䄴䅐兂䝁䅅杣桂䝁䄰䅉灂䝁䅑児楁䑁䅉杉⭁䑁䅅䅍睁䑁䅁兎ぁ䑁䅷睌兂䝁䅅杣桂䝁䄰材㡁䙁䅁兙祂䝁䅅兢杁䝁䅫䅚㥁䍁䅉䅎楁䑁䄴䅍㡁䍁䄸䅕桂䡁䅉兙瑂䑁䄴䅐兂䝁䅅杣桂䝁䄰䅉灂䝁䅑児楁䑁䅣杉⭁䑁䅙睌祁䑁䅉睌祁䑁䅁杍㉁䑁䅷睌兂䝁䅅杣桂䝁䄰材㡁䙁䅁兙祂䝁䅅兢杁䝁䅫䅚㥁䍁䅉免㍁䍁䅉材㑁䑁䅣睍㑁䑁䅁免㡁䍁䄸䅕桂䡁䅉兙瑂䑁䄴䅐兂䝁䅅杣桂䝁䄰䅉灂䝁䅑児楁䑁䅅䅏楁䑁䄴睎穁䑁䅕免㑁䍁䄴李祁䑁䅕䅍ㅁ䑁䅉䅐癁䙁䅁兙祂䝁䅅兢⭁䅁䅁睈䅁䉁䅯䅁䩂䙁䅅睘乂䕁䅅杕䱂䕁䅕䅖䑂䕁䅅䅕䅁䅁䅅䅁䵁䅁䅁䅖呂䙁䅧杏䭂䅁䅁杄䅁䅁䅷䅁ぁ䑁䅙免㕁䑁䅕䅁䍁䅁䅁䅄䅁䙁䅑睕奂䑁䅯睓䅁䅁䅕䅁䵁䅁䅁䅖呂䙁䅧杏䑂䅁䅁睇䅁䅁䅧䅁䑂䕁䅅䅒䅁䅁䅍䅁煁䅁䅁䅋䩂䝁䄴杤桂䝁䅷兡歂䍁䅁兓歂䝁䅕杢あ䝁䅫杚灂䝁䅕杣灁䅁䅁䅂䅁䅁䄴䅁䩂䙁䅅睘啂䕁䅕杖䅁䅁䅙䅁䝄允䅁䅐兂䝁䅅杣桂䝁䄰䅉灂䝁䅑児楁䑁䅕杉⭁䑁䅅䅐癁䙁䅁兙祂䝁䅅兢⭁䑁䅷䅕桂䡁䅉兙瑂䍁䅁兡歂䑁䄰杉硁䍁䅉材瑁䑁䅅䅏㕁䑁䅍䅍ㅁ䑁䅙䅍㑁䑁䅅䅐癁䙁䅁兙祂䝁䅅兢⭁䑁䅷䅕桂䡁䅉兙瑂䍁䅁兡歂䑁䄰杉穁䍁䅉材祁䑁䅣䅐癁䙁䅁兙祂䝁䅅兢⭁䑁䅷䅕桂䡁䅉兙瑂䍁䅁兡歂䑁䄰杉祁䍁䅉材硁䑁䅁䅍睁䑁䅙䅍㡁䍁䄸䅕桂䡁䅉兙瑂䑁䄴䅐兂䝁䅅杣桂䝁䄰䅉灂䝁䅑児楁䑁䅑杉⭁䑁䅁䅐癁䙁䅁兙祂䝁䅅兢⭁䑁䅷䅕桂䡁䅉兙瑂䍁䅁兡歂䑁䄰杉㍁䍁䅉材㉁䍁䄸杍祁䍁䄸杍睁䑁䅉李㡁䍁䄸䅕桂䡁䅉兙瑂䑁䄴䅐兂䝁䅅杣桂䝁䄰䅉灂䝁䅑児楁䑁䅅睎楁䑁䄴杍㕁䑁䅣免㍁䑁䅫䅐癁䙁䅁兙祂䝁䅅兢⭁䑁䅷䅕桂䡁䅉兙瑂䍁䅁兡歂䑁䄰杉硁䑁䅧杉⭁䑁䅑杍㉁䑁䅙兏畁䑁䅙李ㅁ䑁䅁杍硁䑁䅷睌兂䝁䅅杣桂䝁䄰材䅁䅁䅣䅁䵁䅁䅁䅖呂䙁䅧杏䵂䅁䅁䅃䅁䵁䉙䅁㡁䙁䅁兙祂䝁䅅兢杁䝁䅫䅚㥁䍁䅉兎楁䑁䄴免㡁䍁䄸䅕桂䡁䅉兙瑂䑁䄴䅐兂䝁䅅杣桂䝁䄰䅉灂䝁䅑児楁䑁䅅杉⭁䍁䄰免㑁䑁䅫免穁䑁䅫李㑁䑁䅕䅎㡁䍁䄸䅕桂䡁䅉兙瑂䑁䄴䅐兂䝁䅅杣桂䝁䄰䅉灂䝁䅑児楁䑁䅍杉⭁䑁䅉睎㡁䍁䄸䅕桂䡁䅉兙瑂䑁䄴䅐兂䝁䅅杣桂䝁䄰䅉灂䝁䅑児楁䑁䅉杉⭁䑁䅅䅍睁䑁䅁李睁䑁䅷睌兂䝁䅅杣桂䝁䄰材㡁䙁䅁兙祂䝁䅅兢杁䝁䅫䅚㥁䍁䅉䅎楁䑁䄴䅍㡁䍁䄸䅕桂䡁䅉兙瑂䑁䄴䅐兂䝁䅅杣桂䝁䄰䅉灂䝁䅑児楁䑁䅣杉⭁䑁䅙睌祁䑁䅉睌祁䑁䅁杍㉁䑁䅷睌兂䝁䅅杣桂䝁䄰材㡁䙁䅁兙祂䝁䅅兢杁䝁䅫䅚㥁䍁䅉免㍁䍁䅉材㑁䑁䅣睍㑁䑁䅁免㡁䍁䄸䅕桂䡁䅉兙瑂䑁䄴䅐兂䝁䅅杣桂䝁䄰䅉灂䝁䅑児楁䑁䅅䅏楁䑁䄴䅏㕁䑁䅑睍ㅁ䍁䄴李祁䑁䅕䅍ㅁ䑁䅅䅐癁䙁䅁兙祂䝁䅅兢⭁䅁䅁元䅁䅁䅷䅁啂䙁䅍䅗㙁䙁䅉䅁䭁䅁䅁杺䅅䑁䅷䅕桂䡁䅉兙瑂䍁䅁兡歂䑁䄰杉ㅁ䍁䅉材硁䑁䅷睌兂䝁䅅杣桂䝁䄰材㡁䙁䅁兙祂䝁䅅兢杁䝁䅫䅚㥁䍁䅉免楁䑁䄴兌硁䑁䅧兏祁䑁䅉䅎ぁ䑁䅧䅏穁䑁䅷睌兂䝁䅅杣桂䝁䄰材㡁䙁䅁兙祂䝁䅅兢杁䝁䅫䅚㥁䍁䅉睍楁䑁䄴杍㍁䑁䅷睌兂䝁䅅杣桂䝁䄰材㡁䙁䅁兙祂䝁䅅兢杁䝁䅫䅚㥁䍁䅉杍楁䑁䄴免睁䑁䅁䅍ㅁ䑁䅑䅐癁䙁䅁兙祂䝁䅅兢⭁䑁䅷䅕桂䡁䅉兙瑂䍁䅁兡歂䑁䄰杉ぁ䍁䅉材睁䑁䅷睌兂䝁䅅杣桂䝁䄰材㡁䙁䅁兙祂䝁䅅兢杁䝁䅫䅚㥁䍁䅉睎楁䑁䄴李癁䑁䅉杍癁䑁䅉䅍祁䑁䅙䅐癁䙁䅁兙祂䝁䅅兢⭁䑁䅷䅕桂䡁䅉兙瑂䍁䅁兡歂䑁䄰杉硁䑁䅣杉⭁䑁䅅䅍㉁䑁䅍睍ㅁ䑁䅷睌兂䝁䅅杣桂䝁䄰材㡁䙁䅁兙祂䝁䅅兢杁䝁䅫䅚㥁䍁䅉免㑁䍁䅉材㍁䑁䅫李祁䑁䅙杌硁䑁䅍睍㕁䑁䅑睍㍁䑁䅍李硁䑁䅷睌兂䝁䅅杣桂䝁䄰材䅁䍁䅫䅁䵁䅁䅁䅖呂䙁䅧杏䍂䅁䅁睃䅁䅁䅷䅁啂䙁䅍䅗㙁䙁䅁䅁䵁䅁䅁䅄䅁䙁䅑睕奂䑁䅯兓䅁䅁䄰䅁䝄允䅁䅐兂䝁䅅杣桂䝁䄰䅉灂䝁䅑児楁䑁䅕杉⭁䑁䅅䅐癁䙁䅁兙祂䝁䅅兢⭁䑁䅷䅕桂䡁䅉兙瑂䍁䅁兡歂䑁䄰杉硁䍁䅉材瑁䑁䅅䅏㑁䑁䅫睍ㅁ䑁䅉䅍ㅁ䑁䅣䅐癁䙁䅁兙祂䝁䅅兢⭁䑁䅷䅕桂䡁䅉兙瑂䍁䅁兡歂䑁䄰杉穁䍁䅉材祁䑁䅣䅐癁䙁䅁兙祂䝁䅅兢⭁䑁䅷䅕桂䡁䅉兙瑂䍁䅁兡歂䑁䄰杉祁䍁䅉材硁䑁䅁䅍睁䑁䅙䅍㡁䍁䄸䅕桂䡁䅉兙瑂䑁䄴䅐兂䝁䅅杣桂䝁䄰䅉灂䝁䅑児楁䑁䅑杉⭁䑁䅁䅐癁䙁䅁兙祂䝁䅅兢⭁䑁䅷䅕桂䡁䅉兙瑂䍁䅁兡歂䑁䄰杉㍁䍁䅉材㉁䍁䄸杍祁䍁䄸杍睁䑁䅉李㡁䍁䄸䅕桂䡁䅉兙瑂䑁䄴䅐兂䝁䅅杣桂䝁䄰䅉灂䝁䅑児楁䑁䅅睎楁䑁䄴杍穁䑁䅕免㑁䑁䅅李祁䑁䅷睌兂䝁䅅杣桂䝁䄰材㡁䙁䅁兙祂䝁䅅兢杁䝁䅫䅚㥁䍁䅉免㑁䍁䅉材硁䑁䅉䅏畁䑁䅙䅎ぁ䑁䅙免ㅁ䑁䅷睌兂䝁䅅杣桂䝁䄰材䅁䉁䅫䅁䍁䅁䅁䅁偁䅁䅁杸䅅䑁䅷䅕桂䡁䅉兙瑂䍁䅁兡歂䑁䄰杉ㅁ䍁䅉材硁䑁䅷睌兂䝁䅅杣桂䝁䄰材㡁䙁䅁兙祂䝁䅅兢杁䝁䅫䅚㥁䍁䅉免楁䑁䄴兌硁䑁䅧兏穁䑁䅁兎㉁䑁䅁䅏硁䑁䅷睌兂䝁䅅杣桂䝁䄰材㡁䙁䅁兙祂䝁䅅兢杁䝁䅫䅚㥁䍁䅉睍楁䑁䄴杍㍁䑁䅷睌兂䝁䅅杣桂䝁䄰材㡁䙁䅁兙祂䝁䅅兢杁䝁䅫䅚㥁䍁䅉杍楁䑁䄴免睁䑁䅁䅍ㅁ䑁䅑䅐癁䙁䅁兙祂䝁䅅兢⭁䑁䅷䅕桂䡁䅉兙瑂䍁䅁兡歂䑁䄰杉ぁ䍁䅉材睁䑁䅷睌兂䝁䅅杣桂䝁䄰材㡁䙁䅁兙祂䝁䅅兢杁䝁䅫䅚㥁䍁䅉睎楁䑁䄴李癁䑁䅉杍癁䑁䅉䅍祁䑁䅙䅐癁䙁䅁兙祂䝁䅅兢⭁䑁䅷䅕桂䡁䅉兙瑂䍁䅁兡歂䑁䄰杉硁䑁䅣杉⭁䑁䅉兏㍁䑁䅅睎㕁䑁䅷睌兂䝁䅅杣桂䝁䄰材㡁䙁䅁兙祂䝁䅅兢杁䝁䅫䅚㥁䍁䅉免㑁䍁䅉材ぁ䑁䅑䅎㕁䑁䅉杌ㅁ䑁䅅䅏ㅁ䑁䅫免㡁䍁䄸䅕桂䡁䅉兙瑂䑁䄴䅁允䅁䅁䅄䅁䙁䅑睕奂䑁䅯睒䅁䉁䅅䅁䵁䅁䅁䅖呂䙁䅧杏啂䅁䅁杅䅁䱁䈴䅁㡁䙁䅁兙祂䝁䅅兢杁䝁䅫䅚㥁䍁䅉兎楁䑁䄴免㡁䍁䄸䅕桂䡁䅉兙瑂䑁䄴䅐兂䝁䅅杣桂䝁䄰䅉灂䝁䅑児楁䑁䅅杉⭁䍁䄰免㑁䑁䅫䅍㍁䑁䅧杍㑁䑁䅑䅍㡁䍁䄸䅕桂䡁䅉兙瑂䑁䄴䅐兂䝁䅅杣桂䝁䄰䅉灂䝁䅑児楁䑁䅍杉⭁䑁䅉睎㡁䍁䄸䅕桂䡁䅉兙瑂䑁䄴䅐兂䝁䅅杣桂䝁䄰䅉灂䝁䅑児楁䑁䅉杉⭁䑁䅅䅍睁䑁䅁兎ぁ䑁䅷睌兂䝁䅅杣桂䝁䄰材㡁䙁䅁兙祂䝁䅅兢杁䝁䅫䅚㥁䍁䅉䅎楁䑁䄴䅍㡁䍁䄸䅕桂䡁䅉兙瑂䑁䄴䅐兂䝁䅅杣桂䝁䄰䅉灂䝁䅑児楁䑁䅣杉⭁䑁䅙睌祁䑁䅉睌祁䑁䅁杍㉁䑁䅷睌兂䝁䅅杣桂䝁䄰材㡁䙁䅁兙祂䝁䅅兢杁䝁䅫䅚㥁䍁䅉免㍁䍁䅉材ㅁ䑁䅫䅏㉁䑁䅧兏㡁䍁䄸䅕桂䡁䅉兙瑂䑁䄴䅐兂䝁䅅杣桂䝁䄰䅉灂䝁䅑児楁䑁䅅䅏楁䑁䄴杍ㅁ䑁䅉兏ぁ䍁䄴免㑁䑁䅷睌兂䝁䅅杣桂䝁䄰材䅁䉁䅍䅁佁䅁䅁䅖呂䙁䅧杏卂䙁䅫䅁啁䅁䅁䅹䅅䑁䅷䅕桂䡁䅉兙瑂䍁䅁兡歂䑁䄰杉ㅁ䍁䅉材硁䑁䅷睌兂䝁䅅杣桂䝁䄰材㡁䙁䅁兙祂䝁䅅兢杁䝁䅫䅚㥁䍁䅉免楁䑁䄴兌硁䑁䅧䅏㉁䑁䅉兎㉁䑁䅑李㕁䑁䅷睌兂䝁䅅杣桂䝁䄰材㡁䙁䅁兙祂䝁䅅兢杁䝁䅫䅚㥁䍁䅉睍楁䑁䄴杍㍁䑁䅷睌兂䝁䅅杣桂䝁䄰材㡁䙁䅁兙祂䝁䅅兢杁䝁䅫䅚㥁䍁䅉杍楁䑁䄴免睁䑁䅁䅍ㅁ䑁䅑䅐癁䙁䅁兙祂䝁䅅兢⭁䑁䅷䅕桂䡁䅉兙瑂䍁䅁兡歂䑁䄰杉ぁ䍁䅉材睁䑁䅷睌兂䝁䅅杣桂䝁䄰材㡁䙁䅁兙祂䝁䅅兢杁䝁䅫䅚㥁䍁䅉睎楁䑁䄴李癁䑁䅉杍癁䑁䅉䅍祁䑁䅙䅐癁䙁䅁兙祂䝁䅅兢⭁䑁䅷䅕桂䡁䅉兙瑂䍁䅁兡歂䑁䄰杉硁䑁䅣杉⭁䑁䅅䅍㕁䑁䅧䅍㕁䑁䅷睌兂䝁䅅杣桂䝁䄰材㡁䙁䅁兙祂䝁䅅兢杁䝁䅫䅚㥁䍁䅉免㑁䍁䅉材穁䑁䅫䅏ㅁ䑁䅣睎畁䑁䅅䅍㍁䑁䅫免㉁䑁䅷睌兂䝁䅅杣桂䝁䄰材䅁䉁䅕䅁䵁䅁䅁䅖呂䙁䅧杏偂䅁䅁杆䅁䱁䈴䅁㡁䙁䅁兙祂䝁䅅兢杁䝁䅫䅚㥁䍁䅉兎楁䑁䄴免㡁䍁䄸䅕桂䡁䅉兙瑂䑁䄴䅐兂䝁䅅杣桂䝁䄰䅉灂䝁䅑児楁䑁䅅杉⭁䍁䄰免㑁䑁䅫䅍㍁䑁䅧杍㑁䑁䅑䅍㡁䍁䄸䅕桂䡁䅉兙瑂䑁䄴䅐兂䝁䅅杣桂䝁䄰䅉灂䝁䅑児楁䑁䅍杉⭁䑁䅉睎㡁䍁䄸䅕桂䡁䅉兙瑂䑁䄴䅐兂䝁䅅杣桂䝁䄰䅉灂䝁䅑児楁䑁䅉杉⭁䑁䅅䅍睁䑁䅁李睁䑁䅷睌兂䝁䅅杣桂䝁䄰材㡁䙁䅁兙祂䝁䅅兢杁䝁䅫䅚㥁䍁䅉䅎楁䑁䄴䅍㡁䍁䄸䅕桂䡁䅉兙瑂䑁䄴䅐兂䝁䅅杣桂䝁䄰䅉灂䝁䅑児楁䑁䅣杉⭁䑁䅙睌祁䑁䅉睌祁䑁䅁杍㉁䑁䅷睌兂䝁䅅杣桂䝁䄰材㡁䙁䅁兙祂䝁䅅兢杁䝁䅫䅚㥁䍁䅉免㍁䍁䅉材ㅁ䑁䅫䅏㉁䑁䅧兏㡁䍁䄸䅕桂䡁䅉兙瑂䑁䄴䅐兂䝁䅅杣桂䝁䄰䅉灂䝁䅑児楁䑁䅅䅏楁䑁䄴兎ㅁ䑁䅫免㕁䍁䄴免㑁䑁䅷睌兂䝁䅅杣桂䝁䄰材䅁䉁䅣䅁䵁䅁䅁䅖呂䙁䅧杏䙂䅁䅁䅇䅁䅁䅷䅁啂䙁䅍䅗㙁䕁䄴䅁慁䅁䅁䅄䅁䙁䅑睕奂䑁䅯兔䅁䉁䅷䅁䵁䅁䅁䅖呂䙁䅧杏呂䅁䅁先䅁䵁䉁䅁㡁䙁䅁兙祂䝁䅅兢杁䝁䅫䅚㥁䍁䅉兎楁䑁䄴免㡁䍁䄸䅕桂䡁䅉兙瑂䑁䄴䅐兂䝁䅅杣桂䝁䄰䅉灂䝁䅑児楁䑁䅅杉⭁䍁䄰免㕁䑁䅁睎穁䑁䅅䅏硁䑁䅙杍㡁䍁䄸䅕桂䡁䅉兙瑂䑁䄴䅐兂䝁䅅杣桂䝁䄰䅉灂䝁䅑児楁䑁䅍杉⭁䑁䅉睎㡁䍁䄸䅕桂䡁䅉兙瑂䑁䄴䅐兂䝁䅅杣桂䝁䄰䅉灂䝁䅑児楁䑁䅉杉⭁䑁䅅䅍睁䑁䅁兎ぁ䑁䅷睌兂䝁䅅杣桂䝁䄰材㡁䙁䅁兙祂䝁䅅兢杁䝁䅫䅚㥁䍁䅉䅎楁䑁䄴䅍㡁䍁䄸䅕桂䡁䅉兙瑂䑁䄴䅐兂䝁䅅杣桂䝁䄰䅉灂䝁䅑児楁䑁䅣杉⭁䑁䅕睌硁䑁䅫睌祁䑁䅁杍㉁䑁䅷睌兂䝁䅅杣桂䝁䄰材㡁䙁䅁兙祂䝁䅅兢杁䝁䅫䅚㥁䍁䅉免㍁䍁䅉材㑁䑁䅧䅍穁䑁䅫睍㡁䍁䄸䅕桂䡁䅉兙瑂䑁䄴䅐兂䝁䅅杣桂䝁䄰䅉灂䝁䅑児楁䑁䅅䅏楁䑁䄴䅏ぁ䍁䄴䅎㍁䑁䅙䅍㕁䑁䅅䅐癁䙁䅁兙祂䝁䅅兢⭁䅁䅁杈䅁䵁䉁䅁㡁䙁䅁兙祂䝁䅅兢杁䝁䅫䅚㥁䍁䅉兎楁䑁䄴免㡁䍁䄸䅕桂䡁䅉兙瑂䑁䄴䅐兂䝁䅅杣桂䝁䄰䅉灂䝁䅑児楁䑁䅅杉⭁䍁䄰免㕁䑁䅁睎穁䑁䅅䅏硁䑁䅙杍㡁䍁䄸䅕桂䡁䅉兙瑂䑁䄴䅐兂䝁䅅杣桂䝁䄰䅉灂䝁䅑児楁䑁䅍杉⭁䑁䅉睎㡁䍁䄸䅕桂䡁䅉兙瑂䑁䄴䅐兂䝁䅅杣桂䝁䄰䅉灂䝁䅑児楁䑁䅉杉⭁䑁䅅䅍睁䑁䅁李睁䑁䅷睌兂䝁䅅杣桂䝁䄰材㡁䙁䅁兙祂䝁䅅兢杁䝁䅫䅚㥁䍁䅉䅎楁䑁䄴䅍㡁䍁䄸䅕桂䡁䅉兙瑂䑁䄴䅐兂䝁䅅杣桂䝁䄰䅉灂䝁䅑児楁䑁䅣杉⭁䑁䅕睌硁䑁䅫睌祁䑁䅁杍㉁䑁䅷睌兂䝁䅅杣桂䝁䄰材㡁䙁䅁兙祂䝁䅅兢杁䝁䅫䅚㥁䍁䅉免㍁䍁䅉材㑁䑁䅧䅍穁䑁䅫睍㡁䍁䄸䅕桂䡁䅉兙瑂䑁䄴䅐兂䝁䅅杣桂䝁䄰䅉灂䝁䅑児楁䑁䅅䅏楁䑁䄴杍㑁䑁䅑杌穁䑁䅣李睁䑁䅫䅐癁䙁䅁兙祂䝁䅅兢⭁䅁䅁䅉䅁䅁䅷䅁啂䙁䅍䅗㙁䕁䅧䅁桁䅁䅁䅹䅅䑁䅷䅕桂䡁䅉兙瑂䍁䅁兡歂䑁䄰杉ㅁ䍁䅉材硁䑁䅷睌兂䝁䅅杣桂䝁䄰材㡁䙁䅁兙祂䝁䅅兢杁䝁䅫䅚㥁䍁䅉免楁䑁䄴兌硁䑁䅧䅏㕁䑁䅧䅍睁䑁䅉睎穁䑁䅷睌兂䝁䅅杣桂䝁䄰材㡁䙁䅁兙祂䝁䅅兢杁䝁䅫䅚㥁䍁䅉睍楁䑁䄴杍㍁䑁䅷睌兂䝁䅅杣桂䝁䄰材㡁䙁䅁兙祂䝁䅅兢杁䝁䅫䅚㥁䍁䅉杍楁䑁䄴免睁䑁䅁䅍ㅁ䑁䅑䅐癁䙁䅁兙祂䝁䅅兢⭁䑁䅷䅕桂䡁䅉兙瑂䍁䅁兡歂䑁䄰杉ぁ䍁䅉材睁䑁䅷睌兂䝁䅅杣桂䝁䄰材㡁䙁䅁兙祂䝁䅅兢杁䝁䅫䅚㥁䍁䅉睎楁䑁䄴李癁䑁䅉杍癁䑁䅉䅍祁䑁䅙䅐癁䙁䅁兙祂䝁䅅兢⭁䑁䅷䅕桂䡁䅉兙瑂䍁䅁兡歂䑁䄰杉硁䑁䅣杉⭁䑁䅉䅎睁䑁䅕䅎㑁䑁䅫䅐癁䙁䅁兙祂䝁䅅兢⭁䑁䅷䅕桂䡁䅉兙瑂䍁䅁兡歂䑁䄰杉硁䑁䅧杉⭁䑁䅍睍㕁䑁䅫兎畁䑁䅑睍㕁䑁䅕睍穁䑁䅷睌兂䝁䅅杣桂䝁䄰材䅁䍁䅉䅁䥄允䅁䅐兂䝁䅅杣桂䝁䄰䅉灂䝁䅑児楁䑁䅕杉⭁䑁䅅䅐癁䙁䅁兙祂䝁䅅兢⭁䑁䅷䅕桂䡁䅉兙瑂䍁䅁兡歂䑁䄰杉硁䍁䅉材瑁䑁䅅䅏㑁䑁䅫䅏睁䑁䅁杍㍁䑁䅍䅐癁䙁䅁兙祂䝁䅅兢⭁䑁䅷䅕桂䡁䅉兙瑂䍁䅁兡歂䑁䄰杉穁䍁䅉材祁䑁䅣䅐癁䙁䅁兙祂䝁䅅兢⭁䑁䅷䅕桂䡁䅉兙瑂䍁䅁兡歂䑁䄰杉祁䍁䅉材硁䑁䅁䅍睁䑁䅙䅍㡁䍁䄸䅕桂䡁䅉兙瑂䑁䄴䅐兂䝁䅅杣桂䝁䄰䅉灂䝁䅑児楁䑁䅑杉⭁䑁䅁䅐癁䙁䅁兙祂䝁䅅兢⭁䑁䅷䅕桂䡁䅉兙瑂䍁䅁兡歂䑁䄰杉㍁䍁䅉材㉁䍁䄸杍祁䍁䄸杍睁䑁䅉李㡁䍁䄸䅕桂䡁䅉兙瑂䑁䄴䅐兂䝁䅅杣桂䝁䄰䅉灂䝁䅑児楁䑁䅅睎楁䑁䄴杍ぁ䑁䅁兎ぁ䑁䅧兏㡁䍁䄸䅕桂䡁䅉兙瑂䑁䄴䅐兂䝁䅅杣桂䝁䄰䅉灂䝁䅑児楁䑁䅅䅏楁䑁䄴兎穁䑁䅉䅎睁䍁䄴䅎穁䑁䅫兎穁䑁䅍䅐癁䙁䅁兙祂䝁䅅兢⭁䅁䅁睉䅁䵁䉙䅁㡁䙁䅁兙祂䝁䅅兢杁䝁䅫䅚㥁䍁䅉兎楁䑁䄴免㡁䍁䄸䅕桂䡁䅉兙瑂䑁䄴䅐兂䝁䅅杣桂䝁䄰䅉灂䝁䅑児楁䑁䅅杉⭁䍁䄰免㑁䑁䅧兏穁䑁䅕杍睁䑁䅕睎㡁䍁䄸䅕桂䡁䅉兙瑂䑁䄴䅐兂䝁䅅杣桂䝁䄰䅉灂䝁䅑児楁䑁䅍杉⭁䑁䅉睎㡁䍁䄸䅕桂䡁䅉兙瑂䑁䄴䅐兂䝁䅅杣桂䝁䄰䅉灂䝁䅑児楁䑁䅉杉⭁䑁䅅䅍睁䑁䅁兎ぁ䑁䅷睌兂䝁䅅杣桂䝁䄰材㡁䙁䅁兙祂䝁䅅兢杁䝁䅫䅚㥁䍁䅉䅎楁䑁䄴䅍㡁䍁䄸䅕桂䡁䅉兙瑂䑁䄴䅐兂䝁䅅杣桂䝁䄰䅉灂䝁䅑児楁䑁䅣杉⭁䑁䅙睌祁䑁䅉睌祁䑁䅁杍㉁䑁䅷睌兂䝁䅅杣桂䝁䄰材㡁䙁䅁兙祂䝁䅅兢杁䝁䅫䅚㥁䍁䅉免㍁䍁䅉材祁䑁䅍兎硁䑁䅧免㉁䑁䅉䅐癁䙁䅁兙祂䝁䅅兢⭁䑁䅷䅕桂䡁䅉兙瑂䍁䅁兡歂䑁䄰杉硁䑁䅧杉⭁䑁䅅免ぁ䍁䄴兎睁䑁䅧睎ぁ䑁䅕䅐癁䙁䅁兙祂䝁䅅兢⭁䅁䅁䅊䅁䅁䅷䅁啂䙁䅍䅗㙁䙁䅅䅁汁䅁䅁䅄䅁䙁䅑睕奂䑁䅯杒䅁䍁䅙䅁佄允䅁䅐兂䝁䅅杣桂䝁䄰䅉灂䝁䅑児楁䑁䅕杉⭁䑁䅅䅐癁䙁䅁兙祂䝁䅅兢⭁䑁䅷䅕桂䡁䅉兙瑂䍁䅁兡歂䑁䄰杉硁䍁䅉材瑁䑁䅅䅏㕁䑁䅉杍ぁ䑁䅑䅏㑁䑁䅍䅐癁䙁䅁兙祂䝁䅅兢⭁䑁䅷䅕桂䡁䅉兙瑂䍁䅁兡歂䑁䄰杉穁䍁䅉材祁䑁䅣䅐癁䙁䅁兙祂䝁䅅兢⭁䑁䅷䅕桂䡁䅉兙瑂䍁䅁兡歂䑁䄰杉祁䍁䅉材硁䑁䅁䅍睁䑁䅙䅍㡁䍁䄸䅕桂䡁䅉兙瑂䑁䄴䅐兂䝁䅅杣桂䝁䄰䅉灂䝁䅑児楁䑁䅑杉⭁䑁䅁䅐癁䙁䅁兙祂䝁䅅兢⭁䑁䅷䅕桂䡁䅉兙瑂䍁䅁兡歂䑁䄰杉㍁䍁䅉材㉁䍁䄸杍祁䍁䄸杍睁䑁䅉李㡁䍁䄸䅕桂䡁䅉兙瑂䑁䄴䅐兂䝁䅅杣桂䝁䄰䅉灂䝁䅑児楁䑁䅅睎楁䑁䄴免睁䑁䅙睍穁䑁䅕䅐癁䙁䅁兙祂䝁䅅兢⭁䑁䅷䅕桂䡁䅉兙瑂䍁䅁兡歂䑁䄰杉硁䑁䅧杉⭁䑁䅉睎ぁ䑁䅣睍睁䍁䄴杍祁䑁䅣䅎穁䑁䅍睎穁䑁䅙䅐癁䙁䅁兙祂䝁䅅兢⭁䅁䅁睊䅁䅁䅷䅁啂䙁䅍䅗㙁䕁䅑䅁潁䅁䅁䅁䅁䅁㴽

Sheet Instructions
A1: Executive Compensation Benchmarking Methodology
A3: Effective Date | B3: 44992 | D3: Remember: | E3: • NEO order
A4: Last Revised | B4: 44992 | E4: • Currency
E5: • Incumbents serving for partial years
E6: • Date of fiscal year end
B9: Purpose
B10: Establish guidelines for executive compensation benchmarking in order to maintain consistency across client projects and teams, improve ease of training, and increase the efficiency of the benchmarking exercise
B12: Policy
B13: Roles
B14: · Record each person’s entire name and role as disclosed in the proxy
B15: o Ignore “director” roles (i.e. assume that the CEO is on the Board of directors)
B16: · Capture Executive Chairman role if it is one of the top 5 NEOs, but do not use as a comparison to any of the NEOs, unless indicated by client team
B17: o Footnote and confirm with client team
B19: Base Salary
B20: · Record the base salary in the Summary Compensation Table
B21: · If the incumbent has partial years of service, annualize the base salary
B22: · If the upcoming year’s salary is disclosed, record it in column O; it will be used in lieu of data aging
... B132: · Assume that the peer reviewer has made all of the necessary changes to the raw data sheet

Sheet Import 2024 Data
B3: x | C3: Lookup | D3: Role match | E3: Company | F3: Title | G3: Incumbent | H3: Actual TDC | I3: Target TDC
C4: TSX:HBM_2024_CEO | D4: CEO | E4: Hudbay Minerals Inc. | F4: President & CEO | G4: Peter Kukielski | H4: 5600057 | I4: 5457572.2
C5: TSX:HBM_2024_COO | D5: COO | E5: Hudbay Minerals Inc. | F5: COO | G5: Andre Lauzon | H5: 2604993 | I5: 2503127
C6: TSX:HBM_2024_CFO | D6: CFO | E6: Hudbay Minerals Inc. | F6: CFO | G6: Eugene Lei | H6: 2350784 | I6: 2300974.6
C7: TSX:HBM_2024_Legal | D7: Legal | E7: Hudbay Minerals Inc. | F7: SVP, Legal and Organizational Effectiveness | G7: Patrick Donnelly | H7: 1919023 | I7: 1837927.8
C8: TSX:HBM_2024_Region2 | D8: Region2 | E8: Hudbay Minerals Inc. | F8: SVP, US Business Unit | G8: Javier Del Rio | H8: 2212298.2 | I8: 1818959.7
C9: TSX:HBM_2024_Tech | D9: Tech | E9: Hudbay Minerals Inc. | F9: SVP, Exploration and Technical Services | G9: Olivier Tavchandjian | H9: 465850 | I9: 1304380
C10: TSX:HBM_2024_Region | D10: Region | E10: Hudbay Minerals Inc. | F10: SVP, Canada | G10: Rob Carter | H10: 453500 | I10: 1269800
C14: TSX:K_2024_CEO | D14: CEO | E14: Kinross Gold Corporation | F14: CEO | G14: J. Paul Rollinson | H14: 9344.8458 | I14: 8698.6526
C15: TSX:LUN_2024_CEO | D15: CEO | E15: Lundin Mining Corporation | F15: President & CEO | G15: Jack Lundin | H15: 5366.5489 | I15: 4420
C16: TSX:AGI_2024_CEO | D16: CEO | E16: Alamos Gold Inc. | F16: CEO | G16: John A. McCluskey | H16: 6013.0529 | I16: 5375
C17: TSX:PAAS_2024_CEO | D17: CEO | E17: Pan American Silver Corp. | F17: CEO | G17: Michael Steinmann | H17: 7737.93 | I17: 7690.8
C18: TSX:CS_2024_CEO | D18: CEO | E18: Capstone Copper Corp. | F18: CEO | G18: John MacKenzie | H18: 4278.72 | I18: 4416
... C61: TSX:CG_2024_COO | D61: COO | E61: Centerra Gold Inc. | F61: EVP, COO | G61: Paul Chawrun | H61: 1944.8 | I61: 1980

Sheet Raw Data
D2: INPUTS
AP3: Check with client team 1) whether this benchmarking is necessary and 2) how to treat pension & other in the output tables (i.e., actual, 3-year average)
D4: Peer Ticker(s) | G4: Date | H4: 45852
D5: 1 | E5: TSX:K | G5: Currency | H5: CAD
D6: 2 | E6: TSX:LUN | G6: Client Ticker | H6: TSX:HBM
D7: 3 | E7: TSX:PAAS
D8: 4 | E8: TSX:BTO | G8: CAD/USD
D9: 5 | E9: TSX:IMG | G9: 2025 | H9: =_xll.ciqfunctions.udf.CIQAVG("$CADUSD", "IQ_LASTSALEPRICE", "1/1/"&$G9, "31/12/"&$G9) -> 1.39745
D10: 6 | E10: TSX:CS | G10: =G9-1 -> 2024 | H10: =_xll.ciqfunctions.udf.CIQAVG("$CADUSD", "IQ_LASTSALEPRICE", "1/1/"&$G10, "31/12/"&$G10) -> 1.37017
D11: 7 | E11: TSX:SSRM | G11: =G10-1 -> 2023 | H11: =_xll.ciqfunctions.udf.CIQAVG("$CADUSD", "IQ_LASTSALEPRICE", "1/1/"&$G11, "31/12/"&$G11) -> 1.34954
D12: 8 | E12: TSX:OGC
D13: 9 | E13: TSX:ELD | G13: Data Aging: | H13: 0.03
D14: 10 | E14: TSX:AGI
D15: 11 | E15: NYSE:HL
D16: 12 | E16: TSX:CG
D17: 13 | E17: TSX:FM
D18: 14 | E18: TSX:CDE
D19: 15 | E19: TSX:EQX
D20: 16
D21: 17
D22: 18
D23: 19
D24: 20
D25: 21
D26: 22
D27: 23
D28: 24
Q30: Base Salary | U30: STIP | AA30: Total Cash Compensation | AC30: Long-Term Incentives | AN30: Total Direct Compensation | AP30: Pension & Other | AW30: Total Compensation
A31: Look-Up2 | B31: Look-Up | C31: Look-Up3 | D31: Ticker | E31: Company | F31: Year | G31: Incumbent Start Month | H31: End Month (Typically FYE) | I31: Months | J31: Currency of Disclosure | K31: FX Rate | L31: Role Match | M31: Role Match 2 | N31: Position Match | O31: Position Title | P31: Incumbent | Q31: Actual Paid | R31: Annualized / Converted | S31: Latest (if disclosed) | T31: Latest (if disclosed) - Annualized / Converted | U31: Actual $ | V31: Annualized/ Converted | W31: Actual STI % | X31: 3 Year Average STIP % | Y31: Target STI % | Z31: Target STI $ | AA31: Actual TCC | AB31: Target TCC | AC31: RSUs | AD31: PSUs | AE31: Stock Options | AF31: DSUs | AG31: LT Cash | AH31: Total LTI $ | AI31: Total LTI % | AJ31: 3 Year Average LTIP % | AK31: Target LTI % | AL31: Target LTI $ | AM31: Total LTI (Converted) | AN31: Actual (base + actual bonus + actual LTIP) | AO31: Target (base + target bonus + Target LTIP) | AP31: Pension | AQ31: DB or DC Pension? | AR31: Pension Converted | AS31: Pension 3 Year Average | AT31: Other | AU31: Other Converted | AV31: Other 3 Year Average | AW31: Actual (Actual TDC + Pension + Other) | AX31: Target (Target TDC + Pension + Other) | AY31: Incumbent Specific Notes: | AZ31: Data Recorder | BA31: Peer Reviewer | BB31: Flags
A32: =$D32&"_"&$F32&"_"&$L32 -> TSX:HBM_2025_ | B32: =$D32&"_"&$F32&"_"&$N32 -> TSX:HBM_2025_CEO | C32: =$D32&"_"&$F32&"_"&$M32 -> TSX:HBM_2025_ | D32: =H6 -> TSX:HBM | E32: =_xll.ciqfunctions.udf.CIQ(D32,"IQ_Company_Name") -> Hudbay Minerals Inc. | F32: 2025 | G32: =F32&"-01-01" -> 2025-01-01 | H32: =F32&"-12-31" -> 2025-12-31 | I32: =_xlfn.DAYS(H32,G32)/_xlfn.DAYS(F32&"-12-31",F32&"-01-01")*12 -> 12 | J32: CAD | K32: =IF($J32="CAD",1,IF($J32="USD",VLOOKUP($F32,$G$9:$H$11,2,FALSE),"N/A")) -> 1 | N32: CEO | O32: President & CEO | P32: Peter Kukielski | Q32: 1047525 | R32: 1099901 | S32: 1099901 | T32: =IFERROR(IF((S32*$K32)=0,"-",(S32*$K32)),"-") -> 1099901 | U32: 1615284 | V32: =IFERROR(U32*(12/$I32)*$K32,"-") -> 1615284 | W32: =IFERROR($V32/$R32,"-") -> 1.4685722 | X32: =IFERROR(AVERAGE(W32:W34),"N/A") -> 1.5031237 | Y32: 1.2 | Z32: =IFERROR(IF(ISNUMBER($Y32)=TRUE, $Y32*$R32,$X32*$R32),"-") -> 1319881.2 | AA32: =IFERROR(IF(SUM(R32,V32)=0,"-",SUM(R32,V32)),"-") -> 2715185 | AB32: =IFERROR(IF(SUM(R32,Z32)=0,"-",SUM(R32,Z32)),"-") -> 2419782.2 | AC32: =1/3*2081956 -> 693985.33 | AD32: =2/3*2081956 -> 1387970.7 | AE32: 693985 | AF32: - | AG32: - | AH32: =IFERROR(IF(SUM(AC32:AG32)=0,IF(COUNTIF($AA32:$AE32,"=0")>0,"$0","-"),SUM(AC32:AG32)),"-") -> 2775941 | AI32: =IFERROR($AK32/$P32,"-") -> - | AJ32: =IFERROR(AVERAGE(AI32:AI34),"N/A") -> N/A | AK32: 2.65 | AL32: =IFERROR(IF(ISNUMBER($AK32)=TRUE, $AK32*$R32, $AJ32*$R32), "-") -> 2914737.6 | AM32: =IFERROR($AH32*$K32,"-") -> 2775941 | AN32: =IFERROR(IF(SUM(AA32,AM32)=0,"-",SUM(AA32,AM32)),"-") -> 5491126 | AO32: =IFERROR(IF(SUM($AB32,$AL32)=0,"-",SUM($AB32,$AL32)),"-") -> 5334519.8 | AP32: 91893 | AQ32: DC | AR32: =IFERROR(AP32*(12/$I32)*$K32,"-") -> 91893 | AS32: =IFERROR(AVERAGE(AR32:AR34),"N/A") -> 110427.67 | AT32: 204272 | AU32: =IFERROR(AT32*(12/$H32)*$J32,"-") -> - | AV32: =IFERROR(AVERAGE(AU32:AU34),"N/A") -> N/A | AW32: =IFERROR(IF(SUM(AN32,AR32,AU32)=0,"-",SUM(AN32,AR32,AU32)),"-") -> 5583019 | AX32: =IFERROR(IF(SUM(AO32,AR32,AU32)=0,"-",SUM(AO32,AR32,AU32)),"-") -> 5426412.8 | AY32: - | AZ32: KP | BA32: sc
A33: =$D33&"_"&$F33&"_"&$L33 -> TSX:HBM_2024_ | B33: =$D33&"_"&$F33&"_"&$N33 -> TSX:HBM_2024_CEO | C33: =$D33&"_"&$F33&"_"&$M33 -> TSX:HBM_2024_ | D33: =D32 -> TSX:HBM | E33: =_xll.ciqfunctions.udf.CIQ(D33,"IQ_Company_Name") -> Hudbay Minerals Inc. | F33: 2024 | G33: =F33&"-01-01" -> 2024-01-01 | H33: =F33&"-12-31" -> 2024-12-31 | I33: =_xlfn.DAYS(H33,G33)/_xlfn.DAYS(F33&"-12-31",F33&"-01-01")*12 -> 12 | J33: CAD | K33: =IF($J33="CAD",1,IF($J33="USD",VLOOKUP($F33,$G$9:$H$11,2,FALSE),"N/A")) -> 1 | N33: =N32 -> CEO | O33: =O32 -> President & CEO | P33: =P32 -> Peter Kukielski | Q33: 1017015 | R33: =IFERROR(Q33*(12/$I33)*$K33,"-") -> 1017015 | S33: - | T33: =IFERROR(IF((S33*$K33)=0,"-",(S33*$K33)),"-") -> - | U33: 1632919 | V33: =IFERROR(U33*(12/$I33)*$K33,"-") -> 1632919 | W33: =IFERROR($V33/$R33,"-") -> 1.6055997 | Y33: - | Z33: =IFERROR(IF(ISNUMBER($Y33)=TRUE, $Y33*$R33,$X33*$R33),"-") -> 0 | AA33: =IFERROR(IF(SUM(R33,V33)=0,"-",SUM(R33,V33)),"-") -> 2649934 | AB33: =IFERROR(IF(SUM(R33,Z33)=0,"-",SUM(R33,Z33)),"-") -> 1017015 | AC33: =1/3*1906903 -> 635634.33 | AD33: =2/3*1906903 -> 1271268.7 | AE33: 635634 | AF33: - | AG33: - | AH33: =IFERROR(IF(SUM(AC33:AG33)=0,IF(COUNTIF($AA33:$AE33,"=0")>0,"$0","-"),SUM(AC33:AG33)),"-") -> 2542537 | AI33: =IFERROR($AK33/$P33,"-") -> - | AK33: - | AL33: =IFERROR(IF(ISNUMBER($AK33)=TRUE, $AK33*$R33, $AJ33*$R33), "-") -> 0 | AM33: =IFERROR($AH33*$K33,"-") -> 2542537 | AN33: =IFERROR(IF(SUM(AA33,AM33)=0,"-",SUM(AA33,AM33)),"-") -> 5192471 | AO33: =IFERROR(IF(SUM($AB33,$AL33)=0,"-",SUM($AB33,$AL33)),"-") -> 1017015 | AP33: 122042 | AQ33: DC | AR33: =IFERROR(AP33*(12/$I33)*$K33,"-") -> 122042 | AT33: 255034 | AU33: =IFERROR(AT33*(12/$H33)*$J33,"-") -> - | AW33: =IFERROR(IF(SUM(AN33,AR33,AU33)=0,"-",SUM(AN33,AR33,AU33)),"-") -> 5314513 | AX33: =IFERROR(IF(SUM(AO33,AR33,AU33)=0,"-",SUM(AO33,AR33,AU33)),"-") -> 1139057 | AY33: - | AZ33: KP | BA33: sc
A34: =$D34&"_"&$F34&"_"&$L34 -> TSX:HBM_2023_ | B34: =$D34&"_"&$F34&"_"&$N34 -> TSX:HBM_2023_CEO | C34: =$D34&"_"&$F34&"_"&$M34 -> TSX:HBM_2023_ | D34: =D33 -> TSX:HBM | E34: =_xll.ciqfunctions.udf.CIQ(D34,"IQ_Company_Name") -> Hudbay Minerals Inc. | F34: 2023 | G34: =F34&"-01-01" -> 2023-01-01 | H34: =F34&"-12-31" -> 2023-12-31 | I34: =_xlfn.DAYS(H34,G34)/_xlfn.DAYS(F34&"-12-31",F34&"-01-01")*12 -> 12 | J34: CAD | K34: =IF($J34="CAD",1,IF($J34="USD",VLOOKUP($F34,$G$9:$H$11,2,FALSE),"N/A")) -> 1 | N34: =N33 -> CEO | O34: =O33 -> President & CEO | P34: =P33 -> Peter Kukielski | Q34: 977899 | R34: =IFERROR(Q34*(12/$I34)*$K34,"-") -> 977899 | S34: - | T34: =IFERROR(IF((S34*$K34)=0,"-",(S34*$K34)),"-") -> - | U34: 1403480 | V34: =IFERROR(U34*(12/$I34)*$K34,"-") -> 1403480 | W34: =IFERROR($V34/$R34,"-") -> 1.4351993 | Y34: - | Z34: =IFERROR(IF(ISNUMBER($Y34)=TRUE, $Y34*$R34,$X34*$R34),"-") -> 0 | AA34: =IFERROR(IF(SUM(R34,V34)=0,"-",SUM(R34,V34)),"-") -> 2381379 | AB34: =IFERROR(IF(SUM(R34,Z34)=0,"-",SUM(R34,Z34)),"-") -> 977899 | AC34: =1/3*1833560 -> 611186.67 | AD34: =2/3*1833560 -> 1222373.3 | AE34: 611187 | AF34: - | AG34: - | AH34: =IFERROR(IF(SUM(AC34:AG34)=0,IF(COUNTIF($AA34:$AE34,"=0")>0,"$0","-"),SUM(AC34:AG34)),"-") -> 2444747 | AI34: =IFERROR($AK34/$P34,"-") -> - | AK34: - | AL34: =IFERROR(IF(ISNUMBER($AK34)=TRUE, $AK34*$R34, $AJ34*$R34), "-") -> 0 | AM34: =IFERROR($AH34*$K34,"-") -> 2444747 | AN34: =IFERROR(IF(SUM(AA34,AM34)=0,"-",SUM(AA34,AM34)),"-") -> 4826126 | AO34: =IFERROR(IF(SUM($AB34,$AL34)=0,"-",SUM($AB34,$AL34)),"-") -> 977899 | AP34: 117348 | AQ34: DC | AR34: =IFERROR(AP34*(12/$I34)*$K34,"-") -> 117348 | AT34: 275237 | AU34: =IFERROR(AT34*(12/$H34)*$J34,"-") -> - | AW34: =IFERROR(IF(SUM(AN34,AR34,AU34)=0,"-",SUM(AN34,AR34,AU34)),"-") -> 4943474 | AX34: =IFERROR(IF(SUM(AO34,AR34,AU34)=0,"-",SUM(AO34,AR34,AU34)),"-") -> 1095247 | AY34: - | AZ34: KP | BA34: sc
A35: =$D35&"_"&$F35&"_"&$L35 -> TSX:HBM_2025_COO | B35: =$D35&"_"&$F35&"_"&$N35 -> TSX:HBM_2025_NEO1 | C35: =$D35&"_"&$F35&"_"&$M35 -> TSX:HBM_2025_2nd Highest | D35: =D34 -> TSX:HBM | E35: =_xll.ciqfunctions.udf.CIQ(D35,"IQ_Company_Name") -> Hudbay Minerals Inc. | F35: =F32 -> 2025 | G35: =F35&"-01-01" -> 2025-01-01 | H35: =F35&"-12-31" -> 2025-12-31 | I35: =_xlfn.DAYS(H35,G35)/_xlfn.DAYS(F35&"-12-31",F35&"-01-01")*12 -> 12 | J35: CAD | K35: =IF($J35="CAD",1,IF($J35="USD",VLOOKUP($F35,$G$9:$H$11,2,FALSE),"N/A")) -> 1 | L35: COO | M35: 2nd Highest | N35: NEO1 | O35: COO | P35: Andre Lauzon | Q35: 651000 | R35: 696570 | S35: 696570 | T35: =IFERROR(IF((S35*$K35)=0,"-",(S35*$K35)),"-") -> 696570 | U35: 749952 | V35: =IFERROR(U35*(12/$I35)*$K35,"-") -> 749952 | W35: =IFERROR($V35/$R35,"-") -> 1.0766355 | X35: =IFERROR(AVERAGE(W35:W37),"N/A") -> 1.1211787 | Y35: 0.9 | Z35: =IFERROR(IF(ISNUMBER($Y35)=TRUE, $Y35*$R35,$X35*$R35),"-") -> 626913 | AA35: =IFERROR(IF(SUM(R35,V35)=0,"-",SUM(R35,V35)),"-") -> 1446522 | AB35: =IFERROR(IF(SUM(R35,Z35)=0,"-",SUM(R35,Z35)),"-") -> 1323483 | AC35: =1/3*830025 -> 276675 | AD35: =2/3*830025 -> 553350 | AE35: 276675 | AF35: - | AG35: - | AH35: =IFERROR(IF(SUM(AC35:AG35)=0,IF(COUNTIF($AA35:$AE35,"=0")>0,"$0","-"),SUM(AC35:AG35)),"-") -> 1106700 | AI35: =IFERROR($AK35/$P35,"-") -> - | AJ35: =IFERROR(AVERAGE(AI35:AI37),"N/A") -> N/A | AK35: 1.8 | AL35: =IFERROR(IF(ISNUMBER($AK35)=TRUE, $AK35*$R35, $AJ35*$R35), "-") -> 1253826 | AM35: =IFERROR($AH35*$K35,"-") -> 1106700 | AN35: =IFERROR(IF(SUM(AA35,AM35)=0,"-",SUM(AA35,AM35)),"-") -> 2553222 | AO35: =IFERROR(IF(SUM($AB35,$AL35)=0,"-",SUM($AB35,$AL35)),"-") -> 2577309 | AP35: 44310 | AQ35: DC | AR35: =IFERROR(AP35*(12/$I35)*$K35,"-") -> 44310 | AS35: =IFERROR(AVERAGE(AR35:AR37),"N/A") -> 61826 | AT35: 97046 | AU35: =IFERROR(AT35*(12/$H35)*$J35,"-") -> - | AV35: =IFERROR(AVERAGE(AU35:AU37),"N/A") -> N/A | AW35: =IFERROR(IF(SUM(AN35,AR35,AU35)=0,"-",SUM(AN35,AR35,AU35)),"-") -> 2597532 | AX35: =IFERROR(IF(SUM(AO35,AR35,AU35)=0,"-",SUM(AO35,AR35,AU35)),"-") -> 2621619 | AY35: - | AZ35: KP | BA35: sc
A36: =$D36&"_"&$F36&"_"&$L36 -> TSX:HBM_2024_COO | B36: =$D36&"_"&$F36&"_"&$N36 -> TSX:HBM_2024_NEO1 | C36: =$D36&"_"&$F36&"_"&$M36 -> TSX:HBM_2024_ | D36: =D35 -> TSX:HBM | E36: =_xll.ciqfunctions.udf.CIQ(D36,"IQ_Company_Name") -> Hudbay Minerals Inc. | F36: =F33 -> 2024 | G36: =F36&"-01-01" -> 2024-01-01 | H36: =F36&"-12-31" -> 2024-12-31 | I36: =_xlfn.DAYS(H36,G36)/_xlfn.DAYS(F36&"-12-31",F36&"-01-01")*12 -> 12 | J36: CAD | K36: =IF($J36="CAD",1,IF($J36="USD",VLOOKUP($F36,$G$9:$H$11,2,FALSE),"N/A")) -> 1 | L36: COO | N36: =N35 -> NEO1 | O36: =O35 -> COO | P36: =P35 -> Andre Lauzon | Q36: 620000 | R36: =IFERROR(Q36*(12/$I36)*$K36,"-") -> 620000 | S36: - | T36: =IFERROR(IF((S36*$K36)=0,"-",(S36*$K36)),"-") -> - | U36: 740466 | V36: =IFERROR(U36*(12/$I36)*$K36,"-") -> 740466 | W36: =IFERROR($V36/$R36,"-") -> 1.1943 | Y36: - | Z36: =IFERROR(IF(ISNUMBER($Y36)=TRUE, $Y36*$R36,$X36*$R36),"-") -> 0 | AA36: =IFERROR(IF(SUM(R36,V36)=0,"-",SUM(R36,V36)),"-") -> 1360466 | AB36: =IFERROR(IF(SUM(R36,Z36)=0,"-",SUM(R36,Z36)),"-") -> 620000 | AC36: =1/3*790500 -> 263500 | AD36: =2/3*790500 -> 527000 | AE36: 263500 | AF36: - | AG36: - | AH36: =IFERROR(IF(SUM(AC36:AG36)=0,IF(COUNTIF($AA36:$AE36,"=0")>0,"$0","-"),SUM(AC36:AG36)),"-") -> 1054000 | AI36: =IFERROR($AK36/$P36,"-") -> - | AK36: - | AL36: =IFERROR(IF(ISNUMBER($AK36)=TRUE, $AK36*$R36, $AJ36*$R36), "-") -> 0 | AM36: =IFERROR($AH36*$K36,"-") -> 1054000 | AN36: =IFERROR(IF(SUM(AA36,AM36)=0,"-",SUM(AA36,AM36)),"-") -> 2414466 | AO36: =IFERROR(IF(SUM($AB36,$AL36)=0,"-",SUM($AB36,$AL36)),"-") -> 620000 | AP36: 74400 | AQ36: DC | AR36: =IFERROR(AP36*(12/$I36)*$K36,"-") -> 74400 | AT36: 85127 | AU36: =IFERROR(AT36*(12/$H36)*$J36,"-") -> - | AW36: =IFERROR(IF(SUM(AN36,AR36,AU36)=0,"-",SUM(AN36,AR36,AU36)),"-") -> 2488866 | AX36: =IFERROR(IF(SUM(AO36,AR36,AU36)=0,"-",SUM(AO36,AR36,AU36)),"-") -> 694400 | AY36: - | AZ36: KP | BA36: sc
A37: =$D37&"_"&$F37&"_"&$L37 -> TSX:HBM_2023_COO | B37: =$D37&"_"&$F37&"_"&$N37 -> TSX:HBM_2023_NEO1 | C37: =$D37&"_"&$F37&"_"&$M37 -> TSX:HBM_2023_ | D37: =D36 -> TSX:HBM | E37: =_xll.ciqfunctions.udf.CIQ(D37,"IQ_Company_Name") -> Hudbay Minerals Inc. | F37: =F34 -> 2023 | G37: =F37&"-01-01" -> 2023-01-01 | H37: =F37&"-12-31" -> 2023-12-31 | I37: =_xlfn.DAYS(H37,G37)/_xlfn.DAYS(F37&"-12-31",F37&"-01-01")*12 -> 12 | J37: CAD | K37: =IF($J37="CAD",1,IF($J37="USD",VLOOKUP($F37,$G$9:$H$11,2,FALSE),"N/A")) -> 1 | L37: COO | N37: =N36 -> NEO1 | O37: =O36 -> COO | P37: =P36 -> Andre Lauzon | Q37: 556400 | R37: =IFERROR(Q37*(12/$I37)*$K37,"-") -> 556400 | S37: - | T37: =IFERROR(IF((S37*$K37)=0,"-",(S37*$K37)),"-") -> - | U37: 607923 | V37: =IFERROR(U37*(12/$I37)*$K37,"-") -> 607923 | W37: =IFERROR($V37/$R37,"-") -> 1.0926006 | Y37: - | Z37: =IFERROR(IF(ISNUMBER($Y37)=TRUE, $Y37*$R37,$X37*$R37),"-") -> 0 | AA37: =IFERROR(IF(SUM(R37,V37)=0,"-",SUM(R37,V37)),"-") -> 1164323 | AB37: =IFERROR(IF(SUM(R37,Z37)=0,"-",SUM(R37,Z37)),"-") -> 556400 | AC37: =1/3*709410 -> 236470 | AD37: =2/3*709410 -> 472940 | AE37: 236470 | AF37: - | AG37: - | AH37: =IFERROR(IF(SUM(AC37:AG37)=0,IF(COUNTIF($AA37:$AE37,"=0")>0,"$0","-"),SUM(AC37:AG37)),"-") -> 945880 | AI37: =IFERROR($AK37/$P37,"-") -> - | AK37: - | AL37: =IFERROR(IF(ISNUMBER($AK37)=TRUE, $AK37*$R37, $AJ37*$R37), "-") -> 0 | AM37: =IFERROR($AH37*$K37,"-") -> 945880 | AN37: =IFERROR(IF(SUM(AA37,AM37)=0,"-",SUM(AA37,AM37)),"-") -> 2110203 | AO37: =IFERROR(IF(SUM($AB37,$AL37)=0,"-",SUM($AB37,$AL37)),"-") -> 556400 | AP37: 66768 | AQ37: DC | AR37: =IFERROR(AP37*(12/$I37)*$K37,"-") -> 66768 | AT37: 179092 | AU37: =IFERROR(AT37*(12/$H37)*$J37,"-") -> - | AW37: =IFERROR(IF(SUM(AN37,AR37,AU37)=0,"-",SUM(AN37,AR37,AU37)),"-") -> 2176971 | AX37: =IFERROR(IF(SUM(AO37,AR37,AU37)=0,"-",SUM(AO37,AR37,AU37)),"-") -> 623168 | AY37: - | AZ37: KP | BA37: sc
A38: =$D38&"_"&$F38&"_"&$L38 -> TSX:HBM_2025_ | B38: =$D38&"_"&$F38&"_"&$N38 -> TSX:HBM_2025_CFO | C38: =$D38&"_"&$F38&"_"&$M38 -> TSX:HBM_2025_ | D38: =D37 -> TSX:HBM | E38: =_xll.ciqfunctions.udf.CIQ(D38,"IQ_Company_Name") -> Hudbay Minerals Inc. | F38: =F35 -> 2025 | G38: =F38&"-01-01" -> 2025-01-01 | H38: =F38&"-12-31" -> 2025-12-31 | I38: =_xlfn.DAYS(H38,G38)/_xlfn.DAYS(F38&"-12-31",F38&"-01-01")*12 -> 12 | J38: CAD | K38: =IF($J38="CAD",1,IF($J38="USD",VLOOKUP($F38,$G$9:$H$11,2,FALSE),"N/A")) -> 1 | N38: CFO | O38: CFO | P38: Eugene Lei | Q38: 573681 | R38: 625312 | S38: 625312 | T38: =IFERROR(IF((S38*$K38)=0,"-",(S38*$K38)),"-") -> 625312 | U38: 664494 | V38: =IFERROR(U38*(12/$I38)*$K38,"-") -> 664494 | W38: =IFERROR($V38/$R38,"-") -> 1.0626599 | X38: =IFERROR(AVERAGE(W38:W40),"N/A") -> 1.1210197 | Y38: 0.9 | Z38: =IFERROR(IF(ISNUMBER($Y38)=TRUE, $Y38*$R38,$X38*$R38),"-") -> 562780.8 | AA38: =IFERROR(IF(SUM(R38,V38)=0,"-",SUM(R38,V38)),"-") -> 1289806 | AB38: =IFERROR(IF(SUM(R38,Z38)=0,"-",SUM(R38,Z38)),"-") -> 1188092.8 | AC38: =1/3*731443 -> 243814.33 | AD38: =2/3*731443 -> 487628.67 | AE38: 243814 | AF38: - | AG38: - | AH38: =IFERROR(IF(SUM(AC38:AG38)=0,IF(COUNTIF($AA38:$AE38,"=0")>0,"$0","-"),SUM(AC38:AG38)),"-") -> 975257 | AI38: =IFERROR($AK38/$P38,"-") -> - | AJ38: =IFERROR(AVERAGE(AI38:AI40),"N/A") -> N/A | AK38: 1.8 | AL38: =IFERROR(IF(ISNUMBER($AK38)=TRUE, $AK38*$R38, $AJ38*$R38), "-") -> 1125561.6 | AM38: =IFERROR($AH38*$K38,"-") -> 975257 | AN38: =IFERROR(IF(SUM(AA38,AM38)=0,"-",SUM(AA38,AM38)),"-") -> 2265063 | AO38: =IFERROR(IF(SUM($AB38,$AL38)=0,"-",SUM($AB38,$AL38)),"-") -> 2313654.4 | AP38: 138981 | AQ38: DC & DB | AR38: =IFERROR(AP38*(12/$I38)*$K38,"-") -> 138981 | AS38: =IFERROR(AVERAGE(AR38:AR40),"N/A") -> 126721.33 | AT38: 118675 | AU38: =IFERROR(AT38*(12/$H38)*$J38,"-") -> - | AV38: =IFERROR(AVERAGE(AU38:AU40),"N/A") -> N/A | AW38: =IFERROR(IF(SUM(AN38,AR38,AU38)=0,"-",SUM(AN38,AR38,AU38)),"-") -> 2404044 | AX38: =IFERROR(IF(SUM(AO38,AR38,AU38)=0,"-",SUM(AO38,AR38,AU38)),"-") -> 2452635.4 | AY38: - | AZ38: KP | BA38: sc
A39: =$D39&"_"&$F39&"_"&$L39 -> TSX:HBM_2024_ | B39: =$D39&"_"&$F39&"_"&$N39 -> TSX:HBM_2024_CFO | C39: =$D39&"_"&$F39&"_"&$M39 -> TSX:HBM_2024_ | D39: =D38 -> TSX:HBM | E39: =_xll.ciqfunctions.udf.CIQ(D39,"IQ_Company_Name") -> Hudbay Minerals Inc. | F39: =F36 -> 2024 | G39: =F39&"-01-01" -> 2024-01-01 | H39: =F39&"-12-31" -> 2024-12-31 | I39: =_xlfn.DAYS(H39,G39)/_xlfn.DAYS(F39&"-12-31",F39&"-01-01")*12 -> 12 | J39: CAD | K39: =IF($J39="CAD",1,IF($J39="USD",VLOOKUP($F39,$G$9:$H$11,2,FALSE),"N/A")) -> 1 | N39: =N38 -> CFO | O39: =O38 -> CFO | P39: =P38 -> Eugene Lei | Q39: 551616 | R39: =IFERROR(Q39*(12/$I39)*$K39,"-") -> 551616 | S39: - | T39: =IFERROR(IF((S39*$K39)=0,"-",(S39*$K39)),"-") -> - | U39: 658795 | V39: =IFERROR(U39*(12/$I39)*$K39,"-") -> 658795 | W39: =IFERROR($V39/$R39,"-") -> 1.1943 | Y39: - | Z39: =IFERROR(IF(ISNUMBER($Y39)=TRUE, $Y39*$R39,$X39*$R39),"-") -> 0 | AA39: =IFERROR(IF(SUM(R39,V39)=0,"-",SUM(R39,V39)),"-") -> 1210411 | AB39: =IFERROR(IF(SUM(R39,Z39)=0,"-",SUM(R39,Z39)),"-") -> 551616 | AC39: =1/3*661939 -> 220646.33 | AD39: =2/3*661939 -> 441292.67 | AE39: 220646 | AF39: - | AG39: - | AH39: =IFERROR(IF(SUM(AC39:AG39)=0,IF(COUNTIF($AA39:$AE39,"=0")>0,"$0","-"),SUM(AC39:AG39)),"-") -> 882585 | AI39: =IFERROR($AK39/$P39,"-") -> - | AK39: - | AL39: =IFERROR(IF(ISNUMBER($AK39)=TRUE, $AK39*$R39, $AJ39*$R39), "-") -> 0 | AM39: =IFERROR($AH39*$K39,"-") -> 882585 | AN39: =IFERROR(IF(SUM(AA39,AM39)=0,"-",SUM(AA39,AM39)),"-") -> 2092996 | AO39: =IFERROR(IF(SUM($AB39,$AL39)=0,"-",SUM($AB39,$AL39)),"-") -> 551616 | AP39: 132222 | AQ39: DC & DB | AR39: =IFERROR(AP39*(12/$I39)*$K39,"-") -> 132222 | AT39: 103501 | AU39: =IFERROR(AT39*(12/$H39)*$J39,"-") -> - | AW39: =IFERROR(IF(SUM(AN39,AR39,AU39)=0,"-",SUM(AN39,AR39,AU39)),"-") -> 2225218 | AX39: =IFERROR(IF(SUM(AO39,AR39,AU39)=0,"-",SUM(AO39,AR39,AU39)),"-") -> 683838 | AY39: - | AZ39: KP | BA39: sc
A40: =$D40&"_"&$F40&"_"&$L40 -> TSX:HBM_2023_ | B40: =$D40&"_"&$F40&"_"&$N40 -> TSX:HBM_2023_CFO | C40: =$D40&"_"&$F40&"_"&$M40 -> TSX:HBM_2023_ | D40: =D39 -> TSX:HBM | E40: =_xll.ciqfunctions.udf.CIQ(D40,"IQ_Company_Name") -> Hudbay Minerals Inc. | F40: =F37 -> 2023 | G40: =F40&"-01-01" -> 2023-01-01 | H40: =F40&"-12-31" -> 2023-12-31 | I40: =_xlfn.DAYS(H40,G40)/_xlfn.DAYS(F40&"-12-31",F40&"-01-01")*12 -> 12 | J40: CAD | K40: =IF($J40="CAD",1,IF($J40="USD",VLOOKUP($F40,$G$9:$H$11,2,FALSE),"N/A")) -> 1 | N40: =N39 -> CFO | O40: =O39 -> CFO | P40: =P39 -> Eugene Lei | Q40: 530400 | R40: =IFERROR(Q40*(12/$I40)*$K40,"-") -> 530400 | S40: - | T40: =IFERROR(IF((S40*$K40)=0,"-",(S40*$K40)),"-") -> - | U40: 586675 | V40: =IFERROR(U40*(12/$I40)*$K40,"-") -> 586675 | W40: =IFERROR($V40/$R40,"-") -> 1.1060992 | Y40: - | Z40: =IFERROR(IF(ISNUMBER($Y40)=TRUE, $Y40*$R40,$X40*$R40),"-") -> 0 | AA40: =IFERROR(IF(SUM(R40,V40)=0,"-",SUM(R40,V40)),"-") -> 1117075 | AB40: =IFERROR(IF(SUM(R40,Z40)=0,"-",SUM(R40,Z40)),"-") -> 530400 | AC40: =1/3*636480 -> 212160 | AD40: =2/3*636480 -> 424320 | AE40: 212160 | AF40: - | AG40: - | AH40: =IFERROR(IF(SUM(AC40:AG40)=0,IF(COUNTIF($AA40:$AE40,"=0")>0,"$0","-"),SUM(AC40:AG40)),"-") -> 848640 | AI40: =IFERROR($AK40/$P40,"-") -> - | AK40: - | AL40: =IFERROR(IF(ISNUMBER($AK40)=TRUE, $AK40*$R40, $AJ40*$R40), "-") -> 0 | AM40: =IFERROR($AH40*$K40,"-") -> 848640 | AN40: =IFERROR(IF(SUM(AA40,AM40)=0,"-",SUM(AA40,AM40)),"-") -> 1965715 | AO40: =IFERROR(IF(SUM($AB40,$AL40)=0,"-",SUM($AB40,$AL40)),"-") -> 530400 | AP40: 108961 | AQ40: DC & DB | AR40: =IFERROR(AP40*(12/$I40)*$K40,"-") -> 108961 | AT40: 141406 | AU40: =IFERROR(AT40*(12/$H40)*$J40,"-") -> - | AW40: =IFERROR(IF(SUM(AN40,AR40,AU40)=0,"-",SUM(AN40,AR40,AU40)),"-") -> 2074676 | AX40: =IFERROR(IF(SUM(AO40,AR40,AU40)=0,"-",SUM(AO40,AR40,AU40)),"-") -> 639361 | AY40: - | AZ40: KP | BA40: sc
A41: =$D41&"_"&$F41&"_"&$L41 -> TSX:HBM_2025_Legal | B41: =$D41&"_"&$F41&"_"&$N41 -> TSX:HBM_2025_NEO3 | C41: =$D41&"_"&$F41&"_"&$M41 -> TSX:HBM_2025_ | D41: =D40 -> TSX:HBM | E41: =_xll.ciqfunctions.udf.CIQ(D41,"IQ_Company_Name") -> Hudbay Minerals Inc. | F41: =F38 -> 2025 | G41: =F41&"-01-01" -> 2025-01-01 | H41: =F41&"-12-31" -> 2025-12-31 | I41: =_xlfn.DAYS(H41,G41)/_xlfn.DAYS(F41&"-12-31",F41&"-01-01")*12 -> 12 | J41: CAD | K41: =IF($J41="CAD",1,IF($J41="USD",VLOOKUP($F41,$G$9:$H$11,2,FALSE),"N/A")) -> 1 | L41: Legal | N41: NEO3 | O41: SVP, Legal and Organizational Effectiveness | P41: Patrick Donnelly | Q41: 501660 | R41: 526743 | S41: 526743 | T41: =IFERROR(IF((S41*$K41)=0,"-",(S41*$K41)),"-") -> 526743 | U41: 478583 | V41: =IFERROR(U41*(12/$I41)*$K41,"-") -> 478583 | W41: =IFERROR($V41/$R41,"-") -> 0.90857021 | X41: =IFERROR(AVERAGE(W41:W43),"N/A") -> 0.91062429 | Y41: 0.75 | Z41: =IFERROR(IF(ISNUMBER($Y41)=TRUE, $Y41*$R41,$X41*$R41),"-") -> 395057.25 | AA41: =IFERROR(IF(SUM(R41,V41)=0,"-",SUM(R41,V41)),"-") -> 1005326 | AB41: =IFERROR(IF(SUM(R41,Z41)=0,"-",SUM(R41,Z41)),"-") -> 921800.25 | AC41: =1/3*564367 -> 188122.33 | AD41: =2/3*564367 -> 376244.67 | AE41: 188122 | AF41: - | AG41: - | AH41: =IFERROR(IF(SUM(AC41:AG41)=0,IF(COUNTIF($AA41:$AE41,"=0")>0,"$0","-"),SUM(AC41:AG41)),"-") -> 752489 | AI41: =IFERROR($AK41/$P41,"-") -> - | AJ41: =IFERROR(AVERAGE(AI41:AI43),"N/A") -> N/A | AK41: 1.5 | AL41: =IFERROR(IF(ISNUMBER($AK41)=TRUE, $AK41*$R41, $AJ41*$R41), "-") -> 790114.5 | AM41: =IFERROR($AH41*$K41,"-") -> 752489 | AN41: =IFERROR(IF(SUM(AA41,AM41)=0,"-",SUM(AA41,AM41)),"-") -> 1757815 | AO41: =IFERROR(IF(SUM($AB41,$AL41)=0,"-",SUM($AB41,$AL41)),"-") -> 1711914.8 | AP41: 91935 | AQ41: DB | AR41: =IFERROR(AP41*(12/$I41)*$K41,"-") -> 91935 | AS41: =IFERROR(AVERAGE(AR41:AR43),"N/A") -> 89596 | AT41: 92458 | AU41: =IFERROR(AT41*(12/$H41)*$J41,"-") -> - | AV41: =IFERROR(AVERAGE(AU41:AU43),"N/A") -> N/A | AW41: =IFERROR(IF(SUM(AN41,AR41,AU41)=0,"-",SUM(AN41,AR41,AU41)),"-") -> 1849750 | AX41: =IFERROR(IF(SUM(AO41,AR41,AU41)=0,"-",SUM(AO41,AR41,AU41)),"-") -> 1803849.8 | AY41: - | AZ41: KP | BA41: sc
A42: =$D42&"_"&$F42&"_"&$L42 -> TSX:HBM_2024_Legal | B42: =$D42&"_"&$F42&"_"&$N42 -> TSX:HBM_2024_NEO3 | C42: =$D42&"_"&$F42&"_"&$M42 -> TSX:HBM_2024_ | D42: =D41 -> TSX:HBM | E42: =_xll.ciqfunctions.udf.CIQ(D42,"IQ_Company_Name") -> Hudbay Minerals Inc. | F42: =F39 -> 2024 | G42: =F42&"-01-01" -> 2024-01-01 | H42: =F42&"-12-31" -> 2024-12-31 | I42: =_xlfn.DAYS(H42,G42)/_xlfn.DAYS(F42&"-12-31",F42&"-01-01")*12 -> 12 | J42: CAD | K42: =IF($J42="CAD",1,IF($J42="USD",VLOOKUP($F42,$G$9:$H$11,2,FALSE),"N/A")) -> 1 | L42: Legal | N42: =N41 -> NEO3 | O42: =O41 -> SVP, Legal and Organizational Effectiveness | P42: =P41 -> Patrick Donnelly | Q42: 487048 | R42: =IFERROR(Q42*(12/$I42)*$K42,"-") -> 487048 | S42: - | T42: =IFERROR(IF((S42*$K42)=0,"-",(S42*$K42)),"-") -> - | U42: 479256 | V42: =IFERROR(U42*(12/$I42)*$K42,"-") -> 479256 | W42: =IFERROR($V42/$R42,"-") -> 0.98400158 | Y42: - | Z42: =IFERROR(IF(ISNUMBER($Y42)=TRUE, $Y42*$R42,$X42*$R42),"-") -> 0 | AA42: =IFERROR(IF(SUM(R42,V42)=0,"-",SUM(R42,V42)),"-") -> 966304 | AB42: =IFERROR(IF(SUM(R42,Z42)=0,"-",SUM(R42,Z42)),"-") -> 487048 | AC42: =1/3*547929 -> 182643 | AD42: =2/3*547929 -> 365286 | AE42: 182643 | AF42: - | AG42: - | AH42: =IFERROR(IF(SUM(AC42:AG42)=0,IF(COUNTIF($AA42:$AE42,"=0")>0,"$0","-"),SUM(AC42:AG42)),"-") -> 730572 | AI42: =IFERROR($AK42/$P42,"-") -> - | AK42: - | AL42: =IFERROR(IF(ISNUMBER($AK42)=TRUE, $AK42*$R42, $AJ42*$R42), "-") -> 0 | AM42: =IFERROR($AH42*$K42,"-") -> 730572 | AN42: =IFERROR(IF(SUM(AA42,AM42)=0,"-",SUM(AA42,AM42)),"-") -> 1696876 | AO42: =IFERROR(IF(SUM($AB42,$AL42)=0,"-",SUM($AB42,$AL42)),"-") -> 487048 | AP42: 122673 | AQ42: DB | AR42: =IFERROR(AP42*(12/$I42)*$K42,"-") -> 122673 | AT42: 84863 | AU42: =IFERROR(AT42*(12/$H42)*$J42,"-") -> - | AW42: =IFERROR(IF(SUM(AN42,AR42,AU42)=0,"-",SUM(AN42,AR42,AU42)),"-") -> 1819549 | AX42: =IFERROR(IF(SUM(AO42,AR42,AU42)=0,"-",SUM(AO42,AR42,AU42)),"-") -> 609721 | AY42: - | AZ42: KP | BA42: sc
A43: =$D43&"_"&$F43&"_"&$L43 -> TSX:HBM_2023_Legal | B43: =$D43&"_"&$F43&"_"&$N43 -> TSX:HBM_2023_NEO3 | C43: =$D43&"_"&$F43&"_"&$M43 -> TSX:HBM_2023_ | D43: =D42 -> TSX:HBM | E43: =_xll.ciqfunctions.udf.CIQ(D43,"IQ_Company_Name") -> Hudbay Minerals Inc. | F43: =F40 -> 2023 | G43: =F43&"-01-01" -> 2023-01-01 | H43: =F43&"-12-31" -> 2023-12-31 | I43: =_xlfn.DAYS(H43,G43)/_xlfn.DAYS(F43&"-12-31",F43&"-01-01")*12 -> 12 | J43: CAD | K43: =IF($J43="CAD",1,IF($J43="USD",VLOOKUP($F43,$G$9:$H$11,2,FALSE),"N/A")) -> 1 | L43: Legal | N43: =N42 -> NEO3 | O43: =O42 -> SVP, Legal and Organizational Effectiveness | P43: =P42 -> Patrick Donnelly | Q43: 463855 | R43: =IFERROR(Q43*(12/$I43)*$K43,"-") -> 463855 | S43: - | T43: =IFERROR(IF((S43*$K43)=0,"-",(S43*$K43)),"-") -> - | U43: 389314 | V43: =IFERROR(U43*(12/$I43)*$K43,"-") -> 389314 | W43: =IFERROR($V43/$R43,"-") -> 0.83930107 | Y43: - | Z43: =IFERROR(IF(ISNUMBER($Y43)=TRUE, $Y43*$R43,$X43*$R43),"-") -> 0 | AA43: =IFERROR(IF(SUM(R43,V43)=0,"-",SUM(R43,V43)),"-") -> 853169 | AB43: =IFERROR(IF(SUM(R43,Z43)=0,"-",SUM(R43,Z43)),"-") -> 463855 | AC43: =1/3*521883 -> 173961 | AD43: =2/3*521883 -> 347922 | AE43: 173961 | AF43: - | AG43: - | AH43: =IFERROR(IF(SUM(AC43:AG43)=0,IF(COUNTIF($AA43:$AE43,"=0")>0,"$0","-"),SUM(AC43:AG43)),"-") -> 695844 | AI43: =IFERROR($AK43/$P43,"-") -> - | AK43: - | AL43: =IFERROR(IF(ISNUMBER($AK43)=TRUE, $AK43*$R43, $AJ43*$R43), "-") -> 0 | AM43: =IFERROR($AH43*$K43,"-") -> 695844 | AN43: =IFERROR(IF(SUM(AA43,AM43)=0,"-",SUM(AA43,AM43)),"-") -> 1549013 | AO43: =IFERROR(IF(SUM($AB43,$AL43)=0,"-",SUM($AB43,$AL43)),"-") -> 463855 | AP43: 54180 | AQ43: DB | AR43: =IFERROR(AP43*(12/$I43)*$K43,"-") -> 54180 | AT43: 104737 | AU43: =IFERROR(AT43*(12/$H43)*$J43,"-") -> - | AW43: =IFERROR(IF(SUM(AN43,AR43,AU43)=0,"-",SUM(AN43,AR43,AU43)),"-") -> 1603193 | AX43: =IFERROR(IF(SUM(AO43,AR43,AU43)=0,"-",SUM(AO43,AR43,AU43)),"-") -> 518035 | AY43: - | AZ43: KP | BA43: sc
A44: =$D44&"_"&$F44&"_"&$L44 -> TSX:HBM_2025_Region | B44: =$D44&"_"&$F44&"_"&$N44 -> TSX:HBM_2025_NEO2 | C44: =$D44&"_"&$F44&"_"&$M44 -> TSX:HBM_2025_ | D44: =D40 -> TSX:HBM | E44: =_xll.ciqfunctions.udf.CIQ(D44,"IQ_Company_Name") -> Hudbay Minerals Inc. | F44: =F38 -> 2025 | G44: =F44&"-01-01" -> 2025-01-01 | H44: =F44&"-12-31" -> 2025-12-31 | I44: =_xlfn.DAYS(H44,G44)/_xlfn.DAYS(F44&"-12-31",F44&"-01-01")*12 -> 12 | J44: CAD | K44: =IF($J44="CAD",1,IF($J44="USD",VLOOKUP($F44,$G$9:$H$11,2,FALSE),"N/A")) -> 1 | L44: Region | N44: NEO2 | O44: SVP, US Business Unit | P44: Javier Del Rio | Q44: 606683 | R44: 639905 | S44: 639905 | T44: =IFERROR(IF((S44*$K44)=0,"-",(S44*$K44)),"-") -> 639905 | U44: 468480 | V44: =IFERROR(U44*(12/$I44)*$K44,"-") -> 468480 | W44: =IFERROR($V44/$R44,"-") -> 0.73210867 | X44: =IFERROR(AVERAGE(W44:W46),"N/A") -> 0.75223656 | Y44: 0.6 | Z44: =IFERROR(IF(ISNUMBER($Y44)=TRUE, $Y44*$R44,$X44*$R44),"-") -> 383943 | AA44: =IFERROR(IF(SUM(R44,V44)=0,"-",SUM(R44,V44)),"-") -> 1108385 | AB44: =IFERROR(IF(SUM(R44,Z44)=0,"-",SUM(R44,Z44)),"-") -> 1023848 | AC44: =1/3*565464 -> 188488 | AD44: =2/3*565464 -> 376976 | AE44: 188488 | AF44: - | AG44: - | AH44: =IFERROR(IF(SUM(AC44:AG44)=0,IF(COUNTIF($AA44:$AE44,"=0")>0,"$0","-"),SUM(AC44:AG44)),"-") -> 753952 | AI44: =IFERROR($AK44/$P44,"-") -> - | AJ44: =IFERROR(AVERAGE(AI44:AI46),"N/A") -> N/A | AK44: 1.2 | AL44: =IFERROR(IF(ISNUMBER($AK44)=TRUE, $AK44*$R44, $AJ44*$R44), "-") -> 767886 | AM44: =IFERROR($AH44*$K44,"-") -> 753952 | AN44: =IFERROR(IF(SUM(AA44,AM44)=0,"-",SUM(AA44,AM44)),"-") -> 1862337 | AO44: =IFERROR(IF(SUM($AB44,$AL44)=0,"-",SUM($AB44,$AL44)),"-") -> 1791734 | AP44: 14385 | AQ44: DC | AR44: =IFERROR(AP44*(12/$I44)*$K44,"-") -> 14385 | AS44: =IFERROR(AVERAGE(AR44:AR46),"N/A") -> 13570 | AT44: 156358 | AU44: =IFERROR(AT44*(12/$H44)*$J44,"-") -> - | AV44: =IFERROR(AVERAGE(AU44:AU46),"N/A") -> N/A | AW44: =IFERROR(IF(SUM(AN44,AR44,AU44)=0,"-",SUM(AN44,AR44,AU44)),"-") -> 1876722 | AX44: =IFERROR(IF(SUM(AO44,AR44,AU44)=0,"-",SUM(AO44,AR44,AU44)),"-") -> 1806119 | AY44: - | AZ44: KP | BA44: sc | BC44: =R44/Q44 -1 -> 0.054760064
A45: =$D45&"_"&$F45&"_"&$L45 -> TSX:HBM_2024_Region | B45: =$D45&"_"&$F45&"_"&$N45 -> TSX:HBM_2024_NEO2 | C45: =$D45&"_"&$F45&"_"&$M45 -> TSX:HBM_2024_ | D45: =D44 -> TSX:HBM | E45: =_xll.ciqfunctions.udf.CIQ(D45,"IQ_Company_Name") -> Hudbay Minerals Inc. | F45: =F39 -> 2024 | G45: =F45&"-01-01" -> 2024-01-01 | H45: =F45&"-12-31" -> 2024-12-31 | I45: =_xlfn.DAYS(H45,G45)/_xlfn.DAYS(F45&"-12-31",F45&"-01-01")*12 -> 12 | J45: CAD | K45: =IF($J45="CAD",1,IF($J45="USD",VLOOKUP($F45,$G$9:$H$11,2,FALSE),"N/A")) -> 1 | L45: Region | N45: =N44 -> NEO2 | O45: =O44 -> SVP, US Business Unit | P45: =P44 -> Javier Del Rio | Q45: 558917 | R45: =IFERROR(Q45*(12/$I45)*$K45,"-") -> 558917 | S45: - | T45: =IFERROR(IF((S45*$K45)=0,"-",(S45*$K45)),"-") -> - | U45: 445010 | V45: =IFERROR(U45*(12/$I45)*$K45,"-") -> 445010 | W45: =IFERROR($V45/$R45,"-") -> 0.79620051 | Y45: - | Z45: =IFERROR(IF(ISNUMBER($Y45)=TRUE, $Y45*$R45,$X45*$R45),"-") -> 0 | AA45: =IFERROR(IF(SUM(R45,V45)=0,"-",SUM(R45,V45)),"-") -> 1003927 | AB45: =IFERROR(IF(SUM(R45,Z45)=0,"-",SUM(R45,Z45)),"-") -> 558917 | AC45: =1/3*479373 -> 159791 | AD45: =2/3*479373 -> 319582 | AE45: 159791 | AF45: - | AG45: - | AH45: =IFERROR(IF(SUM(AC45:AG45)=0,IF(COUNTIF($AA45:$AE45,"=0")>0,"$0","-"),SUM(AC45:AG45)),"-") -> 639164 | AI45: =IFERROR($AK45/$P45,"-") -> - | AK45: - | AL45: =IFERROR(IF(ISNUMBER($AK45)=TRUE, $AK45*$R45, $AJ45*$R45), "-") -> 0 | AM45: =IFERROR($AH45*$K45,"-") -> 639164 | AN45: =IFERROR(IF(SUM(AA45,AM45)=0,"-",SUM(AA45,AM45)),"-") -> 1643091 | AO45: =IFERROR(IF(SUM($AB45,$AL45)=0,"-",SUM($AB45,$AL45)),"-") -> 558917 | AP45: 13455 | AQ45: DB | AR45: =IFERROR(AP45*(12/$I45)*$K45,"-") -> 13455 | AT45: =523315-421713 -> 101602 | AU45: =IFERROR(AT45*(12/$H45)*$J45,"-") -> - | AW45: =IFERROR(IF(SUM(AN45,AR45,AU45)=0,"-",SUM(AN45,AR45,AU45)),"-") -> 1656546 | AX45: =IFERROR(IF(SUM(AO45,AR45,AU45)=0,"-",SUM(AO45,AR45,AU45)),"-") -> 572372 | AY45: Other compensation includes tax top-ups for duplicate tax levied on income in US and Peru (-421713) | AZ45: KP | BA45: sc
A46: =$D46&"_"&$F46&"_"&$L46 -> TSX:HBM_2023_Region | B46: =$D46&"_"&$F46&"_"&$N46 -> TSX:HBM_2023_NEO2 | C46: =$D46&"_"&$F46&"_"&$M46 -> TSX:HBM_2023_ | D46: =D45 -> TSX:HBM | E46: =_xll.ciqfunctions.udf.CIQ(D46,"IQ_Company_Name") -> Hudbay Minerals Inc. | F46: =F40 -> 2023 | G46: =F46&"-01-01" -> 2023-01-01 | H46: =F46&"-12-31" -> 2023-12-31 | I46: =_xlfn.DAYS(H46,G46)/_xlfn.DAYS(F46&"-12-31",F46&"-01-01")*12 -> 12 | J46: CAD | K46: =IF($J46="CAD",1,IF($J46="USD",VLOOKUP($F46,$G$9:$H$11,2,FALSE),"N/A")) -> 1 | L46: Region | N46: =N45 -> NEO2 | O46: =O45 -> SVP, US Business Unit | P46: =P45 -> Javier Del Rio | Q46: 537420 | R46: =IFERROR(Q46*(12/$I46)*$K46,"-") -> 537420 | S46: - | T46: =IFERROR(IF((S46*$K46)=0,"-",(S46*$K46)),"-") -> - | U46: 391457 | V46: =IFERROR(U46*(12/$I46)*$K46,"-") -> 391457 | W46: =IFERROR($V46/$R46,"-") -> 0.72840051 | Y46: - | Z46: =IFERROR(IF(ISNUMBER($Y46)=TRUE, $Y46*$R46,$X46*$R46),"-") -> 0 | AA46: =IFERROR(IF(SUM(R46,V46)=0,"-",SUM(R46,V46)),"-") -> 928877 | AB46: =IFERROR(IF(SUM(R46,Z46)=0,"-",SUM(R46,Z46)),"-") -> 537420 | AC46: =1/3*462914 -> 154304.67 | AD46: =2/3*462914 -> 308609.33 | AE46: 154305 | AF46: - | AG46: - | AH46: =IFERROR(IF(SUM(AC46:AG46)=0,IF(COUNTIF($AA46:$AE46,"=0")>0,"$0","-"),SUM(AC46:AG46)),"-") -> 617219 | AI46: =IFERROR($AK46/$P46,"-") -> - | AK46: - | AL46: =IFERROR(IF(ISNUMBER($AK46)=TRUE, $AK46*$R46, $AJ46*$R46), "-") -> 0 | AM46: =IFERROR($AH46*$K46,"-") -> 617219 | AN46: =IFERROR(IF(SUM(AA46,AM46)=0,"-",SUM(AA46,AM46)),"-") -> 1546096 | AO46: =IFERROR(IF(SUM($AB46,$AL46)=0,"-",SUM($AB46,$AL46)),"-") -> 537420 | AP46: 12870 | AQ46: DB | AR46: =IFERROR(AP46*(12/$I46)*$K46,"-") -> 12870 | AT46: 144308 | AU46: =IFERROR(AT46*(12/$H46)*$J46,"-") -> - | AW46: =IFERROR(IF(SUM(AN46,AR46,AU46)=0,"-",SUM(AN46,AR46,AU46)),"-") -> 1558966 | AX46: =IFERROR(IF(SUM(AO46,AR46,AU46)=0,"-",SUM(AO46,AR46,AU46)),"-") -> 550290 | AY46: - | AZ46: KP | BA46: sc
A47: =$D47&"_"&$F47&"_"&$L47 -> TSX:HBM_2025_ | B47: =$D47&"_"&$F47&"_"&$N47 -> TSX:HBM_2025_NEO2 | C47: =$D47&"_"&$F47&"_"&$M47 -> TSX:HBM_2025_ | D47: =D40 -> TSX:HBM | E47: =_xll.ciqfunctions.udf.CIQ(D47,"IQ_Company_Name") -> Hudbay Minerals Inc. | F47: =F38 -> 2025 | G47: =F47&"-01-01" -> 2025-01-01 | H47: =F47&"-12-31" -> 2025-12-31 | I47: =_xlfn.DAYS(H47,G47)/_xlfn.DAYS(F47&"-12-31",F47&"-01-01")*12 -> 12 | J47: CAD | K47: =IF($J47="CAD",1,IF($J47="USD",VLOOKUP($F47,$G$9:$H$11,2,FALSE),"N/A")) -> 1 | N47: NEO2 | O47: SVP, Canada | P47: Robert Carter | Q47: 467105 | R47: 467105 | S47: =+Q47 -> 467105 | T47: =IFERROR(IF((S47*$K47)=0,"-",(S47*$K47)),"-") -> 467105 | V47: =IFERROR(U47*(12/$I47)*$K47,"-") -> 0 | W47: =IFERROR($V47/$R47,"-") -> 0 | X47: =IFERROR(AVERAGE(W47:W49),"N/A") -> 0 | Y47: 0.6 | Z47: =IFERROR(IF(ISNUMBER($Y47)=TRUE, $Y47*$R47,$X47*$R47),"-") -> 280263 | AA47: =IFERROR(IF(SUM(R47,V47)=0,"-",SUM(R47,V47)),"-") -> 467105 | AB47: =IFERROR(IF(SUM(R47,Z47)=0,"-",SUM(R47,Z47)),"-") -> 747368 | AF47: - | AG47: - | AH47: =IFERROR(IF(SUM(AC47:AG47)=0,IF(COUNTIF($AA47:$AE47,"=0")>0,"$0","-"),SUM(AC47:AG47)),"-") -> - | AI47: =IFERROR($AK47/$P47,"-") -> - | AJ47: =IFERROR(AVERAGE(AI47:AI49),"N/A") -> N/A | AK47: 1.2 | AL47: =IFERROR(IF(ISNUMBER($AK47)=TRUE, $AK47*$R47, $AJ47*$R47), "-") -> 560526 | AM47: =IFERROR($AH47*$K47,"-") -> - | AN47: =IFERROR(IF(SUM(AA47,AM47)=0,"-",SUM(AA47,AM47)),"-") -> 467105 | AO47: =IFERROR(IF(SUM($AB47,$AL47)=0,"-",SUM($AB47,$AL47)),"-") -> 1307894 | AQ47: DC | AR47: =IFERROR(AP47*(12/$I47)*$K47,"-") -> 0 | AS47: =IFERROR(AVERAGE(AR47:AR49),"N/A") -> 0 | AU47: =IFERROR(AT47*(12/$H47)*$J47,"-") -> - | AV47: =IFERROR(AVERAGE(AU47:AU49),"N/A") -> N/A | AW47: =IFERROR(IF(SUM(AN47,AR47,AU47)=0,"-",SUM(AN47,AR47,AU47)),"-") -> 467105 | AX47: =IFERROR(IF(SUM(AO47,AR47,AU47)=0,"-",SUM(AO47,AR47,AU47)),"-") -> 1307894 | AY47: Based on Feb. 11 Materials | AZ47: KP | BA47: sc
A48: =$D48&"_"&$F48&"_"&$L48 -> TSX:HBM_2024_ | B48: =$D48&"_"&$F48&"_"&$N48 -> TSX:HBM_2024_NEO2 | C48: =$D48&"_"&$F48&"_"&$M48 -> TSX:HBM_2024_ | D48: =D47 -> TSX:HBM | E48: =_xll.ciqfunctions.udf.CIQ(D48,"IQ_Company_Name") -> Hudbay Minerals Inc. | F48: =F39 -> 2024 | G48: =F48&"-01-01" -> 2024-01-01 | H48: =F48&"-12-31" -> 2024-12-31 | I48: =_xlfn.DAYS(H48,G48)/_xlfn.DAYS(F48&"-12-31",F48&"-01-01")*12 -> 12 | J48: CAD | K48: =IF($J48="CAD",1,IF($J48="USD",VLOOKUP($F48,$G$9:$H$11,2,FALSE),"N/A")) -> 1 | N48: =N47 -> NEO2 | O48: =O47 -> SVP, Canada | P48: =P47 -> Robert Carter | R48: =IFERROR(Q48*(12/$I48)*$K48,"-") -> 0 | S48: - | T48: =IFERROR(IF((S48*$K48)=0,"-",(S48*$K48)),"-") -> - | V48: =IFERROR(U48*(12/$I48)*$K48,"-") -> 0 | W48: =IFERROR($V48/$R48,"-") -> - | Y48: - | Z48: =IFERROR(IF(ISNUMBER($Y48)=TRUE, $Y48*$R48,$X48*$R48),"-") -> 0 | AA48: =IFERROR(IF(SUM(R48,V48)=0,"-",SUM(R48,V48)),"-") -> - | AB48: =IFERROR(IF(SUM(R48,Z48)=0,"-",SUM(R48,Z48)),"-") -> - | AF48: - | AG48: - | AH48: =IFERROR(IF(SUM(AC48:AG48)=0,IF(COUNTIF($AA48:$AE48,"=0")>0,"$0","-"),SUM(AC48:AG48)),"-") -> - | AI48: =IFERROR($AK48/$P48,"-") -> - | AK48: - | AL48: =IFERROR(IF(ISNUMBER($AK48)=TRUE, $AK48*$R48, $AJ48*$R48), "-") -> 0 | AM48: =IFERROR($AH48*$K48,"-") -> - | AN48: =IFERROR(IF(SUM(AA48,AM48)=0,"-",SUM(AA48,AM48)),"-") -> - | AO48: =IFERROR(IF(SUM($AB48,$AL48)=0,"-",SUM($AB48,$AL48)),"-") -> - | AQ48: DB | AR48: =IFERROR(AP48*(12/$I48)*$K48,"-") -> 0 | AU48: =IFERROR(AT48*(12/$H48)*$J48,"-") -> - | AW48: =IFERROR(IF(SUM(AN48,AR48,AU48)=0,"-",SUM(AN48,AR48,AU48)),"-") -> - | AX48: =IFERROR(IF(SUM(AO48,AR48,AU48)=0,"-",SUM(AO48,AR48,AU48)),"-") -> - | AZ48: KP | BA48: sc
A49: =$D49&"_"&$F49&"_"&$L49 -> TSX:HBM_2023_ | B49: =$D49&"_"&$F49&"_"&$N49 -> TSX:HBM_2023_NEO2 | C49: =$D49&"_"&$F49&"_"&$M49 -> TSX:HBM_2023_ | D49: =D48 -> TSX:HBM | E49: =_xll.ciqfunctions.udf.CIQ(D49,"IQ_Company_Name") -> Hudbay Minerals Inc. | F49: =F40 -> 2023 | G49: =F49&"-01-01" -> 2023-01-01 | H49: =F49&"-12-31" -> 2023-12-31 | I49: =_xlfn.DAYS(H49,G49)/_xlfn.DAYS(F49&"-12-31",F49&"-01-01")*12 -> 12 | J49: CAD | K49: =IF($J49="CAD",1,IF($J49="USD",VLOOKUP($F49,$G$9:$H$11,2,FALSE),"N/A")) -> 1 | N49: =N48 -> NEO2 | O49: =O48 -> SVP, Canada | P49: =P48 -> Robert Carter | R49: =IFERROR(Q49*(12/$I49)*$K49,"-") -> 0 | S49: - | T49: =IFERROR(IF((S49*$K49)=0,"-",(S49*$K49)),"-") -> - | V49: =IFERROR(U49*(12/$I49)*$K49,"-") -> 0 | W49: =IFERROR($V49/$R49,"-") -> - | Y49: - | Z49: =IFERROR(IF(ISNUMBER($Y49)=TRUE, $Y49*$R49,$X49*$R49),"-") -> 0 | AA49: =IFERROR(IF(SUM(R49,V49)=0,"-",SUM(R49,V49)),"-") -> - | AB49: =IFERROR(IF(SUM(R49,Z49)=0,"-",SUM(R49,Z49)),"-") -> - | AF49: - | AG49: - | AH49: =IFERROR(IF(SUM(AC49:AG49)=0,IF(COUNTIF($AA49:$AE49,"=0")>0,"$0","-"),SUM(AC49:AG49)),"-") -> - | AI49: =IFERROR($AK49/$P49,"-") -> - | AK49: - | AL49: =IFERROR(IF(ISNUMBER($AK49)=TRUE, $AK49*$R49, $AJ49*$R49), "-") -> 0 | AM49: =IFERROR($AH49*$K49,"-") -> - | AN49: =IFERROR(IF(SUM(AA49,AM49)=0,"-",SUM(AA49,AM49)),"-") -> - | AO49: =IFERROR(IF(SUM($AB49,$AL49)=0,"-",SUM($AB49,$AL49)),"-") -> - | AQ49: DB | AR49: =IFERROR(AP49*(12/$I49)*$K49,"-") -> 0 | AU49: =IFERROR(AT49*(12/$H49)*$J49,"-") -> - | AW49: =IFERROR(IF(SUM(AN49,AR49,AU49)=0,"-",SUM(AN49,AR49,AU49)),"-") -> - | AX49: =IFERROR(IF(SUM(AO49,AR49,AU49)=0,"-",SUM(AO49,AR49,AU49)),"-") -> - | AZ49: KP | BA49: sc
A50: =$D50&"_"&$F50&"_"&$L50 -> TSX:HBM_2025_Tech | B50: =$D50&"_"&$F50&"_"&$N50 -> TSX:HBM_2025_NEO4 | C50: =$D50&"_"&$F50&"_"&$M50 -> TSX:HBM_2025_ | D50: =D43 -> TSX:HBM | E50: =_xll.ciqfunctions.udf.CIQ(D50,"IQ_Company_Name") -> Hudbay Minerals Inc. | F50: =F41 -> 2025 | G50: =F50&"-01-01" -> 2025-01-01 | H50: =F50&"-12-31" -> 2025-12-31 | I50: =_xlfn.DAYS(H50,G50)/_xlfn.DAYS(F50&"-12-31",F50&"-01-01")*12 -> 12 | J50: CAD | K50: =IF($J50="CAD",1,IF($J50="USD",VLOOKUP($F50,$G$9:$H$11,2,FALSE),"N/A")) -> 1 | L50: Tech | N50: NEO4 | O50: SVP, Exploration & Technical Services | P50: Olivier Tavchandjian | Q50: 484484 | R50: 484484 | S50: =+Q50 -> 484484 | T50: =IFERROR(IF((S50*$K50)=0,"-",(S50*$K50)),"-") -> 484484 | V50: =IFERROR(U50*(12/$I50)*$K50,"-") -> 0 | W50: =IFERROR($V50/$R50,"-") -> 0 | X50: =IFERROR(AVERAGE(W50:W52),"N/A") -> 0 | Y50: 0.6 | Z50: =IFERROR(IF(ISNUMBER($Y50)=TRUE, $Y50*$R50,$X50*$R50),"-") -> 290690.4 | AA50: =IFERROR(IF(SUM(R50,V50)=0,"-",SUM(R50,V50)),"-") -> 484484 | AB50: =IFERROR(IF(SUM(R50,Z50)=0,"-",SUM(R50,Z50)),"-") -> 775174.4 | AF50: - | AG50: - | AH50: =IFERROR(IF(SUM(AC50:AG50)=0,IF(COUNTIF($AA50:$AE50,"=0")>0,"$0","-"),SUM(AC50:AG50)),"-") -> - | AI50: =IFERROR($AK50/$P50,"-") -> - | AJ50: =IFERROR(AVERAGE(AI50:AI52),"N/A") -> N/A | AK50: 1.2 | AL50: =IFERROR(IF(ISNUMBER($AK50)=TRUE, $AK50*$R50, $AJ50*$R50), "-") -> 581380.8 | AM50: =IFERROR($AH50*$K50,"-") -> - | AN50: =IFERROR(IF(SUM(AA50,AM50)=0,"-",SUM(AA50,AM50)),"-") -> 484484 | AO50: =IFERROR(IF(SUM($AB50,$AL50)=0,"-",SUM($AB50,$AL50)),"-") -> 1356555.2 | AQ50: DC | AR50: =IFERROR(AP50*(12/$I50)*$K50,"-") -> 0 | AS50: =IFERROR(AVERAGE(AR50:AR52),"N/A") -> 0 | AU50: =IFERROR(AT50*(12/$H50)*$J50,"-") -> - | AV50: =IFERROR(AVERAGE(AU50:AU52),"N/A") -> N/A | AW50: =IFERROR(IF(SUM(AN50,AR50,AU50)=0,"-",SUM(AN50,AR50,AU50)),"-") -> 484484 | AX50: =IFERROR(IF(SUM(AO50,AR50,AU50)=0,"-",SUM(AO50,AR50,AU50)),"-") -> 1356555.2 | AY50: Based on Feb. 11 Materials | AZ50: KP | BA50: sc
A51: =$D51&"_"&$F51&"_"&$L51 -> TSX:HBM_2024_Tech | B51: =$D51&"_"&$F51&"_"&$N51 -> TSX:HBM_2024_NEO4 | C51: =$D51&"_"&$F51&"_"&$M51 -> TSX:HBM_2024_ | D51: =D50 -> TSX:HBM | E51: =_xll.ciqfunctions.udf.CIQ(D51,"IQ_Company_Name") -> Hudbay Minerals Inc. | F51: =F42 -> 2024 | G51: =F51&"-01-01" -> 2024-01-01 | H51: =F51&"-12-31" -> 2024-12-31 | I51: =_xlfn.DAYS(H51,G51)/_xlfn.DAYS(F51&"-12-31",F51&"-01-01")*12 -> 12 | J51: CAD | K51: =IF($J51="CAD",1,IF($J51="USD",VLOOKUP($F51,$G$9:$H$11,2,FALSE),"N/A")) -> 1 | L51: Tech | N51: =N50 -> NEO4 | O51: =O50 -> SVP, Exploration & Technical Services | P51: =P50 -> Olivier Tavchandjian | R51: =IFERROR(Q51*(12/$I51)*$K51,"-") -> 0 | S51: - | T51: =IFERROR(IF((S51*$K51)=0,"-",(S51*$K51)),"-") -> - | V51: =IFERROR(U51*(12/$I51)*$K51,"-") -> 0 | W51: =IFERROR($V51/$R51,"-") -> - | Y51: - | Z51: =IFERROR(IF(ISNUMBER($Y51)=TRUE, $Y51*$R51,$X51*$R51),"-") -> 0 | AA51: =IFERROR(IF(SUM(R51,V51)=0,"-",SUM(R51,V51)),"-") -> - | AB51: =IFERROR(IF(SUM(R51,Z51)=0,"-",SUM(R51,Z51)),"-") -> - | AF51: - | AG51: - | AH51: =IFERROR(IF(SUM(AC51:AG51)=0,IF(COUNTIF($AA51:$AE51,"=0")>0,"$0","-"),SUM(AC51:AG51)),"-") -> - | AI51: =IFERROR($AK51/$P51,"-") -> - | AK51: - | AL51: =IFERROR(IF(ISNUMBER($AK51)=TRUE, $AK51*$R51, $AJ51*$R51), "-") -> 0 | AM51: =IFERROR($AH51*$K51,"-") -> - | AN51: =IFERROR(IF(SUM(AA51,AM51)=0,"-",SUM(AA51,AM51)),"-") -> - | AO51: =IFERROR(IF(SUM($AB51,$AL51)=0,"-",SUM($AB51,$AL51)),"-") -> - | AQ51: DB | AR51: =IFERROR(AP51*(12/$I51)*$K51,"-") -> 0 | AU51: =IFERROR(AT51*(12/$H51)*$J51,"-") -> - | AW51: =IFERROR(IF(SUM(AN51,AR51,AU51)=0,"-",SUM(AN51,AR51,AU51)),"-") -> - | AX51: =IFERROR(IF(SUM(AO51,AR51,AU51)=0,"-",SUM(AO51,AR51,AU51)),"-") -> - | AZ51: KP | BA51: sc
A52: =$D52&"_"&$F52&"_"&$L52 -> TSX:HBM_2023_Tech | B52: =$D52&"_"&$F52&"_"&$N52 -> TSX:HBM_2023_NEO4 | C52: =$D52&"_"&$F52&"_"&$M52 -> TSX:HBM_2023_ | D52: =D51 -> TSX:HBM | E52: =_xll.ciqfunctions.udf.CIQ(D52,"IQ_Company_Name") -> Hudbay Minerals Inc. | F52: =F43 -> 2023 | G52: =F52&"-01-01" -> 2023-01-01 | H52: =F52&"-12-31" -> 2023-12-31 | I52: =_xlfn.DAYS(H52,G52)/_xlfn.DAYS(F52&"-12-31",F52&"-01-01")*12 -> 12 | J52: CAD | K52: =IF($J52="CAD",1,IF($J52="USD",VLOOKUP($F52,$G$9:$H$11,2,FALSE),"N/A")) -> 1 | L52: Tech | N52: =N51 -> NEO4 | O52: =O51 -> SVP, Exploration & Technical Services | P52: =P51 -> Olivier Tavchandjian | R52: =IFERROR(Q52*(12/$I52)*$K52,"-") -> 0 | S52: - | T52: =IFERROR(IF((S52*$K52)=0,"-",(S52*$K52)),"-") -> - | V52: =IFERROR(U52*(12/$I52)*$K52,"-") -> 0 | W52: =IFERROR($V52/$R52,"-") -> - | Y52: - | Z52: =IFERROR(IF(ISNUMBER($Y52)=TRUE, $Y52*$R52,$X52*$R52),"-") -> 0 | AA52: =IFERROR(IF(SUM(R52,V52)=0,"-",SUM(R52,V52)),"-") -> - | AB52: =IFERROR(IF(SUM(R52,Z52)=0,"-",SUM(R52,Z52)),"-") -> - | AF52: - | AG52: - | AH52: =IFERROR(IF(SUM(AC52:AG52)=0,IF(COUNTIF($AA52:$AE52,"=0")>0,"$0","-"),SUM(AC52:AG52)),"-") -> - | AI52: =IFERROR($AK52/$P52,"-") -> - | AK52: - | AL52: =IFERROR(IF(ISNUMBER($AK52)=TRUE, $AK52*$R52, $AJ52*$R52), "-") -> 0 | AM52: =IFERROR($AH52*$K52,"-") -> - | AN52: =IFERROR(IF(SUM(AA52,AM52)=0,"-",SUM(AA52,AM52)),"-") -> - | AO52: =IFERROR(IF(SUM($AB52,$AL52)=0,"-",SUM($AB52,$AL52)),"-") -> - | AQ52: DB | AR52: =IFERROR(AP52*(12/$I52)*$K52,"-") -> 0 | AU52: =IFERROR(AT52*(12/$H52)*$J52,"-") -> - | AW52: =IFERROR(IF(SUM(AN52,AR52,AU52)=0,"-",SUM(AN52,AR52,AU52)),"-") -> - | AX52: =IFERROR(IF(SUM(AO52,AR52,AU52)=0,"-",SUM(AO52,AR52,AU52)),"-") -> - | AZ52: KP | BA52: sc
A53: =$D53&"_"&$F53&"_"&$L53 -> TSX:K_2025_ | B53: =$D53&"_"&$F53&"_"&$N53 -> TSX:K_2025_CEO | C53: =$D53&"_"&$F53&"_"&$M53 -> TSX:K_2025_ | D53: =E5 -> TSX:K | E53: =_xll.ciqfunctions.udf.CIQ(D53,"IQ_Company_Name") -> Kinross Gold Corporation | F53: =$G$9 -> 2025 | G53: =F53&"-01-01" -> 2025-01-01 | H53: =F53&"-12-31" -> 2025-12-31 | I53: =_xlfn.DAYS(H53,G53)/_xlfn.DAYS(F53&"-12-31",F53&"-01-01")*12 -> 12 | J53: USD | K53: =IF($J53="CAD",1,IF($J53="USD",VLOOKUP($F53,$G$9:$H$11,2,FALSE),"N/A")) -> 1.39745 | N53: CEO | O53: CEO | P53: J. Paul Rollinson | Q53: 1240320 | R53: =IFERROR(Q53*(12/$I53)*$K53,"-") -> 1733285.2 | S53: - | T53: =IFERROR(IF((S53*$K53)=0,"-",(S53*$K53)),"-") -> - | U53: 2302344 | V53: =IFERROR(U53*(12/$I53)*$K53,"-") -> 3217410.6 | W53: =IFERROR($V53/$R53,"-") -> 1.85625 | X53: =IFERROR(AVERAGE(W53:W55),"N/A") -> 1.8375002 | Y53: 1.5 | Z53: =IFERROR(IF(ISNUMBER($Y53)=TRUE, $Y53*$R53,$X53*$R53),"-") -> 2599927.8 | AA53: =IFERROR(IF(SUM(R53,V53)=0,"-",SUM(R53,V53)),"-") -> 4950695.8 | AB53: =IFERROR(IF(SUM(R53,Z53)=0,"-",SUM(R53,Z53)),"-") -> 4333213 | AC53: =0.45*4589184 -> 2065132.8 | AD53: =0.55*4589184 -> 2524051.2 | AE53: - | AF53: - | AG53: - | AH53: =IFERROR(IF(SUM(AC53:AG53)=0,IF(COUNTIF($AC53:$AG53,"=0")>0,"$0","-"),SUM(AC53:AG53)),"-") -> 4589184 | AI53: =IFERROR($AM53/$R53,"-") -> 3.7 | AJ53: =IFERROR(AVERAGE(AI53:AI55),"N/A") -> 3.1533335 | AK53: - | AL53: =IFERROR(IF(ISNUMBER($AK53)=TRUE, $AK53*$R53, $AJ53*$R53), "-") -> 5465626.3 | AM53: =IFERROR($AH53*$K53,"-") -> 6413155.2 | AN53: =IFERROR(IF(SUM(AA53,AM53)=0,"-",SUM(AA53,AM53)),"-") -> 11363851 | AO53: =IFERROR(IF(SUM($AB53,$AL53)=0,"-",SUM($AB53,$AL53)),"-") -> 9798839.2 | AP53: 558144 | AQ53: DC | AR53: =IFERROR(AP53*(12/$I53)*$K53,"-") -> 779978.33 | AS53: =IFERROR(AVERAGE(AR53:AR55),"N/A") -> 743122.5 | AT53: 300964 | AU53: =IFERROR(AT53*(12/$I53)*$K53,"-") -> 420582.14 | AV53: =IFERROR(AVERAGE(AU53:AU55),"N/A") -> 417683.12 | AW53: =IFERROR(IF(SUM(AN53,AR53,AU53)=0,"-",SUM(AN53,AR53,AU53)),"-") -> 12564411 | AX53: =IFERROR(IF(SUM(AO53,AR53,AU53)=0,"-",SUM(AO53,AR53,AU53)),"-") -> 10999400 | AY53: - | AZ53: KP | BA53: sc
A54: =$D54&"_"&$F54&"_"&$L54 -> TSX:K_2024_ | B54: =$D54&"_"&$F54&"_"&$N54 -> TSX:K_2024_CEO | C54: =$D54&"_"&$F54&"_"&$M54 -> TSX:K_2024_ | D54: =D53 -> TSX:K | E54: =_xll.ciqfunctions.udf.CIQ(D54,"IQ_Company_Name") -> Kinross Gold Corporation | F54: =$G$10 -> 2024 | G54: =F54&"-01-01" -> 2024-01-01 | H54: =F54&"-12-31" -> 2024-12-31 | I54: =_xlfn.DAYS(H54,G54)/_xlfn.DAYS(F54&"-12-31",F54&"-01-01")*12 -> 12 | J54: USD | K54: =IF($J54="CAD",1,IF($J54="USD",VLOOKUP($F54,$G$9:$H$11,2,FALSE),"N/A")) -> 1.37017 | N54: =N53 -> CEO | O54: =O53 -> CEO | P54: =P53 -> J. Paul Rollinson | Q54: 1181500 | R54: =IFERROR(Q54*(12/$I54)*$K54,"-") -> 1618855.9 | S54: - | T54: =IFERROR(IF((S54*$K54)=0,"-",(S54*$K54)),"-") -> - | U54: 2259619 | V54: =IFERROR(U54*(12/$I54)*$K54,"-") -> 3096062.2 | W54: =IFERROR($V54/$R54,"-") -> 1.9125002 | Y54: - | Z54: =IFERROR(IF(ISNUMBER($Y54)=TRUE, $Y54*$R54,$X54*$R54),"-") -> 0 | AA54: =IFERROR(IF(SUM(R54,V54)=0,"-",SUM(R54,V54)),"-") -> 4714918 | AB54: =IFERROR(IF(SUM(R54,Z54)=0,"-",SUM(R54,Z54)),"-") -> 1618855.9 | AC54: =0.45*3379090 -> 1520590.5 | AD54: =0.55*3379090 -> 1858499.5 | AE54: - | AF54: - | AG54: - | AH54: =IFERROR(IF(SUM(AC54:AG54)=0,IF(COUNTIF($AC54:$AG54,"=0")>0,"$0","-"),SUM(AC54:AG54)),"-") -> 3379090 | AI54: =IFERROR($AM54/$R54,"-") -> 2.86 | AK54: - | AL54: =IFERROR(IF(ISNUMBER($AK54)=TRUE, $AK54*$R54, $AJ54*$R54), "-") -> 0 | AM54: =IFERROR($AH54*$K54,"-") -> 4629927.7 | AN54: =IFERROR(IF(SUM(AA54,AM54)=0,"-",SUM(AA54,AM54)),"-") -> 9344845.8 | AO54: =IFERROR(IF(SUM($AB54,$AL54)=0,"-",SUM($AB54,$AL54)),"-") -> 1618855.9 | AP54: 531675 | AQ54: DC | AR54: =IFERROR(AP54*(12/$I54)*$K54,"-") -> 728485.13 | AT54: 300233 | AU54: =IFERROR(AT54*(12/$I54)*$K54,"-") -> 411370.25 | AW54: =IFERROR(IF(SUM(AN54,AR54,AU54)=0,"-",SUM(AN54,AR54,AU54)),"-") -> 10484701 | AX54: =IFERROR(IF(SUM(AO54,AR54,AU54)=0,"-",SUM(AO54,AR54,AU54)),"-") -> 2758711.2 | AY54: - | AZ54: KP | BA54: sc
A55: =$D55&"_"&$F55&"_"&$L55 -> TSX:K_2023_ | B55: =$D55&"_"&$F55&"_"&$N55 -> TSX:K_2023_CEO | C55: =$D55&"_"&$F55&"_"&$M55 -> TSX:K_2023_ | D55: =D54 -> TSX:K | E55: =_xll.ciqfunctions.udf.CIQ(D55,"IQ_Company_Name") -> Kinross Gold Corporation | F55: =$G$11 -> 2023 | G55: =F55&"-01-01" -> 2023-01-01 | H55: =F55&"-12-31" -> 2023-12-31 | I55: =_xlfn.DAYS(H55,G55)/_xlfn.DAYS(F55&"-12-31",F55&"-01-01")*12 -> 12 | J55: USD | K55: =IF($J55="CAD",1,IF($J55="USD",VLOOKUP($F55,$G$9:$H$11,2,FALSE),"N/A")) -> 1.34954 | N55: =N54 -> CEO | O55: =O54 -> CEO | P55: =P54 -> J. Paul Rollinson | Q55: 1187077 | R55: =IFERROR(Q55*(12/$I55)*$K55,"-") -> 1602007.9 | S55: - | T55: =IFERROR(IF((S55*$K55)=0,"-",(S55*$K55)),"-") -> - | U55: 2069966 | V55: =IFERROR(U55*(12/$I55)*$K55,"-") -> 2793501.9 | W55: =IFERROR($V55/$R55,"-") -> 1.7437504 | Y55: - | Z55: =IFERROR(IF(ISNUMBER($Y55)=TRUE, $Y55*$R55,$X55*$R55),"-") -> 0 | AA55: =IFERROR(IF(SUM(R55,V55)=0,"-",SUM(R55,V55)),"-") -> 4395509.8 | AB55: =IFERROR(IF(SUM(R55,Z55)=0,"-",SUM(R55,Z55)),"-") -> 1602007.9 | AC55: =0.45*3442524 -> 1549135.8 | AD55: =0.55*3442524 -> 1893388.2 | AE55: - | AF55: - | AG55: - | AH55: =IFERROR(IF(SUM(AC55:AG55)=0,IF(COUNTIF($AC55:$AG55,"=0")>0,"$0","-"),SUM(AC55:AG55)),"-") -> 3442524 | AI55: =IFERROR($AM55/$R55,"-") -> 2.9000006 | AK55: - | AL55: =IFERROR(IF(ISNUMBER($AK55)=TRUE, $AK55*$R55, $AJ55*$R55), "-") -> 0 | AM55: =IFERROR($AH55*$K55,"-") -> 4645823.8 | AN55: =IFERROR(IF(SUM(AA55,AM55)=0,"-",SUM(AA55,AM55)),"-") -> 9041333.6 | AO55: =IFERROR(IF(SUM($AB55,$AL55)=0,"-",SUM($AB55,$AL55)),"-") -> 1602007.9 | AP55: 534185 | AQ55: DC | AR55: =IFERROR(AP55*(12/$I55)*$K55,"-") -> 720904.02 | AT55: 312030 | AU55: =IFERROR(AT55*(12/$I55)*$K55,"-") -> 421096.97 | AW55: =IFERROR(IF(SUM(AN55,AR55,AU55)=0,"-",SUM(AN55,AR55,AU55)),"-") -> 10183335 | AX55: =IFERROR(IF(SUM(AO55,AR55,AU55)=0,"-",SUM(AO55,AR55,AU55)),"-") -> 2744008.9 | AY55: - | AZ55: KP | BA55: sc
A56: =$D56&"_"&$F56&"_"&$L56 -> TSX:K_2025_ | B56: =$D56&"_"&$F56&"_"&$N56 -> TSX:K_2025_CFO | C56: =$D56&"_"&$F56&"_"&$M56 -> TSX:K_2025_ | D56: =D55 -> TSX:K | E56: =_xll.ciqfunctions.udf.CIQ(D56,"IQ_Company_Name") -> Kinross Gold Corporation | F56: =F53 -> 2025 | G56: =F56&"-01-01" -> 2025-01-01 | H56: =F56&"-12-31" -> 2025-12-31 | I56: =_xlfn.DAYS(H56,G56)/_xlfn.DAYS(F56&"-12-31",F56&"-01-01")*12 -> 12 | J56: USD | K56: =IF($J56="CAD",1,IF($J56="USD",VLOOKUP($F56,$G$9:$H$11,2,FALSE),"N/A")) -> 1.39745 | N56: CFO | O56: CFO | P56: Andrea S. Freeborough | Q56: 488832 | R56: =IFERROR(Q56*(12/$I56)*$K56,"-") -> 683118.28 | S56: - | T56: =IFERROR(IF((S56*$K56)=0,"-",(S56*$K56)),"-") -> - | U56: 549936 | V56: =IFERROR(U56*(12/$I56)*$K56,"-") -> 768508.06 | W56: =IFERROR($V56/$R56,"-") -> 1.125 | X56: =IFERROR(AVERAGE(W56:W58),"N/A") -> 1.0852238 | Y56: 0.9 | Z56: =IFERROR(IF(ISNUMBER($Y56)=TRUE, $Y56*$R56,$X56*$R56),"-") -> 614806.45 | AA56: =IFERROR(IF(SUM(R56,V56)=0,"-",SUM(R56,V56)),"-") -> 1451626.3 | AB56: =IFERROR(IF(SUM(R56,Z56)=0,"-",SUM(R56,Z56)),"-") -> 1297924.7 | AC56: =0.45*1143867 -> 514740.15 | AD56: =0.55*1143867 -> 629126.85 | AE56: - | AF56: - | AG56: - | AH56: =IFERROR(IF(SUM(AC56:AG56)=0,IF(COUNTIF($AC56:$AG56,"=0")>0,"$0","-"),SUM(AC56:AG56)),"-") -> 1143867 | AI56: =IFERROR($AM56/$R56,"-") -> 2.3400002 | AJ56: =IFERROR(AVERAGE(AI56:AI58),"N/A") -> 2.1443588 | AK56: - | AL56: =IFERROR(IF(ISNUMBER($AK56)=TRUE, $AK56*$R56, $AJ56*$R56), "-") -> 1464850.7 | AM56: =IFERROR($AH56*$K56,"-") -> 1598496.9 | AN56: =IFERROR(IF(SUM(AA56,AM56)=0,"-",SUM(AA56,AM56)),"-") -> 3050123.3 | AO56: =IFERROR(IF(SUM($AB56,$AL56)=0,"-",SUM($AB56,$AL56)),"-") -> 2762775.4 | AP56: 167181 | AQ56: DC | AR56: =IFERROR(AP56*(12/$I56)*$K56,"-") -> 233627.09 | AS56: =IFERROR(AVERAGE(AR56:AR58),"N/A") -> 203165.45 | AT56: 64868 | AU56: =IFERROR(AT56*(12/$I56)*$K56,"-") -> 90649.787 | AV56: =IFERROR(AVERAGE(AU56:AU58),"N/A") -> 94974.175 | AW56: =IFERROR(IF(SUM(AN56,AR56,AU56)=0,"-",SUM(AN56,AR56,AU56)),"-") -> 3374400.2 | AX56: =IFERROR(IF(SUM(AO56,AR56,AU56)=0,"-",SUM(AO56,AR56,AU56)),"-") -> 3087052.3 | AY56: Ms. Freeborough’s 2024 STI calculated on formula would have been US$518,383. However, the human resources and compensation committee decided to reduce her STI payment by C$41,000 and increase her long-term incentive by the same amount to better align to the company’s target pay mix. | AZ56: KP | BA56: sc
A57: =$D57&"_"&$F57&"_"&$L57 -> TSX:K_2024_ | B57: =$D57&"_"&$F57&"_"&$N57 -> TSX:K_2024_CFO | C57: =$D57&"_"&$F57&"_"&$M57 -> TSX:K_2024_ | D57: =D56 -> TSX:K | E57: =_xll.ciqfunctions.udf.CIQ(D57,"IQ_Company_Name") -> Kinross Gold Corporation | F57: =F54 -> 2024 | G57: =F57&"-01-01" -> 2024-01-01 | H57: =F57&"-12-31" -> 2024-12-31 | I57: =_xlfn.DAYS(H57,G57)/_xlfn.DAYS(F57&"-12-31",F57&"-01-01")*12 -> 12 | J57: USD | K57: =IF($J57="CAD",1,IF($J57="USD",VLOOKUP($F57,$G$9:$H$11,2,FALSE),"N/A")) -> 1.37017 | N57: =N56 -> CFO | O57: =O56 -> CFO | P57: =P56 -> Andrea S. Freeborough | Q57: 451750 | R57: =IFERROR(Q57*(12/$I57)*$K57,"-") -> 618974.3 | S57: - | T57: =IFERROR(IF((S57*$K57)=0,"-",(S57*$K57)),"-") -> - | U57: 489888 | V57: =IFERROR(U57*(12/$I57)*$K57,"-") -> 671229.84 | W57: =IFERROR($V57/$R57,"-") -> 1.0844228 | Y57: - | Z57: =IFERROR(IF(ISNUMBER($Y57)=TRUE, $Y57*$R57,$X57*$R57),"-") -> 0 | AA57: =IFERROR(IF(SUM(R57,V57)=0,"-",SUM(R57,V57)),"-") -> 1290204.1 | AB57: =IFERROR(IF(SUM(R57,Z57)=0,"-",SUM(R57,Z57)),"-") -> 618974.3 | AC57: =0.45*941030 -> 423463.5 | AD57: =0.55*941030 -> 517566.5 | AE57: - | AF57: - | AG57: - | AH57: =IFERROR(IF(SUM(AC57:AG57)=0,IF(COUNTIF($AC57:$AG57,"=0")>0,"$0","-"),SUM(AC57:AG57)),"-") -> 941030 | AI57: =IFERROR($AM57/$R57,"-") -> 2.0830769 | AK57: - | AL57: =IFERROR(IF(ISNUMBER($AK57)=TRUE, $AK57*$R57, $AJ57*$R57), "-") -> 0 | AM57: =IFERROR($AH57*$K57,"-") -> 1289371.1 | AN57: =IFERROR(IF(SUM(AA57,AM57)=0,"-",SUM(AA57,AM57)),"-") -> 2579575.2 | AO57: =IFERROR(IF(SUM($AB57,$AL57)=0,"-",SUM($AB57,$AL57)),"-") -> 618974.3 | AP57: 145916 | AQ57: DC | AR57: =IFERROR(AP57*(12/$I57)*$K57,"-") -> 199929.73 | AT57: 79205 | AU57: =IFERROR(AT57*(12/$I57)*$K57,"-") -> 108524.31 | AW57: =IFERROR(IF(SUM(AN57,AR57,AU57)=0,"-",SUM(AN57,AR57,AU57)),"-") -> 2888029.3 | AX57: =IFERROR(IF(SUM(AO57,AR57,AU57)=0,"-",SUM(AO57,AR57,AU57)),"-") -> 927428.34 | AY57: - | AZ57: KP | BA57: sc
A58: =$D58&"_"&$F58&"_"&$L58 -> TSX:K_2023_ | B58: =$D58&"_"&$F58&"_"&$N58 -> TSX:K_2023_CFO | C58: =$D58&"_"&$F58&"_"&$M58 -> TSX:K_2023_ | D58: =D57 -> TSX:K | E58: =_xll.ciqfunctions.udf.CIQ(D58,"IQ_Company_Name") -> Kinross Gold Corporation | F58: =F55 -> 2023 | G58: =F58&"-01-01" -> 2023-01-01 | H58: =F58&"-12-31" -> 2023-12-31 | I58: =_xlfn.DAYS(H58,G58)/_xlfn.DAYS(F58&"-12-31",F58&"-01-01")*12 -> 12 | J58: USD | K58: =IF($J58="CAD",1,IF($J58="USD",VLOOKUP($F58,$G$9:$H$11,2,FALSE),"N/A")) -> 1.34954 | N58: =N57 -> CFO | O58: =O57 -> CFO | P58: =P57 -> Andrea S. Freeborough | Q58: 457441 | R58: =IFERROR(Q58*(12/$I58)*$K58,"-") -> 617334.93 | S58: - | T58: =IFERROR(IF((S58*$K58)=0,"-",(S58*$K58)),"-") -> - | U58: 478597 | V58: =IFERROR(U58*(12/$I58)*$K58,"-") -> 645885.8 | W58: =IFERROR($V58/$R58,"-") -> 1.0462486 | Y58: - | Z58: =IFERROR(IF(ISNUMBER($Y58)=TRUE, $Y58*$R58,$X58*$R58),"-") -> 0 | AA58: =IFERROR(IF(SUM(R58,V58)=0,"-",SUM(R58,V58)),"-") -> 1263220.7 | AB58: =IFERROR(IF(SUM(R58,Z58)=0,"-",SUM(R58,Z58)),"-") -> 617334.93 | AC58: =0.45*919456 -> 413755.2 | AD58: =0.55*919456 -> 505700.8 | AE58: - | AF58: - | AG58: - | AH58: =IFERROR(IF(SUM(AC58:AG58)=0,IF(COUNTIF($AC58:$AG58,"=0")>0,"$0","-"),SUM(AC58:AG58)),"-") -> 919456 | AI58: =IFERROR($AM58/$R58,"-") -> 2.0099991 | AK58: - | AL58: =IFERROR(IF(ISNUMBER($AK58)=TRUE, $AK58*$R58, $AJ58*$R58), "-") -> 0 | AM58: =IFERROR($AH58*$K58,"-") -> 1240842.7 | AN58: =IFERROR(IF(SUM(AA58,AM58)=0,"-",SUM(AA58,AM58)),"-") -> 2504063.4 | AO58: =IFERROR(IF(SUM($AB58,$AL58)=0,"-",SUM($AB58,$AL58)),"-") -> 617334.93 | AP58: 130370 | AQ58: DC | AR58: =IFERROR(AP58*(12/$I58)*$K58,"-") -> 175939.53 | AT58: 63539 | AU58: =IFERROR(AT58*(12/$I58)*$K58,"-") -> 85748.422 | AW58: =IFERROR(IF(SUM(AN58,AR58,AU58)=0,"-",SUM(AN58,AR58,AU58)),"-") -> 2765751.3 | AX58: =IFERROR(IF(SUM(AO58,AR58,AU58)=0,"-",SUM(AO58,AR58,AU58)),"-") -> 879022.88 | AY58: - | AZ58: KP | BA58: sc
A59: =$D59&"_"&$F59&"_"&$L59 -> TSX:K_2025_ | B59: =$D59&"_"&$F59&"_"&$N59 -> TSX:K_2025_NEO1 | C59: =$D59&"_"&$F59&"_"&$M59 -> TSX:K_2025_2nd Highest | D59: =D58 -> TSX:K | E59: =_xll.ciqfunctions.udf.CIQ(D59,"IQ_Company_Name") -> Kinross Gold Corporation | F59: =F56 -> 2025 | G59: =F59&"-01-01" -> 2025-01-01 | H59: =F59&"-12-31" -> 2025-12-31 | I59: =_xlfn.DAYS(H59,G59)/_xlfn.DAYS(F59&"-12-31",F59&"-01-01")*12 -> 12 | J59: USD | K59: =IF($J59="CAD",1,IF($J59="USD",VLOOKUP($F59,$G$9:$H$11,2,FALSE),"N/A")) -> 1.39745 | M59: 2nd Highest | N59: NEO1 | O59: President | P59: Geoffrey P. Gold | Q59: 656640 | R59: =IFERROR(Q59*(12/$I59)*$K59,"-") -> 917621.57 | S59: - | T59: =IFERROR(IF((S59*$K59)=0,"-",(S59*$K59)),"-") -> - | U59: 1149120 | V59: =IFERROR(U59*(12/$I59)*$K59,"-") -> 1605837.7 | W59: =IFERROR($V59/$R59,"-") -> 1.75 | X59: =IFERROR(AVERAGE(W59:W61),"N/A") -> 1.6563885 | Y59: 1.4 | Z59: =IFERROR(IF(ISNUMBER($Y59)=TRUE, $Y59*$R59,$X59*$R59),"-") -> 1284670.2 | AA59: =IFERROR(IF(SUM(R59,V59)=0,"-",SUM(R59,V59)),"-") -> 2523459.3 | AB59: =IFERROR(IF(SUM(R59,Z59)=0,"-",SUM(R59,Z59)),"-") -> 2202291.8 | AC59: =0.45*1904256 -> 856915.2 | AD59: =0.55*1904256 -> 1047340.8 | AE59: - | AF59: - | AG59: - | AH59: =IFERROR(IF(SUM(AC59:AG59)=0,IF(COUNTIF($AC59:$AG59,"=0")>0,"$0","-"),SUM(AC59:AG59)),"-") -> 1904256 | AI59: =IFERROR($AM59/$R59,"-") -> 2.9 | AJ59: =IFERROR(AVERAGE(AI59:AI61),"N/A") -> 2.7311111 | AK59: - | AL59: =IFERROR(IF(ISNUMBER($AK59)=TRUE, $AK59*$R59, $AJ59*$R59), "-") -> 2506126.5 | AM59: =IFERROR($AH59*$K59,"-") -> 2661102.5 | AN59: =IFERROR(IF(SUM(AA59,AM59)=0,"-",SUM(AA59,AM59)),"-") -> 5184561.9 | AO59: =IFERROR(IF(SUM($AB59,$AL59)=0,"-",SUM($AB59,$AL59)),"-") -> 4708418.2 | AP59: 295488 | AQ59: DC | AR59: =IFERROR(AP59*(12/$I59)*$K59,"-") -> 412929.71 | AS59: =IFERROR(AVERAGE(AR59:AR61),"N/A") -> 399299.15 | AT59: 95581 | AU59: =IFERROR(AT59*(12/$I59)*$K59,"-") -> 133569.67 | AV59: =IFERROR(AVERAGE(AU59:AU61),"N/A") -> 138792.75 | AW59: =IFERROR(IF(SUM(AN59,AR59,AU59)=0,"-",SUM(AN59,AR59,AU59)),"-") -> 5731061.2 | AX59: =IFERROR(IF(SUM(AO59,AR59,AU59)=0,"-",SUM(AO59,AR59,AU59)),"-") -> 5254917.6 | AY59: Mr. Gold’s 2024 STI calculated on formula would have been US$1,116,517. However, the human resources and compensation committee decided to reduce his STI payment by C$200,000 and increase his long-term incentive by the same amount to better align to the company’s target pay mix. | AZ59: KP | BA59: sc | BB59: Geoffrey P Gold - President level lower than CEO
A60: =$D60&"_"&$F60&"_"&$L60 -> TSX:K_2024_ | B60: =$D60&"_"&$F60&"_"&$N60 -> TSX:K_2024_NEO1 | C60: =$D60&"_"&$F60&"_"&$M60 -> TSX:K_2024_ | D60: =D59 -> TSX:K | E60: =_xll.ciqfunctions.udf.CIQ(D60,"IQ_Company_Name") -> Kinross Gold Corporation | F60: =F57 -> 2024 | G60: =F60&"-01-01" -> 2024-01-01 | H60: =F60&"-12-31" -> 2024-12-31 | I60: =_xlfn.DAYS(H60,G60)/_xlfn.DAYS(F60&"-12-31",F60&"-01-01")*12 -> 12 | J60: USD | K60: =IF($J60="CAD",1,IF($J60="USD",VLOOKUP($F60,$G$9:$H$11,2,FALSE),"N/A")) -> 1.37017 | N60: =N59 -> NEO1 | O60: =O59 -> President | P60: =P59 -> Geoffrey P. Gold | Q60: 625500 | R60: =IFERROR(Q60*(12/$I60)*$K60,"-") -> 857041.34 | S60: - | T60: =IFERROR(IF((S60*$K60)=0,"-",(S60*$K60)),"-") -> - | U60: 977517 | V60: =IFERROR(U60*(12/$I60)*$K60,"-") -> 1339364.5 | W60: =IFERROR($V60/$R60,"-") -> 1.562777 | Y60: - | Z60: =IFERROR(IF(ISNUMBER($Y60)=TRUE, $Y60*$R60,$X60*$R60),"-") -> 0 | AA60: =IFERROR(IF(SUM(R60,V60)=0,"-",SUM(R60,V60)),"-") -> 2196405.8 | AB60: =IFERROR(IF(SUM(R60,Z60)=0,"-",SUM(R60,Z60)),"-") -> 857041.34 | AC60: =0.45*1602670 -> 721201.5 | AD60: =0.55*1602670 -> 881468.5 | AE60: - | AF60: - | AG60: - | AH60: =IFERROR(IF(SUM(AC60:AG60)=0,IF(COUNTIF($AC60:$AG60,"=0")>0,"$0","-"),SUM(AC60:AG60)),"-") -> 1602670 | AI60: =IFERROR($AM60/$R60,"-") -> 2.5622222 | AK60: - | AL60: =IFERROR(IF(ISNUMBER($AK60)=TRUE, $AK60*$R60, $AJ60*$R60), "-") -> 0 | AM60: =IFERROR($AH60*$K60,"-") -> 2195930.4 | AN60: =IFERROR(IF(SUM(AA60,AM60)=0,"-",SUM(AA60,AM60)),"-") -> 4392336.2 | AO60: =IFERROR(IF(SUM($AB60,$AL60)=0,"-",SUM($AB60,$AL60)),"-") -> 857041.34 | AP60: 281475 | AQ60: DC | AR60: =IFERROR(AP60*(12/$I60)*$K60,"-") -> 385668.6 | AT60: 105108 | AU60: =IFERROR(AT60*(12/$I60)*$K60,"-") -> 144015.83 | AW60: =IFERROR(IF(SUM(AN60,AR60,AU60)=0,"-",SUM(AN60,AR60,AU60)),"-") -> 4922020.6 | AX60: =IFERROR(IF(SUM(AO60,AR60,AU60)=0,"-",SUM(AO60,AR60,AU60)),"-") -> 1386725.8 | AY60: Mr. Gold was appointed President on January 1, 2024 ; excluding 2023 compensation | AZ60: KP | BA60: sc
A61: =$D61&"_"&$F61&"_"&$L61 -> TSX:K_2023_ | B61: =$D61&"_"&$F61&"_"&$N61 -> TSX:K_2023_NEO1 | C61: =$D61&"_"&$F61&"_"&$M61 -> TSX:K_2023_ | D61: =D60 -> TSX:K | E61: =_xll.ciqfunctions.udf.CIQ(D61,"IQ_Company_Name") -> Kinross Gold Corporation | F61: =F58 -> 2023 | G61: =F61&"-01-01" -> 2023-01-01 | H61: =F61&"-12-31" -> 2023-12-31 | I61: =_xlfn.DAYS(H61,G61)/_xlfn.DAYS(F61&"-12-31",F61&"-01-01")*12 -> 12 | J61: USD | K61: =IF($J61="CAD",1,IF($J61="USD",VLOOKUP($F61,$G$9:$H$11,2,FALSE),"N/A")) -> 1.34954 | N61: =N60 -> NEO1 | O61: =O60 -> President | P61: =P60 -> Geoffrey P. Gold | Q61: - | R61: =IFERROR(Q61*(12/$I61)*$K61,"-") -> - | S61: - | T61: =IFERROR(IF((S61*$K61)=0,"-",(S61*$K61)),"-") -> - | U61: - | V61: =IFERROR(U61*(12/$I61)*$K61,"-") -> - | W61: =IFERROR($V61/$R61,"-") -> - | Y61: - | Z61: =IFERROR(IF(ISNUMBER($Y61)=TRUE, $Y61*$R61,$X61*$R61),"-") -> - | AA61: =IFERROR(IF(SUM(R61,V61)=0,"-",SUM(R61,V61)),"-") -> - | AB61: =IFERROR(IF(SUM(R61,Z61)=0,"-",SUM(R61,Z61)),"-") -> - | AC61: - | AD61: - | AE61: - | AF61: - | AG61: - | AH61: =IFERROR(IF(SUM(AC61:AG61)=0,IF(COUNTIF($AC61:$AG61,"=0")>0,"$0","-"),SUM(AC61:AG61)),"-") -> - | AI61: =IFERROR($AM61/$R61,"-") -> - | AK61: - | AL61: =IFERROR(IF(ISNUMBER($AK61)=TRUE, $AK61*$R61, $AJ61*$R61), "-") -> - | AM61: =IFERROR($AH61*$K61,"-") -> - | AN61: =IFERROR(IF(SUM(AA61,AM61)=0,"-",SUM(AA61,AM61)),"-") -> - | AO61: =IFERROR(IF(SUM($AB61,$AL61)=0,"-",SUM($AB61,$AL61)),"-") -> - | AP61: - | AQ61: DC | AR61: =IFERROR(AP61*(12/$I61)*$K61,"-") -> - | AT61: - | AU61: =IFERROR(AT61*(12/$I61)*$K61,"-") -> - | AW61: =IFERROR(IF(SUM(AN61,AR61,AU61)=0,"-",SUM(AN61,AR61,AU61)),"-") -> - | AX61: =IFERROR(IF(SUM(AO61,AR61,AU61)=0,"-",SUM(AO61,AR61,AU61)),"-") -> - | AY61: - | AZ61: KP | BA61: sc
A62: =$D62&"_"&$F62&"_"&$L62 -> TSX:K_2025_COO | B62: =$D62&"_"&$F62&"_"&$N62 -> TSX:K_2025_NEO2 | C62: =$D62&"_"&$F62&"_"&$M62 -> TSX:K_2025_ | D62: =D61 -> TSX:K | E62: =_xll.ciqfunctions.udf.CIQ(D62,"IQ_Company_Name") -> Kinross Gold Corporation | F62: =F59 -> 2025 | G62: =F62&"-01-01" -> 2025-01-01 | H62: =F62&"-12-31" -> 2025-12-31 | I62: =_xlfn.DAYS(H62,G62)/_xlfn.DAYS(F62&"-12-31",F62&"-01-01")*12 -> 12 | J62: USD | K62: =IF($J62="CAD",1,IF($J62="USD",VLOOKUP($F62,$G$9:$H$11,2,FALSE),"N/A")) -> 1.39745 | L62: COO | N62: NEO2 | O62: EVP & COO | P62: Claude J.S. Schimper | Q62: 488832 | R62: =IFERROR(Q62*(12/$I62)*$K62,"-") -> 683118.28 | S62: - | T62: =IFERROR(IF((S62*$K62)=0,"-",(S62*$K62)),"-") -> - | U62: 544437 | V62: =IFERROR(U62*(12/$I62)*$K62,"-") -> 760823.49 | W62: =IFERROR($V62/$R62,"-") -> 1.1137507 | X62: =IFERROR(AVERAGE(W62:W64),"N/A") -> 1.1100004 | Y62: 0.9 | Z62: =IFERROR(IF(ISNUMBER($Y62)=TRUE, $Y62*$R62,$X62*$R62),"-") -> 614806.45 | AA62: =IFERROR(IF(SUM(R62,V62)=0,"-",SUM(R62,V62)),"-") -> 1443941.8 | AB62: =IFERROR(IF(SUM(R62,Z62)=0,"-",SUM(R62,Z62)),"-") -> 1297924.7 | AC62: =0.45*1222080 -> 549936 | AD62: =0.55*1222080 -> 672144 | AE62: - | AF62: - | AG62: - | AH62: =IFERROR(IF(SUM(AC62:AG62)=0,IF(COUNTIF($AC62:$AG62,"=0")>0,"$0","-"),SUM(AC62:AG62)),"-") -> 1222080 | AI62: =IFERROR($AM62/$R62,"-") -> 2.5 | AJ62: =IFERROR(AVERAGE(AI62:AI64),"N/A") -> 2.2866667 | AK62: - | AL62: =IFERROR(IF(ISNUMBER($AK62)=TRUE, $AK62*$R62, $AJ62*$R62), "-") -> 1562063.8 | AM62: =IFERROR($AH62*$K62,"-") -> 1707795.7 | AN62: =IFERROR(IF(SUM(AA62,AM62)=0,"-",SUM(AA62,AM62)),"-") -> 3151737.5 | AO62: =IFERROR(IF(SUM($AB62,$AL62)=0,"-",SUM($AB62,$AL62)),"-") -> 2859988.5 | AP62: 139319 | AQ62: DC | AR62: =IFERROR(AP62*(12/$I62)*$K62,"-") -> 194691.34 | AS62: =IFERROR(AVERAGE(AR62:AR64),"N/A") -> 181862.27 | AT62: 76532 | AU62: =IFERROR(AT62*(12/$I62)*$K62,"-") -> 106949.64 | AV62: =IFERROR(AVERAGE(AU62:AU64),"N/A") -> 150583.58 | AW62: =IFERROR(IF(SUM(AN62,AR62,AU62)=0,"-",SUM(AN62,AR62,AU62)),"-") -> 3453378.4 | AX62: =IFERROR(IF(SUM(AO62,AR62,AU62)=0,"-",SUM(AO62,AR62,AU62)),"-") -> 3161629.5 | AY62: - | AZ62: KP | BA62: sc
A63: =$D63&"_"&$F63&"_"&$L63 -> TSX:K_2024_COO | B63: =$D63&"_"&$F63&"_"&$N63 -> TSX:K_2024_NEO2 | C63: =$D63&"_"&$F63&"_"&$M63 -> TSX:K_2024_ | D63: =D62 -> TSX:K | E63: =_xll.ciqfunctions.udf.CIQ(D63,"IQ_Company_Name") -> Kinross Gold Corporation | F63: =F60 -> 2024 | G63: =F63&"-01-01" -> 2024-01-01 | H63: =F63&"-12-31" -> 2024-12-31 | I63: =_xlfn.DAYS(H63,G63)/_xlfn.DAYS(F63&"-12-31",F63&"-01-01")*12 -> 12 | J63: USD | K63: =IF($J63="CAD",1,IF($J63="USD",VLOOKUP($F63,$G$9:$H$11,2,FALSE),"N/A")) -> 1.37017 | L63: COO | N63: =N62 -> NEO2 | O63: =O62 -> EVP & COO | P63: =P62 -> Claude J.S. Schimper | Q63: 451750 | R63: =IFERROR(Q63*(12/$I63)*$K63,"-") -> 618974.3 | S63: - | T63: =IFERROR(IF((S63*$K63)=0,"-",(S63*$K63)),"-") -> - | U63: 523465 | V63: =IFERROR(U63*(12/$I63)*$K63,"-") -> 717236.04 | W63: =IFERROR($V63/$R63,"-") -> 1.1587493 | Y63: - | Z63: =IFERROR(IF(ISNUMBER($Y63)=TRUE, $Y63*$R63,$X63*$R63),"-") -> 0 | AA63: =IFERROR(IF(SUM(R63,V63)=0,"-",SUM(R63,V63)),"-") -> 1336210.3 | AB63: =IFERROR(IF(SUM(R63,Z63)=0,"-",SUM(R63,Z63)),"-") -> 618974.3 | AC63: =0.45*975780 -> 439101 | AD63: =0.55*975780 -> 536679 | AE63: - | AF63: - | AG63: - | AH63: =IFERROR(IF(SUM(AC63:AG63)=0,IF(COUNTIF($AC63:$AG63,"=0")>0,"$0","-"),SUM(AC63:AG63)),"-") -> 975780 | AI63: =IFERROR($AM63/$R63,"-") -> 2.16 | AK63: - | AL63: =IFERROR(IF(ISNUMBER($AK63)=TRUE, $AK63*$R63, $AJ63*$R63), "-") -> 0 | AM63: =IFERROR($AH63*$K63,"-") -> 1336984.5 | AN63: =IFERROR(IF(SUM(AA63,AM63)=0,"-",SUM(AA63,AM63)),"-") -> 2673194.8 | AO63: =IFERROR(IF(SUM($AB63,$AL63)=0,"-",SUM($AB63,$AL63)),"-") -> 618974.3 | AP63: 128750 | AQ63: DC | AR63: =IFERROR(AP63*(12/$I63)*$K63,"-") -> 176409.39 | AT63: 97423 | AU63: =IFERROR(AT63*(12/$I63)*$K63,"-") -> 133486.07 | AW63: =IFERROR(IF(SUM(AN63,AR63,AU63)=0,"-",SUM(AN63,AR63,AU63)),"-") -> 2983090.3 | AX63: =IFERROR(IF(SUM(AO63,AR63,AU63)=0,"-",SUM(AO63,AR63,AU63)),"-") -> 928869.76 | AY63: - | AZ63: KP | BA63: sc
A64: =$D64&"_"&$F64&"_"&$L64 -> TSX:K_2023_COO | B64: =$D64&"_"&$F64&"_"&$N64 -> TSX:K_2023_NEO2 | C64: =$D64&"_"&$F64&"_"&$M64 -> TSX:K_2023_ | D64: =D63 -> TSX:K | E64: =_xll.ciqfunctions.udf.CIQ(D64,"IQ_Company_Name") -> Kinross Gold Corporation | F64: =F61 -> 2023 | G64: =F64&"-01-01" -> 2023-01-01 | H64: =F64&"-12-31" -> 2023-12-31 | I64: =_xlfn.DAYS(H64,G64)/_xlfn.DAYS(F64&"-12-31",F64&"-01-01")*12 -> 12 | J64: USD | K64: =IF($J64="CAD",1,IF($J64="USD",VLOOKUP($F64,$G$9:$H$11,2,FALSE),"N/A")) -> 1.34954 | L64: COO | N64: =N63 -> NEO2 | O64: =O63 -> EVP & COO | P64: =P63 -> Claude J.S. Schimper | Q64: 453660 | R64: =IFERROR(Q64*(12/$I64)*$K64,"-") -> 612232.32 | S64: - | T64: =IFERROR(IF((S64*$K64)=0,"-",(S64*$K64)),"-") -> - | U64: 479746 | V64: =IFERROR(U64*(12/$I64)*$K64,"-") -> 647436.42 | W64: =IFERROR($V64/$R64,"-") -> 1.0575012 | Y64: - | Z64: =IFERROR(IF(ISNUMBER($Y64)=TRUE, $Y64*$R64,$X64*$R64),"-") -> 0 | AA64: =IFERROR(IF(SUM(R64,V64)=0,"-",SUM(R64,V64)),"-") -> 1259668.7 | AB64: =IFERROR(IF(SUM(R64,Z64)=0,"-",SUM(R64,Z64)),"-") -> 612232.32 | AC64: =0.45*998052 -> 449123.4 | AD64: =0.55*998052 -> 548928.6 | AE64: - | AF64: - | AG64: - | AH64: =IFERROR(IF(SUM(AC64:AG64)=0,IF(COUNTIF($AC64:$AG64,"=0")>0,"$0","-"),SUM(AC64:AG64)),"-") -> 998052 | AI64: =IFERROR($AM64/$R64,"-") -> 2.2 | AK64: - | AL64: =IFERROR(IF(ISNUMBER($AK64)=TRUE, $AK64*$R64, $AJ64*$R64), "-") -> 0 | AM64: =IFERROR($AH64*$K64,"-") -> 1346911.1 | AN64: =IFERROR(IF(SUM(AA64,AM64)=0,"-",SUM(AA64,AM64)),"-") -> 2606579.8 | AO64: =IFERROR(IF(SUM($AB64,$AL64)=0,"-",SUM($AB64,$AL64)),"-") -> 612232.32 | AP64: 129293 | AQ64: DC | AR64: =IFERROR(AP64*(12/$I64)*$K64,"-") -> 174486.08 | AT64: 156583 | AU64: =IFERROR(AT64*(12/$I64)*$K64,"-") -> 211315.02 | AW64: =IFERROR(IF(SUM(AN64,AR64,AU64)=0,"-",SUM(AN64,AR64,AU64)),"-") -> 2992380.9 | AX64: =IFERROR(IF(SUM(AO64,AR64,AU64)=0,"-",SUM(AO64,AR64,AU64)),"-") -> 998033.41 | AY64: - | AZ64: KP | BA64: sc
A65: =$D65&"_"&$F65&"_"&$L65 -> TSX:K_2025_ | B65: =$D65&"_"&$F65&"_"&$N65 -> TSX:K_2025_NEO3 | C65: =$D65&"_"&$F65&"_"&$M65 -> TSX:K_2025_ | D65: =D64 -> TSX:K | E65: =_xll.ciqfunctions.udf.CIQ(D65,"IQ_Company_Name") -> Kinross Gold Corporation | F65: =F62 -> 2025 | G65: =F65&"-01-01" -> 2025-01-01 | H65: =F65&"-12-31" -> 2025-12-31 | I65: =_xlfn.DAYS(H65,G65)/_xlfn.DAYS(F65&"-12-31",F65&"-01-01")*12 -> 12 | J65: USD | K65: =IF($J65="CAD",1,IF($J65="USD",VLOOKUP($F65,$G$9:$H$11,2,FALSE),"N/A")) -> 1.39745 | N65: NEO3 | O65: EVP, Corporate Development | P65: Ryan J. Latinovich | Q65: 474240 | R65: =IFERROR(Q65*(12/$I65)*$K65,"-") -> 662726.69 | S65: - | T65: =IFERROR(IF((S65*$K65)=0,"-",(S65*$K65)),"-") -> - | U65: 517514 | V65: =IFERROR(U65*(12/$I65)*$K65,"-") -> 723199.94 | W65: =IFERROR($V65/$R65,"-") -> 1.0912492 | X65: =IFERROR(AVERAGE(W65:W67),"N/A") -> 1.0912492 | Y65: 0.9 | Z65: =IFERROR(IF(ISNUMBER($Y65)=TRUE, $Y65*$R65,$X65*$R65),"-") -> 596454.02 | AA65: =IFERROR(IF(SUM(R65,V65)=0,"-",SUM(R65,V65)),"-") -> 1385926.6 | AB65: =IFERROR(IF(SUM(R65,Z65)=0,"-",SUM(R65,Z65)),"-") -> 1259180.7 | AC65: =0.45*972192 -> 437486.4 | AD65: =0.55*972192 -> 534705.6 | AE65: - | AF65: - | AG65: - | AH65: =IFERROR(IF(SUM(AC65:AG65)=0,IF(COUNTIF($AC65:$AG65,"=0")>0,"$0","-"),SUM(AC65:AG65)),"-") -> 972192 | AI65: =IFERROR($AM65/$R65,"-") -> 2.05 | AJ65: =IFERROR(AVERAGE(AI65:AI67),"N/A") -> 2.05 | AK65: - | AL65: =IFERROR(IF(ISNUMBER($AK65)=TRUE, $AK65*$R65, $AJ65*$R65), "-") -> 1358589.7 | AM65: =IFERROR($AH65*$K65,"-") -> 1358589.7 | AN65: =IFERROR(IF(SUM(AA65,AM65)=0,"-",SUM(AA65,AM65)),"-") -> 2744516.3 | AO65: =IFERROR(IF(SUM($AB65,$AL65)=0,"-",SUM($AB65,$AL65)),"-") -> 2617770.4 | AP65: 135160 | AQ65: DC | AR65: =IFERROR(AP65*(12/$I65)*$K65,"-") -> 188879.34 | AS65: =IFERROR(AVERAGE(AR65:AR67),"N/A") -> 188879.34 | AT65: 70966 | AU65: =IFERROR(AT65*(12/$I65)*$K65,"-") -> 99171.437 | AV65: =IFERROR(AVERAGE(AU65:AU67),"N/A") -> 99171.437 | AW65: =IFERROR(IF(SUM(AN65,AR65,AU65)=0,"-",SUM(AN65,AR65,AU65)),"-") -> 3032567.1 | AX65: =IFERROR(IF(SUM(AO65,AR65,AU65)=0,"-",SUM(AO65,AR65,AU65)),"-") -> 2905821.2 | AY65: Joined in Dec 2024, and received an hire grant of C1.5M in RSUs, but this was not included since only the full year of pay for 2025 was recorded. He also received a signing bonus of C$500K, which was not included. | AZ65: KP | BA65: sc
A66: =$D66&"_"&$F66&"_"&$L66 -> TSX:K_2024_ | B66: =$D66&"_"&$F66&"_"&$N66 -> TSX:K_2024_NEO3 | C66: =$D66&"_"&$F66&"_"&$M66 -> TSX:K_2024_ | D66: =D65 -> TSX:K | E66: =_xll.ciqfunctions.udf.CIQ(D66,"IQ_Company_Name") -> Kinross Gold Corporation | F66: =F63 -> 2024 | G66: =F66&"-12-01" -> 2024-12-01 | H66: =F66&"-12-31" -> 2024-12-31 | I66: =_xlfn.DAYS(H66,G66)/_xlfn.DAYS(F66&"-12-31",F66&"-01-01")*12 -> 0.98630137 | J66: USD | K66: =IF($J66="CAD",1,IF($J66="USD",VLOOKUP($F66,$G$9:$H$11,2,FALSE),"N/A")) -> 1.37017 | N66: =N65 -> NEO3 | O66: =O65 -> EVP, Corporate Development | P66: =P65 -> Ryan J. Latinovich | Q66: - | R66: =IFERROR(Q66*(12/$I66)*$K66,"-") -> - | S66: - | T66: =IFERROR(IF((S66*$K66)=0,"-",(S66*$K66)),"-") -> - | U66: - | W66: =IFERROR($V66/$R66,"-") -> - | Y66: - | Z66: =IFERROR(IF(ISNUMBER($Y66)=TRUE, $Y66*$R66,$X66*$R66),"-") -> - | AA66: =IFERROR(IF(SUM(R66,V66)=0,"-",SUM(R66,V66)),"-") -> - | AB66: =IFERROR(IF(SUM(R66,Z66)=0,"-",SUM(R66,Z66)),"-") -> - | AC66: - | AD66: - | AE66: - | AF66: - | AG66: - | AH66: =IFERROR(IF(SUM(AC66:AG66)=0,IF(COUNTIF($AC66:$AG66,"=0")>0,"$0","-"),SUM(AC66:AG66)),"-") -> - | AI66: =IFERROR($AM66/$R66,"-") -> - | AK66: - | AL66: =IFERROR(IF(ISNUMBER($AK66)=TRUE, $AK66*$R66, $AJ66*$R66), "-") -> - | AM66: =IFERROR($AH66*$K66,"-") -> - | AN66: =IFERROR(IF(SUM(AA66,AM66)=0,"-",SUM(AA66,AM66)),"-") -> - | AO66: =IFERROR(IF(SUM($AB66,$AL66)=0,"-",SUM($AB66,$AL66)),"-") -> - | AP66: - | AQ66: - | AR66: =IFERROR(AP66*(12/$I66)*$K66,"-") -> - | AT66: - | AU66: =IFERROR(AT66*(12/$I66)*$K66,"-") -> - | AY66: - | AZ66: KP | BA66: sc
A67: =$D67&"_"&$F67&"_"&$L67 -> TSX:K_2023_ | B67: =$D67&"_"&$F67&"_"&$N67 -> TSX:K_2023_NEO3 | C67: =$D67&"_"&$F67&"_"&$M67 -> TSX:K_2023_ | D67: =D66 -> TSX:K | E67: =_xll.ciqfunctions.udf.CIQ(D67,"IQ_Company_Name") -> Kinross Gold Corporation | F67: =F64 -> 2023 | G67: =F67&"-01-01" -> 2023-01-01 | H67: =F67&"-12-31" -> 2023-12-31 | I67: =_xlfn.DAYS(H67,G67)/_xlfn.DAYS(F67&"-12-31",F67&"-01-01")*12 -> 12 | J67: USD | K67: =IF($J67="CAD",1,IF($J67="USD",VLOOKUP($F67,$G$9:$H$11,2,FALSE),"N/A")) -> 1.34954 | N67: =N66 -> NEO3 | O67: =O66 -> EVP, Corporate Development | P67: =P66 -> Ryan J. Latinovich | Q67: - | R67: =IFERROR(Q67*(12/$I67)*$K67,"-") -> - | S67: - | T67: =IFERROR(IF((S67*$K67)=0,"-",(S67*$K67)),"-") -> - | U67: - | Y67: - | AC67: - | AD67: - | AE67: - | AF67: - | AG67: - | AK67: - | AP67: - | AQ67: - | AR67: =IFERROR(AP67*(12/$I67)*$K67,"-") -> - | AT67: - | AU67: =IFERROR(AT67*(12/$I67)*$K67,"-") -> - | AY67: - | AZ67: KP | BA67: sc
A68: =$D68&"_"&$F68&"_"&$L68 -> TSX:LUN_2025_ | B68: =$D68&"_"&$F68&"_"&$N68 -> TSX:LUN_2025_CEO | C68: =$D68&"_"&$F68&"_"&$M68 -> TSX:LUN_2025_ | D68: =E6 -> TSX:LUN | E68: =_xll.ciqfunctions.udf.CIQ(D68,"IQ_Company_Name") -> Lundin Mining Corporation | F68: =$G$9 -> 2025 | G68: =F68&"-01-01" -> 2025-01-01 | H68: =F68&"-12-31" -> 2025-12-31 | I68: =_xlfn.DAYS(H68,G68)/_xlfn.DAYS(F68&"-12-31",F68&"-01-01")*12 -> 12 | J68: USD | K68: =IF($J68="CAD",1,IF($J68="USD",VLOOKUP($F68,$G$9:$H$11,2,FALSE),"N/A")) -> 1.39745 | N68: CEO | O68: CEO | P68: Jack Lundin | Q68: 608235 | R68: 850000 | S68: 644013 | T68: 900000 | U68: 974607 | V68: =IFERROR(U68*(12/$I68)*$K68,"-") -> 1361964.6 | W68: =IFERROR($V68/$R68,"-") -> 1.6023112 | X68: =IFERROR(AVERAGE(W68:W70),"N/A") -> 1.9805665 | Y68: 1.2 | Z68: =IFERROR(IF(ISNUMBER($Y68)=TRUE, $Y68*$R68,$X68*$R68),"-") -> 1020000 | AA68: =IFERROR(IF(SUM(R68,V68)=0,"-",SUM(R68,V68)),"-") -> 2211964.6 | AB68: =IFERROR(IF(SUM(R68,Z68)=0,"-",SUM(R68,Z68)),"-") -> 1870000 | AC68: - | AD68: 1853781 | AE68: 1852964 | AF68: - | AG68: - | AH68: =IFERROR(IF(SUM(AC68:AG68)=0,IF(COUNTIF($AC68:$AG68,"=0")>0,"$0","-"),SUM(AC68:AG68)),"-") -> 3706745 | AI68: =IFERROR($AM68/$R68,"-") -> 6.0941068 | AJ68: =IFERROR(AVERAGE(AI68:AI70),"N/A") -> 4.5233271 | AK68: 4 | AL68: =IFERROR(IF(ISNUMBER($AK68)=TRUE, $AK68*$R68, $AJ68*$R68), "-") -> 3400000 | AM68: =IFERROR($AH68*$K68,"-") -> 5179990.8 | AN68: =IFERROR(IF(SUM(AA68,AM68)=0,"-",SUM(AA68,AM68)),"-") -> 7391955.4 | AO68: =IFERROR(IF(SUM($AB68,$AL68)=0,"-",SUM($AB68,$AL68)),"-") -> 5270000 | AP68: N/A | AQ68: N/A | AR68: =IFERROR(AP68*(12/$I68)*$K68,"-") -> - | AS68: =IFERROR(AVERAGE(AR68:AR70),"N/A") -> 0 | AT68: 30732 | AU68: =IFERROR(AT68*(12/$I68)*$K68,"-") -> 42946.433 | AV68: =IFERROR(AVERAGE(AU68:AU70),"N/A") -> 29571.407 | AW68: =IFERROR(IF(SUM(AN68,AR68,AU68)=0,"-",SUM(AN68,AR68,AU68)),"-") -> 7434901.8 | AX68: =IFERROR(IF(SUM(AO68,AR68,AU68)=0,"-",SUM(AO68,AR68,AU68)),"-") -> 5312946.4 | AY68: Jack Lundin was promoted from President to Chief Executive Officer in December 2023. 2026 LTIP target was used (400%), instead of his 300% 2025 target. | AZ68: KP | BA68: sc
A69: =$D69&"_"&$F69&"_"&$L69 -> TSX:LUN_2024_ | B69: =$D69&"_"&$F69&"_"&$N69 -> TSX:LUN_2024_CEO | C69: =$D69&"_"&$F69&"_"&$M69 -> TSX:LUN_2024_ | D69: =D68 -> TSX:LUN | E69: =_xll.ciqfunctions.udf.CIQ(D69,"IQ_Company_Name") -> Lundin Mining Corporation | F69: =$G$10 -> 2024 | G69: =F69&"-01-01" -> 2024-01-01 | H69: =F69&"-12-31" -> 2024-12-31 | I69: =_xlfn.DAYS(H69,G69)/_xlfn.DAYS(F69&"-12-31",F69&"-01-01")*12 -> 12 | J69: USD | K69: =IF($J69="CAD",1,IF($J69="USD",VLOOKUP($F69,$G$9:$H$11,2,FALSE),"N/A")) -> 1.37017 | N69: =N68 -> CEO | O69: =O68 -> CEO | P69: =P68 -> Jack Lundin | Q69: 620620 | R69: =IFERROR(Q69*(12/$I69)*$K69,"-") -> 850354.91 | S69: - | T69: =IFERROR(IF((S69*$K69)=0,"-",(S69*$K69)),"-") -> - | U69: 1463932 | V69: =IFERROR(U69*(12/$I69)*$K69,"-") -> 2005835.7 | W69: =IFERROR($V69/$R69,"-") -> 2.3588218 | Y69: - | Z69: =IFERROR(IF(ISNUMBER($Y69)=TRUE, $Y69*$R69,$X69*$R69),"-") -> 0 | AA69: =IFERROR(IF(SUM(R69,V69)=0,"-",SUM(R69,V69)),"-") -> 2856190.6 | AB69: =IFERROR(IF(SUM(R69,Z69)=0,"-",SUM(R69,Z69)),"-") -> 850354.91 | AC69: - | AD69: =915876 -> 915876 | AE69: 916534 | AF69: - | AG69: - | AH69: =IFERROR(IF(SUM(AC69:AG69)=0,IF(COUNTIF($AC69:$AG69,"=0")>0,"$0","-"),SUM(AC69:AG69)),"-") -> 1832410 | AI69: =IFERROR($AM69/$R69,"-") -> 2.9525475 | AK69: - | AL69: =IFERROR(IF(ISNUMBER($AK69)=TRUE, $AK69*$R69, $AJ69*$R69), "-") -> 0 | AM69: =IFERROR($AH69*$K69,"-") -> 2510713.2 | AN69: =IFERROR(IF(SUM(AA69,AM69)=0,"-",SUM(AA69,AM69)),"-") -> 5366903.8 | AO69: =IFERROR(IF(SUM($AB69,$AL69)=0,"-",SUM($AB69,$AL69)),"-") -> 850354.91 | AP69: N/A | AQ69: N/A | AR69: =IFERROR(AP69*(12/$I69)*$K69,"-") -> - | AT69: 33403 | AU69: =IFERROR(AT69*(12/$I69)*$K69,"-") -> 45767.789 | AW69: =IFERROR(IF(SUM(AN69,AR69,AU69)=0,"-",SUM(AN69,AR69,AU69)),"-") -> 5412671.6 | AX69: =IFERROR(IF(SUM(AO69,AR69,AU69)=0,"-",SUM(AO69,AR69,AU69)),"-") -> 896122.69 | AY69: - | AZ69: KP | BA69: sc
A70: =$D70&"_"&$F70&"_"&$L70 -> TSX:LUN_2023_ | B70: =$D70&"_"&$F70&"_"&$N70 -> TSX:LUN_2023_CEO | C70: =$D70&"_"&$F70&"_"&$M70 -> TSX:LUN_2023_ | D70: =D69 -> TSX:LUN | E70: =_xll.ciqfunctions.udf.CIQ(D70,"IQ_Company_Name") -> Lundin Mining Corporation | F70: =$G$11 -> 2023 | G70: =F70&"-12-01" -> 2023-12-01 | H70: =F70&"-12-31" -> 2023-12-31 | I70: =_xlfn.DAYS(H70,G70)/_xlfn.DAYS(F70&"-12-31",F70&"-01-01")*12 -> 0.98901099 | J70: USD | K70: =IF($J70="CAD",1,IF($J70="USD",VLOOKUP($F70,$G$9:$H$11,2,FALSE),"N/A")) -> 1.34954 | N70: =N69 -> CEO | O70: =O69 -> CEO | P70: =P69 -> Jack Lundin | Q70: - | R70: =IFERROR(Q70*(12/$I70)*$K70,"-") -> - | S70: - | T70: =IFERROR(IF((S70*$K70)=0,"-",(S70*$K70)),"-") -> - | V70: =IFERROR(U70*(12/$I70)*$K70,"-") -> 0 | W70: =IFERROR($V70/$R70,"-") -> - | Y70: - | Z70: =IFERROR(IF(ISNUMBER($Y70)=TRUE, $Y70*$R70,$X70*$R70),"-") -> - | AA70: =IFERROR(IF(SUM(R70,V70)=0,"-",SUM(R70,V70)),"-") -> - | AB70: =IFERROR(IF(SUM(R70,Z70)=0,"-",SUM(R70,Z70)),"-") -> - | AF70: - | AG70: - | AH70: =IFERROR(IF(SUM(AC70:AG70)=0,IF(COUNTIF($AC70:$AG70,"=0")>0,"$0","-"),SUM(AC70:AG70)),"-") -> - | AI70: =IFERROR($AM70/$R70,"-") -> - | AK70: - | AL70: =IFERROR(IF(ISNUMBER($AK70)=TRUE, $AK70*$R70, $AJ70*$R70), "-") -> - | AM70: =IFERROR($AH70*$K70,"-") -> - | AN70: =IFERROR(IF(SUM(AA70,AM70)=0,"-",SUM(AA70,AM70)),"-") -> - | AO70: =IFERROR(IF(SUM($AB70,$AL70)=0,"-",SUM($AB70,$AL70)),"-") -> - | AR70: =IFERROR(AP70*(12/$I70)*$K70,"-") -> 0 | AU70: =IFERROR(AT70*(12/$I70)*$K70,"-") -> 0 | AW70: =IFERROR(IF(SUM(AN70,AR70,AU70)=0,"-",SUM(AN70,AR70,AU70)),"-") -> - | AX70: =IFERROR(IF(SUM(AO70,AR70,AU70)=0,"-",SUM(AO70,AR70,AU70)),"-") -> - | AY70: - | AZ70: KP | BA70: sc
A71: =$D71&"_"&$F71&"_"&$L71 -> TSX:LUN_2025_ | B71: =$D71&"_"&$F71&"_"&$N71 -> TSX:LUN_2025_CFO | C71: =$D71&"_"&$F71&"_"&$M71 -> TSX:LUN_2025_ | D71: =D70 -> TSX:LUN | E71: =_xll.ciqfunctions.udf.CIQ(D71,"IQ_Company_Name") -> Lundin Mining Corporation | F71: =F68 -> 2025 | G71: =F71&"-01-01" -> 2025-01-01 | H71: =F71&"-12-31" -> 2025-12-31 | I71: =_xlfn.DAYS(H71,G71)/_xlfn.DAYS(F71&"-12-31",F71&"-01-01")*12 -> 12 | J71: USD | K71: =IF($J71="CAD",1,IF($J71="USD",VLOOKUP($F71,$G$9:$H$11,2,FALSE),"N/A")) -> 1.39745 | N71: CFO | O71: CFO | P71: Teitur Poulsen | Q71: 542402 | R71: 758000 | S71: 599648 | T71: 838000 | U71: 579612 | V71: =IFERROR(U71*(12/$I71)*$K71,"-") -> 809978.79 | W71: =IFERROR($V71/$R71,"-") -> 1.0685736 | X71: =IFERROR(AVERAGE(W71:W73),"N/A") -> 1.2892132 | Y71: 0.8 | Z71: =IFERROR(IF(ISNUMBER($Y71)=TRUE, $Y71*$R71,$X71*$R71),"-") -> 606400 | AA71: =IFERROR(IF(SUM(R71,V71)=0,"-",SUM(R71,V71)),"-") -> 1567978.8 | AB71: =IFERROR(IF(SUM(R71,Z71)=0,"-",SUM(R71,Z71)),"-") -> 1364400 | AC71: - | AD71: 862993 | AE71: 862629 | AF71: - | AG71: - | AH71: =IFERROR(IF(SUM(AC71:AG71)=0,IF(COUNTIF($AC71:$AG71,"=0")>0,"$0","-"),SUM(AC71:AG71)),"-") -> 1725622 | AI71: =IFERROR($AM71/$R71,"-") -> 3.1813595 | AJ71: =IFERROR(AVERAGE(AI71:AI73),"N/A") -> 2.1400921 | AK71: - | AL71: =IFERROR(IF(ISNUMBER($AK71)=TRUE, $AK71*$R71, $AJ71*$R71), "-") -> 1622189.8 | AM71: =IFERROR($AH71*$K71,"-") -> 2411470.5 | AN71: =IFERROR(IF(SUM(AA71,AM71)=0,"-",SUM(AA71,AM71)),"-") -> 3979449.3 | AO71: =IFERROR(IF(SUM($AB71,$AL71)=0,"-",SUM($AB71,$AL71)),"-") -> 2986589.8 | AP71: N/A | AQ71: N/A | AR71: =IFERROR(AP71*(12/$I71)*$K71,"-") -> - | AS71: =IFERROR(AVERAGE(AR71:AR73),"N/A") -> N/A | AT71: 28676 | AU71: =IFERROR(AT71*(12/$I71)*$K71,"-") -> 40073.276 | AV71: =IFERROR(AVERAGE(AU71:AU73),"N/A") -> 96656.932 | AW71: =IFERROR(IF(SUM(AN71,AR71,AU71)=0,"-",SUM(AN71,AR71,AU71)),"-") -> 4019522.5 | AX71: =IFERROR(IF(SUM(AO71,AR71,AU71)=0,"-",SUM(AO71,AR71,AU71)),"-") -> 3026663.1 | AY71: - | AZ71: KP | BA71: sc
A72: =$D72&"_"&$F72&"_"&$L72 -> TSX:LUN_2024_ | B72: =$D72&"_"&$F72&"_"&$N72 -> TSX:LUN_2024_CFO | C72: =$D72&"_"&$F72&"_"&$M72 -> TSX:LUN_2024_ | D72: =D71 -> TSX:LUN | E72: =_xll.ciqfunctions.udf.CIQ(D72,"IQ_Company_Name") -> Lundin Mining Corporation | F72: =F69 -> 2024 | G72: =F72&"-01-01" -> 2024-01-01 | H72: =F72&"-12-31" -> 2024-12-31 | I72: =_xlfn.DAYS(H72,G72)/_xlfn.DAYS(F72&"-12-31",F72&"-01-01")*12 -> 12 | J72: USD | K72: =IF($J72="CAD",1,IF($J72="USD",VLOOKUP($F72,$G$9:$H$11,2,FALSE),"N/A")) -> 1.37017 | N72: =N71 -> CFO | O72: =O71 -> CFO | P72: =P71 -> Teitur Poulsen | Q72: 529352 | R72: =IFERROR(Q72*(12/$I72)*$K72,"-") -> 725302.23 | S72: - | T72: =IFERROR(IF((S72*$K72)=0,"-",(S72*$K72)),"-") -> - | U72: 1009055 | V72: =IFERROR(U72*(12/$I72)*$K72,"-") -> 1382576.9 | W72: =IFERROR($V72/$R72,"-") -> 1.906208 | Y72: - | Z72: =IFERROR(IF(ISNUMBER($Y72)=TRUE, $Y72*$R72,$X72*$R72),"-") -> 0 | AA72: =IFERROR(IF(SUM(R72,V72)=0,"-",SUM(R72,V72)),"-") -> 2107879.1 | AB72: =IFERROR(IF(SUM(R72,Z72)=0,"-",SUM(R72,Z72)),"-") -> 725302.23 | AC72: - | AD72: =435613 -> 435613 | AE72: 435910 | AF72: - | AG72: - | AH72: =IFERROR(IF(SUM(AC72:AG72)=0,IF(COUNTIF($AC72:$AG72,"=0")>0,"$0","-"),SUM(AC72:AG72)),"-") -> 871523 | AI72: =IFERROR($AM72/$R72,"-") -> 1.646396 | AK72: - | AL72: =IFERROR(IF(ISNUMBER($AK72)=TRUE, $AK72*$R72, $AJ72*$R72), "-") -> 0 | AM72: =IFERROR($AH72*$K72,"-") -> 1194134.7 | AN72: =IFERROR(IF(SUM(AA72,AM72)=0,"-",SUM(AA72,AM72)),"-") -> 3302013.8 | AO72: =IFERROR(IF(SUM($AB72,$AL72)=0,"-",SUM($AB72,$AL72)),"-") -> 725302.23 | AP72: N/A | AQ72: N/A | AR72: =IFERROR(AP72*(12/$I72)*$K72,"-") -> - | AT72: 102270 | AU72: =IFERROR(AT72*(12/$I72)*$K72,"-") -> 140127.29 | AW72: =IFERROR(IF(SUM(AN72,AR72,AU72)=0,"-",SUM(AN72,AR72,AU72)),"-") -> 3442141.1 | AX72: =IFERROR(IF(SUM(AO72,AR72,AU72)=0,"-",SUM(AO72,AR72,AU72)),"-") -> 865429.52 | AY72: - | AZ72: KP | BA72: sc
A73: =$D73&"_"&$F73&"_"&$L73 -> TSX:LUN_2023_ | B73: =$D73&"_"&$F73&"_"&$N73 -> TSX:LUN_2023_CFO | C73: =$D73&"_"&$F73&"_"&$M73 -> TSX:LUN_2023_ | D73: =D72 -> TSX:LUN | E73: =_xll.ciqfunctions.udf.CIQ(D73,"IQ_Company_Name") -> Lundin Mining Corporation | F73: =F70 -> 2023 | G73: =F73&"-01-01" -> 2023-01-01 | H73: =F73&"-12-31" -> 2023-12-31 | I73: =_xlfn.DAYS(H73,G73)/_xlfn.DAYS(F73&"-12-31",F73&"-01-01")*12 -> 12 | J73: USD | K73: =IF($J73="CAD",1,IF($J73="USD",VLOOKUP($F73,$G$9:$H$11,2,FALSE),"N/A")) -> 1.34954 | N73: =N72 -> CFO | O73: =O72 -> CFO | P73: =P72 -> Teitur Poulsen | Q73: 518770 | R73: =IFERROR(Q73*(12/$I73)*$K73,"-") -> 700100.87 | S73: - | T73: =IFERROR(IF((S73*$K73)=0,"-",(S73*$K73)),"-") -> - | U73: 463188 | V73: =IFERROR(U73*(12/$I73)*$K73,"-") -> 625090.73 | W73: =IFERROR($V73/$R73,"-") -> 0.89285811 | Y73: - | Z73: =IFERROR(IF(ISNUMBER($Y73)=TRUE, $Y73*$R73,$X73*$R73),"-") -> 0 | AA73: =IFERROR(IF(SUM(R73,V73)=0,"-",SUM(R73,V73)),"-") -> 1325191.6 | AB73: =IFERROR(IF(SUM(R73,Z73)=0,"-",SUM(R73,Z73)),"-") -> 700100.87 | AC73: =0.33*621702 -> 205161.66 | AD73: =0.67*621702 -> 416540.34 | AE73: 204450 | AF73: - | AG73: - | AH73: =IFERROR(IF(SUM(AC73:AG73)=0,IF(COUNTIF($AC73:$AG73,"=0")>0,"$0","-"),SUM(AC73:AG73)),"-") -> 826152 | AI73: =IFERROR($AM73/$R73,"-") -> 1.5925208 | AK73: - | AL73: =IFERROR(IF(ISNUMBER($AK73)=TRUE, $AK73*$R73, $AJ73*$R73), "-") -> 0 | AM73: =IFERROR($AH73*$K73,"-") -> 1114925.2 | AN73: =IFERROR(IF(SUM(AA73,AM73)=0,"-",SUM(AA73,AM73)),"-") -> 2440116.8 | AO73: =IFERROR(IF(SUM($AB73,$AL73)=0,"-",SUM($AB73,$AL73)),"-") -> 700100.87 | AP73: N/A | AQ73: N/A | AR73: =IFERROR(AP73*(12/$I73)*$K73,"-") -> - | AT73: 81339 | AU73: =IFERROR(AT73*(12/$I73)*$K73,"-") -> 109770.23 | AW73: =IFERROR(IF(SUM(AN73,AR73,AU73)=0,"-",SUM(AN73,AR73,AU73)),"-") -> 2549887 | AX73: =IFERROR(IF(SUM(AO73,AR73,AU73)=0,"-",SUM(AO73,AR73,AU73)),"-") -> 809871.1 | AY73: - | AZ73: KP | BA73: sc
A74: =$D74&"_"&$F74&"_"&$L74 -> TSX:LUN_2025_COO | B74: =$D74&"_"&$F74&"_"&$N74 -> TSX:LUN_2025_NEO1 | C74: =$D74&"_"&$F74&"_"&$M74 -> TSX:LUN_2025_2nd Highest | D74: =D73 -> TSX:LUN | E74: =_xll.ciqfunctions.udf.CIQ(D74,"IQ_Company_Name") -> Lundin Mining Corporation | F74: =F71 -> 2025 | G74: =F74&"-01-01" -> 2025-01-01 | H74: =F74&"-12-31" -> 2025-12-31 | I74: =_xlfn.DAYS(H74,G74)/_xlfn.DAYS(F74&"-12-31",F74&"-01-01")*12 -> 12 | J74: USD | K74: =IF($J74="CAD",1,IF($J74="USD",VLOOKUP($F74,$G$9:$H$11,2,FALSE),"N/A")) -> 1.39745 | L74: COO | M74: 2nd Highest | N74: NEO1 | O74: COO | P74: Juan Andres Morel | Q74: 590781 | R74: =IFERROR(Q74*(12/$I74)*$K74,"-") -> 825586.91 | S74: 623273 | T74: =IFERROR(IF((S74*$K74)=0,"-",(S74*$K74)),"-") -> 870992.85 | U74: 630954 | V74: =IFERROR(U74*(12/$I74)*$K74,"-") -> 881726.67 | W74: =IFERROR($V74/$R74,"-") -> 1.0679998 | X74: =IFERROR(AVERAGE(W74:W76),"N/A") -> 1.134667 | Y74: 0.8 | Z74: =IFERROR(IF(ISNUMBER($Y74)=TRUE, $Y74*$R74,$X74*$R74),"-") -> 660469.53 | AA74: =IFERROR(IF(SUM(R74,V74)=0,"-",SUM(R74,V74)),"-") -> 1707313.6 | AB74: =IFERROR(IF(SUM(R74,Z74)=0,"-",SUM(R74,Z74)),"-") -> 1486056.4 | AC74: - | AD74: 896614 | AE74: 630954 | AF74: - | AG74: - | AH74: =IFERROR(IF(SUM(AC74:AG74)=0,IF(COUNTIF($AC74:$AG74,"=0")>0,"$0","-"),SUM(AC74:AG74)),"-") -> 1527568 | AI74: =IFERROR($AM74/$R74,"-") -> 2.5856756 | AJ74: =IFERROR(AVERAGE(AI74:AI76),"N/A") -> 1.9486686 | AK74: - | AL74: =IFERROR(IF(ISNUMBER($AK74)=TRUE, $AK74*$R74, $AJ74*$R74), "-") -> 1608795.3 | AM74: =IFERROR($AH74*$K74,"-") -> 2134699.9 | AN74: =IFERROR(IF(SUM(AA74,AM74)=0,"-",SUM(AA74,AM74)),"-") -> 3842013.5 | AO74: =IFERROR(IF(SUM($AB74,$AL74)=0,"-",SUM($AB74,$AL74)),"-") -> 3094851.7 | AP74: N/A | AQ74: N/A | AR74: =IFERROR(AP74*(12/$I74)*$K74,"-") -> - | AS74: =IFERROR(AVERAGE(AR74:AR76),"N/A") -> N/A | AT74: 4219 | AU74: =IFERROR(AT74*(12/$I74)*$K74,"-") -> 5895.8416 | AV74: =IFERROR(AVERAGE(AU74:AU76),"N/A") -> 3285.3152 | AW74: =IFERROR(IF(SUM(AN74,AR74,AU74)=0,"-",SUM(AN74,AR74,AU74)),"-") -> 3847909.3 | AX74: =IFERROR(IF(SUM(AO74,AR74,AU74)=0,"-",SUM(AO74,AR74,AU74)),"-") -> 3100747.6 | AY74: - | AZ74: KP | BA74: sc
A75: =$D75&"_"&$F75&"_"&$L75 -> TSX:LUN_2024_COO | B75: =$D75&"_"&$F75&"_"&$N75 -> TSX:LUN_2024_NEO1 | C75: =$D75&"_"&$F75&"_"&$M75 -> TSX:LUN_2024_ | D75: =D74 -> TSX:LUN | E75: =_xll.ciqfunctions.udf.CIQ(D75,"IQ_Company_Name") -> Lundin Mining Corporation | F75: =F72 -> 2024 | G75: =F75&"-01-01" -> 2024-01-01 | H75: =F75&"-12-31" -> 2024-12-31 | I75: =_xlfn.DAYS(H75,G75)/_xlfn.DAYS(F75&"-12-31",F75&"-01-01")*12 -> 12 | J75: USD | K75: =IF($J75="CAD",1,IF($J75="USD",VLOOKUP($F75,$G$9:$H$11,2,FALSE),"N/A")) -> 1.37017 | L75: COO | N75: =N74 -> NEO1 | O75: =O74 -> COO | P75: =P74 -> Juan Andres Morel | Q75: 562287 | R75: =IFERROR(Q75*(12/$I75)*$K75,"-") -> 770428.78 | S75: - | T75: =IFERROR(IF((S75*$K75)=0,"-",(S75*$K75)),"-") -> - | U75: 790576 | V75: =IFERROR(U75*(12/$I75)*$K75,"-") -> 1083223.5 | W75: =IFERROR($V75/$R75,"-") -> 1.4060009 | Y75: - | Z75: =IFERROR(IF(ISNUMBER($Y75)=TRUE, $Y75*$R75,$X75*$R75),"-") -> 0 | AA75: =IFERROR(IF(SUM(R75,V75)=0,"-",SUM(R75,V75)),"-") -> 1853652.3 | AB75: =IFERROR(IF(SUM(R75,Z75)=0,"-",SUM(R75,Z75)),"-") -> 770428.78 | AC75: - | AD75: =468351 -> 468351 | AE75: 468695 | AF75: - | AG75: - | AH75: =IFERROR(IF(SUM(AC75:AG75)=0,IF(COUNTIF($AC75:$AG75,"=0")>0,"$0","-"),SUM(AC75:AG75)),"-") -> 937046 | AI75: =IFERROR($AM75/$R75,"-") -> 1.6664906 | AK75: - | AL75: =IFERROR(IF(ISNUMBER($AK75)=TRUE, $AK75*$R75, $AJ75*$R75), "-") -> 0 | AM75: =IFERROR($AH75*$K75,"-") -> 1283912.3 | AN75: =IFERROR(IF(SUM(AA75,AM75)=0,"-",SUM(AA75,AM75)),"-") -> 3137564.6 | AO75: =IFERROR(IF(SUM($AB75,$AL75)=0,"-",SUM($AB75,$AL75)),"-") -> 770428.78 | AP75: N/A | AQ75: N/A | AR75: =IFERROR(AP75*(12/$I75)*$K75,"-") -> - | AT75: 1466 | AU75: =IFERROR(AT75*(12/$I75)*$K75,"-") -> 2008.6692 | AW75: =IFERROR(IF(SUM(AN75,AR75,AU75)=0,"-",SUM(AN75,AR75,AU75)),"-") -> 3139573.3 | AX75: =IFERROR(IF(SUM(AO75,AR75,AU75)=0,"-",SUM(AO75,AR75,AU75)),"-") -> 772437.45 | AY75: - | AZ75: KP | BA75: sc
A76: =$D76&"_"&$F76&"_"&$L76 -> TSX:LUN_2023_COO | B76: =$D76&"_"&$F76&"_"&$N76 -> TSX:LUN_2023_NEO1 | C76: =$D76&"_"&$F76&"_"&$M76 -> TSX:LUN_2023_ | D76: =D75 -> TSX:LUN | E76: =_xll.ciqfunctions.udf.CIQ(D76,"IQ_Company_Name") -> Lundin Mining Corporation | F76: =F73 -> 2023 | G76: =F76&"-01-01" -> 2023-01-01 | H76: =F76&"-12-31" -> 2023-12-31 | I76: =_xlfn.DAYS(H76,G76)/_xlfn.DAYS(F76&"-12-31",F76&"-01-01")*12 -> 12 | J76: USD | K76: =IF($J76="CAD",1,IF($J76="USD",VLOOKUP($F76,$G$9:$H$11,2,FALSE),"N/A")) -> 1.34954 | L76: COO | N76: =N75 -> NEO1 | O76: =O75 -> COO | P76: =P75 -> Juan Andres Morel | Q76: 609060 | R76: =IFERROR(Q76*(12/$I76)*$K76,"-") -> 821950.83 | S76: - | T76: =IFERROR(IF((S76*$K76)=0,"-",(S76*$K76)),"-") -> - | U76: 566426 | V76: =IFERROR(U76*(12/$I76)*$K76,"-") -> 764414.54 | W76: =IFERROR($V76/$R76,"-") -> 0.93000033 | Y76: - | Z76: =IFERROR(IF(ISNUMBER($Y76)=TRUE, $Y76*$R76,$X76*$R76),"-") -> 0 | AA76: =IFERROR(IF(SUM(R76,V76)=0,"-",SUM(R76,V76)),"-") -> 1586365.4 | AB76: =IFERROR(IF(SUM(R76,Z76)=0,"-",SUM(R76,Z76)),"-") -> 821950.83 | AC76: =0.33*730480 -> 241058.4 | AD76: =0.67*730480 -> 489421.6 | AE76: 240264 | AF76: - | AG76: - | AH76: =IFERROR(IF(SUM(AC76:AG76)=0,IF(COUNTIF($AC76:$AG76,"=0")>0,"$0","-"),SUM(AC76:AG76)),"-") -> 970744 | AI76: =IFERROR($AM76/$R76,"-") -> 1.5938397 | AK76: - | AL76: =IFERROR(IF(ISNUMBER($AK76)=TRUE, $AK76*$R76, $AJ76*$R76), "-") -> 0 | AM76: =IFERROR($AH76*$K76,"-") -> 1310057.9 | AN76: =IFERROR(IF(SUM(AA76,AM76)=0,"-",SUM(AA76,AM76)),"-") -> 2896423.2 | AO76: =IFERROR(IF(SUM($AB76,$AL76)=0,"-",SUM($AB76,$AL76)),"-") -> 821950.83 | AP76: N/A | AQ76: N/A | AR76: =IFERROR(AP76*(12/$I76)*$K76,"-") -> - | AT76: 1446 | AU76: =IFERROR(AT76*(12/$I76)*$K76,"-") -> 1951.4348 | AW76: =IFERROR(IF(SUM(AN76,AR76,AU76)=0,"-",SUM(AN76,AR76,AU76)),"-") -> 2898374.7 | AX76: =IFERROR(IF(SUM(AO76,AR76,AU76)=0,"-",SUM(AO76,AR76,AU76)),"-") -> 823902.27 | AY76: - | AZ76: KP | BA76: sc
A77: =$D77&"_"&$F77&"_"&$L77 -> TSX:LUN_2025_Legal | B77: =$D77&"_"&$F77&"_"&$N77 -> TSX:LUN_2025_NEO2 | C77: =$D77&"_"&$F77&"_"&$M77 -> TSX:LUN_2025_ | D77: =D76 -> TSX:LUN | E77: =_xll.ciqfunctions.udf.CIQ(D77,"IQ_Company_Name") -> Lundin Mining Corporation | F77: =F74 -> 2025 | G77: =F77&"-01-01" -> 2025-01-01 | H77: =F77&"-12-31" -> 2025-12-31 | I77: =_xlfn.DAYS(H77,G77)/_xlfn.DAYS(F77&"-12-31",F77&"-01-01")*12 -> 12 | J77: USD | K77: =IF($J77="CAD",1,IF($J77="USD",VLOOKUP($F77,$G$9:$H$11,2,FALSE),"N/A")) -> 1.39745 | L77: Legal | N77: NEO2 | O77: General Counsel | P77: Peter Brady | Q77: 450809 | R77: 630000 | S77: 450809 | T77: 630000 | U77: =434351-100000/K77 -> 362792.09 | V77: =IFERROR(U77*(12/$I77)*$K77,"-") -> 506983.8 | W77: =IFERROR($V77/$R77,"-") -> 0.8047362 | X77: =IFERROR(AVERAGE(W77:W79),"N/A") -> 0.89841666 | Y77: 0.75 | Z77: =IFERROR(IF(ISNUMBER($Y77)=TRUE, $Y77*$R77,$X77*$R77),"-") -> 472500 | AA77: =IFERROR(IF(SUM(R77,V77)=0,"-",SUM(R77,V77)),"-") -> 1136983.8 | AB77: =IFERROR(IF(SUM(R77,Z77)=0,"-",SUM(R77,Z77)),"-") -> 1102500 | AC77: - | AD77: 518839 | AE77: 434351 | AF77: - | AG77: - | AH77: =IFERROR(IF(SUM(AC77:AG77)=0,IF(COUNTIF($AC77:$AG77,"=0")>0,"$0","-"),SUM(AC77:AG77)),"-") -> 953190 | AI77: =IFERROR($AM77/$R77,"-") -> 2.1143419 | AJ77: =IFERROR(AVERAGE(AI77:AI79),"N/A") -> 1.655852 | AK77: - | AL77: =IFERROR(IF(ISNUMBER($AK77)=TRUE, $AK77*$R77, $AJ77*$R77), "-") -> 1043186.7 | AM77: =IFERROR($AH77*$K77,"-") -> 1332035.4 | AN77: =IFERROR(IF(SUM(AA77,AM77)=0,"-",SUM(AA77,AM77)),"-") -> 2469019.2 | AO77: =IFERROR(IF(SUM($AB77,$AL77)=0,"-",SUM($AB77,$AL77)),"-") -> 2145686.7 | AP77: N/A | AQ77: N/A | AR77: =IFERROR(AP77*(12/$I77)*$K77,"-") -> - | AS77: =IFERROR(AVERAGE(AR77:AR79),"N/A") -> N/A | AT77: 103128 | AU77: =IFERROR(AT77*(12/$I77)*$K77,"-") -> 144116.22 | AV77: =IFERROR(AVERAGE(AU77:AU79),"N/A") -> 279776.46 | AW77: =IFERROR(IF(SUM(AN77,AR77,AU77)=0,"-",SUM(AN77,AR77,AU77)),"-") -> 2613135.4 | AX77: =IFERROR(IF(SUM(AO77,AR77,AU77)=0,"-",SUM(AO77,AR77,AU77)),"-") -> 2289803 | AY77: Peter Brady received an on-hire signing bonus of C$100,000 in 2023 as well as an on-hire grant of 37,000 RSUs (~$250K). In 2024 he received the first installment of a retention bonus of C$100,000, and the second of C$150,000 in 2025. All have been excluded from our benchmarking | AZ77: KP | BA77: sc
A78: =$D78&"_"&$F78&"_"&$L78 -> TSX:LUN_2024_Legal | B78: =$D78&"_"&$F78&"_"&$N78 -> TSX:LUN_2024_NEO2 | C78: =$D78&"_"&$F78&"_"&$M78 -> TSX:LUN_2024_ | D78: =D77 -> TSX:LUN | E78: =_xll.ciqfunctions.udf.CIQ(D78,"IQ_Company_Name") -> Lundin Mining Corporation | F78: =F75 -> 2024 | G78: =F78&"-01-01" -> 2024-01-01 | H78: =F78&"-12-31" -> 2024-12-31 | I78: =_xlfn.DAYS(H78,G78)/_xlfn.DAYS(F78&"-12-31",F78&"-01-01")*12 -> 12 | J78: USD | K78: =IF($J78="CAD",1,IF($J78="USD",VLOOKUP($F78,$G$9:$H$11,2,FALSE),"N/A")) -> 1.37017 | L78: Legal | N78: =N77 -> NEO2 | O78: =O77 -> General Counsel | P78: =P77 -> Peter Brady | Q78: 449037 | R78: =IFERROR(Q78*(12/$I78)*$K78,"-") -> 615257.03 | S78: - | T78: =IFERROR(IF((S78*$K78)=0,"-",(S78*$K78)),"-") -> - | U78: =813377-100000/K78 -> 740393.36 | V78: =IFERROR(U78*(12/$I78)*$K78,"-") -> 1014464.8 | W78: =IFERROR($V78/$R78,"-") -> 1.6488471 | Y78: - | Z78: =IFERROR(IF(ISNUMBER($Y78)=TRUE, $Y78*$R78,$X78*$R78),"-") -> 0 | AA78: =IFERROR(IF(SUM(R78,V78)=0,"-",SUM(R78,V78)),"-") -> 1629721.8 | AB78: =IFERROR(IF(SUM(R78,Z78)=0,"-",SUM(R78,Z78)),"-") -> 615257.03 | AC78: - | AD78: =339458 -> 339458 | AE78: 339661 | AF78: - | AG78: - | AH78: =IFERROR(IF(SUM(AC78:AG78)=0,IF(COUNTIF($AC78:$AG78,"=0")>0,"$0","-"),SUM(AC78:AG78)),"-") -> 679119 | AI78: =IFERROR($AM78/$R78,"-") -> 1.5123898 | AK78: - | AL78: =IFERROR(IF(ISNUMBER($AK78)=TRUE, $AK78*$R78, $AJ78*$R78), "-") -> 0 | AM78: =IFERROR($AH78*$K78,"-") -> 930508.48 | AN78: =IFERROR(IF(SUM(AA78,AM78)=0,"-",SUM(AA78,AM78)),"-") -> 2560230.3 | AO78: =IFERROR(IF(SUM($AB78,$AL78)=0,"-",SUM($AB78,$AL78)),"-") -> 615257.03 | AP78: N/A | AQ78: N/A | AR78: =IFERROR(AP78*(12/$I78)*$K78,"-") -> - | AT78: 205055 | AU78: =IFERROR(AT78*(12/$I78)*$K78,"-") -> 280960.21 | AW78: =IFERROR(IF(SUM(AN78,AR78,AU78)=0,"-",SUM(AN78,AR78,AU78)),"-") -> 2841190.5 | AX78: =IFERROR(IF(SUM(AO78,AR78,AU78)=0,"-",SUM(AO78,AR78,AU78)),"-") -> 896217.24 | AY78: - | AZ78: KP | BA78: sc
A79: =$D79&"_"&$F79&"_"&$L79 -> TSX:LUN_2023_Legal | B79: =$D79&"_"&$F79&"_"&$N79 -> TSX:LUN_2023_NEO2 | C79: =$D79&"_"&$F79&"_"&$M79 -> TSX:LUN_2023_ | D79: =D78 -> TSX:LUN | E79: =_xll.ciqfunctions.udf.CIQ(D79,"IQ_Company_Name") -> Lundin Mining Corporation | F79: =F76 -> 2023 | G79: 45192 | H79: =F79&"-12-31" -> 2023-12-31 | I79: =_xlfn.DAYS(H79,G79)/_xlfn.DAYS(F79&"-12-31",F79&"-01-01")*12 -> 3.2637363 | J79: USD | K79: =IF($J79="CAD",1,IF($J79="USD",VLOOKUP($F79,$G$9:$H$11,2,FALSE),"N/A")) -> 1.34954 | L79: Legal | N79: =N78 -> NEO2 | O79: =O78 -> General Counsel | P79: =P78 -> Peter Brady | Q79: 122709 | R79: =IFERROR(Q79*(12/$I79)*$K79,"-") -> 608875.32 | S79: - | T79: =IFERROR(IF((S79*$K79)=0,"-",(S79*$K79)),"-") -> - | U79: =103754-100000/K79 -> 29654.677 | V79: =IFERROR(U79*(12/$I79)*$K79,"-") -> 147144.88 | W79: =IFERROR($V79/$R79,"-") -> 0.24166669 | Y79: - | Z79: =IFERROR(IF(ISNUMBER($Y79)=TRUE, $Y79*$R79,$X79*$R79),"-") -> 0 | AA79: =IFERROR(IF(SUM(R79,V79)=0,"-",SUM(R79,V79)),"-") -> 756020.19 | AB79: =IFERROR(IF(SUM(R79,Z79)=0,"-",SUM(R79,Z79)),"-") -> 608875.32 | AC79: =0.33*987814-37000*6.71 -> 77708.62 | AD79: =0.67*987814-37000*6.71 -> 413565.38 | AE79: 113669 | AF79: - | AG79: - | AH79: =IFERROR(IF(SUM(AC79:AG79)=0,IF(COUNTIF($AC79:$AG79,"=0")>0,"$0","-"),SUM(AC79:AG79)),"-") -> 604943 | AI79: =IFERROR($AM79/$R79,"-") -> 1.3408242 | AK79: - | AL79: =IFERROR(IF(ISNUMBER($AK79)=TRUE, $AK79*$R79, $AJ79*$R79), "-") -> 0 | AM79: =IFERROR($AH79*$K79,"-") -> 816394.78 | AN79: =IFERROR(IF(SUM(AA79,AM79)=0,"-",SUM(AA79,AM79)),"-") -> 1572415 | AO79: =IFERROR(IF(SUM($AB79,$AL79)=0,"-",SUM($AB79,$AL79)),"-") -> 608875.32 | AP79: N/A | AQ79: N/A | AR79: =IFERROR(AP79*(12/$I79)*$K79,"-") -> - | AT79: 83486 | AU79: =IFERROR(AT79*(12/$I79)*$K79,"-") -> 414252.94 | AW79: =IFERROR(IF(SUM(AN79,AR79,AU79)=0,"-",SUM(AN79,AR79,AU79)),"-") -> 1986667.9 | AX79: =IFERROR(IF(SUM(AO79,AR79,AU79)=0,"-",SUM(AO79,AR79,AU79)),"-") -> 1023128.3 | AY79: - | AZ79: KP | BA79: sc
A80: =$D80&"_"&$F80&"_"&$L80 -> TSX:LUN_2025_ | B80: =$D80&"_"&$F80&"_"&$N80 -> TSX:LUN_2025_NEO3 | C80: =$D80&"_"&$F80&"_"&$M80 -> TSX:LUN_2025_ | D80: =D79 -> TSX:LUN | E80: =_xll.ciqfunctions.udf.CIQ(D80,"IQ_Company_Name") -> Lundin Mining Corporation | F80: =F77 -> 2025 | G80: =F80&"-01-01" -> 2025-01-01 | H80: =F80&"-12-31" -> 2025-12-31 | I80: =_xlfn.DAYS(H80,G80)/_xlfn.DAYS(F80&"-12-31",F80&"-01-01")*12 -> 12 | J80: USD | K80: =IF($J80="CAD",1,IF($J80="USD",VLOOKUP($F80,$G$9:$H$11,2,FALSE),"N/A")) -> 1.39745 | N80: NEO3 | O80: VP, Sustainability | P80: Nathan Monash | Q80: 300539 | R80: 420000 | S80: 304117 | T80: 425000 | U80: =178821-150000/K80 -> 71482.634 | V80: =IFERROR(U80*(12/$I80)*$K80,"-") -> 99893.406 | W80: =IFERROR($V80/$R80,"-") -> 0.23784144 | X80: =IFERROR(AVERAGE(W80:W82),"N/A") -> 0.26079994 | Y80: 0.5 | Z80: =IFERROR(IF(ISNUMBER($Y80)=TRUE, $Y80*$R80,$X80*$R80),"-") -> 210000 | AA80: =IFERROR(IF(SUM(R80,V80)=0,"-",SUM(R80,V80)),"-") -> 519893.41 | AB80: =IFERROR(IF(SUM(R80,Z80)=0,"-",SUM(R80,Z80)),"-") -> 630000 | AC80: =315170*0.333333333 -> 105056.67 | AD80: =315170*0.6666666667 -> 210113.33 | AE80: 209999 | AF80: - | AG80: - | AH80: =IFERROR(IF(SUM(AC80:AG80)=0,IF(COUNTIF($AC80:$AG80,"=0")>0,"$0","-"),SUM(AC80:AG80)),"-") -> 525169 | AI80: =IFERROR($AM80/$R80,"-") -> 1.7473748 | AJ80: =IFERROR(AVERAGE(AI80:AI82),"N/A") -> 1.3776225 | AK80: - | AL80: =IFERROR(IF(ISNUMBER($AK80)=TRUE, $AK80*$R80, $AJ80*$R80), "-") -> 578601.45 | AM80: =IFERROR($AH80*$K80,"-") -> 733897.42 | AN80: =IFERROR(IF(SUM(AA80,AM80)=0,"-",SUM(AA80,AM80)),"-") -> 1253790.8 | AO80: =IFERROR(IF(SUM($AB80,$AL80)=0,"-",SUM($AB80,$AL80)),"-") -> 1208601.4 | AP80: N/A | AQ80: N/A | AR80: =IFERROR(AP80*(12/$I80)*$K80,"-") -> - | AS80: =IFERROR(AVERAGE(AR80:AR82),"N/A") -> N/A | AT80: 166905 | AU80: =IFERROR(AT80*(12/$I80)*$K80,"-") -> 233241.39 | AV80: =IFERROR(AVERAGE(AU80:AU82),"N/A") -> 197785.46 | AW80: =IFERROR(IF(SUM(AN80,AR80,AU80)=0,"-",SUM(AN80,AR80,AU80)),"-") -> 1487032.2 | AX80: =IFERROR(IF(SUM(AO80,AR80,AU80)=0,"-",SUM(AO80,AR80,AU80)),"-") -> 1441842.8 | AY80: Nathan Monash joined the Corporation on September 1, 2023 and his performance equity grants for 2023 include an initial on hire grant of 3,500 PSUs, 7000 RSUs,10,300 options - this year of compensation was excluded.In 2023 he received an on hire signing bonus of C$100,000. In 2024 he received the first installment of a retention bonus of the amount C$100,000 and the second installment in 2025 of $C150,000 | AZ80: KP | BA80: sc
A81: =$D81&"_"&$F81&"_"&$L81 -> TSX:LUN_2024_ | B81: =$D81&"_"&$F81&"_"&$N81 -> TSX:LUN_2024_NEO3 | C81: =$D81&"_"&$F81&"_"&$M81 -> TSX:LUN_2024_ | D81: =D80 -> TSX:LUN | E81: =_xll.ciqfunctions.udf.CIQ(D81,"IQ_Company_Name") -> Lundin Mining Corporation | F81: =F78 -> 2024 | G81: =F81&"-01-01" -> 2024-01-01 | H81: =F81&"-12-31" -> 2024-12-31 | I81: =_xlfn.DAYS(H81,G81)/_xlfn.DAYS(F81&"-12-31",F81&"-01-01")*12 -> 12 | J81: USD | K81: =IF($J81="CAD",1,IF($J81="USD",VLOOKUP($F81,$G$9:$H$11,2,FALSE),"N/A")) -> 1.37017 | N81: =N80 -> NEO3 | O81: =O80 -> VP, Sustainability | P81: =P80 -> Nathan Monash | Q81: 299358 | R81: =IFERROR(Q81*(12/$I81)*$K81,"-") -> 410171.35 | S81: - | T81: =IFERROR(IF((S81*$K81)=0,"-",(S81*$K81)),"-") -> - | U81: =157929-100000/K81 -> 84945.356 | V81: =IFERROR(U81*(12/$I81)*$K81,"-") -> 116389.58 | W81: =IFERROR($V81/$R81,"-") -> 0.28375843 | Y81: - | Z81: =IFERROR(IF(ISNUMBER($Y81)=TRUE, $Y81*$R81,$X81*$R81),"-") -> 0 | AA81: =IFERROR(IF(SUM(R81,V81)=0,"-",SUM(R81,V81)),"-") -> 526560.93 | AB81: =IFERROR(IF(SUM(R81,Z81)=0,"-",SUM(R81,Z81)),"-") -> 410171.35 | AC81: =0.333333333333*226248 -> 75416 | AD81: =0.6666666667*226248 -> 150832 | AE81: 75466 | AF81: - | AG81: - | AH81: =IFERROR(IF(SUM(AC81:AG81)=0,IF(COUNTIF($AC81:$AG81,"=0")>0,"$0","-"),SUM(AC81:AG81)),"-") -> 301714 | AI81: =IFERROR($AM81/$R81,"-") -> 1.0078702 | AK81: - | AL81: =IFERROR(IF(ISNUMBER($AK81)=TRUE, $AK81*$R81, $AJ81*$R81), "-") -> 0 | AM81: =IFERROR($AH81*$K81,"-") -> 413399.47 | AN81: =IFERROR(IF(SUM(AA81,AM81)=0,"-",SUM(AA81,AM81)),"-") -> 939960.4 | AO81: =IFERROR(IF(SUM($AB81,$AL81)=0,"-",SUM($AB81,$AL81)),"-") -> 410171.35 | AP81: N/A | AQ81: N/A | AR81: =IFERROR(AP81*(12/$I81)*$K81,"-") -> - | AT81: 118474 | AU81: =IFERROR(AT81*(12/$I81)*$K81,"-") -> 162329.52 | AW81: =IFERROR(IF(SUM(AN81,AR81,AU81)=0,"-",SUM(AN81,AR81,AU81)),"-") -> 1102289.9 | AX81: =IFERROR(IF(SUM(AO81,AR81,AU81)=0,"-",SUM(AO81,AR81,AU81)),"-") -> 572500.87 | AY81: - | AZ81: KP | BA81: sc
A82: =$D82&"_"&$F82&"_"&$L82 -> TSX:LUN_2023_ | B82: =$D82&"_"&$F82&"_"&$N82 -> TSX:LUN_2023_NEO3 | C82: =$D82&"_"&$F82&"_"&$M82 -> TSX:LUN_2023_ | D82: =D81 -> TSX:LUN | E82: =_xll.ciqfunctions.udf.CIQ(D82,"IQ_Company_Name") -> Lundin Mining Corporation | F82: =F79 -> 2023 | G82: =F82&"-09-01" -> 2023-09-01 | H82: =F82&"-12-31" -> 2023-12-31 | I82: =_xlfn.DAYS(H82,G82)/_xlfn.DAYS(F82&"-12-31",F82&"-01-01")*12 -> 3.989011 | J82: USD | K82: =IF($J82="CAD",1,IF($J82="USD",VLOOKUP($F82,$G$9:$H$11,2,FALSE),"N/A")) -> 1.34954 | N82: =N81 -> NEO3 | O82: =O81 -> VP, Sustainability | P82: =P81 -> Nathan Monash | Q82: - | R82: =IFERROR(Q82*(12/$I82)*$K82,"-") -> - | S82: - | T82: =IFERROR(IF((S82*$K82)=0,"-",(S82*$K82)),"-") -> - | U82: - | V82: =IFERROR(U82*(12/$I82)*$K82,"-") -> - | W82: =IFERROR($V82/$R82,"-") -> - | Y82: - | Z82: =IFERROR(IF(ISNUMBER($Y82)=TRUE, $Y82*$R82,$X82*$R82),"-") -> - | AA82: =IFERROR(IF(SUM(R82,V82)=0,"-",SUM(R82,V82)),"-") -> - | AB82: =IFERROR(IF(SUM(R82,Z82)=0,"-",SUM(R82,Z82)),"-") -> - | AC82: - | AD82: - | AE82: - | AF82: - | AG82: - | AH82: =IFERROR(IF(SUM(AC82:AG82)=0,IF(COUNTIF($AC82:$AG82,"=0")>0,"$0","-"),SUM(AC82:AG82)),"-") -> - | AI82: =IFERROR($AM82/$R82,"-") -> - | AK82: - | AL82: =IFERROR(IF(ISNUMBER($AK82)=TRUE, $AK82*$R82, $AJ82*$R82), "-") -> - | AM82: =IFERROR($AH82*$K82,"-") -> - | AN82: =IFERROR(IF(SUM(AA82,AM82)=0,"-",SUM(AA82,AM82)),"-") -> - | AO82: =IFERROR(IF(SUM($AB82,$AL82)=0,"-",SUM($AB82,$AL82)),"-") -> - | AP82: - | AQ82: - | AR82: =IFERROR(AP82*(12/$I82)*$K82,"-") -> - | AT82: - | AU82: =IFERROR(AT82*(12/$I82)*$K82,"-") -> - | AW82: =IFERROR(IF(SUM(AN82,AR82,AU82)=0,"-",SUM(AN82,AR82,AU82)),"-") -> - | AX82: =IFERROR(IF(SUM(AO82,AR82,AU82)=0,"-",SUM(AO82,AR82,AU82)),"-") -> - | AY82: - | AZ82: KP | BA82: sc
A83: =$D83&"_"&$F83&"_"&$L83 -> TSX:PAAS_2025_ | B83: =$D83&"_"&$F83&"_"&$N83 -> TSX:PAAS_2025_CEO | C83: =$D83&"_"&$F83&"_"&$M83 -> TSX:PAAS_2025_ | D83: =E7 -> TSX:PAAS | E83: =_xll.ciqfunctions.udf.CIQ(D83,"IQ_Company_Name") -> Pan American Silver Corp. | F83: =$G$9 -> 2025 | G83: =F83&"-01-01" -> 2025-01-01 | H83: =F83&"-12-31" -> 2025-12-31 | I83: =_xlfn.DAYS(H83,G83)/_xlfn.DAYS(F83&"-12-31",F83&"-01-01")*12 -> 12 | J83: CAD | K83: =IF($J83="CAD",1,IF($J83="USD",VLOOKUP($F83,$G$9:$H$11,2,FALSE),"N/A")) -> 1 | N83: CEO | O83: President & CEO | P83: Michael Steinmann | Q83: 1562300 | R83: =IFERROR(Q83*(12/$I83)*$K83,"-") -> 1562300 | S83: - | T83: =IFERROR(IF((S83*$K83)=0,"-",(S83*$K83)),"-") -> - | U83: 2856080 | V83: =IFERROR(U83*(12/$I83)*$K83,"-") -> 2856080 | W83: =IFERROR($V83/$R83,"-") -> 1.8281252 | X83: =IFERROR(AVERAGE(W83:W85),"N/A") -> 1.4841238 | Y83: 1.25 | Z83: =IFERROR(IF(ISNUMBER($Y83)=TRUE, $Y83*$R83,$X83*$R83),"-") -> 1952875 | AA83: =IFERROR(IF(SUM(R83,V83)=0,"-",SUM(R83,V83)),"-") -> 4418380 | AB83: =IFERROR(IF(SUM(R83,Z83)=0,"-",SUM(R83,Z83)),"-") -> 3515175 | AC83: 1952700 | AD83: 2734200 | AE83: - | AF83: - | AG83: - | AH83: =IFERROR(IF(SUM(AC83:AG83)=0,IF(COUNTIF($AC83:$AG83,"=0")>0,"$0","-"),SUM(AC83:AG83)),"-") -> 4686900 | AI83: =IFERROR($AM83/$R83,"-") -> 3 | AJ83: =IFERROR(AVERAGE(AI83:AI85),"N/A") -> 2.9167117 | AK83: 3 | AL83: =IFERROR(IF(ISNUMBER($AK83)=TRUE, $AK83*$R83, $AJ83*$R83), "-") -> 4686900 | AM83: =IFERROR($AH83*$K83,"-") -> 4686900 | AN83: =IFERROR(IF(SUM(AA83,AM83)=0,"-",SUM(AA83,AM83)),"-") -> 9105280 | AO83: =IFERROR(IF(SUM($AB83,$AL83)=0,"-",SUM($AB83,$AL83)),"-") -> 8202075 | AP83: 703035 | AQ83: DC | AR83: =IFERROR(AP83*(12/$I83)*$K83,"-") -> 703035 | AS83: =IFERROR(AVERAGE(AR83:AR85),"N/A") -> 663150 | AT83: - | AU83: =IFERROR(AT83*(12/$I83)*$K83,"-") -> - | AV83: =IFERROR(AVERAGE(AU83:AU85),"N/A") -> N/A | AW83: =IFERROR(IF(SUM(AN83,AR83,AU83)=0,"-",SUM(AN83,AR83,AU83)),"-") -> 9808315 | AX83: =IFERROR(IF(SUM(AO83,AR83,AU83)=0,"-",SUM(AO83,AR83,AU83)),"-") -> 8905110 | AY83: CEO received an award of CAD$5 million in RSUs in December 2025, which, will vest in full, in cash, on the third anniversary of the grant date. This award has been excluded | AZ83: KP | BA83: sc
A84: =$D84&"_"&$F84&"_"&$L84 -> TSX:PAAS_2024_ | B84: =$D84&"_"&$F84&"_"&$N84 -> TSX:PAAS_2024_CEO | C84: =$D84&"_"&$F84&"_"&$M84 -> TSX:PAAS_2024_ | D84: =D83 -> TSX:PAAS | E84: =_xll.ciqfunctions.udf.CIQ(D84,"IQ_Company_Name") -> Pan American Silver Corp. | F84: =$G$10 -> 2024 | G84: =F84&"-01-01" -> 2024-01-01 | H84: =F84&"-12-31" -> 2024-12-31 | I84: =_xlfn.DAYS(H84,G84)/_xlfn.DAYS(F84&"-12-31",F84&"-01-01")*12 -> 12 | J84: CAD | K84: =IF($J84="CAD",1,IF($J84="USD",VLOOKUP($F84,$G$9:$H$11,2,FALSE),"N/A")) -> 1 | N84: =N83 -> CEO | O84: =O83 -> President & CEO | P84: =P83 -> Michael Steinmann | Q84: 1508000 | R84: =IFERROR(Q84*(12/$I84)*$K84,"-") -> 1508000 | S84: - | T84: =IFERROR(IF((S84*$K84)=0,"-",(S84*$K84)),"-") -> - | U84: 1932130 | V84: =IFERROR(U84*(12/$I84)*$K84,"-") -> 1932130 | W84: =IFERROR($V84/$R84,"-") -> 1.2812533 | Y84: - | Z84: =IFERROR(IF(ISNUMBER($Y84)=TRUE, $Y84*$R84,$X84*$R84),"-") -> 0 | AA84: =IFERROR(IF(SUM(R84,V84)=0,"-",SUM(R84,V84)),"-") -> 3440130 | AB84: =IFERROR(IF(SUM(R84,Z84)=0,"-",SUM(R84,Z84)),"-") -> 1508000 | AC84: 1885000 | AD84: 2412800 | AE84: - | AF84: - | AG84: - | AH84: =IFERROR(IF(SUM(AC84:AG84)=0,IF(COUNTIF($AC84:$AG84,"=0")>0,"$0","-"),SUM(AC84:AG84)),"-") -> 4297800 | AI84: =IFERROR($AM84/$R84,"-") -> 2.85 | AK84: - | AL84: =IFERROR(IF(ISNUMBER($AK84)=TRUE, $AK84*$R84, $AJ84*$R84), "-") -> 0 | AM84: =IFERROR($AH84*$K84,"-") -> 4297800 | AN84: =IFERROR(IF(SUM(AA84,AM84)=0,"-",SUM(AA84,AM84)),"-") -> 7737930 | AO84: =IFERROR(IF(SUM($AB84,$AL84)=0,"-",SUM($AB84,$AL84)),"-") -> 1508000 | AP84: 678600 | AQ84: DC | AR84: =IFERROR(AP84*(12/$I84)*$K84,"-") -> 678600 | AT84: - | AU84: =IFERROR(AT84*(12/$I84)*$K84,"-") -> - | AW84: =IFERROR(IF(SUM(AN84,AR84,AU84)=0,"-",SUM(AN84,AR84,AU84)),"-") -> 8416530 | AX84: =IFERROR(IF(SUM(AO84,AR84,AU84)=0,"-",SUM(AO84,AR84,AU84)),"-") -> 2186600 | AY84: - | AZ84: KP | BA84: sc
A85: =$D85&"_"&$F85&"_"&$L85 -> TSX:PAAS_2023_ | B85: =$D85&"_"&$F85&"_"&$N85 -> TSX:PAAS_2023_CEO | C85: =$D85&"_"&$F85&"_"&$M85 -> TSX:PAAS_2023_ | D85: =D84 -> TSX:PAAS | E85: =_xll.ciqfunctions.udf.CIQ(D85,"IQ_Company_Name") -> Pan American Silver Corp. | F85: =$G$11 -> 2023 | G85: =F85&"-01-01" -> 2023-01-01 | H85: =F85&"-12-31" -> 2023-12-31 | I85: =_xlfn.DAYS(H85,G85)/_xlfn.DAYS(F85&"-12-31",F85&"-01-01")*12 -> 12 | J85: CAD | K85: =IF($J85="CAD",1,IF($J85="USD",VLOOKUP($F85,$G$9:$H$11,2,FALSE),"N/A")) -> 1 | N85: =N84 -> CEO | O85: =O84 -> President & CEO | P85: =P84 -> Michael Steinmann | Q85: 1425175 | R85: =IFERROR(Q85*(12/$I85)*$K85,"-") -> 1425175 | S85: - | T85: =IFERROR(IF((S85*$K85)=0,"-",(S85*$K85)),"-") -> - | U85: 1914000 | V85: =IFERROR(U85*(12/$I85)*$K85,"-") -> 1914000 | W85: =IFERROR($V85/$R85,"-") -> 1.342993 | Y85: - | Z85: =IFERROR(IF(ISNUMBER($Y85)=TRUE, $Y85*$R85,$X85*$R85),"-") -> 0 | AA85: =IFERROR(IF(SUM(R85,V85)=0,"-",SUM(R85,V85)),"-") -> 3339175 | AB85: =IFERROR(IF(SUM(R85,Z85)=0,"-",SUM(R85,Z85)),"-") -> 1425175 | AC85: =(5483200-1350000)*0.11 -> 454652 | AD85: =(5483200-1350000)*0.56 -> 2314592 | AE85: - | AF85: =(5483200-1350000)*0.33 -> 1363956 | AG85: - | AH85: =IFERROR(IF(SUM(AC85:AG85)=0,IF(COUNTIF($AC85:$AG85,"=0")>0,"$0","-"),SUM(AC85:AG85)),"-") -> 4133200 | AI85: =IFERROR($AM85/$R85,"-") -> 2.9001351 | AK85: - | AL85: =IFERROR(IF(ISNUMBER($AK85)=TRUE, $AK85*$R85, $AJ85*$R85), "-") -> 0 | AM85: =IFERROR($AH85*$K85,"-") -> 4133200 | AN85: =IFERROR(IF(SUM(AA85,AM85)=0,"-",SUM(AA85,AM85)),"-") -> 7472375 | AO85: =IFERROR(IF(SUM($AB85,$AL85)=0,"-",SUM($AB85,$AL85)),"-") -> 1425175 | AP85: 607815 | AQ85: DC | AR85: =IFERROR(AP85*(12/$I85)*$K85,"-") -> 607815 | AT85: - | AU85: =IFERROR(AT85*(12/$I85)*$K85,"-") -> - | AW85: =IFERROR(IF(SUM(AN85,AR85,AU85)=0,"-",SUM(AN85,AR85,AU85)),"-") -> 8080190 | AX85: =IFERROR(IF(SUM(AO85,AR85,AU85)=0,"-",SUM(AO85,AR85,AU85)),"-") -> 2032990 | AY85: - | AZ85: KP | BA85: sc
A86: =$D86&"_"&$F86&"_"&$L86 -> TSX:PAAS_2025_ | B86: =$D86&"_"&$F86&"_"&$N86 -> TSX:PAAS_2025_CFO | C86: =$D86&"_"&$F86&"_"&$M86 -> TSX:PAAS_2025_ | D86: =D85 -> TSX:PAAS | E86: =_xll.ciqfunctions.udf.CIQ(D86,"IQ_Company_Name") -> Pan American Silver Corp. | F86: =F83 -> 2025 | G86: =F86&"-01-01" -> 2025-01-01 | H86: =F86&"-12-31" -> 2025-12-31 | I86: =_xlfn.DAYS(H86,G86)/_xlfn.DAYS(F86&"-12-31",F86&"-01-01")*12 -> 12 | J86: CAD | K86: =IF($J86="CAD",1,IF($J86="USD",VLOOKUP($F86,$G$9:$H$11,2,FALSE),"N/A")) -> 1 | N86: CFO | O86: CFO | P86: Ignacio Couturier | Q86: 650000 | R86: =IFERROR(Q86*(12/$I86)*$K86,"-") -> 650000 | S86: - | T86: =IFERROR(IF((S86*$K86)=0,"-",(S86*$K86)),"-") -> - | U86: 758875 | V86: =IFERROR(U86*(12/$I86)*$K86,"-") -> 758875 | W86: =IFERROR($V86/$R86,"-") -> 1.1675 | X86: =IFERROR(AVERAGE(W86:W88),"N/A") -> 1.0040643 | Y86: 0.8 | Z86: =IFERROR(IF(ISNUMBER($Y86)=TRUE, $Y86*$R86,$X86*$R86),"-") -> 520000 | AA86: =IFERROR(IF(SUM(R86,V86)=0,"-",SUM(R86,V86)),"-") -> 1408875 | AB86: =IFERROR(IF(SUM(R86,Z86)=0,"-",SUM(R86,Z86)),"-") -> 1170000 | AC86: 780000 | AD86: 650000 | AE86: - | AF86: - | AG86: - | AH86: =IFERROR(IF(SUM(AC86:AG86)=0,IF(COUNTIF($AC86:$AG86,"=0")>0,"$0","-"),SUM(AC86:AG86)),"-") -> 1430000 | AI86: =IFERROR($AM86/$R86,"-") -> 2.2 | AJ86: =IFERROR(AVERAGE(AI86:AI88),"N/A") -> 1.8773601 | AK86: 2.2 | AL86: =IFERROR(IF(ISNUMBER($AK86)=TRUE, $AK86*$R86, $AJ86*$R86), "-") -> 1430000 | AM86: =IFERROR($AH86*$K86,"-") -> 1430000 | AN86: =IFERROR(IF(SUM(AA86,AM86)=0,"-",SUM(AA86,AM86)),"-") -> 2838875 | AO86: =IFERROR(IF(SUM($AB86,$AL86)=0,"-",SUM($AB86,$AL86)),"-") -> 2600000 | AP86: 292500 | AQ86: DC | AR86: =IFERROR(AP86*(12/$I86)*$K86,"-") -> 292500 | AS86: =IFERROR(AVERAGE(AR86:AR88),"N/A") -> 180416.67 | AT86: - | AU86: =IFERROR(AT86*(12/$I86)*$K86,"-") -> - | AV86: =IFERROR(AVERAGE(AU86:AU88),"N/A") -> N/A | AW86: =IFERROR(IF(SUM(AN86,AR86,AU86)=0,"-",SUM(AN86,AR86,AU86)),"-") -> 3131375 | AX86: =IFERROR(IF(SUM(AO86,AR86,AU86)=0,"-",SUM(AO86,AR86,AU86)),"-") -> 2892500 | AY86: - | AZ86: KP | BA86: sc
A87: =$D87&"_"&$F87&"_"&$L87 -> TSX:PAAS_2024_ | B87: =$D87&"_"&$F87&"_"&$N87 -> TSX:PAAS_2024_CFO | C87: =$D87&"_"&$F87&"_"&$M87 -> TSX:PAAS_2024_ | D87: =D86 -> TSX:PAAS | E87: =_xll.ciqfunctions.udf.CIQ(D87,"IQ_Company_Name") -> Pan American Silver Corp. | F87: =F84 -> 2024 | G87: =F87&"-01-01" -> 2024-01-01 | H87: =F87&"-12-31" -> 2024-12-31 | I87: =_xlfn.DAYS(H87,G87)/_xlfn.DAYS(F87&"-12-31",F87&"-01-01")*12 -> 12 | J87: CAD | K87: =IF($J87="CAD",1,IF($J87="USD",VLOOKUP($F87,$G$9:$H$11,2,FALSE),"N/A")) -> 1 | N87: =N86 -> CFO | O87: =O86 -> CFO | P87: =P86 -> Ignacio Couturier | Q87: 575000 | R87: =IFERROR(Q87*(12/$I87)*$K87,"-") -> 575000 | S87: - | T87: =IFERROR(IF((S87*$K87)=0,"-",(S87*$K87)),"-") -> - | U87: 507730 | V87: =IFERROR(U87*(12/$I87)*$K87,"-") -> 507730 | W87: =IFERROR($V87/$R87,"-") -> 0.8830087 | Y87: - | Z87: =IFERROR(IF(ISNUMBER($Y87)=TRUE, $Y87*$R87,$X87*$R87),"-") -> 0 | AA87: =IFERROR(IF(SUM(R87,V87)=0,"-",SUM(R87,V87)),"-") -> 1082730 | AB87: =IFERROR(IF(SUM(R87,Z87)=0,"-",SUM(R87,Z87)),"-") -> 575000 | AC87: 575000 | AD87: 460000 | AE87: - | AF87: - | AG87: - | AH87: =IFERROR(IF(SUM(AC87:AG87)=0,IF(COUNTIF($AC87:$AG87,"=0")>0,"$0","-"),SUM(AC87:AG87)),"-") -> 1035000 | AI87: =IFERROR($AM87/$R87,"-") -> 1.8 | AK87: - | AL87: =IFERROR(IF(ISNUMBER($AK87)=TRUE, $AK87*$R87, $AJ87*$R87), "-") -> 0 | AM87: =IFERROR($AH87*$K87,"-") -> 1035000 | AN87: =IFERROR(IF(SUM(AA87,AM87)=0,"-",SUM(AA87,AM87)),"-") -> 2117730 | AO87: =IFERROR(IF(SUM($AB87,$AL87)=0,"-",SUM($AB87,$AL87)),"-") -> 575000 | AP87: 143750 | AQ87: DC | AR87: =IFERROR(AP87*(12/$I87)*$K87,"-") -> 143750 | AT87: - | AU87: =IFERROR(AT87*(12/$I87)*$K87,"-") -> - | AW87: =IFERROR(IF(SUM(AN87,AR87,AU87)=0,"-",SUM(AN87,AR87,AU87)),"-") -> 2261480 | AX87: =IFERROR(IF(SUM(AO87,AR87,AU87)=0,"-",SUM(AO87,AR87,AU87)),"-") -> 718750 | AY87: - | AZ87: KP | BA87: sc
A88: =$D88&"_"&$F88&"_"&$L88 -> TSX:PAAS_2023_ | B88: =$D88&"_"&$F88&"_"&$N88 -> TSX:PAAS_2023_CFO | C88: =$D88&"_"&$F88&"_"&$M88 -> TSX:PAAS_2023_ | D88: =D87 -> TSX:PAAS | E88: =_xll.ciqfunctions.udf.CIQ(D88,"IQ_Company_Name") -> Pan American Silver Corp. | F88: =F85 -> 2023 | G88: =F88&"-01-01" -> 2023-01-01 | H88: =F88&"-12-31" -> 2023-12-31 | I88: =_xlfn.DAYS(H88,G88)/_xlfn.DAYS(F88&"-12-31",F88&"-01-01")*12 -> 12 | J88: CAD | K88: =IF($J88="CAD",1,IF($J88="USD",VLOOKUP($F88,$G$9:$H$11,2,FALSE),"N/A")) -> 1 | N88: =N87 -> CFO | O88: =O87 -> CFO | P88: =P87 -> Ignacio Couturier | Q88: 498750 | R88: =IFERROR(Q88*(12/$I88)*$K88,"-") -> 498750 | S88: - | T88: =IFERROR(IF((S88*$K88)=0,"-",(S88*$K88)),"-") -> - | U88: 479640 | V88: =IFERROR(U88*(12/$I88)*$K88,"-") -> 479640 | W88: =IFERROR($V88/$R88,"-") -> 0.96168421 | Y88: - | Z88: =IFERROR(IF(ISNUMBER($Y88)=TRUE, $Y88*$R88,$X88*$R88),"-") -> 0 | AA88: =IFERROR(IF(SUM(R88,V88)=0,"-",SUM(R88,V88)),"-") -> 978390 | AB88: =IFERROR(IF(SUM(R88,Z88)=0,"-",SUM(R88,Z88)),"-") -> 498750 | AC88: =(939750-126000-131250)*0.49 -> 334425 | AD88: =(939750-126000-131250)*0.51 -> 348075 | AE88: 131500 | AF88: - | AG88: - | AH88: =IFERROR(IF(SUM(AC88:AG88)=0,IF(COUNTIF($AC88:$AG88,"=0")>0,"$0","-"),SUM(AC88:AG88)),"-") -> 814000 | AI88: =IFERROR($AM88/$R88,"-") -> 1.6320802 | AK88: - | AL88: =IFERROR(IF(ISNUMBER($AK88)=TRUE, $AK88*$R88, $AJ88*$R88), "-") -> 0 | AM88: =IFERROR($AH88*$K88,"-") -> 814000 | AN88: =IFERROR(IF(SUM(AA88,AM88)=0,"-",SUM(AA88,AM88)),"-") -> 1792390 | AO88: =IFERROR(IF(SUM($AB88,$AL88)=0,"-",SUM($AB88,$AL88)),"-") -> 498750 | AP88: 105000 | AQ88: DC | AR88: =IFERROR(AP88*(12/$I88)*$K88,"-") -> 105000 | AT88: - | AU88: =IFERROR(AT88*(12/$I88)*$K88,"-") -> - | AW88: =IFERROR(IF(SUM(AN88,AR88,AU88)=0,"-",SUM(AN88,AR88,AU88)),"-") -> 1897390 | AX88: =IFERROR(IF(SUM(AO88,AR88,AU88)=0,"-",SUM(AO88,AR88,AU88)),"-") -> 603750 | AY88: - | AZ88: KP | BA88: sc
A89: =$D89&"_"&$F89&"_"&$L89 -> TSX:PAAS_2025_ | B89: =$D89&"_"&$F89&"_"&$N89 -> TSX:PAAS_2025_- | C89: =$D89&"_"&$F89&"_"&$M89 -> TSX:PAAS_2025_2nd Highest | D89: =D88 -> TSX:PAAS | E89: =_xll.ciqfunctions.udf.CIQ(D89,"IQ_Company_Name") -> Pan American Silver Corp. | F89: =F86 -> 2025 | G89: =F89&"-01-01" -> 2025-01-01 | H89: =F89&"-12-31" -> 2025-12-31 | I89: =_xlfn.DAYS(H89,G89)/_xlfn.DAYS(F89&"-12-31",F89&"-01-01")*12 -> 12 | J89: CAD | K89: =IF($J89="CAD",1,IF($J89="USD",VLOOKUP($F89,$G$9:$H$11,2,FALSE),"N/A")) -> 1 | M89: 2nd Highest | N89: - | O89: Former COO | P89: Steven Busby | Q89: 808100 | R89: =IFERROR(Q89*(12/$I89)*$K89,"-") -> 808100 | S89: - | T89: =IFERROR(IF((S89*$K89)=0,"-",(S89*$K89)),"-") -> - | U89: 945477 | V89: =IFERROR(U89*(12/$I89)*$K89,"-") -> 945477 | W89: =IFERROR($V89/$R89,"-") -> 1.17 | X89: =IFERROR(AVERAGE(W89:W91),"N/A") -> 0.94709104 | Y89: 0.8 | Z89: =IFERROR(IF(ISNUMBER($Y89)=TRUE, $Y89*$R89,$X89*$R89),"-") -> 646480 | AA89: =IFERROR(IF(SUM(R89,V89)=0,"-",SUM(R89,V89)),"-") -> 1753577 | AB89: =IFERROR(IF(SUM(R89,Z89)=0,"-",SUM(R89,Z89)),"-") -> 1454580 | AC89: 969700 | AD89: 808100 | AE89: - | AF89: - | AG89: - | AH89: =IFERROR(IF(SUM(AC89:AG89)=0,IF(COUNTIF($AC89:$AG89,"=0")>0,"$0","-"),SUM(AC89:AG89)),"-") -> 1777800 | AI89: =IFERROR($AM89/$R89,"-") -> 2.1999753 | AJ89: =IFERROR(AVERAGE(AI89:AI91),"N/A") -> 2.2062785 | AK89: 2.2 | AL89: =IFERROR(IF(ISNUMBER($AK89)=TRUE, $AK89*$R89, $AJ89*$R89), "-") -> 1777820 | AM89: =IFERROR($AH89*$K89,"-") -> 1777800 | AN89: =IFERROR(IF(SUM(AA89,AM89)=0,"-",SUM(AA89,AM89)),"-") -> 3531377 | AO89: =IFERROR(IF(SUM($AB89,$AL89)=0,"-",SUM($AB89,$AL89)),"-") -> 3232400 | AP89: 363645 | AQ89: DC | AR89: =IFERROR(AP89*(12/$I89)*$K89,"-") -> 363645 | AS89: =IFERROR(AVERAGE(AR89:AR91),"N/A") -> 346890 | AT89: - | AU89: =IFERROR(AT89*(12/$I89)*$K89,"-") -> - | AV89: =IFERROR(AVERAGE(AU89:AU91),"N/A") -> N/A | AW89: =IFERROR(IF(SUM(AN89,AR89,AU89)=0,"-",SUM(AN89,AR89,AU89)),"-") -> 3895022 | AX89: =IFERROR(IF(SUM(AO89,AR89,AU89)=0,"-",SUM(AO89,AR89,AU89)),"-") -> 3596045 | AY89: Mr. Busby was the Company's Chief Operating Officer until October 20, 2025. He then transitioned to the role of Special Advisor to the CEO for the remainder of the year | AZ89: KP | BA89: sc | BB89: Former COO
A90: =$D90&"_"&$F90&"_"&$L90 -> TSX:PAAS_2024_ | B90: =$D90&"_"&$F90&"_"&$N90 -> TSX:PAAS_2024_- | C90: =$D90&"_"&$F90&"_"&$M90 -> TSX:PAAS_2024_ | D90: =D89 -> TSX:PAAS | E90: =_xll.ciqfunctions.udf.CIQ(D90,"IQ_Company_Name") -> Pan American Silver Corp. | F90: =F87 -> 2024 | G90: =F90&"-01-01" -> 2024-01-01 | H90: =F90&"-12-31" -> 2024-12-31 | I90: =_xlfn.DAYS(H90,G90)/_xlfn.DAYS(F90&"-12-31",F90&"-01-01")*12 -> 12 | J90: CAD | K90: =IF($J90="CAD",1,IF($J90="USD",VLOOKUP($F90,$G$9:$H$11,2,FALSE),"N/A")) -> 1 | N90: =N89 -> - | O90: =O89 -> Former COO | P90: =P89 -> Steven Busby | Q90: 780000 | R90: =IFERROR(Q90*(12/$I90)*$K90,"-") -> 780000 | S90: - | T90: =IFERROR(IF((S90*$K90)=0,"-",(S90*$K90)),"-") -> - | U90: 639000 | V90: =IFERROR(U90*(12/$I90)*$K90,"-") -> 639000 | W90: =IFERROR($V90/$R90,"-") -> 0.81923077 | Y90: - | Z90: =IFERROR(IF(ISNUMBER($Y90)=TRUE, $Y90*$R90,$X90*$R90),"-") -> 0 | AA90: =IFERROR(IF(SUM(R90,V90)=0,"-",SUM(R90,V90)),"-") -> 1419000 | AB90: =IFERROR(IF(SUM(R90,Z90)=0,"-",SUM(R90,Z90)),"-") -> 780000 | AC90: 936000 | AD90: 780000 | AE90: - | AF90: - | AG90: - | AH90: =IFERROR(IF(SUM(AC90:AG90)=0,IF(COUNTIF($AC90:$AG90,"=0")>0,"$0","-"),SUM(AC90:AG90)),"-") -> 1716000 | AI90: =IFERROR($AM90/$R90,"-") -> 2.2 | AK90: - | AL90: =IFERROR(IF(ISNUMBER($AK90)=TRUE, $AK90*$R90, $AJ90*$R90), "-") -> 0 | AM90: =IFERROR($AH90*$K90,"-") -> 1716000 | AN90: =IFERROR(IF(SUM(AA90,AM90)=0,"-",SUM(AA90,AM90)),"-") -> 3135000 | AO90: =IFERROR(IF(SUM($AB90,$AL90)=0,"-",SUM($AB90,$AL90)),"-") -> 780000 | AP90: 351000 | AQ90: DC | AR90: =IFERROR(AP90*(12/$I90)*$K90,"-") -> 351000 | AT90: - | AU90: =IFERROR(AT90*(12/$I90)*$K90,"-") -> - | AW90: =IFERROR(IF(SUM(AN90,AR90,AU90)=0,"-",SUM(AN90,AR90,AU90)),"-") -> 3486000 | AX90: =IFERROR(IF(SUM(AO90,AR90,AU90)=0,"-",SUM(AO90,AR90,AU90)),"-") -> 1131000 | AY90: - | AZ90: KP | BA90: sc
A91: =$D91&"_"&$F91&"_"&$L91 -> TSX:PAAS_2023_ | B91: =$D91&"_"&$F91&"_"&$N91 -> TSX:PAAS_2023_- | C91: =$D91&"_"&$F91&"_"&$M91 -> TSX:PAAS_2023_ | D91: =D90 -> TSX:PAAS | E91: =_xll.ciqfunctions.udf.CIQ(D91,"IQ_Company_Name") -> Pan American Silver Corp. | F91: =F88 -> 2023 | G91: =F91&"-01-01" -> 2023-01-01 | H91: =F91&"-12-31" -> 2023-12-31 | I91: =_xlfn.DAYS(H91,G91)/_xlfn.DAYS(F91&"-12-31",F91&"-01-01")*12 -> 12 | J91: CAD | K91: =IF($J91="CAD",1,IF($J91="USD",VLOOKUP($F91,$G$9:$H$11,2,FALSE),"N/A")) -> 1 | N91: =N90 -> - | O91: =O90 -> Former COO | P91: =P90 -> Steven Busby | Q91: 743625 | R91: =IFERROR(Q91*(12/$I91)*$K91,"-") -> 743625 | S91: - | T91: =IFERROR(IF((S91*$K91)=0,"-",(S91*$K91)),"-") -> - | U91: 633600 | V91: =IFERROR(U91*(12/$I91)*$K91,"-") -> 633600 | W91: =IFERROR($V91/$R91,"-") -> 0.85204236 | Y91: - | Z91: =IFERROR(IF(ISNUMBER($Y91)=TRUE, $Y91*$R91,$X91*$R91),"-") -> 0 | AA91: =IFERROR(IF(SUM(R91,V91)=0,"-",SUM(R91,V91)),"-") -> 1377225 | AB91: =IFERROR(IF(SUM(R91,Z91)=0,"-",SUM(R91,Z91)),"-") -> 743625 | AC91: =(2374500-724500)*0.14 -> 231000 | AD91: =(2374500-724500)*0.45 -> 742500 | AE91: - | AF91: =(2374500-724500)*0.41 -> 676500 | AG91: - | AH91: =IFERROR(IF(SUM(AC91:AG91)=0,IF(COUNTIF($AC91:$AG91,"=0")>0,"$0","-"),SUM(AC91:AG91)),"-") -> 1650000 | AI91: =IFERROR($AM91/$R91,"-") -> 2.2188603 | AK91: - | AL91: =IFERROR(IF(ISNUMBER($AK91)=TRUE, $AK91*$R91, $AJ91*$R91), "-") -> 0 | AM91: =IFERROR($AH91*$K91,"-") -> 1650000 | AN91: =IFERROR(IF(SUM(AA91,AM91)=0,"-",SUM(AA91,AM91)),"-") -> 3027225 | AO91: =IFERROR(IF(SUM($AB91,$AL91)=0,"-",SUM($AB91,$AL91)),"-") -> 743625 | AP91: 326025 | AQ91: DC | AR91: =IFERROR(AP91*(12/$I91)*$K91,"-") -> 326025 | AT91: - | AU91: =IFERROR(AT91*(12/$I91)*$K91,"-") -> - | AW91: =IFERROR(IF(SUM(AN91,AR91,AU91)=0,"-",SUM(AN91,AR91,AU91)),"-") -> 3353250 | AX91: =IFERROR(IF(SUM(AO91,AR91,AU91)=0,"-",SUM(AO91,AR91,AU91)),"-") -> 1069650 | AY91: - | AZ91: KP | BA91: sc
A92: =$D92&"_"&$F92&"_"&$L92 -> TSX:PAAS_2025_Legal | B92: =$D92&"_"&$F92&"_"&$N92 -> TSX:PAAS_2025_NEO2 | C92: =$D92&"_"&$F92&"_"&$M92 -> TSX:PAAS_2025_ | D92: =D91 -> TSX:PAAS | E92: =_xll.ciqfunctions.udf.CIQ(D92,"IQ_Company_Name") -> Pan American Silver Corp. | F92: =F89 -> 2025 | G92: =F92&"-01-01" -> 2025-01-01 | H92: =F92&"-12-31" -> 2025-12-31 | I92: =_xlfn.DAYS(H92,G92)/_xlfn.DAYS(F92&"-12-31",F92&"-01-01")*12 -> 12 | J92: CAD | K92: =IF($J92="CAD",1,IF($J92="USD",VLOOKUP($F92,$G$9:$H$11,2,FALSE),"N/A")) -> 1 | L92: Legal | N92: NEO2 | O92: General Counsel | P92: Christopher Lemon | Q92: 700000 | R92: =IFERROR(Q92*(12/$I92)*$K92,"-") -> 700000 | S92: - | T92: =IFERROR(IF((S92*$K92)=0,"-",(S92*$K92)),"-") -> - | U92: 824250 | V92: =IFERROR(U92*(12/$I92)*$K92,"-") -> 824250 | W92: =IFERROR($V92/$R92,"-") -> 1.1775 | X92: =IFERROR(AVERAGE(W92:W94),"N/A") -> 1.0042077 | Y92: 0.8 | Z92: =IFERROR(IF(ISNUMBER($Y92)=TRUE, $Y92*$R92,$X92*$R92),"-") -> 560000 | AA92: =IFERROR(IF(SUM(R92,V92)=0,"-",SUM(R92,V92)),"-") -> 1524250 | AB92: =IFERROR(IF(SUM(R92,Z92)=0,"-",SUM(R92,Z92)),"-") -> 1260000 | AC92: 840000 | AD92: 700000 | AE92: - | AF92: - | AG92: - | AH92: =IFERROR(IF(SUM(AC92:AG92)=0,IF(COUNTIF($AC92:$AG92,"=0")>0,"$0","-"),SUM(AC92:AG92)),"-") -> 1540000 | AI92: =IFERROR($AM92/$R92,"-") -> 2.2 | AJ92: =IFERROR(AVERAGE(AI92:AI94),"N/A") -> 2.2175094 | AK92: 2.2 | AL92: =IFERROR(IF(ISNUMBER($AK92)=TRUE, $AK92*$R92, $AJ92*$R92), "-") -> 1540000 | AM92: =IFERROR($AH92*$K92,"-") -> 1540000 | AN92: =IFERROR(IF(SUM(AA92,AM92)=0,"-",SUM(AA92,AM92)),"-") -> 3064250 | AO92: =IFERROR(IF(SUM($AB92,$AL92)=0,"-",SUM($AB92,$AL92)),"-") -> 2800000 | AP92: 315000 | AQ92: DC | AR92: =IFERROR(AP92*(12/$I92)*$K92,"-") -> 315000 | AS92: =IFERROR(AVERAGE(AR92:AR94),"N/A") -> 246251.67 | AT92: - | AU92: =IFERROR(AT92*(12/$I92)*$K92,"-") -> - | AV92: =IFERROR(AVERAGE(AU92:AU94),"N/A") -> N/A | AW92: =IFERROR(IF(SUM(AN92,AR92,AU92)=0,"-",SUM(AN92,AR92,AU92)),"-") -> 3379250 | AX92: =IFERROR(IF(SUM(AO92,AR92,AU92)=0,"-",SUM(AO92,AR92,AU92)),"-") -> 3115000 | AY92: - | AZ92: KP | BA92: sc
A93: =$D93&"_"&$F93&"_"&$L93 -> TSX:PAAS_2024_Legal | B93: =$D93&"_"&$F93&"_"&$N93 -> TSX:PAAS_2024_NEO2 | C93: =$D93&"_"&$F93&"_"&$M93 -> TSX:PAAS_2024_ | D93: =D92 -> TSX:PAAS | E93: =_xll.ciqfunctions.udf.CIQ(D93,"IQ_Company_Name") -> Pan American Silver Corp. | F93: =F90 -> 2024 | G93: =F93&"-01-01" -> 2024-01-01 | H93: =F93&"-12-31" -> 2024-12-31 | I93: =_xlfn.DAYS(H93,G93)/_xlfn.DAYS(F93&"-12-31",F93&"-01-01")*12 -> 12 | J93: CAD | K93: =IF($J93="CAD",1,IF($J93="USD",VLOOKUP($F93,$G$9:$H$11,2,FALSE),"N/A")) -> 1 | L93: Legal | N93: =N92 -> NEO2 | O93: =O92 -> General Counsel | P93: =P92 -> Christopher Lemon | Q93: 634400 | R93: =IFERROR(Q93*(12/$I93)*$K93,"-") -> 634400 | S93: - | T93: =IFERROR(IF((S93*$K93)=0,"-",(S93*$K93)),"-") -> - | U93: 567790 | V93: =IFERROR(U93*(12/$I93)*$K93,"-") -> 567790 | W93: =IFERROR($V93/$R93,"-") -> 0.89500315 | Y93: - | Z93: =IFERROR(IF(ISNUMBER($Y93)=TRUE, $Y93*$R93,$X93*$R93),"-") -> 0 | AA93: =IFERROR(IF(SUM(R93,V93)=0,"-",SUM(R93,V93)),"-") -> 1202190 | AB93: =IFERROR(IF(SUM(R93,Z93)=0,"-",SUM(R93,Z93)),"-") -> 634400 | AC93: 761280 | AD93: 634400 | AE93: - | AF93: - | AG93: - | AH93: =IFERROR(IF(SUM(AC93:AG93)=0,IF(COUNTIF($AC93:$AG93,"=0")>0,"$0","-"),SUM(AC93:AG93)),"-") -> 1395680 | AI93: =IFERROR($AM93/$R93,"-") -> 2.2 | AK93: - | AL93: =IFERROR(IF(ISNUMBER($AK93)=TRUE, $AK93*$R93, $AJ93*$R93), "-") -> 0 | AM93: =IFERROR($AH93*$K93,"-") -> 1395680 | AN93: =IFERROR(IF(SUM(AA93,AM93)=0,"-",SUM(AA93,AM93)),"-") -> 2597870 | AO93: =IFERROR(IF(SUM($AB93,$AL93)=0,"-",SUM($AB93,$AL93)),"-") -> 634400 | AP93: 285480 | AQ93: DC | AR93: =IFERROR(AP93*(12/$I93)*$K93,"-") -> 285480 | AT93: - | AU93: =IFERROR(AT93*(12/$I93)*$K93,"-") -> - | AW93: =IFERROR(IF(SUM(AN93,AR93,AU93)=0,"-",SUM(AN93,AR93,AU93)),"-") -> 2883350 | AX93: =IFERROR(IF(SUM(AO93,AR93,AU93)=0,"-",SUM(AO93,AR93,AU93)),"-") -> 919880 | AY93: - | AZ93: KP | BA93: sc
A94: =$D94&"_"&$F94&"_"&$L94 -> TSX:PAAS_2023_Legal | B94: =$D94&"_"&$F94&"_"&$N94 -> TSX:PAAS_2023_NEO2 | C94: =$D94&"_"&$F94&"_"&$M94 -> TSX:PAAS_2023_ | D94: =D93 -> TSX:PAAS | E94: =_xll.ciqfunctions.udf.CIQ(D94,"IQ_Company_Name") -> Pan American Silver Corp. | F94: =F91 -> 2023 | G94: =F94&"-01-01" -> 2023-01-01 | H94: =F94&"-12-31" -> 2023-12-31 | I94: =_xlfn.DAYS(H94,G94)/_xlfn.DAYS(F94&"-12-31",F94&"-01-01")*12 -> 12 | J94: CAD | K94: =IF($J94="CAD",1,IF($J94="USD",VLOOKUP($F94,$G$9:$H$11,2,FALSE),"N/A")) -> 1 | L94: Legal | N94: =N93 -> NEO2 | O94: =O93 -> General Counsel | P94: =P93 -> Christopher Lemon | Q94: 595775 | R94: =IFERROR(Q94*(12/$I94)*$K94,"-") -> 595775 | S94: - | T94: =IFERROR(IF((S94*$K94)=0,"-",(S94*$K94)),"-") -> - | U94: 560100 | V94: =IFERROR(U94*(12/$I94)*$K94,"-") -> 560100 | W94: =IFERROR($V94/$R94,"-") -> 0.94012001 | Y94: - | Z94: =IFERROR(IF(ISNUMBER($Y94)=TRUE, $Y94*$R94,$X94*$R94),"-") -> 0 | AA94: =IFERROR(IF(SUM(R94,V94)=0,"-",SUM(R94,V94)),"-") -> 1155875 | AB94: =IFERROR(IF(SUM(R94,Z94)=0,"-",SUM(R94,Z94)),"-") -> 595775 | AC94: =(1895100-553100)*0.55 -> 738100 | AD94: =(1895100-553100)*0.45 -> 603900 | AE94: - | AF94: - | AG94: - | AH94: =IFERROR(IF(SUM(AC94:AG94)=0,IF(COUNTIF($AC94:$AG94,"=0")>0,"$0","-"),SUM(AC94:AG94)),"-") -> 1342000 | AI94: =IFERROR($AM94/$R94,"-") -> 2.2525282 | AK94: - | AL94: =IFERROR(IF(ISNUMBER($AK94)=TRUE, $AK94*$R94, $AJ94*$R94), "-") -> 0 | AM94: =IFERROR($AH94*$K94,"-") -> 1342000 | AN94: =IFERROR(IF(SUM(AA94,AM94)=0,"-",SUM(AA94,AM94)),"-") -> 2497875 | AO94: =IFERROR(IF(SUM($AB94,$AL94)=0,"-",SUM($AB94,$AL94)),"-") -> 595775 | AP94: 138275 | AQ94: DC | AR94: =IFERROR(AP94*(12/$I94)*$K94,"-") -> 138275 | AT94: - | AU94: =IFERROR(AT94*(12/$I94)*$K94,"-") -> - | AW94: =IFERROR(IF(SUM(AN94,AR94,AU94)=0,"-",SUM(AN94,AR94,AU94)),"-") -> 2636150 | AX94: =IFERROR(IF(SUM(AO94,AR94,AU94)=0,"-",SUM(AO94,AR94,AU94)),"-") -> 734050 | AY94: - | AZ94: KP | BA94: sc
A95: =$D95&"_"&$F95&"_"&$L95 -> TSX:PAAS_2025_COO | B95: =$D95&"_"&$F95&"_"&$N95 -> TSX:PAAS_2025_NEO1 | C95: =$D95&"_"&$F95&"_"&$M95 -> TSX:PAAS_2025_ | D95: =D94 -> TSX:PAAS | E95: =_xll.ciqfunctions.udf.CIQ(D95,"IQ_Company_Name") -> Pan American Silver Corp. | F95: =F92 -> 2025 | G95: =F95&"-10-20" -> 2025-10-20 | H95: =F95&"-12-31" -> 2025-12-31 | I95: 12 | J95: CAD | K95: =IF($J95="CAD",1,IF($J95="USD",VLOOKUP($F95,$G$9:$H$11,2,FALSE),"N/A")) -> 1 | L95: COO | N95: NEO1 | O95: COO | P95: Scott Campbell | Q95: 632222 | R95: 760000 | S95: - | T95: =IFERROR(IF((S95*$K95)=0,"-",(S95*$K95)),"-") -> - | U95: 879700 | V95: =IFERROR(U95*(12/$I95)*$K95,"-") -> 879700 | W95: =IFERROR($V95/$R95,"-") -> 1.1575 | X95: =IFERROR(AVERAGE(W95:W97),"N/A") -> 1.1575 | Y95: 0.8 | Z95: =IFERROR(IF(ISNUMBER($Y95)=TRUE, $Y95*$R95,$X95*$R95),"-") -> 608000 | AA95: =IFERROR(IF(SUM(R95,V95)=0,"-",SUM(R95,V95)),"-") -> 1639700 | AB95: =IFERROR(IF(SUM(R95,Z95)=0,"-",SUM(R95,Z95)),"-") -> 1368000 | AC95: 912000 | AD95: 760000 | AE95: - | AF95: - | AG95: - | AH95: =IFERROR(IF(SUM(AC95:AG95)=0,IF(COUNTIF($AC95:$AG95,"=0")>0,"$0","-"),SUM(AC95:AG95)),"-") -> 1672000 | AI95: =IFERROR($AM95/$R95,"-") -> 2.2 | AJ95: =IFERROR(AVERAGE(AI95:AI97),"N/A") -> 2.2 | AK95: 2.2 | AL95: =IFERROR(IF(ISNUMBER($AK95)=TRUE, $AK95*$R95, $AJ95*$R95), "-") -> 1672000 | AM95: =IFERROR($AH95*$K95,"-") -> 1672000 | AN95: =IFERROR(IF(SUM(AA95,AM95)=0,"-",SUM(AA95,AM95)),"-") -> 3311700 | AO95: =IFERROR(IF(SUM($AB95,$AL95)=0,"-",SUM($AB95,$AL95)),"-") -> 3040000 | AP95: 150000 | AQ95: DC | AR95: =IFERROR(AP95*(12/$I95)*$K95,"-") -> 150000 | AS95: =IFERROR(AVERAGE(AR95:AR97),"N/A") -> 150000 | AT95: - | AU95: =IFERROR(AT95*(12/$I95)*$K95,"-") -> - | AV95: =IFERROR(AVERAGE(AU95:AU97),"N/A") -> N/A | AW95: =IFERROR(IF(SUM(AN95,AR95,AU95)=0,"-",SUM(AN95,AR95,AU95)),"-") -> 3461700 | AX95: =IFERROR(IF(SUM(AO95,AR95,AU95)=0,"-",SUM(AO95,AR95,AU95)),"-") -> 3190000 | AY95: Mr. Campbell joined the Company on April 2, 2024 as SVP, Projects and Operations and was promoted to Chief Operating Officer on October 20, 2025, his 2025 actual 2025 compensation is a combination of pay from both roles, but targets have been captured. | AZ95: KP | BA95: sc | BB95: Scott Campbell was promoted to COO effective October 20, 2025
A96: =$D96&"_"&$F96&"_"&$L96 -> TSX:PAAS_2024_COO | B96: =$D96&"_"&$F96&"_"&$N96 -> TSX:PAAS_2024_NEO1 | C96: =$D96&"_"&$F96&"_"&$M96 -> TSX:PAAS_2024_ | D96: =D95 -> TSX:PAAS | E96: =_xll.ciqfunctions.udf.CIQ(D96,"IQ_Company_Name") -> Pan American Silver Corp. | F96: =F93 -> 2024 | G96: =F96&"-01-01" -> 2024-01-01 | H96: =F96&"-12-31" -> 2024-12-31 | I96: =_xlfn.DAYS(H96,G96)/_xlfn.DAYS(F96&"-12-31",F96&"-01-01")*12 -> 12 | J96: CAD | K96: =IF($J96="CAD",1,IF($J96="USD",VLOOKUP($F96,$G$9:$H$11,2,FALSE),"N/A")) -> 1 | L96: COO | N96: =N95 -> NEO1 | O96: =O95 -> COO | P96: =P95 -> Scott Campbell | Q96: - | R96: =IFERROR(Q96*(12/$I96)*$K96,"-") -> - | S96: - | T96: =IFERROR(IF((S96*$K96)=0,"-",(S96*$K96)),"-") -> - | U96: - | V96: =IFERROR(U96*(12/$I96)*$K96,"-") -> - | W96: =IFERROR($V96/$R96,"-") -> - | Y96: - | Z96: =IFERROR(IF(ISNUMBER($Y96)=TRUE, $Y96*$R96,$X96*$R96),"-") -> - | AA96: =IFERROR(IF(SUM(R96,V96)=0,"-",SUM(R96,V96)),"-") -> - | AB96: =IFERROR(IF(SUM(R96,Z96)=0,"-",SUM(R96,Z96)),"-") -> - | AC96: - | AD96: - | AE96: - | AF96: - | AG96: - | AH96: =IFERROR(IF(SUM(AC96:AG96)=0,IF(COUNTIF($AC96:$AG96,"=0")>0,"$0","-"),SUM(AC96:AG96)),"-") -> - | AI96: =IFERROR($AM96/$R96,"-") -> - | AK96: - | AL96: =IFERROR(IF(ISNUMBER($AK96)=TRUE, $AK96*$R96, $AJ96*$R96), "-") -> - | AM96: =IFERROR($AH96*$K96,"-") -> - | AN96: =IFERROR(IF(SUM(AA96,AM96)=0,"-",SUM(AA96,AM96)),"-") -> - | AO96: =IFERROR(IF(SUM($AB96,$AL96)=0,"-",SUM($AB96,$AL96)),"-") -> - | AP96: - | AQ96: - | AR96: =IFERROR(AP96*(12/$I96)*$K96,"-") -> - | AT96: - | AU96: =IFERROR(AT96*(12/$I96)*$K96,"-") -> - | AW96: =IFERROR(IF(SUM(AN96,AR96,AU96)=0,"-",SUM(AN96,AR96,AU96)),"-") -> - | AX96: =IFERROR(IF(SUM(AO96,AR96,AU96)=0,"-",SUM(AO96,AR96,AU96)),"-") -> - | AY96: - | AZ96: KP | BA96: sc
A97: =$D97&"_"&$F97&"_"&$L97 -> TSX:PAAS_2023_COO | B97: =$D97&"_"&$F97&"_"&$N97 -> TSX:PAAS_2023_NEO1 | C97: =$D97&"_"&$F97&"_"&$M97 -> TSX:PAAS_2023_ | D97: =D96 -> TSX:PAAS | E97: =_xll.ciqfunctions.udf.CIQ(D97,"IQ_Company_Name") -> Pan American Silver Corp. | F97: =F94 -> 2023 | G97: =F97&"-01-01" -> 2023-01-01 | H97: =F97&"-12-31" -> 2023-12-31 | I97: =_xlfn.DAYS(H97,G97)/_xlfn.DAYS(F97&"-12-31",F97&"-01-01")*12 -> 12 | J97: CAD | K97: =IF($J97="CAD",1,IF($J97="USD",VLOOKUP($F97,$G$9:$H$11,2,FALSE),"N/A")) -> 1 | L97: COO | N97: =N96 -> NEO1 | O97: =O96 -> COO | P97: =P96 -> Scott Campbell | Q97: - | R97: =IFERROR(Q97*(12/$I97)*$K97,"-") -> - | S97: - | T97: =IFERROR(IF((S97*$K97)=0,"-",(S97*$K97)),"-") -> - | U97: - | V97: =IFERROR(U97*(12/$I97)*$K97,"-") -> - | W97: =IFERROR($V97/$R97,"-") -> - | Y97: - | Z97: =IFERROR(IF(ISNUMBER($Y97)=TRUE, $Y97*$R97,$X97*$R97),"-") -> - | AA97: =IFERROR(IF(SUM(R97,V97)=0,"-",SUM(R97,V97)),"-") -> - | AB97: =IFERROR(IF(SUM(R97,Z97)=0,"-",SUM(R97,Z97)),"-") -> - | AC97: - | AD97: - | AE97: - | AF97: - | AG97: - | AH97: =IFERROR(IF(SUM(AC97:AG97)=0,IF(COUNTIF($AC97:$AG97,"=0")>0,"$0","-"),SUM(AC97:AG97)),"-") -> - | AI97: =IFERROR($AM97/$R97,"-") -> - | AK97: - | AL97: =IFERROR(IF(ISNUMBER($AK97)=TRUE, $AK97*$R97, $AJ97*$R97), "-") -> - | AM97: =IFERROR($AH97*$K97,"-") -> - | AN97: =IFERROR(IF(SUM(AA97,AM97)=0,"-",SUM(AA97,AM97)),"-") -> - | AO97: =IFERROR(IF(SUM($AB97,$AL97)=0,"-",SUM($AB97,$AL97)),"-") -> - | AP97: - | AQ97: - | AR97: =IFERROR(AP97*(12/$I97)*$K97,"-") -> - | AT97: - | AU97: =IFERROR(AT97*(12/$I97)*$K97,"-") -> - | AW97: =IFERROR(IF(SUM(AN97,AR97,AU97)=0,"-",SUM(AN97,AR97,AU97)),"-") -> - | AX97: =IFERROR(IF(SUM(AO97,AR97,AU97)=0,"-",SUM(AO97,AR97,AU97)),"-") -> - | AY97: - | AZ97: KP | BA97: sc
A98: =$D98&"_"&$F98&"_"&$L98 -> TSX:BTO_2025_ | B98: =$D98&"_"&$F98&"_"&$N98 -> TSX:BTO_2025_CEO | C98: =$D98&"_"&$F98&"_"&$M98 -> TSX:BTO_2025_ | D98: =E8 -> TSX:BTO | E98: =_xll.ciqfunctions.udf.CIQ(D98,"IQ_Company_Name") -> B2Gold Corp. | F98: =$G$9 -> 2025 | G98: =F98&"-01-01" -> 2025-01-01 | H98: =F98&"-12-31" -> 2025-12-31 | I98: =_xlfn.DAYS(H98,G98)/_xlfn.DAYS(F98&"-12-31",F98&"-01-01")*12 -> 12 | J98: USD | K98: =IF($J98="CAD",1,IF($J98="USD",VLOOKUP($F98,$G$9:$H$11,2,FALSE),"N/A")) -> 1.39745 | N98: CEO | O98: Director, President, & CEO | P98: Clive Johnson | Q98: 949000 | R98: =IFERROR(Q98*(12/$I98)*$K98,"-") -> 1326180.1 | S98: - | T98: =IFERROR(IF((S98*$K98)=0,"-",(S98*$K98)),"-") -> - | U98: 1010685 | V98: =IFERROR(U98*(12/$I98)*$K98,"-") -> 1412381.8 | W98: =IFERROR($V98/$R98,"-") -> 1.065 | X98: =IFERROR(AVERAGE(W98:W100),"N/A") -> 0.72512821 | Y98: 1 | Z98: =IFERROR(IF(ISNUMBER($Y98)=TRUE, $Y98*$R98,$X98*$R98),"-") -> 1326180.1 | AA98: =IFERROR(IF(SUM(R98,V98)=0,"-",SUM(R98,V98)),"-") -> 2738561.8 | AB98: =IFERROR(IF(SUM(R98,Z98)=0,"-",SUM(R98,Z98)),"-") -> 2652360.1 | AC98: 2729835 | AD98: - | AE98: - | AF98: - | AG98: - | AH98: =IFERROR(IF(SUM(AC98:AG98)=0,IF(COUNTIF($AC98:$AG98,"=0")>0,"$0","-"),SUM(AC98:AG98)),"-") -> 2729835 | AI98: =IFERROR($AM98/$R98,"-") -> 2.8765385 | AJ98: =IFERROR(AVERAGE(AI98:AI100),"N/A") -> 2.7537179 | AK98: =0.54/0.23 -> 2.3478261 | AL98: =IFERROR(IF(ISNUMBER($AK98)=TRUE, $AK98*$R98, $AJ98*$R98), "-") -> 3113640.1 | AM98: =IFERROR($AH98*$K98,"-") -> 3814807.9 | AN98: =IFERROR(IF(SUM(AA98,AM98)=0,"-",SUM(AA98,AM98)),"-") -> 6553369.7 | AO98: =IFERROR(IF(SUM($AB98,$AL98)=0,"-",SUM($AB98,$AL98)),"-") -> 5766000.2 | AP98: N/A | AQ98: N/A | AR98: =IFERROR(AP98*(12/$I98)*$K98,"-") -> - | AS98: =IFERROR(AVERAGE(AR98:AR100),"N/A") -> N/A | AT98: =149833-144602 -> 5231 | AU98: =IFERROR(AT98*(12/$I98)*$K98,"-") -> 7310.061 | AV98: =IFERROR(AVERAGE(AU98:AU100),"N/A") -> 8739.6115 | AW98: =IFERROR(IF(SUM(AN98,AR98,AU98)=0,"-",SUM(AN98,AR98,AU98)),"-") -> 6560679.8 | AX98: =IFERROR(IF(SUM(AO98,AR98,AU98)=0,"-",SUM(AO98,AR98,AU98)),"-") -> 5773310.3 | AY98: For the CEO only for 2025, LTI awards consisted entirely of RSUs to reflect Mr. Johnson’s retirement | AZ98: KP | BA98: sc
A99: =$D99&"_"&$F99&"_"&$L99 -> TSX:BTO_2024_ | B99: =$D99&"_"&$F99&"_"&$N99 -> TSX:BTO_2024_CEO | C99: =$D99&"_"&$F99&"_"&$M99 -> TSX:BTO_2024_ | D99: =D98 -> TSX:BTO | E99: =_xll.ciqfunctions.udf.CIQ(D99,"IQ_Company_Name") -> B2Gold Corp. | F99: =$G$10 -> 2024 | G99: =F99&"-01-01" -> 2024-01-01 | H99: =F99&"-12-31" -> 2024-12-31 | I99: =_xlfn.DAYS(H99,G99)/_xlfn.DAYS(F99&"-12-31",F99&"-01-01")*12 -> 12 | J99: USD | K99: =IF($J99="CAD",1,IF($J99="USD",VLOOKUP($F99,$G$9:$H$11,2,FALSE),"N/A")) -> 1.37017 | N99: =N98 -> CEO | O99: =O98 -> Director, President, & CEO | P99: =P98 -> Clive Johnson | Q99: 949000 | R99: =IFERROR(Q99*(12/$I99)*$K99,"-") -> 1300291.3 | T99: =IFERROR(IF((S99*$K99)=0,"-",(S99*$K99)),"-") -> - | U99: 469755 | V99: =IFERROR(U99*(12/$I99)*$K99,"-") -> 643644.21 | W99: =IFERROR($V99/$R99,"-") -> 0.495 | Y99: - | Z99: =IFERROR(IF(ISNUMBER($Y99)=TRUE, $Y99*$R99,$X99*$R99),"-") -> 0 | AA99: =IFERROR(IF(SUM(R99,V99)=0,"-",SUM(R99,V99)),"-") -> 1943935.5 | AB99: =IFERROR(IF(SUM(R99,Z99)=0,"-",SUM(R99,Z99)),"-") -> 1300291.3 | AC99: =0.4*2555000 -> 1022000 | AD99: =0.6*2555000 -> 1533000 | AE99: - | AF99: - | AG99: - | AH99: =IFERROR(IF(SUM(AC99:AG99)=0,IF(COUNTIF($AC99:$AG99,"=0")>0,"$0","-"),SUM(AC99:AG99)),"-") -> 2555000 | AI99: =IFERROR($AM99/$R99,"-") -> 2.6923077 | AK99: - | AL99: =IFERROR(IF(ISNUMBER($AK99)=TRUE, $AK99*$R99, $AJ99*$R99), "-") -> 0 | AM99: =IFERROR($AH99*$K99,"-") -> 3500784.4 | AN99: =IFERROR(IF(SUM(AA99,AM99)=0,"-",SUM(AA99,AM99)),"-") -> 5444719.9 | AO99: =IFERROR(IF(SUM($AB99,$AL99)=0,"-",SUM($AB99,$AL99)),"-") -> 1300291.3 | AP99: N/A | AQ99: N/A | AR99: =IFERROR(AP99*(12/$I99)*$K99,"-") -> - | AT99: =303652-162438-134262 -> 6952 | AU99: =IFERROR(AT99*(12/$I99)*$K99,"-") -> 9525.4218 | AW99: =IFERROR(IF(SUM(AN99,AR99,AU99)=0,"-",SUM(AN99,AR99,AU99)),"-") -> 5454245.3 | AX99: =IFERROR(IF(SUM(AO99,AR99,AU99)=0,"-",SUM(AO99,AR99,AU99)),"-") -> 1309816.8 | AY99: - | AZ99: KP | BA99: sc
A100: =$D100&"_"&$F100&"_"&$L100 -> TSX:BTO_2023_ | B100: =$D100&"_"&$F100&"_"&$N100 -> TSX:BTO_2023_CEO | C100: =$D100&"_"&$F100&"_"&$M100 -> TSX:BTO_2023_ | D100: =D99 -> TSX:BTO | E100: =_xll.ciqfunctions.udf.CIQ(D100,"IQ_Company_Name") -> B2Gold Corp. | F100: =$G$11 -> 2023 | G100: =F100&"-01-01" -> 2023-01-01 | H100: =F100&"-12-31" -> 2023-12-31 | I100: =_xlfn.DAYS(H100,G100)/_xlfn.DAYS(F100&"-12-31",F100&"-01-01")*12 -> 12 | J100: USD | K100: =IF($J100="CAD",1,IF($J100="USD",VLOOKUP($F100,$G$9:$H$11,2,FALSE),"N/A")) -> 1.34954 | N100: =N99 -> CEO | O100: =O99 -> Director, President, & CEO | P100: =P99 -> Clive Johnson | Q100: 949000 | R100: =IFERROR(Q100*(12/$I100)*$K100,"-") -> 1280713.5 | T100: =IFERROR(IF((S100*$K100)=0,"-",(S100*$K100)),"-") -> - | U100: 584000 | V100: =IFERROR(U100*(12/$I100)*$K100,"-") -> 788131.36 | W100: =IFERROR($V100/$R100,"-") -> 0.61538462 | Y100: - | Z100: =IFERROR(IF(ISNUMBER($Y100)=TRUE, $Y100*$R100,$X100*$R100),"-") -> 0 | AA100: =IFERROR(IF(SUM(R100,V100)=0,"-",SUM(R100,V100)),"-") -> 2068844.8 | AB100: =IFERROR(IF(SUM(R100,Z100)=0,"-",SUM(R100,Z100)),"-") -> 1280713.5 | AC100: =0.5*2555000 -> 1277500 | AD100: =0.5*2555000 -> 1277500 | AE100: - | AF100: - | AG100: - | AH100: =IFERROR(IF(SUM(AC100:AG100)=0,IF(COUNTIF($AC100:$AG100,"=0")>0,"$0","-"),SUM(AC100:AG100)),"-") -> 2555000 | AI100: =IFERROR($AM100/$R100,"-") -> 2.6923077 | AK100: - | AL100: =IFERROR(IF(ISNUMBER($AK100)=TRUE, $AK100*$R100, $AJ100*$R100), "-") -> 0 | AM100: =IFERROR($AH100*$K100,"-") -> 3448074.7 | AN100: =IFERROR(IF(SUM(AA100,AM100)=0,"-",SUM(AA100,AM100)),"-") -> 5516919.5 | AO100: =IFERROR(IF(SUM($AB100,$AL100)=0,"-",SUM($AB100,$AL100)),"-") -> 1280713.5 | AP100: N/A | AQ100: N/A | AR100: =IFERROR(AP100*(12/$I100)*$K100,"-") -> - | AT100: =510558-201179-302426 -> 6953 | AU100: =IFERROR(AT100*(12/$I100)*$K100,"-") -> 9383.3516 | AW100: =IFERROR(IF(SUM(AN100,AR100,AU100)=0,"-",SUM(AN100,AR100,AU100)),"-") -> 5526302.9 | AX100: =IFERROR(IF(SUM(AO100,AR100,AU100)=0,"-",SUM(AO100,AR100,AU100)),"-") -> 1290096.8 | AY100: - | AZ100: KP | BA100: sc
A101: =$D101&"_"&$F101&"_"&$L101 -> TSX:BTO_2025_ | B101: =$D101&"_"&$F101&"_"&$N101 -> TSX:BTO_2025_CFO | C101: =$D101&"_"&$F101&"_"&$M101 -> TSX:BTO_2025_2nd Highest | D101: =D100 -> TSX:BTO | E101: =_xll.ciqfunctions.udf.CIQ(D101,"IQ_Company_Name") -> B2Gold Corp. | F101: =F98 -> 2025 | G101: =F101&"-01-01" -> 2025-01-01 | H101: =F101&"-12-31" -> 2025-12-31 | I101: =_xlfn.DAYS(H101,G101)/_xlfn.DAYS(F101&"-12-31",F101&"-01-01")*12 -> 12 | J101: USD | K101: =IF($J101="CAD",1,IF($J101="USD",VLOOKUP($F101,$G$9:$H$11,2,FALSE),"N/A")) -> 1.39745 | M101: 2nd Highest | N101: CFO | O101: Senior VP Finance & CFO | P101: Michael Cinnamond | Q101: 474500 | R101: =IFERROR(Q101*(12/$I101)*$K101,"-") -> 663090.03 | T101: =IFERROR(IF((S101*$K101)=0,"-",(S101*$K101)),"-") -> - | U101: 379007 | V101: =IFERROR(U101*(12/$I101)*$K101,"-") -> 529643.33 | W101: =IFERROR($V101/$R101,"-") -> 0.79875026 | X101: =IFERROR(AVERAGE(W101:W103),"N/A") -> 0.68125044 | Y101: 0.75 | Z101: =IFERROR(IF(ISNUMBER($Y101)=TRUE, $Y101*$R101,$X101*$R101),"-") -> 497317.52 | AA101: =IFERROR(IF(SUM(R101,V101)=0,"-",SUM(R101,V101)),"-") -> 1192733.4 | AB101: =IFERROR(IF(SUM(R101,Z101)=0,"-",SUM(R101,Z101)),"-") -> 1160407.5 | AC101: =0.5*1547418 -> 773709 | AD101: =0.5*1547418 -> 773709 | AE101: - | AF101: - | AG101: - | AH101: =IFERROR(IF(SUM(AC101:AG101)=0,IF(COUNTIF($AC101:$AG101,"=0")>0,"$0","-"),SUM(AC101:AG101)),"-") -> 1547418 | AI101: =IFERROR($AM101/$R101,"-") -> 3.2611549 | AJ101: =IFERROR(AVERAGE(AI101:AI103),"N/A") -> 2.8819234 | AK101: - | AL101: =IFERROR(IF(ISNUMBER($AK101)=TRUE, $AK101*$R101, $AJ101*$R101), "-") -> 1910974.7 | AM101: =IFERROR($AH101*$K101,"-") -> 2162439.3 | AN101: =IFERROR(IF(SUM(AA101,AM101)=0,"-",SUM(AA101,AM101)),"-") -> 3355172.6 | AO101: =IFERROR(IF(SUM($AB101,$AL101)=0,"-",SUM($AB101,$AL101)),"-") -> 3071382.2 | AP101: N/A | AQ101: N/A | AR101: =IFERROR(AP101*(12/$I101)*$K101,"-") -> - | AS101: =IFERROR(AVERAGE(AR101:AR103),"N/A") -> N/A | AT101: =59018-53787 -> 5231 | AU101: =IFERROR(AT101*(12/$I101)*$K101,"-") -> 7310.061 | AV101: =IFERROR(AVERAGE(AU101:AU103),"N/A") -> 8739.6115 | AW101: =IFERROR(IF(SUM(AN101,AR101,AU101)=0,"-",SUM(AN101,AR101,AU101)),"-") -> 3362482.7 | AX101: =IFERROR(IF(SUM(AO101,AR101,AU101)=0,"-",SUM(AO101,AR101,AU101)),"-") -> 3078692.3 | AY101: - | AZ101: KP | BA101: sc
A102: =$D102&"_"&$F102&"_"&$L102 -> TSX:BTO_2024_ | B102: =$D102&"_"&$F102&"_"&$N102 -> TSX:BTO_2024_CFO | C102: =$D102&"_"&$F102&"_"&$M102 -> TSX:BTO_2024_ | D102: =D101 -> TSX:BTO | E102: =_xll.ciqfunctions.udf.CIQ(D102,"IQ_Company_Name") -> B2Gold Corp. | F102: =F99 -> 2024 | G102: =F102&"-01-01" -> 2024-01-01 | H102: =F102&"-12-31" -> 2024-12-31 | I102: =_xlfn.DAYS(H102,G102)/_xlfn.DAYS(F102&"-12-31",F102&"-01-01")*12 -> 12 | J102: USD | K102: =IF($J102="CAD",1,IF($J102="USD",VLOOKUP($F102,$G$9:$H$11,2,FALSE),"N/A")) -> 1.37017 | N102: =N101 -> CFO | O102: =O101 -> Senior VP Finance & CFO | P102: =P101 -> Michael Cinnamond | Q102: 474500 | R102: =IFERROR(Q102*(12/$I102)*$K102,"-") -> 650145.67 | S102: - | T102: =IFERROR(IF((S102*$K102)=0,"-",(S102*$K102)),"-") -> - | U102: 234878 | V102: =IFERROR(U102*(12/$I102)*$K102,"-") -> 321822.79 | W102: =IFERROR($V102/$R102,"-") -> 0.49500105 | Y102: - | Z102: =IFERROR(IF(ISNUMBER($Y102)=TRUE, $Y102*$R102,$X102*$R102),"-") -> 0 | AA102: =IFERROR(IF(SUM(R102,V102)=0,"-",SUM(R102,V102)),"-") -> 971968.45 | AB102: =IFERROR(IF(SUM(R102,Z102)=0,"-",SUM(R102,Z102)),"-") -> 650145.67 | AC102: =0.5*1277500 -> 638750 | AD102: =0.5*1277500 -> 638750 | AE102: - | AF102: - | AG102: - | AH102: =IFERROR(IF(SUM(AC102:AG102)=0,IF(COUNTIF($AC102:$AG102,"=0")>0,"$0","-"),SUM(AC102:AG102)),"-") -> 1277500 | AI102: =IFERROR($AM102/$R102,"-") -> 2.6923077 | AK102: - | AL102: =IFERROR(IF(ISNUMBER($AK102)=TRUE, $AK102*$R102, $AJ102*$R102), "-") -> 0 | AM102: =IFERROR($AH102*$K102,"-") -> 1750392.2 | AN102: =IFERROR(IF(SUM(AA102,AM102)=0,"-",SUM(AA102,AM102)),"-") -> 2722360.6 | AO102: =IFERROR(IF(SUM($AB102,$AL102)=0,"-",SUM($AB102,$AL102)),"-") -> 650145.67 | AP102: N/A | AQ102: N/A | AR102: =IFERROR(AP102*(12/$I102)*$K102,"-") -> - | AT102: =97563-50321-40290 -> 6952 | AU102: =IFERROR(AT102*(12/$I102)*$K102,"-") -> 9525.4218 | AW102: =IFERROR(IF(SUM(AN102,AR102,AU102)=0,"-",SUM(AN102,AR102,AU102)),"-") -> 2731886.1 | AX102: =IFERROR(IF(SUM(AO102,AR102,AU102)=0,"-",SUM(AO102,AR102,AU102)),"-") -> 659671.09 | AY102: - | AZ102: KP | BA102: sc
...

Sheet Master - Summary
A1: =TODAY() -> 46204
A2: CAD | B2: Position
B3: Year | C3: 2018
C4: Company | D4: Market Cap | E4: TEV | F4: Incumbent | G4: Position Title | H4: Annualized / Converted | I4: Annualized/ Converted | J4: Actual STI % | K4: 3 Year Average STIP % | L4: Target STI $ | M4: Target STI % | N4: Actual TCC | O4: Target TCC | P4: Total LTI (Converted) | Q4: Total LTI % | R4: 3 Year Average LTIP % | S4: Target LTI $ | T4: Target LTI % | U4: Actual (base + actual bonus + actual LTIP) | V4: Target (base + target bonus + Target LTIP) | X4: Cash | Y4: Equity
C5: =+C2& " Benchmarking - "&'Raw Data'!H5&" $000s" -> Benchmarking - CAD $000s
C6: Company | D6: Market Cap | E6: TEV | F6: Incumbent | G6: Title | H6: Base Salary | I6: STIP | L6: STIP | N6: Total Cash Compensation | P6: LTIP | S6: LTIP | U6: Total Direct Compensation | X6: Pay Mix
A7: Look-up | B7: Ticker | D7: Market Cap | E7: TEV | F7: Incumbent | G7: Title | H7: Base Salary | I7: Actual $ | J7: Actual % | K7: 3 Year Average STIP % | L7: Target $ | M7: Target % | N7: Actual $ | O7: Target $ | P7: Actual $ | Q7: Actual% | R7: 3 Year Average LTIP % | S7: Target $ | T7: Target % | U7: Actual $ | V7: Target $ | X7: Cash | Y7: Equity
A8: =$B8&"_"&$C$3&"_"&$C$2 -> TSX:T_2018_ | B8: TSX:T | C8: =IFERROR(INDEX(Raw_Data,MATCH($A8,Look_Up,0),MATCH(C$4,Component,0)),"-") -> - | D8: =_xll.ciqfunctions.udf.CIQ(B8, "IQ_MARKETCAP", $A$1,$A$2) -> #PEND | E8: =_xll.ciqfunctions.udf.CIQ($B8, "IQ_TEV", $A$1,$A$2) -> #PEND | F8: =IFERROR(INDEX(Raw_Data,MATCH($A8,Look_Up,0),MATCH(F$4,Component,0)),"-") -> - | G8: =IFERROR(INDEX(Raw_Data,MATCH($A8,Look_Up,0),MATCH(G$4,Component,0)),"-") -> - | H8: =IFERROR(INDEX(Raw_Data,MATCH($A8,Look_Up,0),MATCH(H$4,Component,0))/1000,"-") -> - | I8: =IFERROR(INDEX(Raw_Data,MATCH($A8,Look_Up,0),MATCH(I$4,Component,0))/1000,"-") -> - | J8: =IFERROR(INDEX(Raw_Data,MATCH($A8,Look_Up,0),MATCH(J$4,Component,0)),"-") -> - | K8: =IFERROR(INDEX(Raw_Data,MATCH($A8,Look_Up,0),MATCH(K$4,Component,0)),"-") -> - | L8: =IFERROR(INDEX(Raw_Data,MATCH($A8,Look_Up,0),MATCH(L$4,Component,0))/1000,"-") -> - | M8: =IFERROR(INDEX(Raw_Data,MATCH($A8,Look_Up,0),MATCH(M$4,Component,0)),"-") -> - | N8: =IFERROR(INDEX(Raw_Data,MATCH($A8,Look_Up,0),MATCH(N$4,Component,0))/1000,"-") -> - | O8: =IFERROR(INDEX(Raw_Data,MATCH($A8,Look_Up,0),MATCH(O$4,Component,0))/1000,"-") -> - | P8: =IFERROR(INDEX(Raw_Data,MATCH($A8,Look_Up,0),MATCH(P$4,Component,0))/1000,"-") -> - | Q8: =IFERROR(INDEX(Raw_Data,MATCH($A8,Look_Up,0),MATCH(Q$4,Component,0)),"-") -> - | R8: =IFERROR(INDEX(Raw_Data,MATCH($A8,Look_Up,0),MATCH(R$4,Component,0)),"-") -> - | S8: =IFERROR(INDEX(Raw_Data,MATCH($A8,Look_Up,0),MATCH(S$4,Component,0))/1000,"-") -> - | T8: =IFERROR(INDEX(Raw_Data,MATCH($A8,Look_Up,0),MATCH(T$4,Component,0)),"-") -> - | U8: =IFERROR(INDEX(Raw_Data,MATCH($A8,Look_Up,0),MATCH(U$4,Component,0))/1000,"-") -> - | V8: =IFERROR(INDEX(Raw_Data,MATCH($A8,Look_Up,0),MATCH(V$4,Component,0))/1000,"-") -> - | X8: =IFERROR(N8/U8,"-") -> - | Y8: =IFERROR(P8/U8,"-") -> -
A9: =$B9&"_"&$C$3&"_"&$C$2 -> TSX:S_2018_ | B9: TSX:S | C9: =IFERROR(INDEX(Raw_Data,MATCH($A9,Look_Up,0),MATCH(C$4,Component,0)),"-") -> - | D9: =_xll.ciqfunctions.udf.CIQ(B9, "IQ_MARKETCAP", $A$1,$A$2) -> #PEND | E9: =_xll.ciqfunctions.udf.CIQ($B9, "IQ_TEV", $A$1,$A$2) -> #PEND | F9: =IFERROR(INDEX(Raw_Data,MATCH($A9,Look_Up,0),MATCH(F$4,Component,0)),"-") -> - | G9: =IFERROR(INDEX(Raw_Data,MATCH($A9,Look_Up,0),MATCH(G$4,Component,0)),"-") -> - | H9: =IFERROR(INDEX(Raw_Data,MATCH($A9,Look_Up,0),MATCH(H$4,Component,0))/1000,"-") -> - | I9: =IFERROR(INDEX(Raw_Data,MATCH($A9,Look_Up,0),MATCH(I$4,Component,0))/1000,"-") -> - | J9: =IFERROR(INDEX(Raw_Data,MATCH($A9,Look_Up,0),MATCH(J$4,Component,0)),"-") -> - | K9: =IFERROR(INDEX(Raw_Data,MATCH($A9,Look_Up,0),MATCH(K$4,Component,0)),"-") -> - | L9: =IFERROR(INDEX(Raw_Data,MATCH($A9,Look_Up,0),MATCH(L$4,Component,0))/1000,"-") -> - | M9: =IFERROR(INDEX(Raw_Data,MATCH($A9,Look_Up,0),MATCH(M$4,Component,0)),"-") -> - | N9: =IFERROR(INDEX(Raw_Data,MATCH($A9,Look_Up,0),MATCH(N$4,Component,0))/1000,"-") -> - | O9: =IFERROR(INDEX(Raw_Data,MATCH($A9,Look_Up,0),MATCH(O$4,Component,0))/1000,"-") -> - | P9: =IFERROR(INDEX(Raw_Data,MATCH($A9,Look_Up,0),MATCH(P$4,Component,0))/1000,"-") -> - | Q9: =IFERROR(INDEX(Raw_Data,MATCH($A9,Look_Up,0),MATCH(Q$4,Component,0)),"-") -> - | R9: =IFERROR(INDEX(Raw_Data,MATCH($A9,Look_Up,0),MATCH(R$4,Component,0)),"-") -> - | S9: =IFERROR(INDEX(Raw_Data,MATCH($A9,Look_Up,0),MATCH(S$4,Component,0))/1000,"-") -> - | T9: =IFERROR(INDEX(Raw_Data,MATCH($A9,Look_Up,0),MATCH(T$4,Component,0)),"-") -> - | U9: =IFERROR(INDEX(Raw_Data,MATCH($A9,Look_Up,0),MATCH(U$4,Component,0))/1000,"-") -> - | V9: =IFERROR(INDEX(Raw_Data,MATCH($A9,Look_Up,0),MATCH(V$4,Component,0))/1000,"-") -> - | X9: =IFERROR(N9/U9,"-") -> - | Y9: =IFERROR(P9/U9,"-") -> -
A10: =$B10&"_"&$C$3&"_"&$C$2 -> TSX:R_2018_ | B10: TSX:R | C10: =IFERROR(INDEX(Raw_Data,MATCH($A10,Look_Up,0),MATCH(C$4,Component,0)),"-") -> - | D10: =_xll.ciqfunctions.udf.CIQ(B10, "IQ_MARKETCAP", $A$1,$A$2) -> #PEND | E10: =_xll.ciqfunctions.udf.CIQ($B10, "IQ_TEV", $A$1,$A$2) -> #PEND | F10: =IFERROR(INDEX(Raw_Data,MATCH($A10,Look_Up,0),MATCH(F$4,Component,0)),"-") -> - | G10: =IFERROR(INDEX(Raw_Data,MATCH($A10,Look_Up,0),MATCH(G$4,Component,0)),"-") -> - | H10: =IFERROR(INDEX(Raw_Data,MATCH($A10,Look_Up,0),MATCH(H$4,Component,0))/1000,"-") -> - | I10: =IFERROR(INDEX(Raw_Data,MATCH($A10,Look_Up,0),MATCH(I$4,Component,0))/1000,"-") -> - | J10: =IFERROR(INDEX(Raw_Data,MATCH($A10,Look_Up,0),MATCH(J$4,Component,0)),"-") -> - | K10: =IFERROR(INDEX(Raw_Data,MATCH($A10,Look_Up,0),MATCH(K$4,Component,0)),"-") -> - | L10: =IFERROR(INDEX(Raw_Data,MATCH($A10,Look_Up,0),MATCH(L$4,Component,0))/1000,"-") -> - | M10: =IFERROR(INDEX(Raw_Data,MATCH($A10,Look_Up,0),MATCH(M$4,Component,0)),"-") -> - | N10: =IFERROR(INDEX(Raw_Data,MATCH($A10,Look_Up,0),MATCH(N$4,Component,0))/1000,"-") -> - | O10: =IFERROR(INDEX(Raw_Data,MATCH($A10,Look_Up,0),MATCH(O$4,Component,0))/1000,"-") -> - | P10: =IFERROR(INDEX(Raw_Data,MATCH($A10,Look_Up,0),MATCH(P$4,Component,0))/1000,"-") -> - | Q10: =IFERROR(INDEX(Raw_Data,MATCH($A10,Look_Up,0),MATCH(Q$4,Component,0)),"-") -> - | R10: =IFERROR(INDEX(Raw_Data,MATCH($A10,Look_Up,0),MATCH(R$4,Component,0)),"-") -> - | S10: =IFERROR(INDEX(Raw_Data,MATCH($A10,Look_Up,0),MATCH(S$4,Component,0))/1000,"-") -> - | T10: =IFERROR(INDEX(Raw_Data,MATCH($A10,Look_Up,0),MATCH(T$4,Component,0)),"-") -> - | U10: =IFERROR(INDEX(Raw_Data,MATCH($A10,Look_Up,0),MATCH(U$4,Component,0))/1000,"-") -> - | V10: =IFERROR(INDEX(Raw_Data,MATCH($A10,Look_Up,0),MATCH(V$4,Component,0))/1000,"-") -> - | X10: =IFERROR(N10/U10,"-") -> - | Y10: =IFERROR(P10/U10,"-") -> -
A11: =$B11&"_"&$C$3&"_"&$C$2 -> TSX:Q_2018_ | B11: TSX:Q | C11: =IFERROR(INDEX(Raw_Data,MATCH($A11,Look_Up,0),MATCH(C$4,Component,0)),"-") -> - | D11: =_xll.ciqfunctions.udf.CIQ(B11, "IQ_MARKETCAP", $A$1,$A$2) -> #PEND | E11: =_xll.ciqfunctions.udf.CIQ($B11, "IQ_TEV", $A$1,$A$2) -> #PEND | F11: =IFERROR(INDEX(Raw_Data,MATCH($A11,Look_Up,0),MATCH(F$4,Component,0)),"-") -> - | G11: =IFERROR(INDEX(Raw_Data,MATCH($A11,Look_Up,0),MATCH(G$4,Component,0)),"-") -> - | H11: =IFERROR(INDEX(Raw_Data,MATCH($A11,Look_Up,0),MATCH(H$4,Component,0))/1000,"-") -> - | I11: =IFERROR(INDEX(Raw_Data,MATCH($A11,Look_Up,0),MATCH(I$4,Component,0))/1000,"-") -> - | J11: =IFERROR(INDEX(Raw_Data,MATCH($A11,Look_Up,0),MATCH(J$4,Component,0)),"-") -> - | K11: =IFERROR(INDEX(Raw_Data,MATCH($A11,Look_Up,0),MATCH(K$4,Component,0)),"-") -> - | L11: =IFERROR(INDEX(Raw_Data,MATCH($A11,Look_Up,0),MATCH(L$4,Component,0))/1000,"-") -> - | M11: =IFERROR(INDEX(Raw_Data,MATCH($A11,Look_Up,0),MATCH(M$4,Component,0)),"-") -> - | N11: =IFERROR(INDEX(Raw_Data,MATCH($A11,Look_Up,0),MATCH(N$4,Component,0))/1000,"-") -> - | O11: =IFERROR(INDEX(Raw_Data,MATCH($A11,Look_Up,0),MATCH(O$4,Component,0))/1000,"-") -> - | P11: =IFERROR(INDEX(Raw_Data,MATCH($A11,Look_Up,0),MATCH(P$4,Component,0))/1000,"-") -> - | Q11: =IFERROR(INDEX(Raw_Data,MATCH($A11,Look_Up,0),MATCH(Q$4,Component,0)),"-") -> - | R11: =IFERROR(INDEX(Raw_Data,MATCH($A11,Look_Up,0),MATCH(R$4,Component,0)),"-") -> - | S11: =IFERROR(INDEX(Raw_Data,MATCH($A11,Look_Up,0),MATCH(S$4,Component,0))/1000,"-") -> - | T11: =IFERROR(INDEX(Raw_Data,MATCH($A11,Look_Up,0),MATCH(T$4,Component,0)),"-") -> - | U11: =IFERROR(INDEX(Raw_Data,MATCH($A11,Look_Up,0),MATCH(U$4,Component,0))/1000,"-") -> - | V11: =IFERROR(INDEX(Raw_Data,MATCH($A11,Look_Up,0),MATCH(V$4,Component,0))/1000,"-") -> - | X11: =IFERROR(N11/U11,"-") -> - | Y11: =IFERROR(P11/U11,"-") -> -
A12: =$B12&"_"&$C$3&"_"&$C$2 -> TSX:P_2018_ | B12: TSX:P | C12: =IFERROR(INDEX(Raw_Data,MATCH($A12,Look_Up,0),MATCH(C$4,Component,0)),"-") -> - | D12: =_xll.ciqfunctions.udf.CIQ(B12, "IQ_MARKETCAP", $A$1,$A$2) -> #PEND | E12: =_xll.ciqfunctions.udf.CIQ($B12, "IQ_TEV", $A$1,$A$2) -> #PEND | F12: =IFERROR(INDEX(Raw_Data,MATCH($A12,Look_Up,0),MATCH(F$4,Component,0)),"-") -> - | G12: =IFERROR(INDEX(Raw_Data,MATCH($A12,Look_Up,0),MATCH(G$4,Component,0)),"-") -> - | H12: =IFERROR(INDEX(Raw_Data,MATCH($A12,Look_Up,0),MATCH(H$4,Component,0))/1000,"-") -> - | I12: =IFERROR(INDEX(Raw_Data,MATCH($A12,Look_Up,0),MATCH(I$4,Component,0))/1000,"-") -> - | J12: =IFERROR(INDEX(Raw_Data,MATCH($A12,Look_Up,0),MATCH(J$4,Component,0)),"-") -> - | K12: =IFERROR(INDEX(Raw_Data,MATCH($A12,Look_Up,0),MATCH(K$4,Component,0)),"-") -> - | L12: =IFERROR(INDEX(Raw_Data,MATCH($A12,Look_Up,0),MATCH(L$4,Component,0))/1000,"-") -> - | M12: =IFERROR(INDEX(Raw_Data,MATCH($A12,Look_Up,0),MATCH(M$4,Component,0)),"-") -> - | N12: =IFERROR(INDEX(Raw_Data,MATCH($A12,Look_Up,0),MATCH(N$4,Component,0))/1000,"-") -> - | O12: =IFERROR(INDEX(Raw_Data,MATCH($A12,Look_Up,0),MATCH(O$4,Component,0))/1000,"-") -> - | P12: =IFERROR(INDEX(Raw_Data,MATCH($A12,Look_Up,0),MATCH(P$4,Component,0))/1000,"-") -> - | Q12: =IFERROR(INDEX(Raw_Data,MATCH($A12,Look_Up,0),MATCH(Q$4,Component,0)),"-") -> - | R12: =IFERROR(INDEX(Raw_Data,MATCH($A12,Look_Up,0),MATCH(R$4,Component,0)),"-") -> - | S12: =IFERROR(INDEX(Raw_Data,MATCH($A12,Look_Up,0),MATCH(S$4,Component,0))/1000,"-") -> - | T12: =IFERROR(INDEX(Raw_Data,MATCH($A12,Look_Up,0),MATCH(T$4,Component,0)),"-") -> - | U12: =IFERROR(INDEX(Raw_Data,MATCH($A12,Look_Up,0),MATCH(U$4,Component,0))/1000,"-") -> - | V12: =IFERROR(INDEX(Raw_Data,MATCH($A12,Look_Up,0),MATCH(V$4,Component,0))/1000,"-") -> - | X12: =IFERROR(N12/U12,"-") -> - | Y12: =IFERROR(P12/U12,"-") -> -
A13: =$B13&"_"&$C$3&"_"&$C$2 -> TSX:O_2018_ | B13: TSX:O | C13: =IFERROR(INDEX(Raw_Data,MATCH($A13,Look_Up,0),MATCH(C$4,Component,0)),"-") -> - | D13: =_xll.ciqfunctions.udf.CIQ(B13, "IQ_MARKETCAP", $A$1,$A$2) -> #PEND | E13: =_xll.ciqfunctions.udf.CIQ($B13, "IQ_TEV", $A$1,$A$2) -> #PEND | F13: =IFERROR(INDEX(Raw_Data,MATCH($A13,Look_Up,0),MATCH(F$4,Component,0)),"-") -> - | G13: =IFERROR(INDEX(Raw_Data,MATCH($A13,Look_Up,0),MATCH(G$4,Component,0)),"-") -> - | H13: =IFERROR(INDEX(Raw_Data,MATCH($A13,Look_Up,0),MATCH(H$4,Component,0))/1000,"-") -> - | I13: =IFERROR(INDEX(Raw_Data,MATCH($A13,Look_Up,0),MATCH(I$4,Component,0))/1000,"-") -> - | J13: =IFERROR(INDEX(Raw_Data,MATCH($A13,Look_Up,0),MATCH(J$4,Component,0)),"-") -> - | K13: =IFERROR(INDEX(Raw_Data,MATCH($A13,Look_Up,0),MATCH(K$4,Component,0)),"-") -> - | L13: =IFERROR(INDEX(Raw_Data,MATCH($A13,Look_Up,0),MATCH(L$4,Component,0))/1000,"-") -> - | M13: =IFERROR(INDEX(Raw_Data,MATCH($A13,Look_Up,0),MATCH(M$4,Component,0)),"-") -> - | N13: =IFERROR(INDEX(Raw_Data,MATCH($A13,Look_Up,0),MATCH(N$4,Component,0))/1000,"-") -> - | O13: =IFERROR(INDEX(Raw_Data,MATCH($A13,Look_Up,0),MATCH(O$4,Component,0))/1000,"-") -> - | P13: =IFERROR(INDEX(Raw_Data,MATCH($A13,Look_Up,0),MATCH(P$4,Component,0))/1000,"-") -> - | Q13: =IFERROR(INDEX(Raw_Data,MATCH($A13,Look_Up,0),MATCH(Q$4,Component,0)),"-") -> - | R13: =IFERROR(INDEX(Raw_Data,MATCH($A13,Look_Up,0),MATCH(R$4,Component,0)),"-") -> - | S13: =IFERROR(INDEX(Raw_Data,MATCH($A13,Look_Up,0),MATCH(S$4,Component,0))/1000,"-") -> - | T13: =IFERROR(INDEX(Raw_Data,MATCH($A13,Look_Up,0),MATCH(T$4,Component,0)),"-") -> - | U13: =IFERROR(INDEX(Raw_Data,MATCH($A13,Look_Up,0),MATCH(U$4,Component,0))/1000,"-") -> - | V13: =IFERROR(INDEX(Raw_Data,MATCH($A13,Look_Up,0),MATCH(V$4,Component,0))/1000,"-") -> - | X13: =IFERROR(N13/U13,"-") -> - | Y13: =IFERROR(P13/U13,"-") -> -
A14: =$B14&"_"&$C$3&"_"&$C$2 -> TSX:N_2018_ | B14: TSX:N | C14: =IFERROR(INDEX(Raw_Data,MATCH($A14,Look_Up,0),MATCH(C$4,Component,0)),"-") -> - | D14: =_xll.ciqfunctions.udf.CIQ(B14, "IQ_MARKETCAP", $A$1,$A$2) -> #PEND | E14: =_xll.ciqfunctions.udf.CIQ($B14, "IQ_TEV", $A$1,$A$2) -> #PEND | F14: =IFERROR(INDEX(Raw_Data,MATCH($A14,Look_Up,0),MATCH(F$4,Component,0)),"-") -> - | G14: =IFERROR(INDEX(Raw_Data,MATCH($A14,Look_Up,0),MATCH(G$4,Component,0)),"-") -> - | H14: =IFERROR(INDEX(Raw_Data,MATCH($A14,Look_Up,0),MATCH(H$4,Component,0))/1000,"-") -> - | I14: =IFERROR(INDEX(Raw_Data,MATCH($A14,Look_Up,0),MATCH(I$4,Component,0))/1000,"-") -> - | J14: =IFERROR(INDEX(Raw_Data,MATCH($A14,Look_Up,0),MATCH(J$4,Component,0)),"-") -> - | K14: =IFERROR(INDEX(Raw_Data,MATCH($A14,Look_Up,0),MATCH(K$4,Component,0)),"-") -> - | L14: =IFERROR(INDEX(Raw_Data,MATCH($A14,Look_Up,0),MATCH(L$4,Component,0))/1000,"-") -> - | M14: =IFERROR(INDEX(Raw_Data,MATCH($A14,Look_Up,0),MATCH(M$4,Component,0)),"-") -> - | N14: =IFERROR(INDEX(Raw_Data,MATCH($A14,Look_Up,0),MATCH(N$4,Component,0))/1000,"-") -> - | O14: =IFERROR(INDEX(Raw_Data,MATCH($A14,Look_Up,0),MATCH(O$4,Component,0))/1000,"-") -> - | P14: =IFERROR(INDEX(Raw_Data,MATCH($A14,Look_Up,0),MATCH(P$4,Component,0))/1000,"-") -> - | Q14: =IFERROR(INDEX(Raw_Data,MATCH($A14,Look_Up,0),MATCH(Q$4,Component,0)),"-") -> - | R14: =IFERROR(INDEX(Raw_Data,MATCH($A14,Look_Up,0),MATCH(R$4,Component,0)),"-") -> - | S14: =IFERROR(INDEX(Raw_Data,MATCH($A14,Look_Up,0),MATCH(S$4,Component,0))/1000,"-") -> - | T14: =IFERROR(INDEX(Raw_Data,MATCH($A14,Look_Up,0),MATCH(T$4,Component,0)),"-") -> - | U14: =IFERROR(INDEX(Raw_Data,MATCH($A14,Look_Up,0),MATCH(U$4,Component,0))/1000,"-") -> - | V14: =IFERROR(INDEX(Raw_Data,MATCH($A14,Look_Up,0),MATCH(V$4,Component,0))/1000,"-") -> - | X14: =IFERROR(N14/U14,"-") -> - | Y14: =IFERROR(P14/U14,"-") -> -
A15: =$B15&"_"&$C$3&"_"&$C$2 -> TSX:M_2018_ | B15: TSX:M | C15: =IFERROR(INDEX(Raw_Data,MATCH($A15,Look_Up,0),MATCH(C$4,Component,0)),"-") -> - | D15: =_xll.ciqfunctions.udf.CIQ(B15, "IQ_MARKETCAP", $A$1,$A$2) -> #PEND | E15: =_xll.ciqfunctions.udf.CIQ($B15, "IQ_TEV", $A$1,$A$2) -> #PEND | F15: =IFERROR(INDEX(Raw_Data,MATCH($A15,Look_Up,0),MATCH(F$4,Component,0)),"-") -> - | G15: =IFERROR(INDEX(Raw_Data,MATCH($A15,Look_Up,0),MATCH(G$4,Component,0)),"-") -> - | H15: =IFERROR(INDEX(Raw_Data,MATCH($A15,Look_Up,0),MATCH(H$4,Component,0))/1000,"-") -> - | I15: =IFERROR(INDEX(Raw_Data,MATCH($A15,Look_Up,0),MATCH(I$4,Component,0))/1000,"-") -> - | J15: =IFERROR(INDEX(Raw_Data,MATCH($A15,Look_Up,0),MATCH(J$4,Component,0)),"-") -> - | K15: =IFERROR(INDEX(Raw_Data,MATCH($A15,Look_Up,0),MATCH(K$4,Component,0)),"-") -> - | L15: =IFERROR(INDEX(Raw_Data,MATCH($A15,Look_Up,0),MATCH(L$4,Component,0))/1000,"-") -> - | M15: =IFERROR(INDEX(Raw_Data,MATCH($A15,Look_Up,0),MATCH(M$4,Component,0)),"-") -> - | N15: =IFERROR(INDEX(Raw_Data,MATCH($A15,Look_Up,0),MATCH(N$4,Component,0))/1000,"-") -> - | O15: =IFERROR(INDEX(Raw_Data,MATCH($A15,Look_Up,0),MATCH(O$4,Component,0))/1000,"-") -> - | P15: =IFERROR(INDEX(Raw_Data,MATCH($A15,Look_Up,0),MATCH(P$4,Component,0))/1000,"-") -> - | Q15: =IFERROR(INDEX(Raw_Data,MATCH($A15,Look_Up,0),MATCH(Q$4,Component,0)),"-") -> - | R15: =IFERROR(INDEX(Raw_Data,MATCH($A15,Look_Up,0),MATCH(R$4,Component,0)),"-") -> - | S15: =IFERROR(INDEX(Raw_Data,MATCH($A15,Look_Up,0),MATCH(S$4,Component,0))/1000,"-") -> - | T15: =IFERROR(INDEX(Raw_Data,MATCH($A15,Look_Up,0),MATCH(T$4,Component,0)),"-") -> - | U15: =IFERROR(INDEX(Raw_Data,MATCH($A15,Look_Up,0),MATCH(U$4,Component,0))/1000,"-") -> - | V15: =IFERROR(INDEX(Raw_Data,MATCH($A15,Look_Up,0),MATCH(V$4,Component,0))/1000,"-") -> - | X15: =IFERROR(N15/U15,"-") -> - | Y15: =IFERROR(P15/U15,"-") -> -
A16: =$B16&"_"&$C$3&"_"&$C$2 -> TSX:L_2018_ | B16: TSX:L | C16: =IFERROR(INDEX(Raw_Data,MATCH($A16,Look_Up,0),MATCH(C$4,Component,0)),"-") -> - | D16: =_xll.ciqfunctions.udf.CIQ(B16, "IQ_MARKETCAP", $A$1,$A$2) -> #PEND | E16: =_xll.ciqfunctions.udf.CIQ($B16, "IQ_TEV", $A$1,$A$2) -> #PEND | F16: =IFERROR(INDEX(Raw_Data,MATCH($A16,Look_Up,0),MATCH(F$4,Component,0)),"-") -> - | G16: =IFERROR(INDEX(Raw_Data,MATCH($A16,Look_Up,0),MATCH(G$4,Component,0)),"-") -> - | H16: =IFERROR(INDEX(Raw_Data,MATCH($A16,Look_Up,0),MATCH(H$4,Component,0))/1000,"-") -> - | I16: =IFERROR(INDEX(Raw_Data,MATCH($A16,Look_Up,0),MATCH(I$4,Component,0))/1000,"-") -> - | J16: =IFERROR(INDEX(Raw_Data,MATCH($A16,Look_Up,0),MATCH(J$4,Component,0)),"-") -> - | K16: =IFERROR(INDEX(Raw_Data,MATCH($A16,Look_Up,0),MATCH(K$4,Component,0)),"-") -> - | L16: =IFERROR(INDEX(Raw_Data,MATCH($A16,Look_Up,0),MATCH(L$4,Component,0))/1000,"-") -> - | M16: =IFERROR(INDEX(Raw_Data,MATCH($A16,Look_Up,0),MATCH(M$4,Component,0)),"-") -> - | N16: =IFERROR(INDEX(Raw_Data,MATCH($A16,Look_Up,0),MATCH(N$4,Component,0))/1000,"-") -> - | O16: =IFERROR(INDEX(Raw_Data,MATCH($A16,Look_Up,0),MATCH(O$4,Component,0))/1000,"-") -> - | P16: =IFERROR(INDEX(Raw_Data,MATCH($A16,Look_Up,0),MATCH(P$4,Component,0))/1000,"-") -> - | Q16: =IFERROR(INDEX(Raw_Data,MATCH($A16,Look_Up,0),MATCH(Q$4,Component,0)),"-") -> - | R16: =IFERROR(INDEX(Raw_Data,MATCH($A16,Look_Up,0),MATCH(R$4,Component,0)),"-") -> - | S16: =IFERROR(INDEX(Raw_Data,MATCH($A16,Look_Up,0),MATCH(S$4,Component,0))/1000,"-") -> - | T16: =IFERROR(INDEX(Raw_Data,MATCH($A16,Look_Up,0),MATCH(T$4,Component,0)),"-") -> - | U16: =IFERROR(INDEX(Raw_Data,MATCH($A16,Look_Up,0),MATCH(U$4,Component,0))/1000,"-") -> - | V16: =IFERROR(INDEX(Raw_Data,MATCH($A16,Look_Up,0),MATCH(V$4,Component,0))/1000,"-") -> - | X16: =IFERROR(N16/U16,"-") -> - | Y16: =IFERROR(P16/U16,"-") -> -
A17: =$B17&"_"&$C$3&"_"&$C$2 -> TSX:K_2018_ | B17: TSX:K | C17: =IFERROR(INDEX(Raw_Data,MATCH($A17,Look_Up,0),MATCH(C$4,Component,0)),"-") -> - | D17: =_xll.ciqfunctions.udf.CIQ(B17, "IQ_MARKETCAP", $A$1,$A$2) -> #PEND | E17: =_xll.ciqfunctions.udf.CIQ($B17, "IQ_TEV", $A$1,$A$2) -> #PEND | F17: =IFERROR(INDEX(Raw_Data,MATCH($A17,Look_Up,0),MATCH(F$4,Component,0)),"-") -> - | G17: =IFERROR(INDEX(Raw_Data,MATCH($A17,Look_Up,0),MATCH(G$4,Component,0)),"-") -> - | H17: =IFERROR(INDEX(Raw_Data,MATCH($A17,Look_Up,0),MATCH(H$4,Component,0))/1000,"-") -> - | I17: =IFERROR(INDEX(Raw_Data,MATCH($A17,Look_Up,0),MATCH(I$4,Component,0))/1000,"-") -> - | J17: =IFERROR(INDEX(Raw_Data,MATCH($A17,Look_Up,0),MATCH(J$4,Component,0)),"-") -> - | K17: =IFERROR(INDEX(Raw_Data,MATCH($A17,Look_Up,0),MATCH(K$4,Component,0)),"-") -> - | L17: =IFERROR(INDEX(Raw_Data,MATCH($A17,Look_Up,0),MATCH(L$4,Component,0))/1000,"-") -> - | M17: =IFERROR(INDEX(Raw_Data,MATCH($A17,Look_Up,0),MATCH(M$4,Component,0)),"-") -> - | N17: =IFERROR(INDEX(Raw_Data,MATCH($A17,Look_Up,0),MATCH(N$4,Component,0))/1000,"-") -> - | O17: =IFERROR(INDEX(Raw_Data,MATCH($A17,Look_Up,0),MATCH(O$4,Component,0))/1000,"-") -> - | P17: =IFERROR(INDEX(Raw_Data,MATCH($A17,Look_Up,0),MATCH(P$4,Component,0))/1000,"-") -> - | Q17: =IFERROR(INDEX(Raw_Data,MATCH($A17,Look_Up,0),MATCH(Q$4,Component,0)),"-") -> - | R17: =IFERROR(INDEX(Raw_Data,MATCH($A17,Look_Up,0),MATCH(R$4,Component,0)),"-") -> - | S17: =IFERROR(INDEX(Raw_Data,MATCH($A17,Look_Up,0),MATCH(S$4,Component,0))/1000,"-") -> - | T17: =IFERROR(INDEX(Raw_Data,MATCH($A17,Look_Up,0),MATCH(T$4,Component,0)),"-") -> - | U17: =IFERROR(INDEX(Raw_Data,MATCH($A17,Look_Up,0),MATCH(U$4,Component,0))/1000,"-") -> - | V17: =IFERROR(INDEX(Raw_Data,MATCH($A17,Look_Up,0),MATCH(V$4,Component,0))/1000,"-") -> - | X17: =IFERROR(N17/U17,"-") -> - | Y17: =IFERROR(P17/U17,"-") -> -
A18: =$B18&"_"&$C$3&"_"&$C$2 -> TSX:J_2018_ | B18: TSX:J | C18: =IFERROR(INDEX(Raw_Data,MATCH($A18,Look_Up,0),MATCH(C$4,Component,0)),"-") -> - | D18: =_xll.ciqfunctions.udf.CIQ(B18, "IQ_MARKETCAP", $A$1,$A$2) -> #PEND | E18: =_xll.ciqfunctions.udf.CIQ($B18, "IQ_TEV", $A$1,$A$2) -> #PEND | F18: =IFERROR(INDEX(Raw_Data,MATCH($A18,Look_Up,0),MATCH(F$4,Component,0)),"-") -> - | G18: =IFERROR(INDEX(Raw_Data,MATCH($A18,Look_Up,0),MATCH(G$4,Component,0)),"-") -> - | H18: =IFERROR(INDEX(Raw_Data,MATCH($A18,Look_Up,0),MATCH(H$4,Component,0))/1000,"-") -> - | I18: =IFERROR(INDEX(Raw_Data,MATCH($A18,Look_Up,0),MATCH(I$4,Component,0))/1000,"-") -> - | J18: =IFERROR(INDEX(Raw_Data,MATCH($A18,Look_Up,0),MATCH(J$4,Component,0)),"-") -> - | K18: =IFERROR(INDEX(Raw_Data,MATCH($A18,Look_Up,0),MATCH(K$4,Component,0)),"-") -> - | L18: =IFERROR(INDEX(Raw_Data,MATCH($A18,Look_Up,0),MATCH(L$4,Component,0))/1000,"-") -> - | M18: =IFERROR(INDEX(Raw_Data,MATCH($A18,Look_Up,0),MATCH(M$4,Component,0)),"-") -> - | N18: =IFERROR(INDEX(Raw_Data,MATCH($A18,Look_Up,0),MATCH(N$4,Component,0))/1000,"-") -> - | O18: =IFERROR(INDEX(Raw_Data,MATCH($A18,Look_Up,0),MATCH(O$4,Component,0))/1000,"-") -> - | P18: =IFERROR(INDEX(Raw_Data,MATCH($A18,Look_Up,0),MATCH(P$4,Component,0))/1000,"-") -> - | Q18: =IFERROR(INDEX(Raw_Data,MATCH($A18,Look_Up,0),MATCH(Q$4,Component,0)),"-") -> - | R18: =IFERROR(INDEX(Raw_Data,MATCH($A18,Look_Up,0),MATCH(R$4,Component,0)),"-") -> - | S18: =IFERROR(INDEX(Raw_Data,MATCH($A18,Look_Up,0),MATCH(S$4,Component,0))/1000,"-") -> - | T18: =IFERROR(INDEX(Raw_Data,MATCH($A18,Look_Up,0),MATCH(T$4,Component,0)),"-") -> - | U18: =IFERROR(INDEX(Raw_Data,MATCH($A18,Look_Up,0),MATCH(U$4,Component,0))/1000,"-") -> - | V18: =IFERROR(INDEX(Raw_Data,MATCH($A18,Look_Up,0),MATCH(V$4,Component,0))/1000,"-") -> - | X18: =IFERROR(N18/U18,"-") -> - | Y18: =IFERROR(P18/U18,"-") -> -
A19: =$B19&"_"&$C$3&"_"&$C$2 -> TSX:I_2018_ | B19: TSX:I | C19: =IFERROR(INDEX(Raw_Data,MATCH($A19,Look_Up,0),MATCH(C$4,Component,0)),"-") -> - | D19: =_xll.ciqfunctions.udf.CIQ(B19, "IQ_MARKETCAP", $A$1,$A$2) -> #PEND | E19: =_xll.ciqfunctions.udf.CIQ($B19, "IQ_TEV", $A$1,$A$2) -> #PEND | F19: =IFERROR(INDEX(Raw_Data,MATCH($A19,Look_Up,0),MATCH(F$4,Component,0)),"-") -> - | G19: =IFERROR(INDEX(Raw_Data,MATCH($A19,Look_Up,0),MATCH(G$4,Component,0)),"-") -> - | H19: =IFERROR(INDEX(Raw_Data,MATCH($A19,Look_Up,0),MATCH(H$4,Component,0))/1000,"-") -> - | I19: =IFERROR(INDEX(Raw_Data,MATCH($A19,Look_Up,0),MATCH(I$4,Component,0))/1000,"-") -> - | J19: =IFERROR(INDEX(Raw_Data,MATCH($A19,Look_Up,0),MATCH(J$4,Component,0)),"-") -> - | K19: =IFERROR(INDEX(Raw_Data,MATCH($A19,Look_Up,0),MATCH(K$4,Component,0)),"-") -> - | L19: =IFERROR(INDEX(Raw_Data,MATCH($A19,Look_Up,0),MATCH(L$4,Component,0))/1000,"-") -> - | M19: =IFERROR(INDEX(Raw_Data,MATCH($A19,Look_Up,0),MATCH(M$4,Component,0)),"-") -> - | N19: =IFERROR(INDEX(Raw_Data,MATCH($A19,Look_Up,0),MATCH(N$4,Component,0))/1000,"-") -> - | O19: =IFERROR(INDEX(Raw_Data,MATCH($A19,Look_Up,0),MATCH(O$4,Component,0))/1000,"-") -> - | P19: =IFERROR(INDEX(Raw_Data,MATCH($A19,Look_Up,0),MATCH(P$4,Component,0))/1000,"-") -> - | Q19: =IFERROR(INDEX(Raw_Data,MATCH($A19,Look_Up,0),MATCH(Q$4,Component,0)),"-") -> - | R19: =IFERROR(INDEX(Raw_Data,MATCH($A19,Look_Up,0),MATCH(R$4,Component,0)),"-") -> - | S19: =IFERROR(INDEX(Raw_Data,MATCH($A19,Look_Up,0),MATCH(S$4,Component,0))/1000,"-") -> - | T19: =IFERROR(INDEX(Raw_Data,MATCH($A19,Look_Up,0),MATCH(T$4,Component,0)),"-") -> - | U19: =IFERROR(INDEX(Raw_Data,MATCH($A19,Look_Up,0),MATCH(U$4,Component,0))/1000,"-") -> - | V19: =IFERROR(INDEX(Raw_Data,MATCH($A19,Look_Up,0),MATCH(V$4,Component,0))/1000,"-") -> - | X19: =IFERROR(N19/U19,"-") -> - | Y19: =IFERROR(P19/U19,"-") -> -
... A27: =$B27&"_"&$C$3&"_"&$C$2 -> TSX:A_2018_ | B27: TSX:A | C27: =IFERROR(INDEX(Raw_Data,MATCH($A27,Look_Up,0),MATCH(C$4,Component,0)),"-") -> - | D27: =_xll.ciqfunctions.udf.CIQ(B27, "IQ_MARKETCAP", $A$1,$A$2) -> #PEND | E27: =_xll.ciqfunctions.udf.CIQ($B27, "IQ_TEV", $A$1,$A$2) -> #PEND | F27: =IFERROR(INDEX(Raw_Data,MATCH($A27,Look_Up,0),MATCH(F$4,Component,0)),"-") -> - | G27: =IFERROR(INDEX(Raw_Data,MATCH($A27,Look_Up,0),MATCH(G$4,Component,0)),"-") -> - | H27: =IFERROR(INDEX(Raw_Data,MATCH($A27,Look_Up,0),MATCH(H$4,Component,0))/1000,"-") -> - | I27: =IFERROR(INDEX(Raw_Data,MATCH($A27,Look_Up,0),MATCH(I$4,Component,0))/1000,"-") -> - | J27: =IFERROR(INDEX(Raw_Data,MATCH($A27,Look_Up,0),MATCH(J$4,Component,0)),"-") -> - | K27: =IFERROR(INDEX(Raw_Data,MATCH($A27,Look_Up,0),MATCH(K$4,Component,0)),"-") -> - | L27: =IFERROR(INDEX(Raw_Data,MATCH($A27,Look_Up,0),MATCH(L$4,Component,0))/1000,"-") -> - | M27: =IFERROR(INDEX(Raw_Data,MATCH($A27,Look_Up,0),MATCH(M$4,Component,0)),"-") -> - | N27: =IFERROR(INDEX(Raw_Data,MATCH($A27,Look_Up,0),MATCH(N$4,Component,0))/1000,"-") -> - | O27: =IFERROR(INDEX(Raw_Data,MATCH($A27,Look_Up,0),MATCH(O$4,Component,0))/1000,"-") -> - | P27: =IFERROR(INDEX(Raw_Data,MATCH($A27,Look_Up,0),MATCH(P$4,Component,0))/1000,"-") -> - | Q27: =IFERROR(INDEX(Raw_Data,MATCH($A27,Look_Up,0),MATCH(Q$4,Component,0)),"-") -> - | R27: =IFERROR(INDEX(Raw_Data,MATCH($A27,Look_Up,0),MATCH(R$4,Component,0)),"-") -> - | S27: =IFERROR(INDEX(Raw_Data,MATCH($A27,Look_Up,0),MATCH(S$4,Component,0))/1000,"-") -> - | T27: =IFERROR(INDEX(Raw_Data,MATCH($A27,Look_Up,0),MATCH(T$4,Component,0)),"-") -> - | U27: =IFERROR(INDEX(Raw_Data,MATCH($A27,Look_Up,0),MATCH(U$4,Component,0))/1000,"-") -> - | V27: =IFERROR(INDEX(Raw_Data,MATCH($A27,Look_Up,0),MATCH(V$4,Component,0))/1000,"-") -> - | X27: =IFERROR(N27/U27,"-") -> - | Y27: =IFERROR(P27/U27,"-") -> -
C28: Summary Statistics
B29: 0.75 | C29: 75th Percentile | D29: =PERCENTILE(D$8:D$27,$B29) -> #NUM! | E29: =PERCENTILE(E$8:E$27,$B29) -> #NUM! | H29: =PERCENTILE(H$8:H$27,$B29) -> #NUM! | I29: =PERCENTILE(I$8:I$27,$B29) -> #NUM! | J29: =PERCENTILE(J$8:J$27,$B29) -> #NUM! | K29: =PERCENTILE(K$8:K$27,$B29) -> #NUM! | L29: =PERCENTILE(L$8:L$27,$B29) -> #NUM! | M29: =PERCENTILE(M$8:M$27,$B29) -> #NUM! | N29: =PERCENTILE(N$8:N$27,$B29) -> #NUM! | O29: =PERCENTILE(O$8:O$27,$B29) -> #NUM! | ... V29: =PERCENTILE(V$8:V$27,$B29) -> #NUM! | X29: =PERCENTILE(X$8:X$27,$B29) -> #NUM! | Y29: =PERCENTILE(Y$8:Y$27,$B29) -> #NUM!
B30: 0.5 | C30: Median | D30: =PERCENTILE(D$8:D$27,$B30) -> #NUM! | E30: =PERCENTILE(E$8:E$27,$B30) -> #NUM! | H30: =PERCENTILE(H$8:H$27,$B30) -> #NUM! | I30: =PERCENTILE(I$8:I$27,$B30) -> #NUM! | J30: =PERCENTILE(J$8:J$27,$B30) -> #NUM! | K30: =PERCENTILE(K$8:K$27,$B30) -> #NUM! | L30: =PERCENTILE(L$8:L$27,$B30) -> #NUM! | M30: =PERCENTILE(M$8:M$27,$B30) -> #NUM! | N30: =PERCENTILE(N$8:N$27,$B30) -> #NUM! | O30: =PERCENTILE(O$8:O$27,$B30) -> #NUM! | ... V30: =PERCENTILE(V$8:V$27,$B30) -> #NUM! | X30: =PERCENTILE(X$8:X$27,$B30) -> #NUM! | Y30: =PERCENTILE(Y$8:Y$27,$B30) -> #NUM!
B31: 0.25 | C31: 25th Percentile | D31: =PERCENTILE(D$8:D$27,$B31) -> #NUM! | E31: =PERCENTILE(E$8:E$27,$B31) -> #NUM! | H31: =PERCENTILE(H$8:H$27,$B31) -> #NUM! | I31: =PERCENTILE(I$8:I$27,$B31) -> #NUM! | J31: =PERCENTILE(J$8:J$27,$B31) -> #NUM! | K31: =PERCENTILE(K$8:K$27,$B31) -> #NUM! | L31: =PERCENTILE(L$8:L$27,$B31) -> #NUM! | M31: =PERCENTILE(M$8:M$27,$B31) -> #NUM! | N31: =PERCENTILE(N$8:N$27,$B31) -> #NUM! | O31: =PERCENTILE(O$8:O$27,$B31) -> #NUM! | ... V31: =PERCENTILE(V$8:V$27,$B31) -> #NUM! | X31: =PERCENTILE(X$8:X$27,$B31) -> #NUM! | Y31: =PERCENTILE(Y$8:Y$27,$B31) -> #NUM!
C32: Average | D32: =AVERAGE(D8:D27) -> #DIV/0! | E32: =AVERAGE(E8:E27) -> #DIV/0! | H32: =AVERAGE(H8:H27) -> #DIV/0! | I32: =AVERAGE(I8:I27) -> #DIV/0! | J32: =AVERAGE(J8:J27) -> #DIV/0! | K32: =AVERAGE(K8:K27) -> #DIV/0! | L32: =AVERAGE(L8:L27) -> #DIV/0! | M32: =AVERAGE(M8:M27) -> #DIV/0! | N32: =AVERAGE(N8:N27) -> #DIV/0! | O32: =AVERAGE(O8:O27) -> #DIV/0! | ... V32: =AVERAGE(V8:V27) -> #DIV/0! | X32: =AVERAGE(X8:X27) -> #DIV/0! | Y32: =AVERAGE(Y8:Y27) -> #DIV/0!
A34: =$B34&"_"&$C$3&"_"&$C$2 -> TSX:RY_2018_ | B34: TSX:RY | C34: =IFERROR(INDEX(Raw_Data,MATCH($A34,Look_Up,0),MATCH(C$4,Component,0)),"-") -> - | D34: =_xll.ciqfunctions.udf.CIQ(B34, "IQ_MARKETCAP", $A$1,$A$2) -> #PEND | E34: =_xll.ciqfunctions.udf.CIQ($B34, "IQ_TEV", $A$1,$A$2) -> #PEND | F34: =IFERROR(INDEX(Raw_Data,MATCH($A34,Look_Up,0),MATCH(F$4,Component,0)),"-") -> - | G34: =IFERROR(INDEX(Raw_Data,MATCH($A34,Look_Up,0),MATCH(G$4,Component,0)),"-") -> - | H34: =IFERROR(INDEX(Raw_Data,MATCH($A34,Look_Up,0),MATCH(H$4,Component,0))/1000,"-") -> - | I34: =IFERROR(INDEX(Raw_Data,MATCH($A34,Look_Up,0),MATCH(I$4,Component,0))/1000,"-") -> - | J34: =IFERROR(INDEX(Raw_Data,MATCH($A34,Look_Up,0),MATCH(J$4,Component,0)),"-") -> - | K34: =IFERROR(INDEX(Raw_Data,MATCH($A34,Look_Up,0),MATCH(K$4,Component,0)),"-") -> - | L34: =IFERROR(INDEX(Raw_Data,MATCH($A34,Look_Up,0),MATCH(L$4,Component,0))/1000,"-") -> - | M34: =IFERROR(INDEX(Raw_Data,MATCH($A34,Look_Up,0),MATCH(M$4,Component,0)),"-") -> - | N34: =IFERROR(INDEX(Raw_Data,MATCH($A34,Look_Up,0),MATCH(N$4,Component,0))/1000,"-") -> - | O34: =IFERROR(INDEX(Raw_Data,MATCH($A34,Look_Up,0),MATCH(O$4,Component,0))/1000,"-") -> - | P34: =IFERROR(INDEX(Raw_Data,MATCH($A34,Look_Up,0),MATCH(P$4,Component,0))/1000,"-") -> - | Q34: =IFERROR(INDEX(Raw_Data,MATCH($A34,Look_Up,0),MATCH(Q$4,Component,0)),"-") -> - | R34: =IFERROR(INDEX(Raw_Data,MATCH($A34,Look_Up,0),MATCH(R$4,Component,0)),"-") -> - | S34: =IFERROR(INDEX(Raw_Data,MATCH($A34,Look_Up,0),MATCH(S$4,Component,0))/1000,"-") -> - | T34: =IFERROR(INDEX(Raw_Data,MATCH($A34,Look_Up,0),MATCH(T$4,Component,0)),"-") -> - | U34: =IFERROR(INDEX(Raw_Data,MATCH($A34,Look_Up,0),MATCH(U$4,Component,0))/1000,"-") -> - | V34: =IFERROR(INDEX(Raw_Data,MATCH($A34,Look_Up,0),MATCH(V$4,Component,0))/1000,"-") -> - | X34: =IFERROR(N34/U34,"-") -> - | Y34: =IFERROR(P34/U34,"-") -> -
C35: Percent Rank | D35: =IF(D$34>=MAX(D$8:D$27),"max",IF(D$34<=MIN(D$8:D$27),"min",PERCENTRANK(D$8:D$27,D$34))) -> max | E35: =IF(E$34>=MAX(E$8:E$27),"max",IF(E$34<=MIN(E$8:E$27),"min",PERCENTRANK(E$8:E$27,E$34))) -> max | H35: =IF(H$34>=MAX(H$8:H$27),"max",IF(H$34<=MIN(H$8:H$27),"min",PERCENTRANK(H$8:H$27,H$34))) -> max | I35: =IF(I$34>=MAX(I$8:I$27),"max",IF(I$34<=MIN(I$8:I$27),"min",PERCENTRANK(I$8:I$27,I$34))) -> max | J35: =IF(J$34>=MAX(J$8:J$27),"max",IF(J$34<=MIN(J$8:J$27),"min",PERCENTRANK(J$8:J$27,J$34))) -> max | K35: =IF(K$34>=MAX(K$8:K$27),"max",IF(K$34<=MIN(K$8:K$27),"min",PERCENTRANK(K$8:K$27,K$34))) -> max | L35: =IF(L$34>=MAX(L$8:L$27),"max",IF(L$34<=MIN(L$8:L$27),"min",PERCENTRANK(L$8:L$27,L$34))) -> max | M35: =IF(M$34>=MAX(M$8:M$27),"max",IF(M$34<=MIN(M$8:M$27),"min",PERCENTRANK(M$8:M$27,M$34))) -> max | N35: =IF(N$34>=MAX(N$8:N$27),"max",IF(N$34<=MIN(N$8:N$27),"min",PERCENTRANK(N$8:N$27,N$34))) -> max | O35: =IF(O$34>=MAX(O$8:O$27),"max",IF(O$34<=MIN(O$8:O$27),"min",PERCENTRANK(O$8:O$27,O$34))) -> max | ... V35: =IF(V$34>=MAX(V$8:V$27),"max",IF(V$34<=MIN(V$8:V$27),"min",PERCENTRANK(V$8:V$27,V$34))) -> max | X35: =IF(X$34>=MAX(X$8:X27),"max",IF(X$34<=MIN(X$8:X27),"min",PERCENTRANK(X$8:X27,X$34))) -> max | Y35: =IF(Y$34>=MAX(Y$8:Y27),"max",IF(Y$34<=MIN(Y$8:Y27),"min",PERCENTRANK(Y$8:Y27,Y$34))) -> max
C37: =+"Sources: "&C3&" proxy data" -> Sources: 2018 proxy data
C38: Incumbent Specific Notes:
C39: =IFERROR(INDEX(Raw_Data,MATCH(#REF!,Look_Up,0),MATCH(C$38,Component,0)),"N/A") -> N/A

Sheet Master - Charts
C3: Master - Summary | D3: Master - Summary | E3: Master - Summary
C4: Base Salary | D4: Target TCC | E4: Target TDC
B5: LINK DATA HERE
B6: 75th Percentile | C6: ='Master - Summary'!H29 -> #NUM! | D6: ='Master - Summary'!O29 -> #NUM! | E6: ='Master - Summary'!V29 -> #NUM!
B7: Median | C7: ='Master - Summary'!H30 -> #NUM! | D7: ='Master - Summary'!O30 -> #NUM! | E7: ='Master - Summary'!V30 -> #NUM!
B8: 25th Percentile | C8: ='Master - Summary'!H31 -> #NUM! | D8: ='Master - Summary'!O31 -> #NUM! | E8: ='Master - Summary'!V31 -> #NUM!
B9: Average | C9: ='Master - Summary'!H32 -> #DIV/0! | D9: ='Master - Summary'!O32 -> #DIV/0! | E9: ='Master - Summary'!V32 -> #DIV/0!
B10: ='Master - Summary'!C34 -> - | C10: ='Master - Summary'!H34 -> - | D10: ='Master - Summary'!O34 -> - | E10: ='Master - Summary'!V34 -> -
B12: LINK TO CHARTS
B13: 25th | C13: =C8 -> #NUM! | D13: =D8 -> #NUM! | E13: =E8 -> #NUM!
B14: 50th | C14: =(C7-C8) -> #NUM! | D14: =(D7-D8) -> #NUM! | E14: =(E7-E8) -> #NUM!
B15: 75th | C15: =(C6-C7) -> #NUM! | D15: =(D6-D7) -> #NUM! | E15: =(E6-E7) -> #NUM!
B16: Average | C16: =C9 -> #DIV/0! | D16: =D9 -> #DIV/0! | E16: =E9 -> #DIV/0!
B17: ='Master - Summary'!C34 -> - | C17: =C10 -> - | D17: =D10 -> - | E17: =E10 -> -
B19: Distance From Median | C19: =C10-C7 -> #VALUE! | D19: =D10-D7 -> #VALUE! | E19: =E10-E7 -> #VALUE!

Sheet TC Chart
B2: Row | C2: =C24 -> CEO | D2: =D24 -> CEO | E2: =E24 -> CFO | F2: =F24 -> CFO | G2: =G24 -> COO | H2: =H24 -> COO | I2: =I24 -> Legal | J2: =J24 -> Legal | ... N2: =N24 -> Tech
B3: 75th Percentile | C3: 29 | D3: 29 | E3: 29 | F3: 29 | G3: 23 | H3: 23 | I3: 20 | J3: 20 | K3: 29 | L3: 29 | M3: 19 | N3: 19
B4: Median | C4: =C3+1 -> 30 | D4: =D3+1 -> 30 | E4: =E3+1 -> 30 | F4: =F3+1 -> 30 | G4: =G3+1 -> 24 | H4: =H3+1 -> 24 | I4: =I3+1 -> 21 | J4: =J3+1 -> 21 | ... N4: =N3+1 -> 20
B5: 25th Percentile | C5: =C4+1 -> 31 | D5: =D4+1 -> 31 | E5: =E4+1 -> 31 | F5: =F4+1 -> 31 | G5: =G4+1 -> 25 | H5: =H4+1 -> 25 | I5: =I4+1 -> 22 | J5: =J4+1 -> 22 | ... N5: =N4+1 -> 21
B6: Average | C6: =C5+1 -> 32 | D6: =D5+1 -> 32 | E6: =E5+1 -> 32 | F6: =F5+1 -> 32 | G6: =G5+1 -> 26 | H6: =H5+1 -> 26 | I6: =I5+1 -> 23 | J6: =J5+1 -> 23 | ... N6: =N5+1 -> 22
B7: Hudbay Minerals Inc. | C7: 39 | D7: 39 | E7: 39 | F7: 39 | G7: 33 | H7: 33 | I7: 30 | J7: 30 | K7: 39 | L7: 39 | M7: 29 | N7: 29
B8: Hudbay2 | M8: =M7+2 -> 31 | N8: =N7+2 -> 31
B9: Hudbay3 | M9: =M8+2 -> 33 | N9: =N8+2 -> 33
B10: Percentiles | C10: =C7+1 -> 40 | D10: =D7+1 -> 40 | E10: =E7+1 -> 40 | F10: =F7+1 -> 40 | G10: =G7+1 -> 34 | H10: =H7+1 -> 34 | I10: =I7+1 -> 31 | J10: =J7+1 -> 31 | ... N10: =N7+1 -> 30
B12: Address | C12: W | D12: AA | E12: =C12 -> W | F12: =D12 -> AA | G12: =E12 -> W | H12: =F12 -> AA | I12: =G12 -> W | J12: =H12 -> AA | K12: =I12 -> W | L12: =J12 -> AA | ... N12: =L12 -> AA
B13: =B28 -> 75th Percentile | C13: =C$12&C3 -> W29 | D13: =D$12&D3 -> AA29 | E13: =E$12&E3 -> W29 | F13: =F$12&F3 -> AA29 | G13: =G$12&G3 -> W23 | H13: =H$12&H3 -> AA23 | I13: =I$12&I3 -> W20 | J13: =J$12&J3 -> AA20 | ... N13: =N$12&N3 -> AA19
B14: =B29 -> Median | C14: =C$12&C4 -> W30 | D14: =D$12&D4 -> AA30 | E14: =E$12&E4 -> W30 | F14: =F$12&F4 -> AA30 | G14: =G$12&G4 -> W24 | H14: =H$12&H4 -> AA24 | I14: =I$12&I4 -> W21 | J14: =J$12&J4 -> AA21 | ... N14: =N$12&N4 -> AA20
B15: =B30 -> 25th Percentile | C15: =C$12&C5 -> W31 | D15: =D$12&D5 -> AA31 | E15: =E$12&E5 -> W31 | F15: =F$12&F5 -> AA31 | G15: =G$12&G5 -> W25 | H15: =H$12&H5 -> AA25 | I15: =I$12&I5 -> W22 | J15: =J$12&J5 -> AA22 | ... N15: =N$12&N5 -> AA21
B16: =B31 -> Average | C16: =C$12&C6 -> W32 | D16: =D$12&D6 -> AA32 | E16: =E$12&E6 -> W32 | F16: =F$12&F6 -> AA32 | G16: =G$12&G6 -> W26 | H16: =H$12&H6 -> AA26 | I16: =I$12&I6 -> W23 | J16: =J$12&J6 -> AA23 | ... N16: =N$12&N6 -> AA22
B17: =B32 -> Hudbay Minerals Inc. | C17: =C$12&C7 -> W39 | D17: =D$12&D7 -> AA39 | E17: =E$12&E7 -> W39 | F17: =F$12&F7 -> AA39 | G17: =G$12&G7 -> W33 | H17: =H$12&H7 -> AA33 | I17: =I$12&I7 -> W30 | J17: =J$12&J7 -> AA30 | ... N17: =N$12&N7 -> AA29
B18: =B8 -> Hudbay2 | M18: =M$12&M8 -> W31 | N18: =N$12&N8 -> AA31
B19: =B9 -> Hudbay3 | M19: =M$12&M9 -> W33 | N19: =N$12&N9 -> AA33
B20: =B10 -> Percentiles | C20: =C$12&C10 -> W40 | D20: =D$12&D10 -> AA40 | E20: =E$12&E10 -> W40 | F20: =F$12&F10 -> AA40 | G20: =G$12&G10 -> W34 | H20: =H$12&H10 -> AA34 | I20: =I$12&I10 -> W31 | J20: =J$12&J10 -> AA31 | ... N20: =N$12&N10 -> AA30
M21: =M$12&M$10+2 -> W32 | N21: =N$12&N$10+2 -> AA32
M22: =M$12&M$10+4 -> W34 | N22: =N$12&N$10+4 -> AA34
C24: CEO | D24: =C24 -> CEO | E24: CFO | F24: =E24 -> CFO | G24: COO | H24: =G24 -> COO | I24: Legal | J24: =I24 -> Legal | K24: NEO4 | L24: =K24 -> NEO4 | M24: Tech | N24: Tech
C25: CEO (Kukielski) | E25: CFO (Lei) | G25: COO (Lauzon) | I25: Legal (Donnelly) | K25: NEO4 (Del Rio) | M25: Tech (Tavchandjian)
C26: TDC | D26: TC | E26: =C26 -> TDC | F26: =D26 -> TC | G26: =E26 -> TDC | H26: =F26 -> TC | I26: =G26 -> TDC | J26: =H26 -> TC | K26: =I26 -> TDC | L26: =J26 -> TC | ... N26: =L26 -> TC
B27: LINK DATA HERE
B28: 75th Percentile | C28: {=INDIRECT("'"&C$24&"'!"&C13)} -> 7438.801 | D28: {=INDIRECT("'"&D$24&"'!"&D13)} -> 7580.8871 | E28: {=INDIRECT("'"&E$24&"'!"&E13)} -> 2877.8736 | F28: {=INDIRECT("'"&F$24&"'!"&F13)} -> 3038.5029 | G28: {=INDIRECT("'"&G$24&"'!"&G13)} -> 3071.3822 | H28: {=INDIRECT("'"&H$24&"'!"&H13)} -> 3161.6295 | I28: {=INDIRECT("'"&I$24&"'!"&I13)} -> 2334.9154 | J28: {=INDIRECT("'"&J$24&"'!"&J13)} -> 2453.8132 | ... N28: {=INDIRECT("'"&N$24&"'!"&N13)} -> 1682.5808
B29: Median | C29: {=INDIRECT("'"&C$24&"'!"&C14)} -> 5733.7981 | D29: {=INDIRECT("'"&D$24&"'!"&D14)} -> 5886.865 | E29: {=INDIRECT("'"&E$24&"'!"&E14)} -> 2291.3653 | F29: {=INDIRECT("'"&F$24&"'!"&F14)} -> 2307.5603 | G29: {=INDIRECT("'"&G$24&"'!"&G14)} -> 2859.9885 | H29: {=INDIRECT("'"&H$24&"'!"&H14)} -> 3021.2338 | I29: {=INDIRECT("'"&I$24&"'!"&I14)} -> 1624.26 | J29: {=INDIRECT("'"&J$24&"'!"&J14)} -> 1892.7892 | ... N29: {=INDIRECT("'"&N$24&"'!"&N14)} -> 2004.7019
B30: 25th Percentile | C30: {=INDIRECT("'"&C$24&"'!"&C15)} -> 4956.1421 | D30: {=INDIRECT("'"&D$24&"'!"&D15)} -> 5241.8386 | E30: {=INDIRECT("'"&E$24&"'!"&E15)} -> 1941.397 | F30: {=INDIRECT("'"&F$24&"'!"&F15)} -> 2065.5736 | G30: {=INDIRECT("'"&G$24&"'!"&G15)} -> 2378.0618 | H30: {=INDIRECT("'"&H$24&"'!"&H15)} -> 2478.646 | I30: {=INDIRECT("'"&I$24&"'!"&I15)} -> 1523.875 | J30: {=INDIRECT("'"&J$24&"'!"&J15)} -> 1651.632 | ... N30: {=INDIRECT("'"&N$24&"'!"&N15)} -> 0
B31: Average | C31: {=INDIRECT("'"&C$24&"'!"&C16)} -> 6074.7685 | D31: {=INDIRECT("'"&D$24&"'!"&D16)} -> 6401.6905 | E31: {=INDIRECT("'"&E$24&"'!"&E16)} -> 2409.0228 | F31: {=INDIRECT("'"&F$24&"'!"&F16)} -> 2521.0677 | G31: {=INDIRECT("'"&G$24&"'!"&G16)} -> 2733.9998 | H31: {=INDIRECT("'"&H$24&"'!"&H16)} -> 2872.1962 | I31: {=INDIRECT("'"&I$24&"'!"&I16)} -> 1924.9597 | J31: {=INDIRECT("'"&J$24&"'!"&J16)} -> 2059.503 | ... N31: {=INDIRECT("'"&N$24&"'!"&N16)} -> 0
B32: =CEO!C39 -> Hudbay Minerals Inc. | C32: {=INDIRECT("'"&C$24&"'!"&C17)} -> 5334.5198 | D32: {=INDIRECT("'"&D$24&"'!"&D17)} -> 5426.4128 | E32: {=INDIRECT("'"&E$24&"'!"&E17)} -> 2313.6544 | F32: {=INDIRECT("'"&F$24&"'!"&F17)} -> 2452.6354 | G32: {=INDIRECT("'"&G$24&"'!"&G17)} -> 2577.309 | H32: {=INDIRECT("'"&H$24&"'!"&H17)} -> 2621.619 | I32: {=INDIRECT("'"&I$24&"'!"&I17)} -> 1711.9147 | J32: {=INDIRECT("'"&J$24&"'!"&J17)} -> 1803.8498 | ... N32: {=INDIRECT("'"&N$24&"'!"&N17)} -> 0
B33: ='NEO5'!G37 -> -
B34: ='NEO5'!G35 -> SVP, Exploration & Technical Services
B36: LINK TO CHARTS
B37: 25th | C37: =C30 -> 4956.1421 | D37: =D30 -> 5241.8386 | E37: =E30 -> 1941.397 | F37: =F30 -> 2065.5736 | G37: =G30 -> 2378.0618 | H37: =H30 -> 2478.646 | I37: =I30 -> 1523.875 | J37: =J30 -> 1651.632 | ... N37: =N30 -> 0
B38: 50th | C38: =(C29-C30) -> 777.65596 | D38: =(D29-D30) -> 645.02644 | E38: =(E29-E30) -> 349.96825 | F38: =(F29-F30) -> 241.98668 | G38: =(G29-G30) -> 481.92677 | H38: =(H29-H30) -> 542.5878 | I38: =(I29-I30) -> 100.385 | J38: =(J29-J30) -> 241.15723 | ... N38: =(N29-N30) -> 2004.7019
B39: 75th | C39: =(C28-C29) -> 1705.0029 | D39: =(D28-D29) -> 1694.0221 | E39: =(E28-E29) -> 586.50833 | F39: =(F28-F29) -> 730.94256 | G39: =(G28-G29) -> 211.3937 | H39: =(H28-H29) -> 140.39571 | I39: =(I28-I29) -> 710.6554 | J39: =(J28-J29) -> 561.02401 | ... N39: =(N28-N29) -> -322.12111
B40: Average | C40: =C31 -> 6074.7685 | D40: =D31 -> 6401.6905 | E40: =E31 -> 2409.0228 | F40: =F31 -> 2521.0677 | G40: =G31 -> 2733.9998 | H40: =H31 -> 2872.1962 | I40: =I31 -> 1924.9597 | J40: =J31 -> 2059.503 | ... N40: =N31 -> 0
B41: =B32 -> Hudbay Minerals Inc. | C41: =C32 -> 5334.5198 | D41: =D32 -> 5426.4128 | E41: =E32 -> 2313.6544 | F41: =F32 -> 2452.6354 | G41: =G32 -> 2577.309 | H41: =H32 -> 2621.619 | I41: =I32 -> 1711.9147 | ... N41: =N32 -> 0
B42: Percentile | C42: {=INDIRECT("'"&C$24&"'!"&C20)*100} -> 29.2 | D42: {=INDIRECT("'"&D$24&"'!"&D20)*100} -> 25.4 | E42: {=INDIRECT("'"&E$24&"'!"&E20)*100} -> 48.3 | F42: {=INDIRECT("'"&F$24&"'!"&F20)*100} -> 50.9 | G42: {=INDIRECT("'"&G$24&"'!"&G20)*100} -> 45.9 | H42: {=INDIRECT("'"&H$24&"'!"&H20)*100} -> 38.2 | I42: {=INDIRECT("'"&I$24&"'!"&I20)*100} -> 51.2 | J42: {=INDIRECT("'"&J$24&"'!"&J20)*100} -> 42.3 | ... M42: {=INDIRECT("'"&M$24&"'!"&M20)*100} -> 1.5 | N42: {=IF(INDIRECT("'"&N$24&"'!"&N20)="min",0,IF(INDIRECT("'"&N$24&"'!"&N20)="max",100,INDIRECT("'"&N$24&"'!"&N20)*100))} -> 0
M43: {=IFERROR(INDIRECT("'"&M$24&"'!"&M21)*100,"P00")} -> -26.65812 | N43: {=IFERROR(INDIRECT("'"&N$24&"'!"&N21)*100,"P00")} -> 0
M44: {=IFERROR(INDIRECT("'"&M$24&"'!"&M22)*100,"P00")} -> P00 | N44: {=IFERROR(INDIRECT("'"&N$24&"'!"&N22)*100,"P00")} -> P00
N45: ='NEO5'!AB34*100 -> 7.5
B46: Distance From Median | C46: =C32-C29 -> -399.27826 | D46: =D32-D29 -> -460.4522 | E46: =E32-E29 -> 22.289139 | F46: =F32-F29 -> 145.07509 | G46: =G32-G29 -> -282.67953 | H46: =H32-H29 -> -399.6148 | I46: =I32-I29 -> 87.65475 | J46: =J32-J29 -> -88.939485 | ... N46: =N32-N29 -> -2004.7019
B48: Specific Reference Peers
B49: =B33 -> - | M49: 10.8 | N49: =M49+1 -> 11.8
B50: =B34 -> SVP, Exploration & Technical Services | M50: 11.2 | N50: =M50+1 -> 12.2
B51: Javier, Excl. tax top-ups | N51: ='NEO5'!AB33 -> 1382.1368
B52: Company 4
B54: Change in Summary Statistics | O54: Avg
B55: =B28 -> 75th Percentile | D55: =D28/C28-1 -> 0.019100669 | F55: =F28/E28-1 -> 0.055815265 | H55: =H28/G28-1 -> 0.02938328 | J55: =J28/I28-1 -> 0.050921691 | L55: =L28/K28-1 -> 0.041110584 | N55: =N28/M28-1 -> 0.12262759 | O55: =AVERAGE(C55:N55) -> 0.053159846
B56: =B29 -> Median | D56: =D29/C29-1 -> 0.026695557 | F56: =F29/E29-1 -> 0.0070678596 | H56: =H29/G29-1 -> 0.056379692 | J56: =J29/I29-1 -> 0.16532405 | L56: =L29/K29-1 -> 0.016480207 | N56: =N29/M29-1 -> 0.066862433 | O56: =AVERAGE(C56:N56) -> 0.056468299
B57: =B30 -> 25th Percentile | D57: =D30/C30-1 -> 0.057644929 | F57: =F30/E30-1 -> 0.063962507 | H57: =H30/G30-1 -> 0.042296735 | J57: =J30/I30-1 -> 0.083836929 | L57: =L30/K30-1 -> 0.06462614 | N57: =N30/M30-1 -> #DIV/0! | O57: =AVERAGE(C57:N57) -> #DIV/0!
B58: =B31 -> Average | D58: =D31/C31-1 -> 0.053816364 | F58: =F31/E31-1 -> 0.046510529 | H58: =H31/G31-1 -> 0.050547353 | J58: =J31/I31-1 -> 0.069894082 | L58: =L31/K31-1 -> 0.060865806 | N58: =N31/M31-1 -> -1 | O58: =AVERAGE(C58:N58) -> -0.11972764
B59: =B32 -> Hudbay Minerals Inc. | D59: =D32/C32-1 -> 0.017226105 | F59: =F32/E32-1 -> 0.060069905 | H59: =H32/G32-1 -> 0.017192351 | J59: =J32/I32-1 -> 0.053703025 | L59: =L32/K32-1 -> -1 | N59: =N32/M32-1 -> -1 | O59: =AVERAGE(C59:N59) -> -0.30863477
B60: Outpaced Median growth? | D60: =IF(D59>D56,"Yes","No") -> No | F60: =IF(F59>F56,"Yes","No") -> Yes | H60: =IF(H59>H56,"Yes","No") -> No | J60: =IF(J59>J56,"Yes","No") -> No | L60: =IF(L59>L56,"Yes","No") -> No | N60: =IF(N59>N56,"Yes","No") -> No
B61: Outpaced P25 growth? | D61: =IF(D59>D57,"Yes","No") -> No | F61: =IF(F59>F57,"Yes","No") -> No | H61: =IF(H59>H57,"Yes","No") -> No | J61: =IF(J59>J57,"Yes","No") -> No | L61: =IF(L59>L57,"Yes","No") -> No | N61: =IF(N59>N57,"Yes","No") -> #DIV/0!
B66: Peter Kukielski
B67: Eugene Lei
B68: Andre Lauzon
B69: Patrick Donnelly
B70: Patrick Donnelly
B71: Javier Del Rio

Sheet CEO
A1: 45839
A2: CAD | B2: Position | C2: CEO
B3: Year | C3: ='Raw Data'!$G$9 -> 2025 | H3: sorting of table based on size of peers
C4: Company | D4: Market Cap | E4: TEV | F4: Incumbent | G4: Position Title | H4: Latest (if disclosed) - Annualized / Converted | I4: Annualized / Converted | J4: Annualized/ Converted | K4: Actual STI % | L4: 3 Year Average STIP % | M4: Target STI $ | N4: Target STI % | O4: Actual TCC | P4: Target TCC | Q4: Total LTI (Converted) | R4: Total LTI % | S4: 3 Year Average LTIP % | T4: Target LTI $ | U4: Target LTI % | V4: Actual (base + actual bonus + actual LTIP) | W4: Target (base + target bonus + Target LTIP) | X4: ='Raw Data'!AR31 -> Pension Converted | Y4: ='Raw Data'!AU31 -> Other Converted | Z4: Actual (Actual TDC + Pension + Other) | AA4: Target (Target TDC + Pension + Other) | AC4: Cash | AD4: Equity
C5: =+C2& " Benchmarking - "&'Raw Data'!H5&" $000s" -> CEO Benchmarking - CAD $000s | AG5: Company | AH5: Incumbent | AK5: Title | AL5: Actual TDC | AM5: Target TDC
C6: Company | D6: Market Cap | E6: TEV | F6: Incumbent | G6: Title | H6: Next Year Base Salary (If Disclosed) | I6: Base Salary | J6: STIP | M6: STIP | O6: Total Cash Compensation | Q6: LTIP | T6: LTIP | V6: 2025 Total Direct Compensation | X6: Pension | Y6: Other | Z6: Total Compensation | AC6: Pay Mix | AE6: 2024 | AG6: 2024 Total Direct Compensation | AL6: 2024 Total Direct Compensation | AP6: 2025 Total Direct Compensation
A7: Look-up | B7: Ticker | D7: Market Cap | E7: TEV | F7: Incumbent | G7: Title | H7: Base Salary | I7: Base Salary | J7: Actual $ | K7: Actual % | L7: 3 Year Average STIP % | M7: Target $ | N7: Target % | O7: Actual $ | P7: Target $ | Q7: Actual $ | R7: Actual% | S7: 3 Year Average LTIP % | T7: Target $ | U7: Target % | V7: Actual $ | W7: Target $ | Z7: Actual $ | AA7: Target $ | AC7: Cash | AD7: Equity | AE7: =AE6&" Lookup" -> 2024 Lookup | AG7: Company | AH7: Incumbent | AI7: New Peer? | AJ7: New Incumbent? | AK7: Title | AL7: Actual $ | AM7: Target $ | AO7: Target YoY Increase | AP7: Actual $ | AQ7: Target $
